Workbook
Name Consol: "Error"

Sheet PRICE LIST Motasa
A3: KELOMPOK PRODUK | B3: KODE PRODUK PRINSIPAL | C3: NAMA ITEM | D3: ISI/CTN | E3: SATUAN | F3: HARGA INCLUDE PPN 11% IN CTN | G3: HARGA/PCS | H3: Column1 | I3: Column2 | J3: Column3
A4: LADAKU | B4: 1106FG-LDK33 | C4: LADAKU SACHET | D4: 576 | E4: SACHET | F4: 460000 | G4: =F4/D4 -> 798.61111 | H4: 419287 | I4: =Table3[[#This Row],[Column1]]/Table3[[#This Row],[ISI/CTN]] -> 727.92882 | J4: =Table3[[#This Row],[Column2]]/1.11 -> 655.79173
A5: DESAKU SPICES | B5: 1106FG-DSK07 | C5: DESAKU KETUMBAR BUBUK | D5: 192 | E5: SACHET | F5: 156000 | G5: =F5/D5 -> 812.5 | H5: 142193 | I5: =Table3[[#This Row],[Column1]]/Table3[[#This Row],[ISI/CTN]] -> 740.58854 | J5: =Table3[[#This Row],[Column2]]/1.11 -> 667.19688
A6: DESAKU SPICES | B6: 1106FG-DKU02 | C6: DESAKU KUNYIT BUBUK | D6: 432 | E6: SACHET | F6: 351000 | G6: =F6/D6 -> 812.5 | H6: 319934 | I6: =Table3[[#This Row],[Column1]]/Table3[[#This Row],[ISI/CTN]] -> 740.58796 | J6: =Table3[[#This Row],[Column2]]/1.11 -> 667.19636
A7: DESAKU SPICES | B7: 1106FG-DCB02 | C7: DESAKU CABE BUBUK | D7: 120 | E7: SACHET | F7: 234000 | G7: =F7/D7 -> 1950 | H7: 213289 | I7: =Table3[[#This Row],[Column1]]/Table3[[#This Row],[ISI/CTN]] -> 1777.4083 | J7: =Table3[[#This Row],[Column2]]/1.11 -> 1601.2688
A8: DESAKU SPICES | B8: 1106FG-DBP01 | C8: DESAKU BAWANG PUTIH | D8: 432 | E8: SACHET | F8: 351000 | G8: =F8/D8 -> 812.5 | H8: 319934 | I8: =Table3[[#This Row],[Column1]]/Table3[[#This Row],[ISI/CTN]] -> 740.58796 | J8: =Table3[[#This Row],[Column2]]/1.11 -> 667.19636
A9: DESAKU SPICES | B9: 1106FG-DMR01 | C9: DESAKU MARINASI | D9: 432 | E9: SACHET | F9: 351000 | G9: =F9/D9 -> 812.5 | H9: 319934 | I9: =Table3[[#This Row],[Column1]]/Table3[[#This Row],[ISI/CTN]] -> 740.58796 | J9: =Table3[[#This Row],[Column2]]/1.11 -> 667.19636
A10: DESAKU SEASONING | B10: 1106FG-DBL01 | C10: DESAKU BALADO | D10: 120 | E10: SACHET | F10: 216000 | G10: =F10/D10 -> 1800 | H10: 196882 | I10: =Table3[[#This Row],[Column1]]/Table3[[#This Row],[ISI/CTN]] -> 1640.6833 | J10: =Table3[[#This Row],[Column2]]/1.11 -> 1478.0931
A11: DESAKU SEASONING | B11: 1106FG-DKR01 | C11: DESAKU KARI NUSANTARA | D11: 120 | E11: SACHET | F11: 216000 | G11: =F11/D11 -> 1800 | H11: 196882 | I11: =Table3[[#This Row],[Column1]]/Table3[[#This Row],[ISI/CTN]] -> 1640.6833 | J11: =Table3[[#This Row],[Column2]]/1.11 -> 1478.0931
A12: DESAKU SEASONING | B12: 1106FG-DSG02 | C12: DESAKU SAMBAL GORENG | D12: 120 | E12: SACHET | F12: 216000 | G12: =F12/D12 -> 1800 | H12: 196882 | I12: =Table3[[#This Row],[Column1]]/Table3[[#This Row],[ISI/CTN]] -> 1640.6833 | J12: =Table3[[#This Row],[Column2]]/1.11 -> 1478.0931
A13: DESAKU SEASONING | B13: 1106FG-DGL01 | C13: DESAKU GULAI PADANG | D13: 120 | E13: SACHET | F13: 216000 | G13: =F13/D13 -> 1800 | H13: 196882 | I13: =Table3[[#This Row],[Column1]]/Table3[[#This Row],[ISI/CTN]] -> 1640.6833 | J13: =Table3[[#This Row],[Column2]]/1.11 -> 1478.0931
A14: DESAKU SEASONING | B14: 1106FG-DSO01 | C14: DESAKU OPOR | D14: 120 | E14: SACHET | F14: 216000 | G14: =F14/D14 -> 1800 | H14: 196882 | I14: =Table3[[#This Row],[Column1]]/Table3[[#This Row],[ISI/CTN]] -> 1640.6833 | J14: =Table3[[#This Row],[Column2]]/1.11 -> 1478.0931

Sheet FORM DASAR KLP
A3: KODE PRODUK PRINSIPAL | B3: KELOMPOK PRODUK By Principle | C3: NAMA ITEM | D3: ISI/CTN | E3: SATUAN | F3: HARGA INCLUDE PPN 11% IN CTN | G3: HARGA/PCS
A4: 1106FG-LDK33 | B4: LADAKU | C4: LADAKU SACHET | D4: 576 | E4: SACHET | F4: 460000 | G4: 798.61111 | I4: 8 | J4: 6 | K4: 12 | L4: =I4*J4*K4 -> 576
A5: 1106FG-DSK07 | B5: DESAKU SPICES | C5: DESAKU KETUMBAR BUBUK | D5: 192 | E5: SACHET | F5: 156000 | G5: 812.5 | I5: 8 | J5: 2 | K5: 12 | L5: =I5*J5*K5 -> 192
A6: 1106FG-DKU02 | B6: DESAKU SPICES | C6: DESAKU KUNYIT BUBUK | D6: 432 | E6: SACHET | F6: 351000 | G6: 812.5 | I6: 18 | J6: 2 | K6: 12 | L6: =I6*J6*K6 -> 432
A7: 1106FG-DCB02 | B7: DESAKU SPICES | C7: DESAKU CABE BUBUK | D7: 120 | E7: SACHET | F7: 234000 | G7: 1950 | I7: 12 | J7: 1 | K7: 10 | L7: =I7*J7*K7 -> 120
A8: 1106FG-DBP01 | B8: DESAKU SPICES | C8: DESAKU BAWANG PUTIH | D8: 432 | E8: SACHET | F8: 351000 | G8: 812.5 | I8: 36 | J8: 1 | K8: 12 | L8: =I8*J8*K8 -> 432
A9: 1106FG-DMR01 | B9: DESAKU SPICES | C9: DESAKU MARINASI | D9: 432 | E9: SACHET | F9: 351000 | G9: 812.5 | I9: 36 | J9: 1 | K9: 12 | L9: =I9*J9*K9 -> 432
A10: 1106FG-DBL01 | B10: DESAKU SEASONING | C10: DESAKU BALADO | D10: 120 | E10: SACHET | F10: 216000 | G10: 1800 | I10: 12 | J10: 1 | K10: 10 | L10: =I10*J10*K10 -> 120
A11: 1106FG-DKR01 | B11: DESAKU SEASONING | C11: DESAKU KARI NUSANTARA | D11: 120 | E11: SACHET | F11: 216000 | G11: 1800 | I11: 12 | J11: 1 | K11: 10 | L11: =I11*J11*K11 -> 120
A12: 1106FG-DSG02 | B12: DESAKU SEASONING | C12: DESAKU SAMBAL GORENG | D12: 120 | E12: SACHET | F12: 216000 | G12: 1800 | I12: 12 | J12: 1 | K12: 10 | L12: =I12*J12*K12 -> 120
A13: 1106FG-DGL01 | B13: DESAKU SEASONING | C13: DESAKU GULAI PADANG | D13: 120 | E13: SACHET | F13: 216000 | G13: 1800 | I13: 12 | J13: 1 | K13: 10 | L13: =I13*J13*K13 -> 120
A14: 1106FG-DSO01 | B14: DESAKU SEASONING | C14: DESAKU OPOR | D14: 120 | E14: SACHET | F14: 216000 | G14: 1800 | I14: 12 | J14: 1 | K14: 10 | L14: =I14*J14*K14 -> 120
G187: =F187/D187 -> #DIV/0!
G188: =F188/D188 -> #DIV/0!
G189: =F189/D189 -> #DIV/0!
G190: =F190/D190 -> #DIV/0!
G191: =F191/D191 -> #DIV/0!
G192: =F192/D192 -> #DIV/0!
G193: =F193/D193 -> #DIV/0!
G194: =F194/D194 -> #DIV/0!
G195: =F195/D195 -> #DIV/0!
G196: =F196/D196 -> #DIV/0!
G197: =F197/D197 -> #DIV/0!
G198: =F198/D198 -> #DIV/0!
... G1082: =F1082/D1082 -> #DIV/0!

Sheet Cara Buat
A3: 1 | B3: Sortir Daftar Produk Principle sesuai Nama lalu sortir lagi by kelompok | D3: 1 | E3: Buat satu folder master barang, master kelompok, price list, mapping produk win to pcpl dan mapping produk pcpl to win
A4: 2 | B4: Copy dan Paste kan ke Sheet Form Master (sesuaikan kolom nya) | D4: 2 | E4: Master barang, master kelompok, price list, mapping produk win to pcpl dan mapping produk pcpl to win berdiri sendiri dalam satu book
A5: 3 | B5: Sheet kuning adalah rumus, jangan diganggu

Sheet Pvt Map 1
A3: Kode BARANG Win2 | B3: SATUAN Fix Win | C3: Kode Pcpl | D3: Ket. Tambahan / Pembantu | E3: ISI/CTN | F3: Sum of No. Urut Item Sama
A4: A1011001062010 | B4: BTL | C4: 100191 | D4: 7000003082 | E4: 12 | F4: 1
A5: A1011001062010 | B5: BTL | C5: 100191 | D5: 7000003792 | E5: 12 | F5: 2
A6: A1011001052010 | B6: PCH | C6: 100156 | D6: 7000003063 | E6: 12 | F6: 1
A7: A1011001052010 | B7: PCH | C7: (blank) | D7: 7000003778 | E7: 12
A8: A1011002052010 | B8: PCH | C8: 100180 | D8: 7000003075 | E8: 12 | F8: 1
A9: A1011003065010 | B9: PCH | C9: 100151 | D9: 0 | E9: 12 | F9: 1
A10: A1011004065010 | B10: PCH | C10: 100174 | D10: 0 | E10: 12 | F10: 1
A11: A1011005013510 | B11: BTL | C11: 100192 | D11: 7000003083 | E11: 48 | F11: 1
A12: A1011005013510 | B12: BTL | C12: 100201 | D12: 7000003090 | E12: 48 | F12: 2
A13: A1011006013520 | B13: BTL | C13: 100194 | D13: 7000003085 | E13: 48 | F13: 1
A14: A1011006013520 | B14: BTL | C14: 100203 | D14: 7000003092 | E14: 48 | F14: 2
A15: A1011006013520 | B15: BTL | C15: 100215 | D15: 7000003100 | E15: 48 | F15: 3
A16: A1011005027510 | B16: BTL | C16: 100193 | D16: 7000003084 | E16: 24 | F16: 1
A17: A1011005027510 | B17: BTL | C17: 100202 | D17: 7000003091 | E17: 24 | F17: 2
A18: A1011005027510 | B18: BTL | C18: 100231 | D18: 7000003109 | E18: 24 | F18: 3
A19: A1011006007510 | B19: PCH | C19: 100204 | D19: 7000003093 | E19: 48 | F19: 1
A20: A1011000006210 | B20: PCH | C20: 100189 | D20: 7000003080 | E20: 48 | F20: 1
A21: A1011000006210 | B21: PCH | C21: 100222 | D21: 7000003102 | E21: 48 | F21: 2
A22: A1011000006210 | B22: PCH | C22: 100240 | D22: 7000003116 | E22: 48 | F22: 3
A23: A1011000006211 | B23: PCH | C23: 100986 | D23: 7000003134 | E23: 48 | F23: 1
A24: A1011000008010 | B24: PCH | C24: 100179 | D24: 0 | E24: 48 | F24: 1
A25: A1011000030010 | B25: PCH | C25: 100158 | D25: 7000003064 | E25: 24 | F25: 1
A26: A1011000030010 | B26: PCH | C26: 100172 | D26: 7000003071 | E26: 24 | F26: 2
A27: A1011000025010 | B27: PCH | C27: 100220 | D27: 7000003101 | E27: 24 | F27: 1
A28: A1011000025010 | B28: PCH | C28: 100238 | D28: 7000003114 | E28: 24 | F28: 2
A29: A1011000068510 | B29: PCH | C29: 100165 | D29: 7000003067 | E29: 12 | F29: 2
A30: A1011000068510 | B30: PCH | C30: 100187 | D30: 0 | E30: 12 | F30: 1
A31: A1011000068512 | B31: PCH | C31: 100976 | D31: 0 | E31: 12 | F31: 1
A32: A1011000068512 | B32: PCH | C32: 100981 | D32: 0 | E32: 12 | F32: 2
A33: A1011000060010 | B33: PCH | C33: 100225 | D33: 7000003104 | E33: 12 | F33: 1
A34: A1011000060010 | B34: PCH | C34: 100242 | D34: 7000003118 | E34: 12 | F34: 2
A35: A1011000092510 | B35: PCH | C35: 100176 | D35: 7000003072 | E35: 12 | F35: 1
A36: A1011000092510 | B36: PCH | C36: 100188 | D36: 7000003079 | E36: 12 | F36: 2
A37: A1011000082510 | B37: PCH | C37: 100221 | D37: 0 | E37: 12 | F37: 1
A38: A1011000082510 | B38: PCH | C38: 100252 | D38: 7000003121 | E38: 12 | F38: 2
A39: A1011000082510 | B39: PCH | C39: 100239 | D39: 7000003115 | E39: 12 | F39: 3
A40: A1011000082510 | B40: PCH | C40: 100267 | D40: 7000003125 | E40: 12 | F40: 4
A41: A1011000102510 | B41: JRG | C41: 100181 | D41: 7000003076 | E41: 1 | F41: 1
A42: A1011000102510 | B42: JRG | C42: 100228 | D42: 7000003107 | E42: 1 | F42: 2
A43: A1011000013510 | B43: BTL | C43: 100161 | D43: 0 | E43: 48 | F43: 1
A44: A1011000027520 | B44: BTL | C44: 100162 | D44: 0 | E44: 24 | F44: 1
A45: A1011000027520 | B45: BTL | C45: 100236 | D45: 7000003112 | E45: 24 | F45: 2
A46: A1011000062010 | B46: BTL | C46: 100166 | D46: 0 | E46: 12 | F46: 1
A47: A1011000060020 | B47: BTL | C47: 100163 | D47: 0 | E47: 12 | F47: 1
A48: A1011000060020 | B48: BTL | C48: 100226 | D48: 7000003105 | E48: 12 | F48: 2
A49: A1012000062010 | B49: BTL | C49: 110013 | D49: 7000003580 | E49: 12 | F49: 1
A50: A1012000062010 | B50: BTL | C50: 110019 | D50: 7000003153 | E50: 12 | F50: 2
A51: A1020001019510 | B51: BTL | C51: 120011 | D51: 7000003160 | E51: 24 | F51: 1
A52: A1020001019510 | B52: BTL | C52: 120029 | D52: 0 | E52: 24 | F52: 2
A53: A1020001019510 | B53: BTL | C53: 120041 | D53: 7000003177 | E53: 24 | F53: 3
A54: A1020002042010 | B54: BTL | C54: 120031 | D54: 7000003169 | E54: 24 | F54: 1
A55: A1020002042010 | B55: BTL | C55: 120033 | D55: 0 | E55: 24 | F55: 2
A56: A1020002042010 | B56: BTL | C56: 120040 | D56: 7000003176 | E56: 24 | F56: 3
A57: A1020002013510 | B57: BTL | C57: 120030 | D57: 7000003168 | E57: 48 | F57: 1
A58: A1020002013510 | B58: BTL | C58: 120035 | D58: 7000003171 | E58: 48 | F58: 2
A59: A1020003019510 | B59: BTL | C59: 120032 | D59: 7000003170 | E59: 24 | F59: 1
A60: A1020003019510 | B60: BTL | C60: 120037 | D60: 7000003173 | E60: 24 | F60: 2
A61: A1020002019510 | B61: BTL | C61: 120034 | D61: 0 | E61: 24 | F61: 1
A62: A1020002019510 | B62: BTL | C62: 120038 | D62: 7000003174 | E62: 24 | F62: 2
A63: A1020004019510 | B63: BTL | C63: 120028 | D63: 0 | E63: 24 | F63: 1
A64: A1020004019510 | B64: BTL | C64: 120043 | D64: 7000003179 | E64: 24 | F64: 2
A65: A1041001009010 | B65: PCS | C65: 460166 | D65: 7000003408 | E65: 48 | F65: 1
A66: A1041002009010 | B66: PCS | C66: 460167 | D66: 7000003409 | E66: 48 | F66: 1
A67: A1041003009010 | B67: PCS | C67: 460168 | D67: 7000003410 | E67: 48 | F67: 1
A68: A1041004009010 | B68: PCS | C68: 460169 | D68: 7000003411 | E68: 48 | F68: 1
A69: A1042001009010 | B69: PCS | C69: 460170 | D69: 7000003412 | E69: 48 | F69: 1
A70: A1042004009010 | B70: PCS | C70: 460171 | D70: 7000003413 | E70: 48 | F70: 1
A71: A1041005009010 | B71: PCS | C71: 460172 | D71: 7000003414 | E71: 48 | F71: 1
A72: A1050000025010 | B72: PCS | C72: 460179 | D72: 7000003417 | E72: 24 | F72: 1
A73: A1050000020010 | B73: PCS | C73: 460056 | D73: 0 | E73: 24 | F73: 1
A74: A1050000020010 | B74: PCS | C74: 460178 | D74: 7000003416 | E74: 24 | F74: 2
A75: A1050000025011 | B75: PCS | C75: 460918 | D75: 7000003427 | E75: 24 | F75: 1
A76: A1050000025020 | B76: PCSX3 | C76: 460917 | D76: 0 | E76: 8 | F76: 1
A77: A1050000025020 | B77: PCSX3 | C77: 460921 | D77: 7000003429 | E77: 8 | F77: 2
A78: A1061001020010 | B78: PCS | C78: 460194 | D78: 0 | E78: 24 | F78: 1
A79: A1061002020010 | B79: PCS | C79: 460195 | D79: 0 | E79: 24 | F79: 1
A80: A1061000020010 | B80: PCS | C80: 460183 | D80: 7000003419 | E80: 24 | F80: 1
A81: A1061000020010 | B81: PCS | C81: 460174 | D81: 0 | E81: 24 | F81: 2
A82: A1070001025010 | B82: PCS | C82: 460164 | D82: 0 | E82: 24 | F82: 1
A83: A1070001025010 | B83: PCS | C83: 460190 | D83: 7000003424 | E83: 24 | F83: 2
A84: A1070002025010 | B84: PCS | C84: 460061 | D84: 0 | E84: 24 | F84: 1
A85: A1070002025010 | B85: PCS | C85: 460188 | D85: 7000003423 | E85: 24 | F85: 2
A86: A1070003025010 | B86: PCS | C86: 460192 | D86: 7000003425 | E86: 24 | F86: 1
A87: A1070004025010 | B87: PCS | C87: 460060 | D87: 0 | E87: 24 | F87: 1
A88: A1070004025010 | B88: PCS | C88: 460187 | D88: 7000003422 | E88: 24 | F88: 2
A89: A1070005025010 | B89: PCS | C89: 460054 | D89: 0 | E89: 24 | F89: 1
A90: A1070005025010 | B90: PCS | C90: 460185 | D90: 7000003420 | E90: 24 | F90: 2
A91: A1070006025010 | B91: PCS | C91: 460055 | D91: 0 | E91: 24 | F91: 1
A92: A1070006025010 | B92: PCS | C92: 460186 | D92: 7000003421 | E92: 24 | F92: 2
A93: A1091001046010 | B93: BTL | C93: 410066 | D93: 7000003588 | E93: 12 | F93: 1
A94: A1091001046010 | B94: BTL | C94: 410072 | D94: 7000003404 | E94: 12 | F94: 2
A95: A1091001046010 | B95: BTL | C95: 410075 | D95: 7000003407 | E95: 12 | F95: 2
A96: A1091002046010 | B96: BTL | C96: 410068 | D96: 7000003589 | E96: 12 | F96: 1
A97: A1091002046010 | B97: BTL | C97: 410073 | D97: 7000003405 | E97: 12 | F97: 2
A98: A1092001045010 | B98: BTL | C98: 400129 | D98: 7000003385 | E98: 12 | F98: 1
A99: A1092001045010 | B99: BTL | C99: 400135 | D99: 7000003389 | E99: 12 | F99: 2
A100: A1092002045010 | B100: BTL | C100: 400132 | D100: 7000003386 | E100: 12 | F100: 1
A101: A1092002045010 | B101: BTL | C101: 400138 | D101: 7000003392 | E101: 12 | F101: 2
A102: A1092003045010 | B102: BTL | C102: 400133 | D102: 7000003387 | E102: 12 | F102: 1
...

Sheet Table Pvt 1
A1: Kode Barang Win | B1: Kode Pcpl | C1: SATUAN Fix Win | D1: ISI/CTN | E1: Kode PCPL yang sama
A2: A1011001062010 | B2: 100191 | C2: BTL | D2: 12 | E2: 1
A3: A1011001062010 | B3: 100191 | C3: BTL | D3: 12 | E3: 2
A4: A1011001052010 | B4: 100156 | C4: PCH | D4: 12 | E4: 1
A5: A1011001052010 | B5: (blank) | C5: PCH | D5: 12
A6: A1011002052010 | B6: 100180 | C6: PCH | D6: 12 | E6: 1
A7: A1011003065010 | B7: 100151 | C7: PCH | D7: 12 | E7: 1
A8: A1011004065010 | B8: 100174 | C8: PCH | D8: 12 | E8: 1
A9: A1011005013510 | B9: 100192 | C9: BTL | D9: 48 | E9: 1
A10: A1011005013510 | B10: 100201 | C10: BTL | D10: 48 | E10: 2
A11: A1011006013520 | B11: 100194 | C11: BTL | D11: 48 | E11: 1
A12: A1011006013520 | B12: 100203 | C12: BTL | D12: 48 | E12: 2
A13: A1011006013520 | B13: 100215 | C13: BTL | D13: 48 | E13: 3
A14: A1011005027510 | B14: 100193 | C14: BTL | D14: 24 | E14: 1
A15: A1011005027510 | B15: 100202 | C15: BTL | D15: 24 | E15: 2
A16: A1011005027510 | B16: 100231 | C16: BTL | D16: 24 | E16: 3
A17: A1011006007510 | B17: 100204 | C17: PCH | D17: 48 | E17: 1
... A110: A1100001042510 | B110: 612042 | C110: KLG | D110: 24 | E110: 1
A111: A1100001042510 | B111: 612149 | C111: KLG | D111: 24
A112: A1100002015510 | B112: 612046 | C112: KLG | D112: 60 | E112: 1
A113: A1100002042510 | B113: 612043 | C113: KLG | D113: 24 | E113: 1
A114: A1100002042510 | B114: 612150 | C114: KLG | D114: 24 | E114: 1
A115: A1100003030010 | B115: 612141 | C115: KLG | D115: 24 | E115: 1
A116: A1100003030010 | B116: 612148 | C116: KLG | D116: 24 | E116: 2
A117: A1100003030010 | B117: 612155 | C117: KLG | D117: 24 | E117: 3
A118: A1100004015510 | B118: 612047 | C118: KLG | D118: 60 | E118: 1
A119: A1100004015510 | B119: 612154 | C119: KLG | D119: 60 | E119: 2
A120: A1100004042510 | B120: 612044 | C120: KLG | D120: 24 | E120: 1
A121: A1100004042510 | B121: 612151 | C121: KLG | D121: 24 | E121: 2
A122: A1100005015510 | B122: 612134 | C122: KLG | D122: 60 | E122: 1
A123: A1100005040010 | B123: 612091 | C123: KLG | D123: 24 | E123: 1
... A240: A1120008013010 | B240: 150374 | C240: BTL | D240: 48 | E240: 2
A241: A1120008013010 | B241: 150363 | C241: BTL | D241: 48
A242: A1120008013011 | B242: 150976 | C242: BTL | D242: 48 | E242: 1
A243: A1120008013510 | B243: 150191 | C243: BTL | D243: 48 | E243: 1
A244: A1120008013510 | B244: 150234 | C244: BTL | D244: 48 | E244: 2
A245: A1120008027010 | B245: 150192 | C245: BTL | D245: 24 | E245: 1
A246: A1120008027010 | B246: 150235 | C246: BTL | D246: 24 | E246: 2
A247: A1120008027010 | B247: 150350 | C247: BTL | D247: 24 | E247: 3
A248: A1120008027010 | B248: 150343 | C248: BTL | D248: 24 | E248: 4
A249: A1120008033510 | B249: 150081 | C249: BTL | D249: 24 | E249: 1
A250: A1120008033510 | B250: 150172 | C250: BTL | D250: 24 | E250: 2
A251: A1120008033510 | B251: 150226 | C251: BTL | D251: 24 | E251: 3
A252: A1120008033510 | B252: 150341 | C252: BTL | D252: 24 | E252: 4
A253: A1120008038010 | B253: 150178 | C253: PCH | D253: 12 | E253: 1
... A299: A1092007042510 | B299: 400154 | C299: BTL | D299: 12 | E299: 3
A300: A1011000060011 | B300: (blank) | C300: PCH | D300: (blank) | E300: 1
A301: A1120006027011 | B301: 150984 | C301: BTL | D301: 24 | E301: 1
A302: A1150001000011B | B302: 900044 | C302: PCS | D302: 1 | E302: 1
A303: A1120006000810N | B303: 150204 | C303: PCSX22 | D303: 21 | E303: 2
A304: A1120006000810N | B304: 150326 | C304: PCSX22 | D304: 21 | E304: 3
A305: A1120006000810N | B305: 150409 | C305: PCSX22 | D305: 21 | E305: 1

Sheet Fix Mapping
A1: KODE BARANG | B1: NAMA BARANG | C1: ISI/CTN | D1: SATUAN | E1: NAMA KELOMPOK | F1: Harga Beli Pcs (-PPN) | G1: Harga Beli Krt (- PPN) | H1: Harga Beli Pcs (+PPN) | I1: Harga Beli Krt (+PPN) | J1: Harga Jual Pcs GT (-PPN) | K1: Harga Jual Krt GT (- PPN) | L1: Harga Jual Pcs GT (+PPN | M1: Harga Jual Krt GT (+PPN) | N1: Harga Jual Pcs MT (-PPN) | O1: Harga Jual Krt MT (- PPN) | P1: Harga Jual Pcs MT (+PPN) | Q1: Harga Jual Krt MT (+PPN) | R1: NAMA PRINCIPLE | S1: PCPL KODE 1 | T1: PCPL KODE 2 | U1: PCPL KODE 3 | V1: PCPL KODE 4 | W1: PCPL KODE 5
A2: A1011000006210 | B2: ABC KECAP MANIS 62 GR X 48 PCH | C2: 48 | D2: PCH | E2: KECAP MANIS | F2: 1354.9536 | G2: 65037.773 | H2: 1503.9985 | I2: 72191.928 | J2: 1441.44 | K2: 69189.12 | L2: 1599.9984 | M2: 76799.923 | N2: 1556.76 | O2: 74724.48 | P2: 1728.0036 | Q2: 82944.173 | R2: PT. HEINZ ABC INDONESIA | S2: =IFERROR(VLOOKUP(CONCATENATE(Fix_Mapping[[#This Row],[KODE BARANG]],1),'Form Fix'!$A$6:$F$1063,4,0),0) -> 100189 | T2: =IFERROR(VLOOKUP(CONCATENATE(Fix_Mapping[[#This Row],[KODE BARANG]],2),'Form Fix'!$A$6:$F$1063,4,0),0) -> 100222 | U2: =IFERROR(VLOOKUP(CONCATENATE(Fix_Mapping[[#This Row],[KODE BARANG]],3),'Form Fix'!$A$6:$F$1063,4,0),0) -> 100240 | V2: =IFERROR(VLOOKUP(CONCATENATE(Fix_Mapping[[#This Row],[KODE BARANG]],4),'Form Fix'!$A$6:$F$1063,4,0),0) -> 0 | W2: =IFERROR(VLOOKUP(CONCATENATE(Fix_Mapping[[#This Row],[KODE BARANG]],5),'Form Fix'!$A$6:$F$1063,4,0),0) -> 0
A3: A1011000006211 | B3: ABC KECAP MANIS 62 GR X 48 PCH B5G1 | C3: 48 | D3: PCH | E3: KECAP MANIS | F3: 1129.128 | G3: 54198.144 | H3: 1253.3321 | I3: 60159.94 | J3: 1201.2 | K3: 57657.6 | L3: 1333.332 | M3: 63999.936 | N3: 1297.3 | O3: 62270.4 | P3: 1440.003 | Q3: 69120.144 | R3: PT. HEINZ ABC INDONESIA | S3: =IFERROR(VLOOKUP(CONCATENATE(Fix_Mapping[[#This Row],[KODE BARANG]],1),'Form Fix'!$A$6:$F$1063,4,0),0) -> 100986 | T3: =IFERROR(VLOOKUP(CONCATENATE(Fix_Mapping[[#This Row],[KODE BARANG]],2),'Form Fix'!$A$6:$F$1063,4,0),0) -> 0 | U3: =IFERROR(VLOOKUP(CONCATENATE(Fix_Mapping[[#This Row],[KODE BARANG]],3),'Form Fix'!$A$6:$F$1063,4,0),0) -> 0 | V3: =IFERROR(VLOOKUP(CONCATENATE(Fix_Mapping[[#This Row],[KODE BARANG]],4),'Form Fix'!$A$6:$F$1063,4,0),0) -> 0 | W3: =IFERROR(VLOOKUP(CONCATENATE(Fix_Mapping[[#This Row],[KODE BARANG]],5),'Form Fix'!$A$6:$F$1063,4,0),0) -> 0
A4: A1011000008010 | B4: ABC KECAP MANIS 80 ML X 48 PCH | C4: 48 | D4: PCH | E4: KECAP MANIS | F4: 1990.0928 | G4: 95524.454 | H4: 2209.003 | I4: 106032.14 | J4: 2117.12 | K4: 101621.76 | L4: 2350.0032 | M4: 112800.15 | N4: 2286.4865 | O4: 109751.35 | P4: 2538 | Q4: 121824 | R4: PT. HEINZ ABC INDONESIA | S4: =IFERROR(VLOOKUP(CONCATENATE(Fix_Mapping[[#This Row],[KODE BARANG]],1),'Form Fix'!$A$6:$F$1063,4,0),0) -> 100179 | T4: =IFERROR(VLOOKUP(CONCATENATE(Fix_Mapping[[#This Row],[KODE BARANG]],2),'Form Fix'!$A$6:$F$1063,4,0),0) -> 0 | U4: =IFERROR(VLOOKUP(CONCATENATE(Fix_Mapping[[#This Row],[KODE BARANG]],3),'Form Fix'!$A$6:$F$1063,4,0),0) -> 0 | V4: =IFERROR(VLOOKUP(CONCATENATE(Fix_Mapping[[#This Row],[KODE BARANG]],4),'Form Fix'!$A$6:$F$1063,4,0),0) -> 0 | W4: =IFERROR(VLOOKUP(CONCATENATE(Fix_Mapping[[#This Row],[KODE BARANG]],5),'Form Fix'!$A$6:$F$1063,4,0),0) -> 0
A5: A1011000013010 | B5: ABC KECAP MANIS 135 ML X 48 BTL | C5: 48 | D5: BTL | E5: KECAP MANIS | F5: 6382.6 | G5: 306364.8 | H5: 7084.686 | I5: 340064.93 | J5: 6790 | K5: 325920 | L5: 7536.9 | M5: 361771.2 | N5: 0 | O5: 0 | P5: 0 | Q5: 0 | R5: PT. HEINZ ABC INDONESIA | S5: =IFERROR(VLOOKUP(CONCATENATE(Fix_Mapping[[#This Row],[KODE BARANG]],1),'Form Fix'!$A$6:$F$1063,4,0),0) -> 100234 | T5: =IFERROR(VLOOKUP(CONCATENATE(Fix_Mapping[[#This Row],[KODE BARANG]],2),'Form Fix'!$A$6:$F$1063,4,0),0) -> 0 | U5: =IFERROR(VLOOKUP(CONCATENATE(Fix_Mapping[[#This Row],[KODE BARANG]],3),'Form Fix'!$A$6:$F$1063,4,0),0) -> 0 | V5: =IFERROR(VLOOKUP(CONCATENATE(Fix_Mapping[[#This Row],[KODE BARANG]],4),'Form Fix'!$A$6:$F$1063,4,0),0) -> 0 | W5: =IFERROR(VLOOKUP(CONCATENATE(Fix_Mapping[[#This Row],[KODE BARANG]],5),'Form Fix'!$A$6:$F$1063,4,0),0) -> 0
A6: A1011000013510 | B6: ABC KECAP MANIS 135 ML X 48 BTL | C6: 48 | D6: BTL | E6: KECAP MANIS | F6: 7181.2616 | G6: 344700.56 | H6: 7971.2004 | I6: 382617.62 | J6: 7639.64 | K6: 366702.72 | L6: 8480.0004 | M6: 407040.02 | N6: 8250.81 | O6: 396038.88 | P6: 9158.3991 | Q6: 439603.16 | R6: PT. HEINZ ABC INDONESIA | S6: =IFERROR(VLOOKUP(CONCATENATE(Fix_Mapping[[#This Row],[KODE BARANG]],1),'Form Fix'!$A$6:$F$1063,4,0),0) -> 100161 | T6: =IFERROR(VLOOKUP(CONCATENATE(Fix_Mapping[[#This Row],[KODE BARANG]],2),'Form Fix'!$A$6:$F$1063,4,0),0) -> 0 | U6: =IFERROR(VLOOKUP(CONCATENATE(Fix_Mapping[[#This Row],[KODE BARANG]],3),'Form Fix'!$A$6:$F$1063,4,0),0) -> 0 | V6: =IFERROR(VLOOKUP(CONCATENATE(Fix_Mapping[[#This Row],[KODE BARANG]],4),'Form Fix'!$A$6:$F$1063,4,0),0) -> 0 | W6: =IFERROR(VLOOKUP(CONCATENATE(Fix_Mapping[[#This Row],[KODE BARANG]],5),'Form Fix'!$A$6:$F$1063,4,0),0) -> 0
A7: A1011000025010 | B7: ABC KECAP MANIS 250 GR X 24 PCH | C7: 24 | D7: PCH | E7: KECAP MANIS | F7: 6117.285 | G7: 146814.84 | H7: 6790.1864 | I7: 162964.47 | J7: 6507.75 | K7: 156186 | L7: 7223.6025 | M7: 173366.46 | N7: 7028.37 | O7: 168680.88 | P7: 7801.4907 | Q7: 187235.78 | R7: PT. HEINZ ABC INDONESIA | S7: =IFERROR(VLOOKUP(CONCATENATE(Fix_Mapping[[#This Row],[KODE BARANG]],1),'Form Fix'!$A$6:$F$1063,4,0),0) -> 100220 | T7: =IFERROR(VLOOKUP(CONCATENATE(Fix_Mapping[[#This Row],[KODE BARANG]],2),'Form Fix'!$A$6:$F$1063,4,0),0) -> 100238 | U7: =IFERROR(VLOOKUP(CONCATENATE(Fix_Mapping[[#This Row],[KODE BARANG]],3),'Form Fix'!$A$6:$F$1063,4,0),0) -> 0 | V7: =IFERROR(VLOOKUP(CONCATENATE(Fix_Mapping[[#This Row],[KODE BARANG]],4),'Form Fix'!$A$6:$F$1063,4,0),0) -> 0 | W7: =IFERROR(VLOOKUP(CONCATENATE(Fix_Mapping[[#This Row],[KODE BARANG]],5),'Form Fix'!$A$6:$F$1063,4,0),0) -> 0
A8: A1011000025011 | B8: ABC KECAP MANIS 250 GR X 24 PCH BANDED | C8: 24 | D8: PCH | E8: KECAP MANIS | F8: 6117.285 | G8: 146814.84 | H8: 6790.1864 | I8: 162964.47 | J8: 6507.75 | K8: 156186 | L8: 7223.6025 | M8: 173366.46 | N8: 7028.37 | O8: 168680.88 | P8: 7801.4907 | Q8: 187235.78 | R8: PT. HEINZ ABC INDONESIA | S8: =IFERROR(VLOOKUP(CONCATENATE(Fix_Mapping[[#This Row],[KODE BARANG]],1),'Form Fix'!$A$6:$F$1063,4,0),0) -> 100992 | T8: =IFERROR(VLOOKUP(CONCATENATE(Fix_Mapping[[#This Row],[KODE BARANG]],2),'Form Fix'!$A$6:$F$1063,4,0),0) -> 0 | U8: =IFERROR(VLOOKUP(CONCATENATE(Fix_Mapping[[#This Row],[KODE BARANG]],3),'Form Fix'!$A$6:$F$1063,4,0),0) -> 0 | V8: =IFERROR(VLOOKUP(CONCATENATE(Fix_Mapping[[#This Row],[KODE BARANG]],4),'Form Fix'!$A$6:$F$1063,4,0),0) -> 0 | W8: =IFERROR(VLOOKUP(CONCATENATE(Fix_Mapping[[#This Row],[KODE BARANG]],5),'Form Fix'!$A$6:$F$1063,4,0),0) -> 0
A9: A1011000027520 | B9: ABC KECAP MANIS 275 ML X 24 BTL | C9: 24 | D9: BTL | E9: KECAP MANIS | F9: 15649.731 | G9: 375593.54 | H9: 17371.201 | I9: 416908.83 | J9: 16648.65 | K9: 399567.6 | L9: 18480.002 | M9: 443520.04 | N9: 17980.54 | O9: 431532.96 | P9: 19958.399 | Q9: 479001.59 | R9: PT. HEINZ ABC INDONESIA | S9: =IFERROR(VLOOKUP(CONCATENATE(Fix_Mapping[[#This Row],[KODE BARANG]],1),'Form Fix'!$A$6:$F$1063,4,0),0) -> 100162 | T9: =IFERROR(VLOOKUP(CONCATENATE(Fix_Mapping[[#This Row],[KODE BARANG]],2),'Form Fix'!$A$6:$F$1063,4,0),0) -> 100236 | U9: =IFERROR(VLOOKUP(CONCATENATE(Fix_Mapping[[#This Row],[KODE BARANG]],3),'Form Fix'!$A$6:$F$1063,4,0),0) -> 0 | V9: =IFERROR(VLOOKUP(CONCATENATE(Fix_Mapping[[#This Row],[KODE BARANG]],4),'Form Fix'!$A$6:$F$1063,4,0),0) -> 0 | W9: =IFERROR(VLOOKUP(CONCATENATE(Fix_Mapping[[#This Row],[KODE BARANG]],5),'Form Fix'!$A$6:$F$1063,4,0),0) -> 0
A10: A1011000030010 | B10: ABC KECAP MANIS 300 GR X 24 PCH | C10: 24 | D10: PCH | E10: KECAP MANIS | F10: 8383.7848 | G10: 201210.84 | H10: 9306.0011 | I10: 223344.03 | J10: 8918.92 | K10: 214054.08 | L10: 9900.0012 | M10: 237600.03 | N10: 9632.43 | O10: 231178.32 | P10: 10691.997 | Q10: 256607.94 | R10: PT. HEINZ ABC INDONESIA | S10: =IFERROR(VLOOKUP(CONCATENATE(Fix_Mapping[[#This Row],[KODE BARANG]],1),'Form Fix'!$A$6:$F$1063,4,0),0) -> 100158 | T10: =IFERROR(VLOOKUP(CONCATENATE(Fix_Mapping[[#This Row],[KODE BARANG]],2),'Form Fix'!$A$6:$F$1063,4,0),0) -> 100172 | U10: =IFERROR(VLOOKUP(CONCATENATE(Fix_Mapping[[#This Row],[KODE BARANG]],3),'Form Fix'!$A$6:$F$1063,4,0),0) -> 0 | V10: =IFERROR(VLOOKUP(CONCATENATE(Fix_Mapping[[#This Row],[KODE BARANG]],4),'Form Fix'!$A$6:$F$1063,4,0),0) -> 0 | W10: =IFERROR(VLOOKUP(CONCATENATE(Fix_Mapping[[#This Row],[KODE BARANG]],5),'Form Fix'!$A$6:$F$1063,4,0),0) -> 0
A11: A1011000030012 | B11: ABC KECAP MANIS 600 GR X 12 PCH BANDED | C11: 12 | D11: PCH | E11: KECAP MANIS | F11: 16126.875 | G11: 193522.5 | H11: 17900.831 | I11: 214809.98 | J11: 17156.25 | K11: 205875 | L11: 19043.438 | M11: 228521.25 | N11: 0 | O11: 0 | P11: 0 | Q11: 0 | R11: PT. HEINZ ABC INDONESIA | S11: =IFERROR(VLOOKUP(CONCATENATE(Fix_Mapping[[#This Row],[KODE BARANG]],1),'Form Fix'!$A$6:$F$1063,4,0),0) -> 100991 | T11: =IFERROR(VLOOKUP(CONCATENATE(Fix_Mapping[[#This Row],[KODE BARANG]],2),'Form Fix'!$A$6:$F$1063,4,0),0) -> 109002 | U11: =IFERROR(VLOOKUP(CONCATENATE(Fix_Mapping[[#This Row],[KODE BARANG]],3),'Form Fix'!$A$6:$F$1063,4,0),0) -> 109001 | V11: =IFERROR(VLOOKUP(CONCATENATE(Fix_Mapping[[#This Row],[KODE BARANG]],4),'Form Fix'!$A$6:$F$1063,4,0),0) -> 0 | W11: =IFERROR(VLOOKUP(CONCATENATE(Fix_Mapping[[#This Row],[KODE BARANG]],5),'Form Fix'!$A$6:$F$1063,4,0),0) -> 0
A12: A1011000060010 | B12: ABC KECAP MANIS 600 GR X 12 PCH | C12: 12 | D12: PCH | E12: KECAP MANIS | F12: 16126.922 | G12: 193523.06 | H12: 17900.883 | I12: 214810.6 | J12: 17156.3 | K12: 205875.6 | L12: 19043.493 | M12: 228521.92 | N12: 18528.804 | O12: 222345.65 | P12: 20566.972 | Q12: 246803.67 | R12: PT. HEINZ ABC INDONESIA | S12: =IFERROR(VLOOKUP(CONCATENATE(Fix_Mapping[[#This Row],[KODE BARANG]],1),'Form Fix'!$A$6:$F$1063,4,0),0) -> 100225 | T12: =IFERROR(VLOOKUP(CONCATENATE(Fix_Mapping[[#This Row],[KODE BARANG]],2),'Form Fix'!$A$6:$F$1063,4,0),0) -> 100242 | U12: =IFERROR(VLOOKUP(CONCATENATE(Fix_Mapping[[#This Row],[KODE BARANG]],3),'Form Fix'!$A$6:$F$1063,4,0),0) -> 0 | V12: =IFERROR(VLOOKUP(CONCATENATE(Fix_Mapping[[#This Row],[KODE BARANG]],4),'Form Fix'!$A$6:$F$1063,4,0),0) -> 0 | W12: =IFERROR(VLOOKUP(CONCATENATE(Fix_Mapping[[#This Row],[KODE BARANG]],5),'Form Fix'!$A$6:$F$1063,4,0),0) -> 0
A13: A1011000060020 | B13: ABC KECAP MANIS 600 ML X 12 BTL | C13: 12 | D13: BTL | E13: KECAP MANIS | F13: 23525.408 | G13: 282304.9 | H13: 26113.203 | I13: 313358.44 | J13: 25027.03 | K13: 300324.36 | L13: 27780.003 | M13: 333360.04 | N13: 27029.19 | O13: 324350.28 | P13: 30002.401 | Q13: 360028.81 | R13: PT. HEINZ ABC INDONESIA | S13: =IFERROR(VLOOKUP(CONCATENATE(Fix_Mapping[[#This Row],[KODE BARANG]],1),'Form Fix'!$A$6:$F$1063,4,0),0) -> 100163 | T13: =IFERROR(VLOOKUP(CONCATENATE(Fix_Mapping[[#This Row],[KODE BARANG]],2),'Form Fix'!$A$6:$F$1063,4,0),0) -> 100226 | U13: =IFERROR(VLOOKUP(CONCATENATE(Fix_Mapping[[#This Row],[KODE BARANG]],3),'Form Fix'!$A$6:$F$1063,4,0),0) -> 0 | V13: =IFERROR(VLOOKUP(CONCATENATE(Fix_Mapping[[#This Row],[KODE BARANG]],4),'Form Fix'!$A$6:$F$1063,4,0),0) -> 0 | W13: =IFERROR(VLOOKUP(CONCATENATE(Fix_Mapping[[#This Row],[KODE BARANG]],5),'Form Fix'!$A$6:$F$1063,4,0),0) -> 0
... A44: A1020004019510 | B44: ABC SAUCE KCP INGGRIS 195 ML X 24 BTL | C44: 24 | D44: BTL | E44: SAUCE | F44: 10990.378 | G44: 263769.08 | H44: 12199.32 | I44: 292783.68 | J44: 11691.892 | K44: 280605.41 | L44: 12978 | M44: 311472 | N44: 12627.243 | O44: 303053.84 | P44: 14016.24 | Q44: 336389.76 | R44: PT. HEINZ ABC INDONESIA | S44: =IFERROR(VLOOKUP(CONCATENATE(Fix_Mapping[[#This Row],[KODE BARANG]],1),'Form Fix'!$A$6:$F$1063,4,0),0) -> 120028 | T44: =IFERROR(VLOOKUP(CONCATENATE(Fix_Mapping[[#This Row],[KODE BARANG]],2),'Form Fix'!$A$6:$F$1063,4,0),0) -> 120043 | U44: =IFERROR(VLOOKUP(CONCATENATE(Fix_Mapping[[#This Row],[KODE BARANG]],3),'Form Fix'!$A$6:$F$1063,4,0),0) -> 0 | V44: =IFERROR(VLOOKUP(CONCATENATE(Fix_Mapping[[#This Row],[KODE BARANG]],4),'Form Fix'!$A$6:$F$1063,4,0),0) -> 0 | W44: =IFERROR(VLOOKUP(CONCATENATE(Fix_Mapping[[#This Row],[KODE BARANG]],5),'Form Fix'!$A$6:$F$1063,4,0),0) -> 0
A45: A1020102001820 | B45: ABC SAUCE SACHET TIRAM 18GR X 12 PCSX10 | C45: 12 | D45: PCSX10 | E45: SAUCE | F45: 10824.57 | G45: 129894.84 | H45: 12015.273 | I45: 144183.27 | J45: 11515.5 | K45: 138186 | L45: 12782.205 | M45: 153386.46 | N45: 11515.5 | O45: 138186 | P45: 12782.205 | Q45: 153386.46 | S45: =IFERROR(VLOOKUP(CONCATENATE(Fix_Mapping[[#This Row],[KODE BARANG]],1),'Form Fix'!$A$6:$F$1063,4,0),0) -> 120045 | T45: =IFERROR(VLOOKUP(CONCATENATE(Fix_Mapping[[#This Row],[KODE BARANG]],2),'Form Fix'!$A$6:$F$1063,4,0),0) -> 0 | U45: =IFERROR(VLOOKUP(CONCATENATE(Fix_Mapping[[#This Row],[KODE BARANG]],3),'Form Fix'!$A$6:$F$1063,4,0),0) -> 0 | V45: =IFERROR(VLOOKUP(CONCATENATE(Fix_Mapping[[#This Row],[KODE BARANG]],4),'Form Fix'!$A$6:$F$1063,4,0),0) -> 0 | W45: =IFERROR(VLOOKUP(CONCATENATE(Fix_Mapping[[#This Row],[KODE BARANG]],5),'Form Fix'!$A$6:$F$1063,4,0),0) -> 0
A46: A1030100000310 | B46: ABC TERASI SACHET 3,8 GR X 36 PACK PCSX20 | C46: 36 | D46: PCSX20 | E46: TERASI | F46: 5922.5928 | G46: 213213.34 | H46: 6574.078 | I46: 236666.81 | J46: 6300.6306 | K46: 226822.7 | L46: 6993.7 | M46: 251773.2 | N46: 6615.6622 | O46: 238163.84 | P46: 7343.385 | Q46: 264361.86 | R46: PT. HEINZ ABC INDONESIA | S46: =IFERROR(VLOOKUP(CONCATENATE(Fix_Mapping[[#This Row],[KODE BARANG]],1),'Form Fix'!$A$6:$F$1063,4,0),0) -> 612087 | T46: =IFERROR(VLOOKUP(CONCATENATE(Fix_Mapping[[#This Row],[KODE BARANG]],2),'Form Fix'!$A$6:$F$1063,4,0),0) -> 612137 | U46: =IFERROR(VLOOKUP(CONCATENATE(Fix_Mapping[[#This Row],[KODE BARANG]],3),'Form Fix'!$A$6:$F$1063,4,0),0) -> 612147 | V46: =IFERROR(VLOOKUP(CONCATENATE(Fix_Mapping[[#This Row],[KODE BARANG]],4),'Form Fix'!$A$6:$F$1063,4,0),0) -> 0 | W46: =IFERROR(VLOOKUP(CONCATENATE(Fix_Mapping[[#This Row],[KODE BARANG]],5),'Form Fix'!$A$6:$F$1063,4,0),0) -> 0
A47: A1041001009010 | B47: ABC MR JUSSIE MILKY GRAPE 90 ML X 48 PCS | C47: 48 | D47: PCS | E47: MR JUSSIE MILKY | F47: 1351.9926 | G47: 64895.645 | H47: 1500.7118 | I47: 72034.166 | J47: 1438.29 | K47: 69037.92 | L47: 1596.5019 | M47: 76632.091 | N47: 1510.2 | O47: 72489.6 | P47: 1676.322 | Q47: 80463.456 | R47: PT. HEINZ ABC INDONESIA | S47: =IFERROR(VLOOKUP(CONCATENATE(Fix_Mapping[[#This Row],[KODE BARANG]],1),'Form Fix'!$A$6:$F$1063,4,0),0) -> 460166 | T47: =IFERROR(VLOOKUP(CONCATENATE(Fix_Mapping[[#This Row],[KODE BARANG]],2),'Form Fix'!$A$6:$F$1063,4,0),0) -> 0 | U47: =IFERROR(VLOOKUP(CONCATENATE(Fix_Mapping[[#This Row],[KODE BARANG]],3),'Form Fix'!$A$6:$F$1063,4,0),0) -> 0 | V47: =IFERROR(VLOOKUP(CONCATENATE(Fix_Mapping[[#This Row],[KODE BARANG]],4),'Form Fix'!$A$6:$F$1063,4,0),0) -> 0 | W47: =IFERROR(VLOOKUP(CONCATENATE(Fix_Mapping[[#This Row],[KODE BARANG]],5),'Form Fix'!$A$6:$F$1063,4,0),0) -> 0
A48: A1041002009010 | B48: ABC MR JUSSIE MILKY STRAWBERRY 90 ML X 48 PCS | C48: 48 | D48: PCS | E48: MR JUSSIE MILKY | F48: 1351.9926 | G48: 64895.645 | H48: 1500.7118 | I48: 72034.166 | J48: 1438.29 | K48: 69037.92 | L48: 1596.5019 | M48: 76632.091 | N48: 1510.2 | O48: 72489.6 | P48: 1676.322 | Q48: 80463.456 | R48: PT. HEINZ ABC INDONESIA | S48: =IFERROR(VLOOKUP(CONCATENATE(Fix_Mapping[[#This Row],[KODE BARANG]],1),'Form Fix'!$A$6:$F$1063,4,0),0) -> 460167 | T48: =IFERROR(VLOOKUP(CONCATENATE(Fix_Mapping[[#This Row],[KODE BARANG]],2),'Form Fix'!$A$6:$F$1063,4,0),0) -> 0 | U48: =IFERROR(VLOOKUP(CONCATENATE(Fix_Mapping[[#This Row],[KODE BARANG]],3),'Form Fix'!$A$6:$F$1063,4,0),0) -> 0 | V48: =IFERROR(VLOOKUP(CONCATENATE(Fix_Mapping[[#This Row],[KODE BARANG]],4),'Form Fix'!$A$6:$F$1063,4,0),0) -> 0 | W48: =IFERROR(VLOOKUP(CONCATENATE(Fix_Mapping[[#This Row],[KODE BARANG]],5),'Form Fix'!$A$6:$F$1063,4,0),0) -> 0
A49: A1041003009010 | B49: ABC MR JUSSIE MILKY MANGO 90 ML X 48 PCS | C49: 48 | D49: PCS | E49: MR JUSSIE MILKY | F49: 1351.9926 | G49: 64895.645 | H49: 1500.7118 | I49: 72034.166 | J49: 1438.29 | K49: 69037.92 | L49: 1596.5019 | M49: 76632.091 | N49: 1510.2 | O49: 72489.6 | P49: 1676.322 | Q49: 80463.456 | R49: PT. HEINZ ABC INDONESIA | S49: =IFERROR(VLOOKUP(CONCATENATE(Fix_Mapping[[#This Row],[KODE BARANG]],1),'Form Fix'!$A$6:$F$1063,4,0),0) -> 460168 | T49: =IFERROR(VLOOKUP(CONCATENATE(Fix_Mapping[[#This Row],[KODE BARANG]],2),'Form Fix'!$A$6:$F$1063,4,0),0) -> 0 | U49: =IFERROR(VLOOKUP(CONCATENATE(Fix_Mapping[[#This Row],[KODE BARANG]],3),'Form Fix'!$A$6:$F$1063,4,0),0) -> 0 | V49: =IFERROR(VLOOKUP(CONCATENATE(Fix_Mapping[[#This Row],[KODE BARANG]],4),'Form Fix'!$A$6:$F$1063,4,0),0) -> 0 | W49: =IFERROR(VLOOKUP(CONCATENATE(Fix_Mapping[[#This Row],[KODE BARANG]],5),'Form Fix'!$A$6:$F$1063,4,0),0) -> 0
A50: A1041004009010 | B50: ABC MR JUSSIE MILKY ORANGE 90 ML X 48 PCS | C50: 48 | D50: PCS | E50: MR JUSSIE MILKY | F50: 1351.9926 | G50: 64895.645 | H50: 1500.7118 | I50: 72034.166 | J50: 1438.29 | K50: 69037.92 | L50: 1596.5019 | M50: 76632.091 | N50: 1510.2 | O50: 72489.6 | P50: 1676.322 | Q50: 80463.456 | R50: PT. HEINZ ABC INDONESIA | S50: =IFERROR(VLOOKUP(CONCATENATE(Fix_Mapping[[#This Row],[KODE BARANG]],1),'Form Fix'!$A$6:$F$1063,4,0),0) -> 460169 | T50: =IFERROR(VLOOKUP(CONCATENATE(Fix_Mapping[[#This Row],[KODE BARANG]],2),'Form Fix'!$A$6:$F$1063,4,0),0) -> 0 | U50: =IFERROR(VLOOKUP(CONCATENATE(Fix_Mapping[[#This Row],[KODE BARANG]],3),'Form Fix'!$A$6:$F$1063,4,0),0) -> 0 | V50: =IFERROR(VLOOKUP(CONCATENATE(Fix_Mapping[[#This Row],[KODE BARANG]],4),'Form Fix'!$A$6:$F$1063,4,0),0) -> 0 | W50: =IFERROR(VLOOKUP(CONCATENATE(Fix_Mapping[[#This Row],[KODE BARANG]],5),'Form Fix'!$A$6:$F$1063,4,0),0) -> 0
A51: A1041005009010 | B51: ABC MR JUSSIE MILKY COKLAT 90 ML X 48 PCS | C51: 48 | D51: PCS | E51: MR JUSSIE MILKY | F51: 1351.9926 | G51: 64895.645 | H51: 1500.7118 | I51: 72034.166 | J51: 1438.29 | K51: 69037.92 | L51: 1596.5019 | M51: 76632.091 | N51: 1510.2 | O51: 72489.6 | P51: 1676.322 | Q51: 80463.456 | R51: PT. HEINZ ABC INDONESIA | S51: =IFERROR(VLOOKUP(CONCATENATE(Fix_Mapping[[#This Row],[KODE BARANG]],1),'Form Fix'!$A$6:$F$1063,4,0),0) -> 460172 | T51: =IFERROR(VLOOKUP(CONCATENATE(Fix_Mapping[[#This Row],[KODE BARANG]],2),'Form Fix'!$A$6:$F$1063,4,0),0) -> 0 | U51: =IFERROR(VLOOKUP(CONCATENATE(Fix_Mapping[[#This Row],[KODE BARANG]],3),'Form Fix'!$A$6:$F$1063,4,0),0) -> 0 | V51: =IFERROR(VLOOKUP(CONCATENATE(Fix_Mapping[[#This Row],[KODE BARANG]],4),'Form Fix'!$A$6:$F$1063,4,0),0) -> 0 | W51: =IFERROR(VLOOKUP(CONCATENATE(Fix_Mapping[[#This Row],[KODE BARANG]],5),'Form Fix'!$A$6:$F$1063,4,0),0) -> 0
A52: A1042001009010 | B52: ABC MR JUSSIE FRUITY GUAVA 90 ML X 48 PCS | C52: 48 | D52: PCS | E52: MR JUSSIE FRUITY | F52: 1351.9926 | G52: 64895.645 | H52: 1500.7118 | I52: 72034.166 | J52: 1438.29 | K52: 69037.92 | L52: 1596.5019 | M52: 76632.091 | N52: 1510.2 | O52: 72489.6 | P52: 1676.322 | Q52: 80463.456 | R52: PT. HEINZ ABC INDONESIA | S52: =IFERROR(VLOOKUP(CONCATENATE(Fix_Mapping[[#This Row],[KODE BARANG]],1),'Form Fix'!$A$6:$F$1063,4,0),0) -> 460170 | T52: =IFERROR(VLOOKUP(CONCATENATE(Fix_Mapping[[#This Row],[KODE BARANG]],2),'Form Fix'!$A$6:$F$1063,4,0),0) -> 0 | U52: =IFERROR(VLOOKUP(CONCATENATE(Fix_Mapping[[#This Row],[KODE BARANG]],3),'Form Fix'!$A$6:$F$1063,4,0),0) -> 0 | V52: =IFERROR(VLOOKUP(CONCATENATE(Fix_Mapping[[#This Row],[KODE BARANG]],4),'Form Fix'!$A$6:$F$1063,4,0),0) -> 0 | W52: =IFERROR(VLOOKUP(CONCATENATE(Fix_Mapping[[#This Row],[KODE BARANG]],5),'Form Fix'!$A$6:$F$1063,4,0),0) -> 0
A53: A1042004009010 | B53: ABC MR JUSSIE FRUITY ORANGE 90 ML X 48 PCS | C53: 48 | D53: PCS | E53: MR JUSSIE FRUITY | F53: 1351.9926 | G53: 64895.645 | H53: 1500.7118 | I53: 72034.166 | J53: 1438.29 | K53: 69037.92 | L53: 1596.5019 | M53: 76632.091 | N53: 1510.2 | O53: 72489.6 | P53: 1676.322 | Q53: 80463.456 | R53: PT. HEINZ ABC INDONESIA | S53: =IFERROR(VLOOKUP(CONCATENATE(Fix_Mapping[[#This Row],[KODE BARANG]],1),'Form Fix'!$A$6:$F$1063,4,0),0) -> 460171 | T53: =IFERROR(VLOOKUP(CONCATENATE(Fix_Mapping[[#This Row],[KODE BARANG]],2),'Form Fix'!$A$6:$F$1063,4,0),0) -> 0 | U53: =IFERROR(VLOOKUP(CONCATENATE(Fix_Mapping[[#This Row],[KODE BARANG]],3),'Form Fix'!$A$6:$F$1063,4,0),0) -> 0 | V53: =IFERROR(VLOOKUP(CONCATENATE(Fix_Mapping[[#This Row],[KODE BARANG]],4),'Form Fix'!$A$6:$F$1063,4,0),0) -> 0 | W53: =IFERROR(VLOOKUP(CONCATENATE(Fix_Mapping[[#This Row],[KODE BARANG]],5),'Form Fix'!$A$6:$F$1063,4,0),0) -> 0
A54: A1050000010010 | B54: ABC KACANG HIJAU 100 ML X 48 PCS | C54: 48 | D54: PCS | E54: KACANG HIJAU | F54: 1422.7027 | G54: 68289.731 | H54: 1579.2 | I54: 75801.601 | J54: 1513.5135 | K54: 72648.65 | L54: 1680 | M54: 80640.001 | N54: 72648.65 | O54: 3487135.2 | P54: 80640.001 | Q54: 3870720.1 | S54: =IFERROR(VLOOKUP(CONCATENATE(Fix_Mapping[[#This Row],[KODE BARANG]],1),'Form Fix'!$A$6:$F$1063,4,0),0) -> 460197 | T54: =IFERROR(VLOOKUP(CONCATENATE(Fix_Mapping[[#This Row],[KODE BARANG]],2),'Form Fix'!$A$6:$F$1063,4,0),0) -> 0 | U54: =IFERROR(VLOOKUP(CONCATENATE(Fix_Mapping[[#This Row],[KODE BARANG]],3),'Form Fix'!$A$6:$F$1063,4,0),0) -> 0 | V54: =IFERROR(VLOOKUP(CONCATENATE(Fix_Mapping[[#This Row],[KODE BARANG]],4),'Form Fix'!$A$6:$F$1063,4,0),0) -> 0 | W54: =IFERROR(VLOOKUP(CONCATENATE(Fix_Mapping[[#This Row],[KODE BARANG]],5),'Form Fix'!$A$6:$F$1063,4,0),0) -> 0
A55: A1050000020010 | B55: ABC KACANG HIJAU 200 ML X 24 PCS | C55: 24 | D55: PCS | E55: KACANG HIJAU | F55: 2930.7696 | G55: 70338.47 | H55: 3253.1543 | I55: 78075.702 | J55: 3117.84 | K55: 74828.16 | L55: 3460.8024 | M55: 83059.258 | N55: 3273.7297 | O55: 78569.514 | P55: 3633.84 | Q55: 87212.16 | R55: PT. HEINZ ABC INDONESIA | S55: =IFERROR(VLOOKUP(CONCATENATE(Fix_Mapping[[#This Row],[KODE BARANG]],1),'Form Fix'!$A$6:$F$1063,4,0),0) -> 460056 | T55: =IFERROR(VLOOKUP(CONCATENATE(Fix_Mapping[[#This Row],[KODE BARANG]],2),'Form Fix'!$A$6:$F$1063,4,0),0) -> 460178 | U55: =IFERROR(VLOOKUP(CONCATENATE(Fix_Mapping[[#This Row],[KODE BARANG]],3),'Form Fix'!$A$6:$F$1063,4,0),0) -> 0 | V55: =IFERROR(VLOOKUP(CONCATENATE(Fix_Mapping[[#This Row],[KODE BARANG]],4),'Form Fix'!$A$6:$F$1063,4,0),0) -> 0 | W55: =IFERROR(VLOOKUP(CONCATENATE(Fix_Mapping[[#This Row],[KODE BARANG]],5),'Form Fix'!$A$6:$F$1063,4,0),0) -> 0
A56: A1050000025010 | B56: ABC KACANG HIJAU 250 ML X 24 PCS | C56: 24 | D56: PCS | E56: KACANG HIJAU | F56: 3446.6698 | G56: 82720.075 | H56: 3825.8035 | I56: 91819.283 | J56: 3666.67 | K56: 88000.08 | L56: 4070.0037 | M56: 97680.089 | N56: 3850 | O56: 92400 | P56: 4273.5 | Q56: 102564 | R56: PT. HEINZ ABC INDONESIA | S56: =IFERROR(VLOOKUP(CONCATENATE(Fix_Mapping[[#This Row],[KODE BARANG]],1),'Form Fix'!$A$6:$F$1063,4,0),0) -> 460179 | T56: =IFERROR(VLOOKUP(CONCATENATE(Fix_Mapping[[#This Row],[KODE BARANG]],2),'Form Fix'!$A$6:$F$1063,4,0),0) -> 0 | U56: =IFERROR(VLOOKUP(CONCATENATE(Fix_Mapping[[#This Row],[KODE BARANG]],3),'Form Fix'!$A$6:$F$1063,4,0),0) -> 0 | V56: =IFERROR(VLOOKUP(CONCATENATE(Fix_Mapping[[#This Row],[KODE BARANG]],4),'Form Fix'!$A$6:$F$1063,4,0),0) -> 0 | W56: =IFERROR(VLOOKUP(CONCATENATE(Fix_Mapping[[#This Row],[KODE BARANG]],5),'Form Fix'!$A$6:$F$1063,4,0),0) -> 0
A57: A1050000025011 | B57: ABC KACANG HIJAU 250 ML X 24 PCS EXTRA 50 ML | C57: 24 | D57: PCS | E57: KACANG HIJAU | F57: 2930.7696 | G57: 70338.47 | H57: 3253.1543 | I57: 78075.702 | J57: 3117.84 | K57: 74828.16 | L57: 3460.8024 | M57: 83059.258 | N57: 3117.84 | O57: 74828.16 | P57: 3460.8024 | Q57: 83059.258 | R57: PT. HEINZ ABC INDONESIA | S57: =IFERROR(VLOOKUP(CONCATENATE(Fix_Mapping[[#This Row],[KODE BARANG]],1),'Form Fix'!$A$6:$F$1063,4,0),0) -> 460918 | T57: =IFERROR(VLOOKUP(CONCATENATE(Fix_Mapping[[#This Row],[KODE BARANG]],2),'Form Fix'!$A$6:$F$1063,4,0),0) -> 0 | U57: =IFERROR(VLOOKUP(CONCATENATE(Fix_Mapping[[#This Row],[KODE BARANG]],3),'Form Fix'!$A$6:$F$1063,4,0),0) -> 0 | V57: =IFERROR(VLOOKUP(CONCATENATE(Fix_Mapping[[#This Row],[KODE BARANG]],4),'Form Fix'!$A$6:$F$1063,4,0),0) -> 0 | W57: =IFERROR(VLOOKUP(CONCATENATE(Fix_Mapping[[#This Row],[KODE BARANG]],5),'Form Fix'!$A$6:$F$1063,4,0),0) -> 0
A58: A1050000025020 | B58: ABC KACANG HIJAU 250 ML X 8 PACK PCSX3 | C58: 8 | D58: PCSX3 | E58: KACANG HIJAU | F58: 6893.3302 | G58: 55146.642 | H58: 7651.5965 | I58: 61212.772 | J58: 7333.33 | K58: 58666.64 | L58: 8139.9963 | M58: 65119.97 | N58: 7700 | O58: 61600 | P58: 8547 | Q58: 68376 | R58: PT. HEINZ ABC INDONESIA | S58: =IFERROR(VLOOKUP(CONCATENATE(Fix_Mapping[[#This Row],[KODE BARANG]],1),'Form Fix'!$A$6:$F$1063,4,0),0) -> 460917 | T58: =IFERROR(VLOOKUP(CONCATENATE(Fix_Mapping[[#This Row],[KODE BARANG]],2),'Form Fix'!$A$6:$F$1063,4,0),0) -> 460921 | U58: =IFERROR(VLOOKUP(CONCATENATE(Fix_Mapping[[#This Row],[KODE BARANG]],3),'Form Fix'!$A$6:$F$1063,4,0),0) -> 0 | V58: =IFERROR(VLOOKUP(CONCATENATE(Fix_Mapping[[#This Row],[KODE BARANG]],4),'Form Fix'!$A$6:$F$1063,4,0),0) -> 0 | W58: =IFERROR(VLOOKUP(CONCATENATE(Fix_Mapping[[#This Row],[KODE BARANG]],5),'Form Fix'!$A$6:$F$1063,4,0),0) -> 0
A59: A1061000020010 | B59: ABC SARI KEDELAI MILK 200 ML X 24 PCS | C59: 24 | D59: PCS | E59: SARI KEDELAI MILK | F59: 2752.2542 | G59: 66054.101 | H59: 3055.0022 | I59: 73320.052 | J59: 2927.93 | K59: 70270.32 | L59: 3250.0023 | M59: 78000.055 | N59: 1859.1173 | O59: 44618.815 | P59: 2063.6202 | Q59: 49526.885 | R59: PT. HEINZ ABC INDONESIA | S59: =IFERROR(VLOOKUP(CONCATENATE(Fix_Mapping[[#This Row],[KODE BARANG]],1),'Form Fix'!$A$6:$F$1063,4,0),0) -> 460183 | T59: =IFERROR(VLOOKUP(CONCATENATE(Fix_Mapping[[#This Row],[KODE BARANG]],2),'Form Fix'!$A$6:$F$1063,4,0),0) -> 460174 | U59: =IFERROR(VLOOKUP(CONCATENATE(Fix_Mapping[[#This Row],[KODE BARANG]],3),'Form Fix'!$A$6:$F$1063,4,0),0) -> 0 | V59: =IFERROR(VLOOKUP(CONCATENATE(Fix_Mapping[[#This Row],[KODE BARANG]],4),'Form Fix'!$A$6:$F$1063,4,0),0) -> 0 | W59: =IFERROR(VLOOKUP(CONCATENATE(Fix_Mapping[[#This Row],[KODE BARANG]],5),'Form Fix'!$A$6:$F$1063,4,0),0) -> 0
A60: A1061001020010 | B60: ABC SARI KEDELAI MILK COKLAT 200 ML X 24 PCS | C60: 24 | D60: PCS | E60: SARI KEDELAI MILK | F60: 3556.772 | G60: 85362.528 | H60: 3948.0169 | I60: 94752.406 | J60: 3783.8 | K60: 90811.2 | L60: 4200.018 | M60: 100800.43 | N60: 4086.5 | O60: 98076 | P60: 4536.015 | Q60: 108864.36 | R60: PT. HEINZ ABC INDONESIA | S60: =IFERROR(VLOOKUP(CONCATENATE(Fix_Mapping[[#This Row],[KODE BARANG]],1),'Form Fix'!$A$6:$F$1063,4,0),0) -> 460194 | T60: =IFERROR(VLOOKUP(CONCATENATE(Fix_Mapping[[#This Row],[KODE BARANG]],2),'Form Fix'!$A$6:$F$1063,4,0),0) -> 0 | U60: =IFERROR(VLOOKUP(CONCATENATE(Fix_Mapping[[#This Row],[KODE BARANG]],3),'Form Fix'!$A$6:$F$1063,4,0),0) -> 0 | V60: =IFERROR(VLOOKUP(CONCATENATE(Fix_Mapping[[#This Row],[KODE BARANG]],4),'Form Fix'!$A$6:$F$1063,4,0),0) -> 0 | W60: =IFERROR(VLOOKUP(CONCATENATE(Fix_Mapping[[#This Row],[KODE BARANG]],5),'Form Fix'!$A$6:$F$1063,4,0),0) -> 0
A61: A1061002020010 | B61: ABC SARI KEDELAI MILK STRAWBERRY 200 ML X 24 PCS | C61: 24 | D61: PCS | E61: SARI KEDELAI MILK | F61: 3556.772 | G61: 85362.528 | H61: 3948.0169 | I61: 94752.406 | J61: 3783.8 | K61: 90811.2 | L61: 4200.018 | M61: 100800.43 | N61: 4086.5 | O61: 98076 | P61: 4536.015 | Q61: 108864.36 | R61: PT. HEINZ ABC INDONESIA | S61: =IFERROR(VLOOKUP(CONCATENATE(Fix_Mapping[[#This Row],[KODE BARANG]],1),'Form Fix'!$A$6:$F$1063,4,0),0) -> 460195 | T61: =IFERROR(VLOOKUP(CONCATENATE(Fix_Mapping[[#This Row],[KODE BARANG]],2),'Form Fix'!$A$6:$F$1063,4,0),0) -> 0 | U61: =IFERROR(VLOOKUP(CONCATENATE(Fix_Mapping[[#This Row],[KODE BARANG]],3),'Form Fix'!$A$6:$F$1063,4,0),0) -> 0 | V61: =IFERROR(VLOOKUP(CONCATENATE(Fix_Mapping[[#This Row],[KODE BARANG]],4),'Form Fix'!$A$6:$F$1063,4,0),0) -> 0 | W61: =IFERROR(VLOOKUP(CONCATENATE(Fix_Mapping[[#This Row],[KODE BARANG]],5),'Form Fix'!$A$6:$F$1063,4,0),0) -> 0
A62: A1070001025010 | B62: ABC JUICE GUAVA 250 ML X 24 PCS | C62: 24 | D62: PCS | E62: JUICE | F62: 6140.6534 | G62: 147375.68 | H62: 6816.1253 | I62: 163587.01 | J62: 6532.61 | K62: 156782.64 | L62: 7251.1971 | M62: 174028.73 | N62: 7055.2216 | O62: 169325.32 | P62: 7831.296 | Q62: 187951.1 | R62: PT. HEINZ ABC INDONESIA | S62: =IFERROR(VLOOKUP(CONCATENATE(Fix_Mapping[[#This Row],[KODE BARANG]],1),'Form Fix'!$A$6:$F$1063,4,0),0) -> 460164 | T62: =IFERROR(VLOOKUP(CONCATENATE(Fix_Mapping[[#This Row],[KODE BARANG]],2),'Form Fix'!$A$6:$F$1063,4,0),0) -> 460190 | U62: =IFERROR(VLOOKUP(CONCATENATE(Fix_Mapping[[#This Row],[KODE BARANG]],3),'Form Fix'!$A$6:$F$1063,4,0),0) -> 0 | V62: =IFERROR(VLOOKUP(CONCATENATE(Fix_Mapping[[#This Row],[KODE BARANG]],4),'Form Fix'!$A$6:$F$1063,4,0),0) -> 0 | W62: =IFERROR(VLOOKUP(CONCATENATE(Fix_Mapping[[#This Row],[KODE BARANG]],5),'Form Fix'!$A$6:$F$1063,4,0),0) -> 0
A63: A1070001100110 | B63: ABC JUICE GUAVA 1 L X 12 PCS | C63: 12 | D63: PCS | E63: JUICE | F63: 20629.193 | G63: 247550.32 | H63: 22898.404 | I63: 274780.85 | J63: 21945.95 | K63: 263351.4 | L63: 24360.005 | M63: 292320.05 | N63: 23701.63 | O63: 284419.56 | P63: 26308.809 | Q63: 315705.71 | R63: PT. HEINZ ABC INDONESIA | S63: =IFERROR(VLOOKUP(CONCATENATE(Fix_Mapping[[#This Row],[KODE BARANG]],1),'Form Fix'!$A$6:$F$1063,4,0),0) -> 460165 | T63: =IFERROR(VLOOKUP(CONCATENATE(Fix_Mapping[[#This Row],[KODE BARANG]],2),'Form Fix'!$A$6:$F$1063,4,0),0) -> 460191 | U63: =IFERROR(VLOOKUP(CONCATENATE(Fix_Mapping[[#This Row],[KODE BARANG]],3),'Form Fix'!$A$6:$F$1063,4,0),0) -> 0 | V63: =IFERROR(VLOOKUP(CONCATENATE(Fix_Mapping[[#This Row],[KODE BARANG]],4),'Form Fix'!$A$6:$F$1063,4,0),0) -> 0 | W63: =IFERROR(VLOOKUP(CONCATENATE(Fix_Mapping[[#This Row],[KODE BARANG]],5),'Form Fix'!$A$6:$F$1063,4,0),0) -> 0
A64: A1070002025010 | B64: ABC JUICE ORANGE 250 ML X 24 PCS | C64: 24 | D64: PCS | E64: JUICE | F64: 6140.6534 | G64: 147375.68 | H64: 6816.1253 | I64: 163587.01 | J64: 6532.61 | K64: 156782.64 | L64: 7251.1971 | M64: 174028.73 | N64: 7055.2216 | O64: 169325.32 | P64: 7831.296 | Q64: 187951.1 | R64: PT. HEINZ ABC INDONESIA | S64: =IFERROR(VLOOKUP(CONCATENATE(Fix_Mapping[[#This Row],[KODE BARANG]],1),'Form Fix'!$A$6:$F$1063,4,0),0) -> 460061 | T64: =IFERROR(VLOOKUP(CONCATENATE(Fix_Mapping[[#This Row],[KODE BARANG]],2),'Form Fix'!$A$6:$F$1063,4,0),0) -> 460188 | U64: =IFERROR(VLOOKUP(CONCATENATE(Fix_Mapping[[#This Row],[KODE BARANG]],3),'Form Fix'!$A$6:$F$1063,4,0),0) -> 0 | V64: =IFERROR(VLOOKUP(CONCATENATE(Fix_Mapping[[#This Row],[KODE BARANG]],4),'Form Fix'!$A$6:$F$1063,4,0),0) -> 0 | W64: =IFERROR(VLOOKUP(CONCATENATE(Fix_Mapping[[#This Row],[KODE BARANG]],5),'Form Fix'!$A$6:$F$1063,4,0),0) -> 0
A65: A1070002100110 | B65: ABC JUICE ORANGE 1 L X 12 PCS | C65: 12 | D65: PCS | E65: JUICE | F65: 20629.193 | G65: 247550.32 | H65: 22898.404 | I65: 274780.85 | J65: 21945.95 | K65: 263351.4 | L65: 24360.005 | M65: 292320.05 | N65: 23701.63 | O65: 284419.56 | P65: 26308.809 | Q65: 315705.71 | R65: PT. HEINZ ABC INDONESIA | S65: =IFERROR(VLOOKUP(CONCATENATE(Fix_Mapping[[#This Row],[KODE BARANG]],1),'Form Fix'!$A$6:$F$1063,4,0),0) -> 460189 | T65: =IFERROR(VLOOKUP(CONCATENATE(Fix_Mapping[[#This Row],[KODE BARANG]],2),'Form Fix'!$A$6:$F$1063,4,0),0) -> 0 | U65: =IFERROR(VLOOKUP(CONCATENATE(Fix_Mapping[[#This Row],[KODE BARANG]],3),'Form Fix'!$A$6:$F$1063,4,0),0) -> 0 | V65: =IFERROR(VLOOKUP(CONCATENATE(Fix_Mapping[[#This Row],[KODE BARANG]],4),'Form Fix'!$A$6:$F$1063,4,0),0) -> 0 | W65: =IFERROR(VLOOKUP(CONCATENATE(Fix_Mapping[[#This Row],[KODE BARANG]],5),'Form Fix'!$A$6:$F$1063,4,0),0) -> 0
A66: A1070003025010 | B66: ABC JUICE APPLE 250 ML X 24 PCS | C66: 24 | D66: PCS | E66: JUICE | F66: 6140.6534 | G66: 147375.68 | H66: 6816.1253 | I66: 163587.01 | J66: 6532.61 | K66: 156782.64 | L66: 7251.1971 | M66: 174028.73 | N66: 7055.2216 | O66: 169325.32 | P66: 7831.296 | Q66: 187951.1 | R66: PT. HEINZ ABC INDONESIA | S66: =IFERROR(VLOOKUP(CONCATENATE(Fix_Mapping[[#This Row],[KODE BARANG]],1),'Form Fix'!$A$6:$F$1063,4,0),0) -> 460192 | T66: =IFERROR(VLOOKUP(CONCATENATE(Fix_Mapping[[#This Row],[KODE BARANG]],2),'Form Fix'!$A$6:$F$1063,4,0),0) -> 0 | U66: =IFERROR(VLOOKUP(CONCATENATE(Fix_Mapping[[#This Row],[KODE BARANG]],3),'Form Fix'!$A$6:$F$1063,4,0),0) -> 0 | V66: =IFERROR(VLOOKUP(CONCATENATE(Fix_Mapping[[#This Row],[KODE BARANG]],4),'Form Fix'!$A$6:$F$1063,4,0),0) -> 0 | W66: =IFERROR(VLOOKUP(CONCATENATE(Fix_Mapping[[#This Row],[KODE BARANG]],5),'Form Fix'!$A$6:$F$1063,4,0),0) -> 0
... A81: A1100001015511 | B81: ABC SARDINES TOMAT 155 GR X 30 KLG BANDED | C81: 30 | D81: KLG | E81: SARDINES | F81: 18291.892 | G81: 548756.77 | H81: 20304.001 | I81: 609120.02 | J81: 19459.46 | K81: 583783.8 | L81: 21600.001 | M81: 648000.02 | N81: 20432.43 | O81: 612972.9 | P81: 22679.997 | Q81: 680399.92 | R81: PT. HEINZ ABC INDONESIA | S81: =IFERROR(VLOOKUP(CONCATENATE(Fix_Mapping[[#This Row],[KODE BARANG]],1),'Form Fix'!$A$6:$F$1063,4,0),0) -> 612953 | T81: =IFERROR(VLOOKUP(CONCATENATE(Fix_Mapping[[#This Row],[KODE BARANG]],2),'Form Fix'!$A$6:$F$1063,4,0),0) -> 0 | U81: =IFERROR(VLOOKUP(CONCATENATE(Fix_Mapping[[#This Row],[KODE BARANG]],3),'Form Fix'!$A$6:$F$1063,4,0),0) -> 0 | V81: =IFERROR(VLOOKUP(CONCATENATE(Fix_Mapping[[#This Row],[KODE BARANG]],4),'Form Fix'!$A$6:$F$1063,4,0),0) -> 0 | W81: =IFERROR(VLOOKUP(CONCATENATE(Fix_Mapping[[#This Row],[KODE BARANG]],5),'Form Fix'!$A$6:$F$1063,4,0),0) -> 0
A82: A1100001015512 | B82: ABC SARDINES TOMAT 155 GR X 60 KLG PROMO | C82: 60 | D82: KLG | E82: SARDINES | F82: 7775.7477 | G82: 466544.86 | H82: 8631.08 | I82: 517864.8 | J82: 8272.0721 | K82: 496324.32 | L82: 9182 | M82: 550920 | N82: 0 | O82: 0 | P82: 0 | Q82: 0 | S82: =IFERROR(VLOOKUP(CONCATENATE(Fix_Mapping[[#This Row],[KODE BARANG]],1),'Form Fix'!$A$6:$F$1063,4,0),0) -> 612157 | T82: =IFERROR(VLOOKUP(CONCATENATE(Fix_Mapping[[#This Row],[KODE BARANG]],2),'Form Fix'!$A$6:$F$1063,4,0),0) -> 612961 | U82: =IFERROR(VLOOKUP(CONCATENATE(Fix_Mapping[[#This Row],[KODE BARANG]],3),'Form Fix'!$A$6:$F$1063,4,0),0) -> 0 | V82: =IFERROR(VLOOKUP(CONCATENATE(Fix_Mapping[[#This Row],[KODE BARANG]],4),'Form Fix'!$A$6:$F$1063,4,0),0) -> 0 | W82: =IFERROR(VLOOKUP(CONCATENATE(Fix_Mapping[[#This Row],[KODE BARANG]],5),'Form Fix'!$A$6:$F$1063,4,0),0) -> 0
A83: A1100001042510 | B83: ABC SARDINES TOMAT 425 GR X 24 KLG | C83: 24 | D83: KLG | E83: SARDINES | F83: 20705.408 | G83: 496929.8 | H83: 22983.003 | I83: 551592.07 | J83: 22027.03 | K83: 528648.72 | L83: 24450.003 | M83: 586800.08 | N83: 23128.38 | O83: 555081.12 | P83: 25672.502 | Q83: 616140.04 | R83: PT. HEINZ ABC INDONESIA | S83: =IFERROR(VLOOKUP(CONCATENATE(Fix_Mapping[[#This Row],[KODE BARANG]],1),'Form Fix'!$A$6:$F$1063,4,0),0) -> 612042 | T83: =IFERROR(VLOOKUP(CONCATENATE(Fix_Mapping[[#This Row],[KODE BARANG]],2),'Form Fix'!$A$6:$F$1063,4,0),0) -> 0 | U83: =IFERROR(VLOOKUP(CONCATENATE(Fix_Mapping[[#This Row],[KODE BARANG]],3),'Form Fix'!$A$6:$F$1063,4,0),0) -> 0 | V83: =IFERROR(VLOOKUP(CONCATENATE(Fix_Mapping[[#This Row],[KODE BARANG]],4),'Form Fix'!$A$6:$F$1063,4,0),0) -> 0 | W83: =IFERROR(VLOOKUP(CONCATENATE(Fix_Mapping[[#This Row],[KODE BARANG]],5),'Form Fix'!$A$6:$F$1063,4,0),0) -> 0
A84: A1100002015510 | B84: ABC SARDINES CHILI DW 155 GR X 60 KLG | C84: 60 | D84: KLG | E84: SARDINES | F84: 9145.9462 | G84: 548756.77 | H84: 10152 | I84: 609120.02 | J84: 9729.73 | K84: 583783.8 | L84: 10800 | M84: 648000.02 | N84: 10216.22 | O84: 612973.2 | P84: 11340.004 | Q84: 680400.25 | R84: PT. HEINZ ABC INDONESIA | S84: =IFERROR(VLOOKUP(CONCATENATE(Fix_Mapping[[#This Row],[KODE BARANG]],1),'Form Fix'!$A$6:$F$1063,4,0),0) -> 612046 | T84: =IFERROR(VLOOKUP(CONCATENATE(Fix_Mapping[[#This Row],[KODE BARANG]],2),'Form Fix'!$A$6:$F$1063,4,0),0) -> 0 | U84: =IFERROR(VLOOKUP(CONCATENATE(Fix_Mapping[[#This Row],[KODE BARANG]],3),'Form Fix'!$A$6:$F$1063,4,0),0) -> 0 | V84: =IFERROR(VLOOKUP(CONCATENATE(Fix_Mapping[[#This Row],[KODE BARANG]],4),'Form Fix'!$A$6:$F$1063,4,0),0) -> 0 | W84: =IFERROR(VLOOKUP(CONCATENATE(Fix_Mapping[[#This Row],[KODE BARANG]],5),'Form Fix'!$A$6:$F$1063,4,0),0) -> 0
A85: A1100002015512 | B85: ABC SARDINES CHILI DW 155 GR X 60 KLG PROMO | C85: 60 | D85: KLG | E85: SARDINES | F85: 7775.7477 | G85: 466544.86 | H85: 8631.08 | I85: 517864.8 | J85: 8272.0721 | K85: 496324.32 | L85: 9182 | M85: 550920 | N85: 0 | O85: 0 | P85: 0 | Q85: 0 | S85: =IFERROR(VLOOKUP(CONCATENATE(Fix_Mapping[[#This Row],[KODE BARANG]],1),'Form Fix'!$A$6:$F$1063,4,0),0) -> 612158 | T85: =IFERROR(VLOOKUP(CONCATENATE(Fix_Mapping[[#This Row],[KODE BARANG]],2),'Form Fix'!$A$6:$F$1063,4,0),0) -> 0 | U85: =IFERROR(VLOOKUP(CONCATENATE(Fix_Mapping[[#This Row],[KODE BARANG]],3),'Form Fix'!$A$6:$F$1063,4,0),0) -> 0 | V85: =IFERROR(VLOOKUP(CONCATENATE(Fix_Mapping[[#This Row],[KODE BARANG]],4),'Form Fix'!$A$6:$F$1063,4,0),0) -> 0 | W85: =IFERROR(VLOOKUP(CONCATENATE(Fix_Mapping[[#This Row],[KODE BARANG]],5),'Form Fix'!$A$6:$F$1063,4,0),0) -> 0
A86: A1100002042510 | B86: ABC SARDINES CHILI DW 425 GR X 24 KLG | C86: 24 | D86: KLG | E86: SARDINES | F86: 20705.408 | G86: 496929.8 | H86: 22983.003 | I86: 551592.07 | J86: 22027.03 | K86: 528648.72 | L86: 24450.003 | M86: 586800.08 | N86: 23128.38 | O86: 555081.12 | P86: 25672.502 | Q86: 616140.04 | R86: PT. HEINZ ABC INDONESIA | S86: =IFERROR(VLOOKUP(CONCATENATE(Fix_Mapping[[#This Row],[KODE BARANG]],1),'Form Fix'!$A$6:$F$1063,4,0),0) -> 612043 | T86: =IFERROR(VLOOKUP(CONCATENATE(Fix_Mapping[[#This Row],[KODE BARANG]],2),'Form Fix'!$A$6:$F$1063,4,0),0) -> 0 | U86: =IFERROR(VLOOKUP(CONCATENATE(Fix_Mapping[[#This Row],[KODE BARANG]],3),'Form Fix'!$A$6:$F$1063,4,0),0) -> 0 | V86: =IFERROR(VLOOKUP(CONCATENATE(Fix_Mapping[[#This Row],[KODE BARANG]],4),'Form Fix'!$A$6:$F$1063,4,0),0) -> 0 | W86: =IFERROR(VLOOKUP(CONCATENATE(Fix_Mapping[[#This Row],[KODE BARANG]],5),'Form Fix'!$A$6:$F$1063,4,0),0) -> 0
A87: A1100003030010 | B87: ABC SARDINES CHILI 300 GR X 24 KLG | C87: 24 | D87: KLG | E87: SARDINES | F87: 14386.399 | G87: 345273.58 | H87: 15968.903 | I87: 383253.67 | J87: 15304.68 | K87: 367312.32 | L87: 16988.195 | M87: 407716.68 | N87: 16069.911 | O87: 385677.86 | P87: 17837.601 | Q87: 428102.43 | R87: PT. HEINZ ABC INDONESIA | S87: =IFERROR(VLOOKUP(CONCATENATE(Fix_Mapping[[#This Row],[KODE BARANG]],1),'Form Fix'!$A$6:$F$1063,4,0),0) -> 612141 | T87: =IFERROR(VLOOKUP(CONCATENATE(Fix_Mapping[[#This Row],[KODE BARANG]],2),'Form Fix'!$A$6:$F$1063,4,0),0) -> 612148 | U87: =IFERROR(VLOOKUP(CONCATENATE(Fix_Mapping[[#This Row],[KODE BARANG]],3),'Form Fix'!$A$6:$F$1063,4,0),0) -> 612155 | V87: =IFERROR(VLOOKUP(CONCATENATE(Fix_Mapping[[#This Row],[KODE BARANG]],4),'Form Fix'!$A$6:$F$1063,4,0),0) -> 0 | W87: =IFERROR(VLOOKUP(CONCATENATE(Fix_Mapping[[#This Row],[KODE BARANG]],5),'Form Fix'!$A$6:$F$1063,4,0),0) -> 0
A88: A1100004015510 | B88: ABC SARDINES EXTRA PEDAS DW 155 GR X 60 KLG | C88: 60 | D88: KLG | E88: SARDINES | F88: 9145.9462 | G88: 548756.77 | H88: 10152 | I88: 609120.02 | J88: 9729.73 | K88: 583783.8 | L88: 10800 | M88: 648000.02 | N88: 10216.22 | O88: 612973.2 | P88: 11340.004 | Q88: 680400.25 | R88: PT. HEINZ ABC INDONESIA | S88: =IFERROR(VLOOKUP(CONCATENATE(Fix_Mapping[[#This Row],[KODE BARANG]],1),'Form Fix'!$A$6:$F$1063,4,0),0) -> 612047 | T88: =IFERROR(VLOOKUP(CONCATENATE(Fix_Mapping[[#This Row],[KODE BARANG]],2),'Form Fix'!$A$6:$F$1063,4,0),0) -> 612154 | U88: =IFERROR(VLOOKUP(CONCATENATE(Fix_Mapping[[#This Row],[KODE BARANG]],3),'Form Fix'!$A$6:$F$1063,4,0),0) -> 0 | V88: =IFERROR(VLOOKUP(CONCATENATE(Fix_Mapping[[#This Row],[KODE BARANG]],4),'Form Fix'!$A$6:$F$1063,4,0),0) -> 0 | W88: =IFERROR(VLOOKUP(CONCATENATE(Fix_Mapping[[#This Row],[KODE BARANG]],5),'Form Fix'!$A$6:$F$1063,4,0),0) -> 0
A89: A1100004015512 | B89: ABC SARDINES EXTRA PEDAS DW 155 GR X 60 KLG PROMO | C89: 60 | D89: KLG | E89: SARDINES | F89: 7775.774 | G89: 466546.44 | H89: 8631.1091 | I89: 517866.55 | J89: 8272.1 | K89: 496326 | L89: 9182.031 | M89: 550921.86 | N89: 0 | O89: 0 | P89: 0 | Q89: 0 | S89: =IFERROR(VLOOKUP(CONCATENATE(Fix_Mapping[[#This Row],[KODE BARANG]],1),'Form Fix'!$A$6:$F$1063,4,0),0) -> 612963 | T89: =IFERROR(VLOOKUP(CONCATENATE(Fix_Mapping[[#This Row],[KODE BARANG]],2),'Form Fix'!$A$6:$F$1063,4,0),0) -> 612159 | U89: =IFERROR(VLOOKUP(CONCATENATE(Fix_Mapping[[#This Row],[KODE BARANG]],3),'Form Fix'!$A$6:$F$1063,4,0),0) -> 0 | V89: =IFERROR(VLOOKUP(CONCATENATE(Fix_Mapping[[#This Row],[KODE BARANG]],4),'Form Fix'!$A$6:$F$1063,4,0),0) -> 0 | W89: =IFERROR(VLOOKUP(CONCATENATE(Fix_Mapping[[#This Row],[KODE BARANG]],5),'Form Fix'!$A$6:$F$1063,4,0),0) -> 0
A90: A1100004042510 | B90: ABC SARDINES EXTRA PEDAS DW 425 GR X 24 KLG | C90: 24 | D90: KLG | E90: SARDINES | F90: 20705.408 | G90: 496929.8 | H90: 22983.003 | I90: 551592.07 | J90: 22027.03 | K90: 528648.72 | L90: 24450.003 | M90: 586800.08 | N90: 23128.38 | O90: 555081.12 | P90: 25672.502 | Q90: 616140.04 | R90: PT. HEINZ ABC INDONESIA | S90: =IFERROR(VLOOKUP(CONCATENATE(Fix_Mapping[[#This Row],[KODE BARANG]],1),'Form Fix'!$A$6:$F$1063,4,0),0) -> 612044 | T90: =IFERROR(VLOOKUP(CONCATENATE(Fix_Mapping[[#This Row],[KODE BARANG]],2),'Form Fix'!$A$6:$F$1063,4,0),0) -> 612151 | U90: =IFERROR(VLOOKUP(CONCATENATE(Fix_Mapping[[#This Row],[KODE BARANG]],3),'Form Fix'!$A$6:$F$1063,4,0),0) -> 0 | V90: =IFERROR(VLOOKUP(CONCATENATE(Fix_Mapping[[#This Row],[KODE BARANG]],4),'Form Fix'!$A$6:$F$1063,4,0),0) -> 0 | W90: =IFERROR(VLOOKUP(CONCATENATE(Fix_Mapping[[#This Row],[KODE BARANG]],5),'Form Fix'!$A$6:$F$1063,4,0),0) -> 0
A91: A1100005015510 | B91: ABC SARDINES SARUNDENG 155 GR X 60 KLG | C91: 60 | D91: KLG | E91: SARDINES | F91: 9145.9462 | G91: 548756.77 | H91: 10152 | I91: 609120.02 | J91: 9729.73 | K91: 583783.8 | L91: 10800 | M91: 648000.02 | N91: 10216.22 | O91: 612973.2 | P91: 11340.004 | Q91: 680400.25 | R91: PT. HEINZ ABC INDONESIA | S91: =IFERROR(VLOOKUP(CONCATENATE(Fix_Mapping[[#This Row],[KODE BARANG]],1),'Form Fix'!$A$6:$F$1063,4,0),0) -> 612134 | T91: =IFERROR(VLOOKUP(CONCATENATE(Fix_Mapping[[#This Row],[KODE BARANG]],2),'Form Fix'!$A$6:$F$1063,4,0),0) -> 0 | U91: =IFERROR(VLOOKUP(CONCATENATE(Fix_Mapping[[#This Row],[KODE BARANG]],3),'Form Fix'!$A$6:$F$1063,4,0),0) -> 0 | V91: =IFERROR(VLOOKUP(CONCATENATE(Fix_Mapping[[#This Row],[KODE BARANG]],4),'Form Fix'!$A$6:$F$1063,4,0),0) -> 0 | W91: =IFERROR(VLOOKUP(CONCATENATE(Fix_Mapping[[#This Row],[KODE BARANG]],5),'Form Fix'!$A$6:$F$1063,4,0),0) -> 0
A92: A1100005015511 | B92: ABC SARDINES SARUNDENG 155 GR X 60 KLG BANDED | C92: 60 | D92: KLG | E92: SARDINES | F92: 9145.9462 | G92: 548756.77 | H92: 10152 | I92: 609120.02 | J92: 9729.73 | K92: 583783.8 | L92: 10800 | M92: 648000.02 | N92: 10216.22 | O92: 612973.2 | P92: 11340.004 | Q92: 680400.25 | R92: PT. HEINZ ABC INDONESIA | S92: =IFERROR(VLOOKUP(CONCATENATE(Fix_Mapping[[#This Row],[KODE BARANG]],1),'Form Fix'!$A$6:$F$1063,4,0),0) -> 612958 | T92: =IFERROR(VLOOKUP(CONCATENATE(Fix_Mapping[[#This Row],[KODE BARANG]],2),'Form Fix'!$A$6:$F$1063,4,0),0) -> 0 | U92: =IFERROR(VLOOKUP(CONCATENATE(Fix_Mapping[[#This Row],[KODE BARANG]],3),'Form Fix'!$A$6:$F$1063,4,0),0) -> 0 | V92: =IFERROR(VLOOKUP(CONCATENATE(Fix_Mapping[[#This Row],[KODE BARANG]],4),'Form Fix'!$A$6:$F$1063,4,0),0) -> 0 | W92: =IFERROR(VLOOKUP(CONCATENATE(Fix_Mapping[[#This Row],[KODE BARANG]],5),'Form Fix'!$A$6:$F$1063,4,0),0) -> 0
A93: A1100005040010 | B93: ABC SARDINES SARUNDENG 400 GR X 24 KLG | C93: 24 | D93: KLG | E93: SARDINES | F93: 20705.408 | G93: 496929.8 | H93: 22983.003 | I93: 551592.07 | J93: 22027.03 | K93: 528648.72 | L93: 24450.003 | M93: 586800.08 | N93: 23128.38 | O93: 555081.12 | P93: 25672.502 | Q93: 616140.04 | R93: PT. HEINZ ABC INDONESIA | S93: =IFERROR(VLOOKUP(CONCATENATE(Fix_Mapping[[#This Row],[KODE BARANG]],1),'Form Fix'!$A$6:$F$1063,4,0),0) -> 612091 | T93: =IFERROR(VLOOKUP(CONCATENATE(Fix_Mapping[[#This Row],[KODE BARANG]],2),'Form Fix'!$A$6:$F$1063,4,0),0) -> 0 | U93: =IFERROR(VLOOKUP(CONCATENATE(Fix_Mapping[[#This Row],[KODE BARANG]],3),'Form Fix'!$A$6:$F$1063,4,0),0) -> 0 | V93: =IFERROR(VLOOKUP(CONCATENATE(Fix_Mapping[[#This Row],[KODE BARANG]],4),'Form Fix'!$A$6:$F$1063,4,0),0) -> 0 | W93: =IFERROR(VLOOKUP(CONCATENATE(Fix_Mapping[[#This Row],[KODE BARANG]],5),'Form Fix'!$A$6:$F$1063,4,0),0) -> 0
A94: A1110000000810 | B94: ABC TOMAT 8 GR X 21 PACK PCSX22 | C94: 21 | D94: PCSX22 | E94: TOMAT | F94: 5137.5658 | G94: 107888.88 | H94: 5702.698 | I94: 119756.66 | J94: 5465.4955 | K94: 114775.41 | L94: 6066.7 | M94: 127400.7 | N94: 5902.7351 | O94: 123957.44 | P94: 6552.036 | Q94: 137592.76 | R94: PT. HEINZ ABC INDONESIA | S94: =IFERROR(VLOOKUP(CONCATENATE(Fix_Mapping[[#This Row],[KODE BARANG]],1),'Form Fix'!$A$6:$F$1063,4,0),0) -> 190034 | T94: =IFERROR(VLOOKUP(CONCATENATE(Fix_Mapping[[#This Row],[KODE BARANG]],2),'Form Fix'!$A$6:$F$1063,4,0),0) -> 190050 | U94: =IFERROR(VLOOKUP(CONCATENATE(Fix_Mapping[[#This Row],[KODE BARANG]],3),'Form Fix'!$A$6:$F$1063,4,0),0) -> 190065 | V94: =IFERROR(VLOOKUP(CONCATENATE(Fix_Mapping[[#This Row],[KODE BARANG]],4),'Form Fix'!$A$6:$F$1063,4,0),0) -> 0 | W94: =IFERROR(VLOOKUP(CONCATENATE(Fix_Mapping[[#This Row],[KODE BARANG]],5),'Form Fix'!$A$6:$F$1063,4,0),0) -> 0
A95: A1110000013510 | B95: ABC TOMAT 135 ML X 48 BTL | C95: 48 | D95: BTL | E95: TOMAT | F95: 6428.4991 | G95: 308567.96 | H95: 7135.634 | I95: 342510.43 | J95: 6838.8288 | K95: 328263.78 | L95: 7591.1 | M95: 364372.8 | N95: 7385.9351 | O95: 354524.89 | P95: 8198.388 | Q95: 393522.62 | R95: PT. HEINZ ABC INDONESIA | S95: =IFERROR(VLOOKUP(CONCATENATE(Fix_Mapping[[#This Row],[KODE BARANG]],1),'Form Fix'!$A$6:$F$1063,4,0),0) -> 190040 | T95: =IFERROR(VLOOKUP(CONCATENATE(Fix_Mapping[[#This Row],[KODE BARANG]],2),'Form Fix'!$A$6:$F$1063,4,0),0) -> 190067 | U95: =IFERROR(VLOOKUP(CONCATENATE(Fix_Mapping[[#This Row],[KODE BARANG]],3),'Form Fix'!$A$6:$F$1063,4,0),0) -> 0 | V95: =IFERROR(VLOOKUP(CONCATENATE(Fix_Mapping[[#This Row],[KODE BARANG]],4),'Form Fix'!$A$6:$F$1063,4,0),0) -> 0 | W95: =IFERROR(VLOOKUP(CONCATENATE(Fix_Mapping[[#This Row],[KODE BARANG]],5),'Form Fix'!$A$6:$F$1063,4,0),0) -> 0
A96: A1110000027510 | B96: ABC TOMAT 275 ML X 24 BTL | C96: 24 | D96: BTL | E96: TOMAT | F96: 11278.222 | G96: 270677.32 | H96: 12518.826 | I96: 300451.82 | J96: 11998.108 | K96: 287954.59 | L96: 13317.9 | M96: 319629.6 | N96: 12957.957 | O96: 310990.96 | P96: 14383.332 | Q96: 345199.97 | R96: PT. HEINZ ABC INDONESIA | S96: =IFERROR(VLOOKUP(CONCATENATE(Fix_Mapping[[#This Row],[KODE BARANG]],1),'Form Fix'!$A$6:$F$1063,4,0),0) -> 190041 | T96: =IFERROR(VLOOKUP(CONCATENATE(Fix_Mapping[[#This Row],[KODE BARANG]],2),'Form Fix'!$A$6:$F$1063,4,0),0) -> 190068 | U96: =IFERROR(VLOOKUP(CONCATENATE(Fix_Mapping[[#This Row],[KODE BARANG]],3),'Form Fix'!$A$6:$F$1063,4,0),0) -> 0 | V96: =IFERROR(VLOOKUP(CONCATENATE(Fix_Mapping[[#This Row],[KODE BARANG]],4),'Form Fix'!$A$6:$F$1063,4,0),0) -> 0 | W96: =IFERROR(VLOOKUP(CONCATENATE(Fix_Mapping[[#This Row],[KODE BARANG]],5),'Form Fix'!$A$6:$F$1063,4,0),0) -> 0
A97: A1110000033510 | B97: ABC TOMAT 335 ML X 24 BTL | C97: 24 | D97: BTL | E97: TOMAT | F97: 14540.445 | G97: 348970.68 | H97: 16139.894 | I97: 387357.46 | J97: 15468.559 | K97: 371245.41 | L97: 17170.1 | M97: 412082.4 | N97: 16706.043 | O97: 400945.04 | P97: 18543.708 | Q97: 445048.99 | R97: PT. HEINZ ABC INDONESIA | S97: =IFERROR(VLOOKUP(CONCATENATE(Fix_Mapping[[#This Row],[KODE BARANG]],1),'Form Fix'!$A$6:$F$1063,4,0),0) -> 190031 | T97: =IFERROR(VLOOKUP(CONCATENATE(Fix_Mapping[[#This Row],[KODE BARANG]],2),'Form Fix'!$A$6:$F$1063,4,0),0) -> 190066 | U97: =IFERROR(VLOOKUP(CONCATENATE(Fix_Mapping[[#This Row],[KODE BARANG]],3),'Form Fix'!$A$6:$F$1063,4,0),0) -> 0 | V97: =IFERROR(VLOOKUP(CONCATENATE(Fix_Mapping[[#This Row],[KODE BARANG]],4),'Form Fix'!$A$6:$F$1063,4,0),0) -> 0 | W97: =IFERROR(VLOOKUP(CONCATENATE(Fix_Mapping[[#This Row],[KODE BARANG]],5),'Form Fix'!$A$6:$F$1063,4,0),0) -> 0
A98: A1110000100510 | B98: ABC TOMAT 5,7 KG X 1 JRG | C98: 1 | D98: JRG | E98: TOMAT | F98: 91787.105 | G98: 91787.105 | H98: 101883.69 | I98: 101883.69 | J98: 97645.856 | K98: 97645.856 | L98: 108386.9 | M98: 108386.9 | N98: 105457.52 | O98: 105457.52 | P98: 117057.85 | Q98: 117057.85 | R98: PT. HEINZ ABC INDONESIA | S98: =IFERROR(VLOOKUP(CONCATENATE(Fix_Mapping[[#This Row],[KODE BARANG]],1),'Form Fix'!$A$6:$F$1063,4,0),0) -> 190035 | T98: =IFERROR(VLOOKUP(CONCATENATE(Fix_Mapping[[#This Row],[KODE BARANG]],2),'Form Fix'!$A$6:$F$1063,4,0),0) -> 190051 | U98: =IFERROR(VLOOKUP(CONCATENATE(Fix_Mapping[[#This Row],[KODE BARANG]],3),'Form Fix'!$A$6:$F$1063,4,0),0) -> 190070 | V98: =IFERROR(VLOOKUP(CONCATENATE(Fix_Mapping[[#This Row],[KODE BARANG]],4),'Form Fix'!$A$6:$F$1063,4,0),0) -> 0 | W98: =IFERROR(VLOOKUP(CONCATENATE(Fix_Mapping[[#This Row],[KODE BARANG]],5),'Form Fix'!$A$6:$F$1063,4,0),0) -> 0
A99: A1110001100110 | B99: ABC TOMAT PILLOW 1 KG X 6 PCS | C99: 6 | D99: PCS | E99: TOMAT | F99: 16241.337 | G99: 97448.022 | H99: 18027.884 | I99: 108167.3 | J99: 17278.018 | K99: 103668.11 | L99: 19178.6 | M99: 115071.6 | N99: 18660.259 | O99: 111961.56 | P99: 20712.888 | Q99: 124277.33 | R99: PT. HEINZ ABC INDONESIA | S99: =IFERROR(VLOOKUP(CONCATENATE(Fix_Mapping[[#This Row],[KODE BARANG]],1),'Form Fix'!$A$6:$F$1063,4,0),0) -> 190036 | T99: =IFERROR(VLOOKUP(CONCATENATE(Fix_Mapping[[#This Row],[KODE BARANG]],2),'Form Fix'!$A$6:$F$1063,4,0),0) -> 190043 | U99: =IFERROR(VLOOKUP(CONCATENATE(Fix_Mapping[[#This Row],[KODE BARANG]],3),'Form Fix'!$A$6:$F$1063,4,0),0) -> 190069 | V99: =IFERROR(VLOOKUP(CONCATENATE(Fix_Mapping[[#This Row],[KODE BARANG]],4),'Form Fix'!$A$6:$F$1063,4,0),0) -> 0 | W99: =IFERROR(VLOOKUP(CONCATENATE(Fix_Mapping[[#This Row],[KODE BARANG]],5),'Form Fix'!$A$6:$F$1063,4,0),0) -> 0
A100: A1111001012510 | B100: ABC TOMAT HEINZ KETCHUP 125 GR X 48 PCH | C100: 48 | D100: PCH | E100: TOMAT HEINZ | F100: 6234.623 | G100: 299261.91 | H100: 6920.4316 | I100: 332180.72 | J100: 6632.5777 | K100: 318363.73 | L100: 7362.1613 | M100: 353383.74 | N100: 7163.1839 | O100: 343832.83 | P100: 7951.1342 | Q100: 381654.44 | R100: PT. HEINZ ABC INDONESIA | S100: =IFERROR(VLOOKUP(CONCATENATE(Fix_Mapping[[#This Row],[KODE BARANG]],1),'Form Fix'!$A$6:$F$1063,4,0),0) -> 190039 | T100: =IFERROR(VLOOKUP(CONCATENATE(Fix_Mapping[[#This Row],[KODE BARANG]],2),'Form Fix'!$A$6:$F$1063,4,0),0) -> 0 | U100: =IFERROR(VLOOKUP(CONCATENATE(Fix_Mapping[[#This Row],[KODE BARANG]],3),'Form Fix'!$A$6:$F$1063,4,0),0) -> 0 | V100: =IFERROR(VLOOKUP(CONCATENATE(Fix_Mapping[[#This Row],[KODE BARANG]],4),'Form Fix'!$A$6:$F$1063,4,0),0) -> 0 | W100: =IFERROR(VLOOKUP(CONCATENATE(Fix_Mapping[[#This Row],[KODE BARANG]],5),'Form Fix'!$A$6:$F$1063,4,0),0) -> 0
A101: A1111001032510 | B101: ABC TOMAT HEINZ KETCHUP 325 GR X 24 BTL | C101: 24 | D101: BTL | E101: TOMAT HEINZ | F101: 14596.341 | G101: 350312.19 | H101: 16201.939 | I101: 388846.53 | J101: 15528.022 | K101: 372672.54 | L101: 17236.105 | M101: 413666.52 | N101: 16770.264 | O101: 402486.34 | P101: 18614.993 | Q101: 446759.84 | R101: PT. HEINZ ABC INDONESIA | S101: =IFERROR(VLOOKUP(CONCATENATE(Fix_Mapping[[#This Row],[KODE BARANG]],1),'Form Fix'!$A$6:$F$1063,4,0),0) -> 190047 | T101: =IFERROR(VLOOKUP(CONCATENATE(Fix_Mapping[[#This Row],[KODE BARANG]],2),'Form Fix'!$A$6:$F$1063,4,0),0) -> 190057 | U101: =IFERROR(VLOOKUP(CONCATENATE(Fix_Mapping[[#This Row],[KODE BARANG]],3),'Form Fix'!$A$6:$F$1063,4,0),0) -> 0 | V101: =IFERROR(VLOOKUP(CONCATENATE(Fix_Mapping[[#This Row],[KODE BARANG]],4),'Form Fix'!$A$6:$F$1063,4,0),0) -> 0 | W101: =IFERROR(VLOOKUP(CONCATENATE(Fix_Mapping[[#This Row],[KODE BARANG]],5),'Form Fix'!$A$6:$F$1063,4,0),0) -> 0
... A109: A1120006027010 | B109: ABC SAMBAL ASLI 270 ML X 24 BTL | C109: 24 | D109: BTL | E109: SAMBAL | F109: 11271.531 | G109: 270516.73 | H109: 12511.399 | I109: 300273.58 | J109: 11990.99 | K109: 287783.76 | L109: 13309.999 | M109: 319439.97 | N109: 12950.28 | O109: 310806.72 | P109: 14374.811 | Q109: 344995.46 | R109: PT. HEINZ ABC INDONESIA | S109: =IFERROR(VLOOKUP(CONCATENATE(Fix_Mapping[[#This Row],[KODE BARANG]],1),'Form Fix'!$A$6:$F$1063,4,0),0) -> 150168 | T109: =IFERROR(VLOOKUP(CONCATENATE(Fix_Mapping[[#This Row],[KODE BARANG]],2),'Form Fix'!$A$6:$F$1063,4,0),0) -> 150187 | U109: =IFERROR(VLOOKUP(CONCATENATE(Fix_Mapping[[#This Row],[KODE BARANG]],3),'Form Fix'!$A$6:$F$1063,4,0),0) -> 150349 | V109: =IFERROR(VLOOKUP(CONCATENATE(Fix_Mapping[[#This Row],[KODE BARANG]],4),'Form Fix'!$A$6:$F$1063,4,0),0) -> 150331 | W109: =IFERROR(VLOOKUP(CONCATENATE(Fix_Mapping[[#This Row],[KODE BARANG]],5),'Form Fix'!$A$6:$F$1063,4,0),0) -> 0
A110: A1120006027011 | B110: ABC SAMBAL ASLI 270 ML X 24 BTL BANDED | C110: 24 | D110: BTL | E110: SAMBAL | F110: 11271.54 | G110: 270516.96 | H110: 12511.409 | I110: 300273.83 | J110: 11991 | K110: 287784 | L110: 13310.01 | M110: 319440.24 | N110: 12950.28 | O110: 310806.72 | P110: 14374.811 | Q110: 344995.46 | S110: =IFERROR(VLOOKUP(CONCATENATE(Fix_Mapping[[#This Row],[KODE BARANG]],1),'Form Fix'!$A$6:$F$1063,4,0),0) -> 150984 | T110: =IFERROR(VLOOKUP(CONCATENATE(Fix_Mapping[[#This Row],[KODE BARANG]],2),'Form Fix'!$A$6:$F$1063,4,0),0) -> 0 | U110: =IFERROR(VLOOKUP(CONCATENATE(Fix_Mapping[[#This Row],[KODE BARANG]],3),'Form Fix'!$A$6:$F$1063,4,0),0) -> 0 | V110: =IFERROR(VLOOKUP(CONCATENATE(Fix_Mapping[[#This Row],[KODE BARANG]],4),'Form Fix'!$A$6:$F$1063,4,0),0) -> 0 | W110: =IFERROR(VLOOKUP(CONCATENATE(Fix_Mapping[[#This Row],[KODE BARANG]],5),'Form Fix'!$A$6:$F$1063,4,0),0) -> 0
A111: A1120006033510 | B111: ABC SAMBAL ASLI 335 ML X 24 BTL | C111: 24 | D111: BTL | E111: SAMBAL | F111: 14023.785 | G111: 336570.84 | H111: 15566.401 | I111: 373593.63 | J111: 14918.92 | K111: 358054.08 | L111: 16560.001 | M111: 397440.03 | N111: 16112.43 | O111: 386698.32 | P111: 17884.797 | Q111: 429235.14 | R111: PT. HEINZ ABC INDONESIA | S111: =IFERROR(VLOOKUP(CONCATENATE(Fix_Mapping[[#This Row],[KODE BARANG]],1),'Form Fix'!$A$6:$F$1063,4,0),0) -> 150171 | T111: =IFERROR(VLOOKUP(CONCATENATE(Fix_Mapping[[#This Row],[KODE BARANG]],2),'Form Fix'!$A$6:$F$1063,4,0),0) -> 150329 | U111: =IFERROR(VLOOKUP(CONCATENATE(Fix_Mapping[[#This Row],[KODE BARANG]],3),'Form Fix'!$A$6:$F$1063,4,0),0) -> 0 | V111: =IFERROR(VLOOKUP(CONCATENATE(Fix_Mapping[[#This Row],[KODE BARANG]],4),'Form Fix'!$A$6:$F$1063,4,0),0) -> 0 | W111: =IFERROR(VLOOKUP(CONCATENATE(Fix_Mapping[[#This Row],[KODE BARANG]],5),'Form Fix'!$A$6:$F$1063,4,0),0) -> 0
A112: A1120006038010 | B112: ABC SAMBAL ASLI 380 GR X 12 PCH | C112: 12 | D112: PCH | E112: SAMBAL | F112: 13328.016 | G112: 159936.19 | H112: 14794.097 | I112: 177529.17 | J112: 14178.74 | K112: 170144.88 | L112: 15738.401 | M112: 188860.82 | N112: 15313.038 | O112: 183756.45 | P112: 16997.472 | Q112: 203969.66 | R112: PT. HEINZ ABC INDONESIA | S112: =IFERROR(VLOOKUP(CONCATENATE(Fix_Mapping[[#This Row],[KODE BARANG]],1),'Form Fix'!$A$6:$F$1063,4,0),0) -> 150177 | T112: =IFERROR(VLOOKUP(CONCATENATE(Fix_Mapping[[#This Row],[KODE BARANG]],2),'Form Fix'!$A$6:$F$1063,4,0),0) -> 150221 | U112: =IFERROR(VLOOKUP(CONCATENATE(Fix_Mapping[[#This Row],[KODE BARANG]],3),'Form Fix'!$A$6:$F$1063,4,0),0) -> 150325 | V112: =IFERROR(VLOOKUP(CONCATENATE(Fix_Mapping[[#This Row],[KODE BARANG]],4),'Form Fix'!$A$6:$F$1063,4,0),0) -> 0 | W112: =IFERROR(VLOOKUP(CONCATENATE(Fix_Mapping[[#This Row],[KODE BARANG]],5),'Form Fix'!$A$6:$F$1063,4,0),0) -> 0
A113: A1120006060010 | B113: ABC SAMBAL ASLI 600 ML X 12 BTL | C113: 12 | D113: BTL | E113: SAMBAL | F113: 22898.738 | G113: 274784.86 | H113: 25417.6 | I113: 305011.2 | J113: 24360.36 | K113: 292324.32 | L113: 27040 | M113: 324480 | N113: 26309.19 | O113: 315710.28 | P113: 29203.201 | Q113: 350438.41 | R113: PT. HEINZ ABC INDONESIA | S113: =IFERROR(VLOOKUP(CONCATENATE(Fix_Mapping[[#This Row],[KODE BARANG]],1),'Form Fix'!$A$6:$F$1063,4,0),0) -> 150188 | T113: =IFERROR(VLOOKUP(CONCATENATE(Fix_Mapping[[#This Row],[KODE BARANG]],2),'Form Fix'!$A$6:$F$1063,4,0),0) -> 150332 | U113: =IFERROR(VLOOKUP(CONCATENATE(Fix_Mapping[[#This Row],[KODE BARANG]],3),'Form Fix'!$A$6:$F$1063,4,0),0) -> 0 | V113: =IFERROR(VLOOKUP(CONCATENATE(Fix_Mapping[[#This Row],[KODE BARANG]],4),'Form Fix'!$A$6:$F$1063,4,0),0) -> 0 | W113: =IFERROR(VLOOKUP(CONCATENATE(Fix_Mapping[[#This Row],[KODE BARANG]],5),'Form Fix'!$A$6:$F$1063,4,0),0) -> 0
A114: A1120006069010 | B114: ABC SAMBAL ASLI 690 GR X 6 PCS | C114: 6 | D114: PCS | E114: SAMBAL | F114: 17496.145 | G114: 104976.87 | H114: 19420.721 | I114: 116524.32 | J114: 18612.92 | K114: 111677.52 | L114: 20660.341 | M114: 123962.05 | N114: 20101.95 | O114: 120611.7 | P114: 22313.165 | Q114: 133878.99 | R114: PT. HEINZ ABC INDONESIA | S114: =IFERROR(VLOOKUP(CONCATENATE(Fix_Mapping[[#This Row],[KODE BARANG]],1),'Form Fix'!$A$6:$F$1063,4,0),0) -> 150320 | T114: =IFERROR(VLOOKUP(CONCATENATE(Fix_Mapping[[#This Row],[KODE BARANG]],2),'Form Fix'!$A$6:$F$1063,4,0),0) -> 0 | U114: =IFERROR(VLOOKUP(CONCATENATE(Fix_Mapping[[#This Row],[KODE BARANG]],3),'Form Fix'!$A$6:$F$1063,4,0),0) -> 0 | V114: =IFERROR(VLOOKUP(CONCATENATE(Fix_Mapping[[#This Row],[KODE BARANG]],4),'Form Fix'!$A$6:$F$1063,4,0),0) -> 0 | W114: =IFERROR(VLOOKUP(CONCATENATE(Fix_Mapping[[#This Row],[KODE BARANG]],5),'Form Fix'!$A$6:$F$1063,4,0),0) -> 0
A115: A1120006100510 | B115: ABC SAMBAL ASLI 5 KG X 1 JRG | C115: 1 | D115: JRG | E115: SAMBAL | F115: 118880.28 | G115: 118880.28 | H115: 131957.11 | I115: 131957.11 | J115: 126468.38 | K115: 126468.38 | L115: 140379.9 | M115: 140379.9 | N115: 136585.85 | O115: 136585.85 | P115: 151610.29 | Q115: 151610.29 | R115: PT. HEINZ ABC INDONESIA | S115: =IFERROR(VLOOKUP(CONCATENATE(Fix_Mapping[[#This Row],[KODE BARANG]],1),'Form Fix'!$A$6:$F$1063,4,0),0) -> 150162 | T115: =IFERROR(VLOOKUP(CONCATENATE(Fix_Mapping[[#This Row],[KODE BARANG]],2),'Form Fix'!$A$6:$F$1063,4,0),0) -> 150333 | U115: =IFERROR(VLOOKUP(CONCATENATE(Fix_Mapping[[#This Row],[KODE BARANG]],3),'Form Fix'!$A$6:$F$1063,4,0),0) -> 0 | V115: =IFERROR(VLOOKUP(CONCATENATE(Fix_Mapping[[#This Row],[KODE BARANG]],4),'Form Fix'!$A$6:$F$1063,4,0),0) -> 0 | W115: =IFERROR(VLOOKUP(CONCATENATE(Fix_Mapping[[#This Row],[KODE BARANG]],5),'Form Fix'!$A$6:$F$1063,4,0),0) -> 0
A116: A1120006102410 | B116: ABC SAMBAL ASLI 24 KG X 1 JRG | C116: 1 | D116: JRG | E116: SAMBAL | F116: 459312.79 | G116: 459312.79 | H116: 509837.2 | I116: 509837.2 | J116: 488630.63 | K116: 488630.63 | L116: 542380 | M116: 542380 | N116: 527721.08 | O116: 527721.08 | P116: 585770.4 | Q116: 585770.4 | R116: PT. HEINZ ABC INDONESIA | S116: =IFERROR(VLOOKUP(CONCATENATE(Fix_Mapping[[#This Row],[KODE BARANG]],1),'Form Fix'!$A$6:$F$1063,4,0),0) -> 150163 | T116: =IFERROR(VLOOKUP(CONCATENATE(Fix_Mapping[[#This Row],[KODE BARANG]],2),'Form Fix'!$A$6:$F$1063,4,0),0) -> 150334 | U116: =IFERROR(VLOOKUP(CONCATENATE(Fix_Mapping[[#This Row],[KODE BARANG]],3),'Form Fix'!$A$6:$F$1063,4,0),0) -> 0 | V116: =IFERROR(VLOOKUP(CONCATENATE(Fix_Mapping[[#This Row],[KODE BARANG]],4),'Form Fix'!$A$6:$F$1063,4,0),0) -> 0 | W116: =IFERROR(VLOOKUP(CONCATENATE(Fix_Mapping[[#This Row],[KODE BARANG]],5),'Form Fix'!$A$6:$F$1063,4,0),0) -> 0
A117: A1120007100110 | B117: ABC SAMBAL ASLI PILLOW 1 KG X 6 PCS | C117: 6 | D117: PCS | E117: SAMBAL | F117: 25058.2 | G117: 150349.2 | H117: 27814.602 | I117: 166887.61 | J117: 26657.66 | K117: 159945.96 | L117: 29590.003 | M117: 177540.02 | N117: 28790.27 | O117: 172741.62 | P117: 31957.2 | Q117: 191743.2 | R117: PT. HEINZ ABC INDONESIA | S117: =IFERROR(VLOOKUP(CONCATENATE(Fix_Mapping[[#This Row],[KODE BARANG]],1),'Form Fix'!$A$6:$F$1063,4,0),0) -> 150119 | T117: =IFERROR(VLOOKUP(CONCATENATE(Fix_Mapping[[#This Row],[KODE BARANG]],2),'Form Fix'!$A$6:$F$1063,4,0),0) -> 150231 | U117: =IFERROR(VLOOKUP(CONCATENATE(Fix_Mapping[[#This Row],[KODE BARANG]],3),'Form Fix'!$A$6:$F$1063,4,0),0) -> 150335 | V117: =IFERROR(VLOOKUP(CONCATENATE(Fix_Mapping[[#This Row],[KODE BARANG]],4),'Form Fix'!$A$6:$F$1063,4,0),0) -> 0 | W117: =IFERROR(VLOOKUP(CONCATENATE(Fix_Mapping[[#This Row],[KODE BARANG]],5),'Form Fix'!$A$6:$F$1063,4,0),0) -> 0
A118: A1120008000810 | B118: ABC SAMBAL EXTRA PEDAS 8 GR X 21 PACK PCSX22 | C118: 21 | D118: PCSX22 | E118: SAMBAL | F118: 5669.6382 | G118: 119062.4 | H118: 6293.2984 | I118: 132159.27 | J118: 6031.53 | K118: 126662.13 | L118: 6694.9983 | M118: 140594.96 | N118: 6573.2727 | O118: 138038.73 | P118: 7296.3327 | Q118: 153222.99 | R118: PT. HEINZ ABC INDONESIA | S118: =IFERROR(VLOOKUP(CONCATENATE(Fix_Mapping[[#This Row],[KODE BARANG]],1),'Form Fix'!$A$6:$F$1063,4,0),0) -> 150154 | T118: =IFERROR(VLOOKUP(CONCATENATE(Fix_Mapping[[#This Row],[KODE BARANG]],2),'Form Fix'!$A$6:$F$1063,4,0),0) -> 150241 | U118: =IFERROR(VLOOKUP(CONCATENATE(Fix_Mapping[[#This Row],[KODE BARANG]],3),'Form Fix'!$A$6:$F$1063,4,0),0) -> 150339 | V118: =IFERROR(VLOOKUP(CONCATENATE(Fix_Mapping[[#This Row],[KODE BARANG]],4),'Form Fix'!$A$6:$F$1063,4,0),0) -> 150241 | W118: =IFERROR(VLOOKUP(CONCATENATE(Fix_Mapping[[#This Row],[KODE BARANG]],5),'Form Fix'!$A$6:$F$1063,4,0),0) -> 0
A119: A1120008001510 | B119: ABC SAMBAL EXTRA PEDAS 15 GR X 30 PACK PCSX10 | C119: 30 | D119: PCSX10 | E119: SAMBAL | F119: 5669.6382 | G119: 170089.15 | H119: 6293.2984 | I119: 188798.95 | J119: 6031.53 | K119: 180945.9 | L119: 6694.9983 | M119: 200849.95 | N119: 6573.2727 | O119: 197198.18 | P119: 7296.3327 | Q119: 218889.98 | R119: PT. HEINZ ABC INDONESIA | S119: =IFERROR(VLOOKUP(CONCATENATE(Fix_Mapping[[#This Row],[KODE BARANG]],1),'Form Fix'!$A$6:$F$1063,4,0),0) -> 150153 | T119: =IFERROR(VLOOKUP(CONCATENATE(Fix_Mapping[[#This Row],[KODE BARANG]],2),'Form Fix'!$A$6:$F$1063,4,0),0) -> 150211 | U119: =IFERROR(VLOOKUP(CONCATENATE(Fix_Mapping[[#This Row],[KODE BARANG]],3),'Form Fix'!$A$6:$F$1063,4,0),0) -> 150240 | V119: =IFERROR(VLOOKUP(CONCATENATE(Fix_Mapping[[#This Row],[KODE BARANG]],4),'Form Fix'!$A$6:$F$1063,4,0),0) -> 150340 | W119: =IFERROR(VLOOKUP(CONCATENATE(Fix_Mapping[[#This Row],[KODE BARANG]],5),'Form Fix'!$A$6:$F$1063,4,0),0) -> 0
A120: A1120008007510 | B120: ABC SAMBAL EXTRA PEDAS 65 GR X 48 PCH | C120: 48 | D120: PCH | E120: SAMBAL | F120: 2224.2468 | G120: 106763.85 | H120: 2468.9139 | I120: 118507.87 | J120: 2366.22 | K120: 113578.56 | L120: 2626.5042 | M120: 126072.2 | N120: 2555.5135 | O120: 122664.65 | P120: 2836.62 | Q120: 136157.76 | R120: PT. HEINZ ABC INDONESIA | S120: =IFERROR(VLOOKUP(CONCATENATE(Fix_Mapping[[#This Row],[KODE BARANG]],1),'Form Fix'!$A$6:$F$1063,4,0),0) -> 150181 | T120: =IFERROR(VLOOKUP(CONCATENATE(Fix_Mapping[[#This Row],[KODE BARANG]],2),'Form Fix'!$A$6:$F$1063,4,0),0) -> 150233 | U120: =IFERROR(VLOOKUP(CONCATENATE(Fix_Mapping[[#This Row],[KODE BARANG]],3),'Form Fix'!$A$6:$F$1063,4,0),0) -> 150309 | V120: =IFERROR(VLOOKUP(CONCATENATE(Fix_Mapping[[#This Row],[KODE BARANG]],4),'Form Fix'!$A$6:$F$1063,4,0),0) -> 0 | W120: =IFERROR(VLOOKUP(CONCATENATE(Fix_Mapping[[#This Row],[KODE BARANG]],5),'Form Fix'!$A$6:$F$1063,4,0),0) -> 0
A121: A1120008013010 | B121: ABC SAMBAL EXTRA PEDAS 130 ML X 48 BTL | C121: 48 | D121: BTL | E121: SAMBAL | F121: 5504.546 | G121: 264218.21 | H121: 6110.0461 | I121: 293282.21 | J121: 5855.9 | K121: 281083.2 | L121: 6500.049 | M121: 312002.35 | N121: 0 | O121: 0 | P121: 0 | Q121: 0 | R121: PT. HEINZ ABC INDONESIA | S121: =IFERROR(VLOOKUP(CONCATENATE(Fix_Mapping[[#This Row],[KODE BARANG]],1),'Form Fix'!$A$6:$F$1063,4,0),0) -> 150295 | T121: =IFERROR(VLOOKUP(CONCATENATE(Fix_Mapping[[#This Row],[KODE BARANG]],2),'Form Fix'!$A$6:$F$1063,4,0),0) -> 150374 | U121: =IFERROR(VLOOKUP(CONCATENATE(Fix_Mapping[[#This Row],[KODE BARANG]],3),'Form Fix'!$A$6:$F$1063,4,0),0) -> 0 | V121: =IFERROR(VLOOKUP(CONCATENATE(Fix_Mapping[[#This Row],[KODE BARANG]],4),'Form Fix'!$A$6:$F$1063,4,0),0) -> 0 | W121: =IFERROR(VLOOKUP(CONCATENATE(Fix_Mapping[[#This Row],[KODE BARANG]],5),'Form Fix'!$A$6:$F$1063,4,0),0) -> 0
A122: A1120008013011 | B122: ABC SAMBAL EXTRA PEDAS 130 ML X 48 BTL BANDED | C122: 48 | D122: BTL | E122: SAMBAL | F122: 5504.546 | G122: 264218.21 | H122: 6110.0461 | I122: 293282.21 | J122: 5855.9 | K122: 281083.2 | L122: 6500.049 | M122: 312002.35 | N122: 0 | O122: 0 | P122: 0 | Q122: 0 | R122: PT. HEINZ ABC INDONESIA | S122: =IFERROR(VLOOKUP(CONCATENATE(Fix_Mapping[[#This Row],[KODE BARANG]],1),'Form Fix'!$A$6:$F$1063,4,0),0) -> 150976 | T122: =IFERROR(VLOOKUP(CONCATENATE(Fix_Mapping[[#This Row],[KODE BARANG]],2),'Form Fix'!$A$6:$F$1063,4,0),0) -> 0 | U122: =IFERROR(VLOOKUP(CONCATENATE(Fix_Mapping[[#This Row],[KODE BARANG]],3),'Form Fix'!$A$6:$F$1063,4,0),0) -> 0 | V122: =IFERROR(VLOOKUP(CONCATENATE(Fix_Mapping[[#This Row],[KODE BARANG]],4),'Form Fix'!$A$6:$F$1063,4,0),0) -> 0 | W122: =IFERROR(VLOOKUP(CONCATENATE(Fix_Mapping[[#This Row],[KODE BARANG]],5),'Form Fix'!$A$6:$F$1063,4,0),0) -> 0
... A139: A1122001001811 | B139: ABC SAMBAL NUS. TERASI 18 GR X 10 PACK PCSX10 B8G2 | C139: 10 | D139: PCSX10 | E139: SAMBAL NUS. | F139: 8197.458 | G139: 81974.58 | H139: 9099.1784 | I139: 90991.784 | J139: 8720.7 | K139: 87207 | L139: 9679.977 | M139: 96799.77 | N139: 9293.8428 | O139: 92938.428 | P139: 10316.166 | Q139: 103161.66 | R139: PT. HEINZ ABC INDONESIA | S139: =IFERROR(VLOOKUP(CONCATENATE(Fix_Mapping[[#This Row],[KODE BARANG]],1),'Form Fix'!$A$6:$F$1063,4,0),0) -> 150960 | T139: =IFERROR(VLOOKUP(CONCATENATE(Fix_Mapping[[#This Row],[KODE BARANG]],2),'Form Fix'!$A$6:$F$1063,4,0),0) -> 150971 | U139: =IFERROR(VLOOKUP(CONCATENATE(Fix_Mapping[[#This Row],[KODE BARANG]],3),'Form Fix'!$A$6:$F$1063,4,0),0) -> 0 | V139: =IFERROR(VLOOKUP(CONCATENATE(Fix_Mapping[[#This Row],[KODE BARANG]],4),'Form Fix'!$A$6:$F$1063,4,0),0) -> 0 | W139: =IFERROR(VLOOKUP(CONCATENATE(Fix_Mapping[[#This Row],[KODE BARANG]],5),'Form Fix'!$A$6:$F$1063,4,0),0) -> 0
A140: A1122001001813 | B140: ABC SAMBAL NUS. TERASI 18GR X 12 PACK PCSX10 PROMO | C140: 12 | D140: PCSX10 | E140: SAMBAL NUS. | F140: 8794.7904 | G140: 105537.48 | H140: 9762.2173 | I140: 117146.61 | J140: 9356.16 | K140: 112273.92 | L140: 10385.338 | M140: 124624.05 | N140: 10105.135 | O140: 121261.62 | P140: 11216.7 | Q140: 134600.4 | S140: =IFERROR(VLOOKUP(CONCATENATE(Fix_Mapping[[#This Row],[KODE BARANG]],1),'Form Fix'!$A$6:$F$1063,4,0),0) -> 150994 | T140: =IFERROR(VLOOKUP(CONCATENATE(Fix_Mapping[[#This Row],[KODE BARANG]],2),'Form Fix'!$A$6:$F$1063,4,0),0) -> 150995 | U140: =IFERROR(VLOOKUP(CONCATENATE(Fix_Mapping[[#This Row],[KODE BARANG]],3),'Form Fix'!$A$6:$F$1063,4,0),0) -> 0 | V140: =IFERROR(VLOOKUP(CONCATENATE(Fix_Mapping[[#This Row],[KODE BARANG]],4),'Form Fix'!$A$6:$F$1063,4,0),0) -> 0 | W140: =IFERROR(VLOOKUP(CONCATENATE(Fix_Mapping[[#This Row],[KODE BARANG]],5),'Form Fix'!$A$6:$F$1063,4,0),0) -> 0
A141: A1122001007010 | B141: ABC SAMBAL NUSANTARA TERASI 70 GR X 48 PCH | C141: 48 | D141: PCH | E141: SAMBAL NUSANTARA | F141: 4394.6504 | G141: 210943.22 | H141: 4878.0619 | I141: 234146.97 | J141: 4675.16 | K141: 224407.68 | L141: 5189.4276 | M141: 249092.52 | N141: 5049.1711 | O141: 242360.21 | P141: 5604.5799 | Q141: 269019.84 | R141: PT. HEINZ ABC INDONESIA | S141: =IFERROR(VLOOKUP(CONCATENATE(Fix_Mapping[[#This Row],[KODE BARANG]],1),'Form Fix'!$A$6:$F$1063,4,0),0) -> 150319 | T141: =IFERROR(VLOOKUP(CONCATENATE(Fix_Mapping[[#This Row],[KODE BARANG]],2),'Form Fix'!$A$6:$F$1063,4,0),0) -> 150375 | U141: =IFERROR(VLOOKUP(CONCATENATE(Fix_Mapping[[#This Row],[KODE BARANG]],3),'Form Fix'!$A$6:$F$1063,4,0),0) -> 0 | V141: =IFERROR(VLOOKUP(CONCATENATE(Fix_Mapping[[#This Row],[KODE BARANG]],4),'Form Fix'!$A$6:$F$1063,4,0),0) -> 0 | W141: =IFERROR(VLOOKUP(CONCATENATE(Fix_Mapping[[#This Row],[KODE BARANG]],5),'Form Fix'!$A$6:$F$1063,4,0),0) -> 0
A142: A1122001018010 | B142: ABC SAMBAL NUSANTARA TERASI 180 GR X 24 PCH | C142: 24 | D142: PCH | E142: SAMBAL NUSANTARA | F142: 15607.384 | G142: 374577.22 | H142: 17324.196 | I142: 415780.71 | J142: 16603.6 | K142: 398486.4 | L142: 18429.996 | M142: 442319.9 | N142: 17931.89 | O142: 430365.36 | P142: 19904.398 | Q142: 477705.55 | R142: PT. HEINZ ABC INDONESIA | S142: =IFERROR(VLOOKUP(CONCATENATE(Fix_Mapping[[#This Row],[KODE BARANG]],1),'Form Fix'!$A$6:$F$1063,4,0),0) -> 150193 | T142: =IFERROR(VLOOKUP(CONCATENATE(Fix_Mapping[[#This Row],[KODE BARANG]],2),'Form Fix'!$A$6:$F$1063,4,0),0) -> 150360 | U142: =IFERROR(VLOOKUP(CONCATENATE(Fix_Mapping[[#This Row],[KODE BARANG]],3),'Form Fix'!$A$6:$F$1063,4,0),0) -> 0 | V142: =IFERROR(VLOOKUP(CONCATENATE(Fix_Mapping[[#This Row],[KODE BARANG]],4),'Form Fix'!$A$6:$F$1063,4,0),0) -> 0 | W142: =IFERROR(VLOOKUP(CONCATENATE(Fix_Mapping[[#This Row],[KODE BARANG]],5),'Form Fix'!$A$6:$F$1063,4,0),0) -> 0
A143: A1122001018011 | B143: ABC SAMBAL NUSANTARA TERASI 180 GR X 12 PCH B8G2 | C143: 12 | D143: PCH | E143: SAMBAL NUSANTARA | F143: 15607.384 | G143: 187288.61 | H143: 17324.196 | I143: 207890.35 | J143: 16603.6 | K143: 199243.2 | L143: 18429.996 | M143: 221159.95 | N143: 0 | O143: 0 | P143: 0 | Q143: 0 | R143: PT. HEINZ ABC INDONESIA | S143: =IFERROR(VLOOKUP(CONCATENATE(Fix_Mapping[[#This Row],[KODE BARANG]],1),'Form Fix'!$A$6:$F$1063,4,0),0) -> 150961 | T143: =IFERROR(VLOOKUP(CONCATENATE(Fix_Mapping[[#This Row],[KODE BARANG]],2),'Form Fix'!$A$6:$F$1063,4,0),0) -> 0 | U143: =IFERROR(VLOOKUP(CONCATENATE(Fix_Mapping[[#This Row],[KODE BARANG]],3),'Form Fix'!$A$6:$F$1063,4,0),0) -> 0 | V143: =IFERROR(VLOOKUP(CONCATENATE(Fix_Mapping[[#This Row],[KODE BARANG]],4),'Form Fix'!$A$6:$F$1063,4,0),0) -> 0 | W143: =IFERROR(VLOOKUP(CONCATENATE(Fix_Mapping[[#This Row],[KODE BARANG]],5),'Form Fix'!$A$6:$F$1063,4,0),0) -> 0
A144: A1122001018020 | B144: ABC SAMBAL NUSANTARA TERASI 180 GR X 24 BTL | C144: 24 | D144: BTL | E144: SAMBAL NUSANTARA | F144: 15607.384 | G144: 374577.22 | H144: 17324.196 | I144: 415780.71 | J144: 16603.6 | K144: 398486.4 | L144: 18429.996 | M144: 442319.9 | N144: 17931.89 | O144: 430365.36 | P144: 19904.398 | Q144: 477705.55 | R144: PT. HEINZ ABC INDONESIA | S144: =IFERROR(VLOOKUP(CONCATENATE(Fix_Mapping[[#This Row],[KODE BARANG]],1),'Form Fix'!$A$6:$F$1063,4,0),0) -> 612095 | T144: =IFERROR(VLOOKUP(CONCATENATE(Fix_Mapping[[#This Row],[KODE BARANG]],2),'Form Fix'!$A$6:$F$1063,4,0),0) -> 0 | U144: =IFERROR(VLOOKUP(CONCATENATE(Fix_Mapping[[#This Row],[KODE BARANG]],3),'Form Fix'!$A$6:$F$1063,4,0),0) -> 0 | V144: =IFERROR(VLOOKUP(CONCATENATE(Fix_Mapping[[#This Row],[KODE BARANG]],4),'Form Fix'!$A$6:$F$1063,4,0),0) -> 0 | W144: =IFERROR(VLOOKUP(CONCATENATE(Fix_Mapping[[#This Row],[KODE BARANG]],5),'Form Fix'!$A$6:$F$1063,4,0),0) -> 0
A145: A1122002001810 | B145: ABC SAMBAL NUSANTARA HIJAU 18 GR X 10 PACK PCSX10 | C145: 10 | D145: PCSX10 | E145: SAMBAL NUSANTARA | F145: 13330.911 | G145: 133309.11 | H145: 14797.311 | I145: 147973.11 | J145: 14181.82 | K145: 141818.2 | L145: 15741.82 | M145: 157418.2 | N145: 15316.363 | O145: 153163.63 | P145: 17001.163 | Q145: 170011.63 | R145: PT. HEINZ ABC INDONESIA | S145: =IFERROR(VLOOKUP(CONCATENATE(Fix_Mapping[[#This Row],[KODE BARANG]],1),'Form Fix'!$A$6:$F$1063,4,0),0) -> 612098 | T145: =IFERROR(VLOOKUP(CONCATENATE(Fix_Mapping[[#This Row],[KODE BARANG]],2),'Form Fix'!$A$6:$F$1063,4,0),0) -> 150196 | U145: =IFERROR(VLOOKUP(CONCATENATE(Fix_Mapping[[#This Row],[KODE BARANG]],3),'Form Fix'!$A$6:$F$1063,4,0),0) -> 0 | V145: =IFERROR(VLOOKUP(CONCATENATE(Fix_Mapping[[#This Row],[KODE BARANG]],4),'Form Fix'!$A$6:$F$1063,4,0),0) -> 0 | W145: =IFERROR(VLOOKUP(CONCATENATE(Fix_Mapping[[#This Row],[KODE BARANG]],5),'Form Fix'!$A$6:$F$1063,4,0),0) -> 0
A146: A1122002001811 | B146: ABC SAMBAL NUS. HIJAU 18 GR X 10 PACK PCSX10 B8G2 | C146: 10 | D146: PCSX10 | E146: SAMBAL NUS. | F146: 10664.723 | G146: 106647.23 | H146: 11837.843 | I146: 118378.43 | J146: 11345.45 | K146: 113454.5 | L146: 12593.45 | M146: 125934.5 | N146: 12253.091 | O146: 122530.91 | P146: 13600.931 | Q146: 136009.31 | R146: PT. HEINZ ABC INDONESIA | S146: =IFERROR(VLOOKUP(CONCATENATE(Fix_Mapping[[#This Row],[KODE BARANG]],1),'Form Fix'!$A$6:$F$1063,4,0),0) -> 612954 | T146: =IFERROR(VLOOKUP(CONCATENATE(Fix_Mapping[[#This Row],[KODE BARANG]],2),'Form Fix'!$A$6:$F$1063,4,0),0) -> 150978 | U146: =IFERROR(VLOOKUP(CONCATENATE(Fix_Mapping[[#This Row],[KODE BARANG]],3),'Form Fix'!$A$6:$F$1063,4,0),0) -> 0 | V146: =IFERROR(VLOOKUP(CONCATENATE(Fix_Mapping[[#This Row],[KODE BARANG]],4),'Form Fix'!$A$6:$F$1063,4,0),0) -> 0 | W146: =IFERROR(VLOOKUP(CONCATENATE(Fix_Mapping[[#This Row],[KODE BARANG]],5),'Form Fix'!$A$6:$F$1063,4,0),0) -> 0
A147: A1122003001810 | B147: ABC SAMBAL NUSANTARA RENDANG 18 GR X 10 PACK PCSX10 | C147: 10 | D147: PCSX10 | E147: SAMBAL NUSANTARA | F147: 13330.911 | G147: 133309.11 | H147: 14797.311 | I147: 147973.11 | J147: 14181.82 | K147: 141818.2 | L147: 15741.82 | M147: 157418.2 | N147: 0 | O147: 0 | P147: 0 | Q147: 0 | R147: PT. HEINZ ABC INDONESIA | S147: =IFERROR(VLOOKUP(CONCATENATE(Fix_Mapping[[#This Row],[KODE BARANG]],1),'Form Fix'!$A$6:$F$1063,4,0),0) -> 612128 | T147: =IFERROR(VLOOKUP(CONCATENATE(Fix_Mapping[[#This Row],[KODE BARANG]],2),'Form Fix'!$A$6:$F$1063,4,0),0) -> 0 | U147: =IFERROR(VLOOKUP(CONCATENATE(Fix_Mapping[[#This Row],[KODE BARANG]],3),'Form Fix'!$A$6:$F$1063,4,0),0) -> 0 | V147: =IFERROR(VLOOKUP(CONCATENATE(Fix_Mapping[[#This Row],[KODE BARANG]],4),'Form Fix'!$A$6:$F$1063,4,0),0) -> 0 | W147: =IFERROR(VLOOKUP(CONCATENATE(Fix_Mapping[[#This Row],[KODE BARANG]],5),'Form Fix'!$A$6:$F$1063,4,0),0) -> 0
A148: A1122003001811 | B148: ABC SAMBAL NUS. RENDANG 18GR X 10 PACK PCSX10 B8G2 | C148: 10 | D148: PCSX10 | E148: SAMBAL NUS. | F148: 10664.723 | G148: 106647.23 | H148: 11837.843 | I148: 118378.43 | J148: 11345.45 | K148: 113454.5 | L148: 12593.45 | M148: 125934.5 | N148: 0 | O148: 0 | P148: 0 | Q148: 0 | R148: PT. HEINZ ABC INDONESIA | S148: =IFERROR(VLOOKUP(CONCATENATE(Fix_Mapping[[#This Row],[KODE BARANG]],1),'Form Fix'!$A$6:$F$1063,4,0),0) -> 612955 | T148: =IFERROR(VLOOKUP(CONCATENATE(Fix_Mapping[[#This Row],[KODE BARANG]],2),'Form Fix'!$A$6:$F$1063,4,0),0) -> 0 | U148: =IFERROR(VLOOKUP(CONCATENATE(Fix_Mapping[[#This Row],[KODE BARANG]],3),'Form Fix'!$A$6:$F$1063,4,0),0) -> 0 | V148: =IFERROR(VLOOKUP(CONCATENATE(Fix_Mapping[[#This Row],[KODE BARANG]],4),'Form Fix'!$A$6:$F$1063,4,0),0) -> 0 | W148: =IFERROR(VLOOKUP(CONCATENATE(Fix_Mapping[[#This Row],[KODE BARANG]],5),'Form Fix'!$A$6:$F$1063,4,0),0) -> 0
A149: A1122004001810 | B149: ABC SAMBAL NUSANTARA GEPREK 18 GR X 10 PACK PCSX10 | C149: 10 | D149: PCSX10 | E149: SAMBAL NUSANTARA | F149: 13330.911 | G149: 133309.11 | H149: 14797.311 | I149: 147973.11 | J149: 14181.82 | K149: 141818.2 | L149: 15741.82 | M149: 157418.2 | N149: 15316.363 | O149: 153163.63 | P149: 17001.163 | Q149: 170011.63 | R149: PT. HEINZ ABC INDONESIA | S149: =IFERROR(VLOOKUP(CONCATENATE(Fix_Mapping[[#This Row],[KODE BARANG]],1),'Form Fix'!$A$6:$F$1063,4,0),0) -> 612130 | T149: =IFERROR(VLOOKUP(CONCATENATE(Fix_Mapping[[#This Row],[KODE BARANG]],2),'Form Fix'!$A$6:$F$1063,4,0),0) -> 150202 | U149: =IFERROR(VLOOKUP(CONCATENATE(Fix_Mapping[[#This Row],[KODE BARANG]],3),'Form Fix'!$A$6:$F$1063,4,0),0) -> 0 | V149: =IFERROR(VLOOKUP(CONCATENATE(Fix_Mapping[[#This Row],[KODE BARANG]],4),'Form Fix'!$A$6:$F$1063,4,0),0) -> 0 | W149: =IFERROR(VLOOKUP(CONCATENATE(Fix_Mapping[[#This Row],[KODE BARANG]],5),'Form Fix'!$A$6:$F$1063,4,0),0) -> 0
A150: A1122004001811 | B150: ABC SAMBAL NUS. GEPREK 18 GR X 10 PACK PCSX10 B8G2 | C150: 10 | D150: PCSX10 | E150: SAMBAL NUS. | F150: 10664.723 | G150: 106647.23 | H150: 11837.843 | I150: 118378.43 | J150: 11345.45 | K150: 113454.5 | L150: 12593.45 | M150: 125934.5 | N150: 0 | O150: 0 | P150: 0 | Q150: 0 | R150: PT. HEINZ ABC INDONESIA | S150: =IFERROR(VLOOKUP(CONCATENATE(Fix_Mapping[[#This Row],[KODE BARANG]],1),'Form Fix'!$A$6:$F$1063,4,0),0) -> 612957 | T150: =IFERROR(VLOOKUP(CONCATENATE(Fix_Mapping[[#This Row],[KODE BARANG]],2),'Form Fix'!$A$6:$F$1063,4,0),0) -> 0 | U150: =IFERROR(VLOOKUP(CONCATENATE(Fix_Mapping[[#This Row],[KODE BARANG]],3),'Form Fix'!$A$6:$F$1063,4,0),0) -> 0 | V150: =IFERROR(VLOOKUP(CONCATENATE(Fix_Mapping[[#This Row],[KODE BARANG]],4),'Form Fix'!$A$6:$F$1063,4,0),0) -> 0 | W150: =IFERROR(VLOOKUP(CONCATENATE(Fix_Mapping[[#This Row],[KODE BARANG]],5),'Form Fix'!$A$6:$F$1063,4,0),0) -> 0
A151: A1122005001810 | B151: ABC SAMBAL NUSANTARA TERI 18 GR X 10 PACK PCSX10 | C151: 10 | D151: PCSX10 | E151: SAMBAL NUSANTARA | F151: 13330.911 | G151: 133309.11 | H151: 14797.311 | I151: 147973.11 | J151: 14181.82 | K151: 141818.2 | L151: 15741.82 | M151: 157418.2 | N151: 15316.363 | O151: 153163.63 | P151: 17001.163 | Q151: 170011.63 | R151: PT. HEINZ ABC INDONESIA | S151: =IFERROR(VLOOKUP(CONCATENATE(Fix_Mapping[[#This Row],[KODE BARANG]],1),'Form Fix'!$A$6:$F$1063,4,0),0) -> 612100 | T151: =IFERROR(VLOOKUP(CONCATENATE(Fix_Mapping[[#This Row],[KODE BARANG]],2),'Form Fix'!$A$6:$F$1063,4,0),0) -> 0 | U151: =IFERROR(VLOOKUP(CONCATENATE(Fix_Mapping[[#This Row],[KODE BARANG]],3),'Form Fix'!$A$6:$F$1063,4,0),0) -> 0 | V151: =IFERROR(VLOOKUP(CONCATENATE(Fix_Mapping[[#This Row],[KODE BARANG]],4),'Form Fix'!$A$6:$F$1063,4,0),0) -> 0 | W151: =IFERROR(VLOOKUP(CONCATENATE(Fix_Mapping[[#This Row],[KODE BARANG]],5),'Form Fix'!$A$6:$F$1063,4,0),0) -> 0
A152: A1122005001811 | B152: ABC SAMBAL NUS. TERI 18 GR X 10 PACK PCSX10 B8G2 | C152: 10 | D152: PCSX10 | E152: SAMBAL NUS. | F152: 10664.723 | G152: 106647.23 | H152: 11837.843 | I152: 118378.43 | J152: 11345.45 | K152: 113454.5 | L152: 12593.45 | M152: 125934.5 | N152: 0 | O152: 0 | P152: 0 | Q152: 0 | R152: PT. HEINZ ABC INDONESIA | S152: =IFERROR(VLOOKUP(CONCATENATE(Fix_Mapping[[#This Row],[KODE BARANG]],1),'Form Fix'!$A$6:$F$1063,4,0),0) -> 612956 | T152: =IFERROR(VLOOKUP(CONCATENATE(Fix_Mapping[[#This Row],[KODE BARANG]],2),'Form Fix'!$A$6:$F$1063,4,0),0) -> 0 | U152: =IFERROR(VLOOKUP(CONCATENATE(Fix_Mapping[[#This Row],[KODE BARANG]],3),'Form Fix'!$A$6:$F$1063,4,0),0) -> 0 | V152: =IFERROR(VLOOKUP(CONCATENATE(Fix_Mapping[[#This Row],[KODE BARANG]],4),'Form Fix'!$A$6:$F$1063,4,0),0) -> 0 | W152: =IFERROR(VLOOKUP(CONCATENATE(Fix_Mapping[[#This Row],[KODE BARANG]],5),'Form Fix'!$A$6:$F$1063,4,0),0) -> 0
... A158: A1130001022011B | B158: B> ABC MINYAK GORENG ROSEBRAND 220ML X 48 CUP | C158: 48 | D158: CUP | E158: MINYAK GORENG | F158: 0 | G158: 0 | H158: 0 | I158: 0 | J158: 0 | K158: 0 | L158: 0 | M158: 0 | N158: 0 | O158: 0 | P158: 0 | Q158: 0 | R158: PT. HEINZ ABC INDONESIA | S158: =IFERROR(VLOOKUP(CONCATENATE(Fix_Mapping[[#This Row],[KODE BARANG]],1),'Form Fix'!$A$6:$F$1063,4,0),0) -> 900005 | T158: =IFERROR(VLOOKUP(CONCATENATE(Fix_Mapping[[#This Row],[KODE BARANG]],2),'Form Fix'!$A$6:$F$1063,4,0),0) -> 0 | U158: =IFERROR(VLOOKUP(CONCATENATE(Fix_Mapping[[#This Row],[KODE BARANG]],3),'Form Fix'!$A$6:$F$1063,4,0),0) -> 0 | V158: =IFERROR(VLOOKUP(CONCATENATE(Fix_Mapping[[#This Row],[KODE BARANG]],4),'Form Fix'!$A$6:$F$1063,4,0),0) -> 0 | W158: =IFERROR(VLOOKUP(CONCATENATE(Fix_Mapping[[#This Row],[KODE BARANG]],5),'Form Fix'!$A$6:$F$1063,4,0),0) -> 0
A159: A1140001000011B | B159: B> ABC T-SHIRT RETAIL GIMMICK X 1 PCS | C159: 1 | D159: PCS | E159: T-SHIRT | F159: 0 | G159: 0 | H159: 0 | I159: 0 | J159: 0 | K159: 0 | L159: 0 | M159: 0 | N159: 0 | O159: 0 | P159: 0 | Q159: 0 | S159: =IFERROR(VLOOKUP(CONCATENATE(Fix_Mapping[[#This Row],[KODE BARANG]],1),'Form Fix'!$A$6:$F$1063,4,0),0) -> 900053 | T159: =IFERROR(VLOOKUP(CONCATENATE(Fix_Mapping[[#This Row],[KODE BARANG]],2),'Form Fix'!$A$6:$F$1063,4,0),0) -> 0 | U159: =IFERROR(VLOOKUP(CONCATENATE(Fix_Mapping[[#This Row],[KODE BARANG]],3),'Form Fix'!$A$6:$F$1063,4,0),0) -> 0 | V159: =IFERROR(VLOOKUP(CONCATENATE(Fix_Mapping[[#This Row],[KODE BARANG]],4),'Form Fix'!$A$6:$F$1063,4,0),0) -> 0 | W159: =IFERROR(VLOOKUP(CONCATENATE(Fix_Mapping[[#This Row],[KODE BARANG]],5),'Form Fix'!$A$6:$F$1063,4,0),0) -> 0
A160: A1150001000011B | B160: B> ABC KAOS CORDIAL SACHET SG X 1 PCS | C160: 1 | D160: PCS | E160: KAOS | F160: 0 | G160: 0 | H160: 0 | I160: 0 | K160: 0 | L160: 0 | M160: 0 | O160: 0 | P160: 0 | Q160: 0 | S160: =IFERROR(VLOOKUP(CONCATENATE(Fix_Mapping[[#This Row],[KODE BARANG]],1),'Form Fix'!$A$6:$F$1063,4,0),0) -> 900044 | T160: =IFERROR(VLOOKUP(CONCATENATE(Fix_Mapping[[#This Row],[KODE BARANG]],2),'Form Fix'!$A$6:$F$1063,4,0),0) -> 0 | U160: =IFERROR(VLOOKUP(CONCATENATE(Fix_Mapping[[#This Row],[KODE BARANG]],3),'Form Fix'!$A$6:$F$1063,4,0),0) -> 0 | V160: =IFERROR(VLOOKUP(CONCATENATE(Fix_Mapping[[#This Row],[KODE BARANG]],4),'Form Fix'!$A$6:$F$1063,4,0),0) -> 0 | W160: =IFERROR(VLOOKUP(CONCATENATE(Fix_Mapping[[#This Row],[KODE BARANG]],5),'Form Fix'!$A$6:$F$1063,4,0),0) -> 0

Sheet Query Map.BrgDoubleDms
A1: Kode BARANG Win2 | B1: Nama Win | C1: PCPL KODE 1 | D1: PCPL KODE 2 | E1: PCPL KODE 3 | F1: PCPL KODE 4 | G1: PCPL KODE 5
A2: A1011000006210 | B2: ABC KECAP MANIS 62 GR X 48 PCH | C2: =IFERROR(VLOOKUP(CONCATENATE(Table43_1[[#This Row],[Kode BARANG Win2]],1),'Form Fix'!$A$6:$F$310,4,0),0) -> 100189 | D2: =IFERROR(VLOOKUP(CONCATENATE(Table43_1[[#This Row],[Kode BARANG Win2]],2),'Form Fix'!$A$6:$F$310,4,0),0) -> 100222 | E2: =IFERROR(VLOOKUP(CONCATENATE(Table43_1[[#This Row],[Kode BARANG Win2]],3),'Form Fix'!$A$6:$F$310,4,0),0) -> 100240 | F2: =IFERROR(VLOOKUP(CONCATENATE(Table43_1[[#This Row],[Kode BARANG Win2]],4),'Form Fix'!$A$6:$F$310,4,0),0) -> 0 | G2: =IFERROR(VLOOKUP(CONCATENATE(Table43_1[[#This Row],[Kode BARANG Win2]],5),'Form Fix'!$A$6:$F$310,4,0),0) -> 0
A3: A1011000006211 | B3: ABC KECAP MANIS 62 GR X 48 PCH B5G1 | C3: =IFERROR(VLOOKUP(CONCATENATE(Table43_1[[#This Row],[Kode BARANG Win2]],1),'Form Fix'!$A$6:$F$310,4,0),0) -> 100986 | D3: =IFERROR(VLOOKUP(CONCATENATE(Table43_1[[#This Row],[Kode BARANG Win2]],2),'Form Fix'!$A$6:$F$310,4,0),0) -> 0 | E3: =IFERROR(VLOOKUP(CONCATENATE(Table43_1[[#This Row],[Kode BARANG Win2]],3),'Form Fix'!$A$6:$F$310,4,0),0) -> 0 | F3: =IFERROR(VLOOKUP(CONCATENATE(Table43_1[[#This Row],[Kode BARANG Win2]],4),'Form Fix'!$A$6:$F$310,4,0),0) -> 0 | G3: =IFERROR(VLOOKUP(CONCATENATE(Table43_1[[#This Row],[Kode BARANG Win2]],5),'Form Fix'!$A$6:$F$310,4,0),0) -> 0
A4: A1011000008010 | B4: ABC KECAP MANIS 80 ML X 48 PCH | C4: =IFERROR(VLOOKUP(CONCATENATE(Table43_1[[#This Row],[Kode BARANG Win2]],1),'Form Fix'!$A$6:$F$310,4,0),0) -> 100179 | D4: =IFERROR(VLOOKUP(CONCATENATE(Table43_1[[#This Row],[Kode BARANG Win2]],2),'Form Fix'!$A$6:$F$310,4,0),0) -> 0 | E4: =IFERROR(VLOOKUP(CONCATENATE(Table43_1[[#This Row],[Kode BARANG Win2]],3),'Form Fix'!$A$6:$F$310,4,0),0) -> 0 | F4: =IFERROR(VLOOKUP(CONCATENATE(Table43_1[[#This Row],[Kode BARANG Win2]],4),'Form Fix'!$A$6:$F$310,4,0),0) -> 0 | G4: =IFERROR(VLOOKUP(CONCATENATE(Table43_1[[#This Row],[Kode BARANG Win2]],5),'Form Fix'!$A$6:$F$310,4,0),0) -> 0
A5: A1011000013010 | B5: ABC KECAP MANIS 135 ML X 48 BTL | C5: =IFERROR(VLOOKUP(CONCATENATE(Table43_1[[#This Row],[Kode BARANG Win2]],1),'Form Fix'!$A$6:$F$310,4,0),0) -> 100234 | D5: =IFERROR(VLOOKUP(CONCATENATE(Table43_1[[#This Row],[Kode BARANG Win2]],2),'Form Fix'!$A$6:$F$310,4,0),0) -> 0 | E5: =IFERROR(VLOOKUP(CONCATENATE(Table43_1[[#This Row],[Kode BARANG Win2]],3),'Form Fix'!$A$6:$F$310,4,0),0) -> 0 | F5: =IFERROR(VLOOKUP(CONCATENATE(Table43_1[[#This Row],[Kode BARANG Win2]],4),'Form Fix'!$A$6:$F$310,4,0),0) -> 0 | G5: =IFERROR(VLOOKUP(CONCATENATE(Table43_1[[#This Row],[Kode BARANG Win2]],5),'Form Fix'!$A$6:$F$310,4,0),0) -> 0
A6: A1011000013510 | B6: ABC KECAP MANIS 135 ML X 48 BTL | C6: =IFERROR(VLOOKUP(CONCATENATE(Table43_1[[#This Row],[Kode BARANG Win2]],1),'Form Fix'!$A$6:$F$310,4,0),0) -> 100161 | D6: =IFERROR(VLOOKUP(CONCATENATE(Table43_1[[#This Row],[Kode BARANG Win2]],2),'Form Fix'!$A$6:$F$310,4,0),0) -> 0 | E6: =IFERROR(VLOOKUP(CONCATENATE(Table43_1[[#This Row],[Kode BARANG Win2]],3),'Form Fix'!$A$6:$F$310,4,0),0) -> 0 | F6: =IFERROR(VLOOKUP(CONCATENATE(Table43_1[[#This Row],[Kode BARANG Win2]],4),'Form Fix'!$A$6:$F$310,4,0),0) -> 0 | G6: =IFERROR(VLOOKUP(CONCATENATE(Table43_1[[#This Row],[Kode BARANG Win2]],5),'Form Fix'!$A$6:$F$310,4,0),0) -> 0
A7: A1011000025010 | B7: ABC KECAP MANIS 250 GR X 24 PCH | C7: =IFERROR(VLOOKUP(CONCATENATE(Table43_1[[#This Row],[Kode BARANG Win2]],1),'Form Fix'!$A$6:$F$310,4,0),0) -> 100220 | D7: =IFERROR(VLOOKUP(CONCATENATE(Table43_1[[#This Row],[Kode BARANG Win2]],2),'Form Fix'!$A$6:$F$310,4,0),0) -> 100238 | E7: =IFERROR(VLOOKUP(CONCATENATE(Table43_1[[#This Row],[Kode BARANG Win2]],3),'Form Fix'!$A$6:$F$310,4,0),0) -> 0 | F7: =IFERROR(VLOOKUP(CONCATENATE(Table43_1[[#This Row],[Kode BARANG Win2]],4),'Form Fix'!$A$6:$F$310,4,0),0) -> 0 | G7: =IFERROR(VLOOKUP(CONCATENATE(Table43_1[[#This Row],[Kode BARANG Win2]],5),'Form Fix'!$A$6:$F$310,4,0),0) -> 0
A8: A1011000025011 | B8: ABC KECAP MANIS 250 GR X 24 PCH BANDED | C8: =IFERROR(VLOOKUP(CONCATENATE(Table43_1[[#This Row],[Kode BARANG Win2]],1),'Form Fix'!$A$6:$F$310,4,0),0) -> 100992 | D8: =IFERROR(VLOOKUP(CONCATENATE(Table43_1[[#This Row],[Kode BARANG Win2]],2),'Form Fix'!$A$6:$F$310,4,0),0) -> 0 | E8: =IFERROR(VLOOKUP(CONCATENATE(Table43_1[[#This Row],[Kode BARANG Win2]],3),'Form Fix'!$A$6:$F$310,4,0),0) -> 0 | F8: =IFERROR(VLOOKUP(CONCATENATE(Table43_1[[#This Row],[Kode BARANG Win2]],4),'Form Fix'!$A$6:$F$310,4,0),0) -> 0 | G8: =IFERROR(VLOOKUP(CONCATENATE(Table43_1[[#This Row],[Kode BARANG Win2]],5),'Form Fix'!$A$6:$F$310,4,0),0) -> 0
A9: A1011000060011 | B9: ABC KECAP MANIS 600 GR X PCH BANDED | C9: =IFERROR(VLOOKUP(CONCATENATE(Table43_1[[#This Row],[Kode BARANG Win2]],1),'Form Fix'!$A$6:$F$310,4,0),0) -> 0 | D9: =IFERROR(VLOOKUP(CONCATENATE(Table43_1[[#This Row],[Kode BARANG Win2]],2),'Form Fix'!$A$6:$F$310,4,0),0) -> 0 | E9: =IFERROR(VLOOKUP(CONCATENATE(Table43_1[[#This Row],[Kode BARANG Win2]],3),'Form Fix'!$A$6:$F$310,4,0),0) -> 0 | F9: =IFERROR(VLOOKUP(CONCATENATE(Table43_1[[#This Row],[Kode BARANG Win2]],4),'Form Fix'!$A$6:$F$310,4,0),0) -> 0 | G9: =IFERROR(VLOOKUP(CONCATENATE(Table43_1[[#This Row],[Kode BARANG Win2]],5),'Form Fix'!$A$6:$F$310,4,0),0) -> 0
A10: A1011000027520 | B10: ABC KECAP MANIS 275 ML X 24 BTL | C10: =IFERROR(VLOOKUP(CONCATENATE(Table43_1[[#This Row],[Kode BARANG Win2]],1),'Form Fix'!$A$6:$F$310,4,0),0) -> 100162 | D10: =IFERROR(VLOOKUP(CONCATENATE(Table43_1[[#This Row],[Kode BARANG Win2]],2),'Form Fix'!$A$6:$F$310,4,0),0) -> 100236 | E10: =IFERROR(VLOOKUP(CONCATENATE(Table43_1[[#This Row],[Kode BARANG Win2]],3),'Form Fix'!$A$6:$F$310,4,0),0) -> 0 | F10: =IFERROR(VLOOKUP(CONCATENATE(Table43_1[[#This Row],[Kode BARANG Win2]],4),'Form Fix'!$A$6:$F$310,4,0),0) -> 0 | G10: =IFERROR(VLOOKUP(CONCATENATE(Table43_1[[#This Row],[Kode BARANG Win2]],5),'Form Fix'!$A$6:$F$310,4,0),0) -> 0
A11: A1011000030010 | B11: ABC KECAP MANIS 300 GR X 24 PCH | C11: =IFERROR(VLOOKUP(CONCATENATE(Table43_1[[#This Row],[Kode BARANG Win2]],1),'Form Fix'!$A$6:$F$310,4,0),0) -> 100158 | D11: =IFERROR(VLOOKUP(CONCATENATE(Table43_1[[#This Row],[Kode BARANG Win2]],2),'Form Fix'!$A$6:$F$310,4,0),0) -> 100172 | E11: =IFERROR(VLOOKUP(CONCATENATE(Table43_1[[#This Row],[Kode BARANG Win2]],3),'Form Fix'!$A$6:$F$310,4,0),0) -> 0 | F11: =IFERROR(VLOOKUP(CONCATENATE(Table43_1[[#This Row],[Kode BARANG Win2]],4),'Form Fix'!$A$6:$F$310,4,0),0) -> 0 | G11: =IFERROR(VLOOKUP(CONCATENATE(Table43_1[[#This Row],[Kode BARANG Win2]],5),'Form Fix'!$A$6:$F$310,4,0),0) -> 0
A12: A1011000030012 | B12: ABC KECAP MANIS 600 GR X 12 PCH BANDED | C12: =IFERROR(VLOOKUP(CONCATENATE(Table43_1[[#This Row],[Kode BARANG Win2]],1),'Form Fix'!$A$6:$F$310,4,0),0) -> 100991 | D12: =IFERROR(VLOOKUP(CONCATENATE(Table43_1[[#This Row],[Kode BARANG Win2]],2),'Form Fix'!$A$6:$F$310,4,0),0) -> 109002 | E12: =IFERROR(VLOOKUP(CONCATENATE(Table43_1[[#This Row],[Kode BARANG Win2]],3),'Form Fix'!$A$6:$F$310,4,0),0) -> 109001 | F12: =IFERROR(VLOOKUP(CONCATENATE(Table43_1[[#This Row],[Kode BARANG Win2]],4),'Form Fix'!$A$6:$F$310,4,0),0) -> 0 | G12: =IFERROR(VLOOKUP(CONCATENATE(Table43_1[[#This Row],[Kode BARANG Win2]],5),'Form Fix'!$A$6:$F$310,4,0),0) -> 0
A13: A1011000045010 | B13: ABC KECAP MANIS 450 GR X 12 PCH | C13: =IFERROR(VLOOKUP(CONCATENATE(Table43_1[[#This Row],[Kode BARANG Win2]],1),'Form Fix'!$A$6:$F$310,4,0),0) -> 100241 | D13: =IFERROR(VLOOKUP(CONCATENATE(Table43_1[[#This Row],[Kode BARANG Win2]],2),'Form Fix'!$A$6:$F$310,4,0),0) -> 0 | E13: =IFERROR(VLOOKUP(CONCATENATE(Table43_1[[#This Row],[Kode BARANG Win2]],3),'Form Fix'!$A$6:$F$310,4,0),0) -> 0 | F13: =IFERROR(VLOOKUP(CONCATENATE(Table43_1[[#This Row],[Kode BARANG Win2]],4),'Form Fix'!$A$6:$F$310,4,0),0) -> 0 | G13: =IFERROR(VLOOKUP(CONCATENATE(Table43_1[[#This Row],[Kode BARANG Win2]],5),'Form Fix'!$A$6:$F$310,4,0),0) -> 0
... A168: A1150001000011B | B168: B> ABC KAOS CORDIAL SACHET SG X 1 PCS | C168: =IFERROR(VLOOKUP(CONCATENATE(Table43_1[[#This Row],[Kode BARANG Win2]],1),'Form Fix'!$A$6:$F$310,4,0),0) -> 900044 | D168: =IFERROR(VLOOKUP(CONCATENATE(Table43_1[[#This Row],[Kode BARANG Win2]],2),'Form Fix'!$A$6:$F$310,4,0),0) -> 0 | E168: =IFERROR(VLOOKUP(CONCATENATE(Table43_1[[#This Row],[Kode BARANG Win2]],3),'Form Fix'!$A$6:$F$310,4,0),0) -> 0 | F168: =IFERROR(VLOOKUP(CONCATENATE(Table43_1[[#This Row],[Kode BARANG Win2]],4),'Form Fix'!$A$6:$F$310,4,0),0) -> 0 | G168: =IFERROR(VLOOKUP(CONCATENATE(Table43_1[[#This Row],[Kode BARANG Win2]],5),'Form Fix'!$A$6:$F$310,4,0),0) -> 0

Sheet Form Fix
C1: UPDATE TGL
O2: =COUNTIF(Table43[LEN 50], ">50") -> 1
D3: PASTE NAMA DAN CODE PRINCIPLE (Buat Format seperti ini dan Ambil dari Daftar Harga Principle) | P3: CPI | AL3: Daftar Harga | AY3: Update Per
I4: ISI SESUAIKAN ANTARA DMS vs WIN | K4: HASIL CODE KELOMPOK, CODE BARANG & NAMA BARANG WIN | P4: Kolom Principle | AL4: Harga Beli | AP4: Harga Jual GT | AT4: Harga Jual Motorist | AX4: MARGIN | BD4: To Win, diisi oleh Admin
A5: CONCATENATE MAPPING | B5: No. Urut Item Sama | C5: NO | D5: Kode Pcpl | E5: Klp Brg Pcpl | F5: Nama Barang Principle | G5: ISI/CTN | H5: Ket. Tambahan / Pembantu | I5: SATUAN Fix Win | J5: Nama Kelompok Win | K5: Kode Kelompok Win | L5: Kode BARANG Win2 | M5: LEN 15 | N5: Nama Win | O5: LEN 50 | P5: Nama Pcpl | Q5: kode 2 Digit (hrf+No) | R5: Nama KLP | S5: kode 2 Digit (Nomor) | T5: Nama Sub KLP | U5: kode 1 Digit (Nomor) | V5: Nama Sub KLP2 | W5: kode 1 Digit (Nomor)5 | X5: Nama Aroma/ Rasa | Y5: kode 2 Digit (Nomor)2 | Z5: Nama Gramasi atau Jumlah Pack per CTN | AA5: kode 4 Digit (Nomor) | AB5: Nama Jenis Kemasan | AC5: kode 1 Digit (Nomor)3 | AD5: Nama Promo | AE5: kode 1 Digit (Nomor)4 | AF5: Gunakan ini apabila item tersebut sachet | AG5: kode 1 Digit (Nomor)32 | AH5: KET TAMBAHAN2 | AI5: KET. GOLONGAN | AJ5: kode 1 Digit (Nomor) | AK5: Tanda Kode Revisi | AL5: Harga Beli Pcs (-PPN) | AM5: Harga Beli Krt (- PPN) | AN5: Harga Beli Pcs (+PPN) | AO5: Harga Beli Krt (+PPN) | AP5: Harga Jual Pcs GT (-PPN) | AQ5: Harga Jual Krt GT (- PPN) | AR5: Harga Jual Pcs GT (+PPN | AS5: Harga Jual Krt GT (+PPN) | AT5: Harga Jual Pcs MT (-PPN) | AU5: Harga Jual Krt MT (- PPN) | AV5: Harga Jual Pcs MT (+PPN) | AW5: Harga Jual Krt MT (+PPN) | AX5: MARGIN | AY5: Efektif Pembuatan | AZ5: Efektif Naik Harga | BA5: Status Pembuatan | BB5: Status Harga | BC5: Status Barang | BD5: Mata Uang | BE5: Kode Golongan | BF5: Nama Golongan | BG5: Kode PCPL To Win | BH5: Kode Jenis Produk | BI5: SAT BSR | BJ5: GD | BK5: Kode PRK | BL5: Kode PRK SJ | BM5: Kode Job | BN5: Approval | BO5: Nama Principle | BP5: HARGA NAIK GT | BQ5: CEK | BR5: FIX HARGA | BS5: HARGA NAIK GT | BT5: CEK | BU5: FIX HARGA | BV5: HARGA MOTORIS +PPN | BW5: FIX HARGA | BX5: HARGA MOTORIS -PPN
A6: =CONCATENATE(Table43[[#This Row],[Kode BARANG Win2]],Table43[[#This Row],[No. Urut Item Sama]]) -> A10110000062101 | B6: 1 | C6: 1 | D6: 100189 | E6: RASA MANTAP SOY | F6: ABC KCP MNS PCH 48X75G 2208 | G6: 48 | H6: 7000003080 | I6: =Table43[[#This Row],[Nama Jenis Kemasan]] -> PCH | J6: =TRIM(CONCATENATE(Table43[[#This Row],[Nama KLP]]," ",Table43[[#This Row],[Nama Sub KLP]])) -> KECAP MANIS | K6: =CONCATENATE(Table43[[#This Row],[kode 2 Digit (hrf+No)]],Table43[[#This Row],[kode 2 Digit (Nomor)]],Table43[[#This Row],[kode 1 Digit (Nomor)]]) -> A1011 | L6: =IF(AG6="",CONCATENATE(Q6,S6,U6,W6,Y6,AA6,AC6,AE6,Table43[[#This Row],[Tanda Kode Revisi]]),CONCATENATE(Q6,S6,U6,W6,Y6,AA6,AC6,AG6)) -> A1011000006210 | M6: =LEN(L6) -> 14 | N6: =IF(AF6<>"",TRIM(UPPER(CONCATENATE(P6," ",R6," ",T6," ",V6," ",X6," ",Z6," ","X"," ",Table43[[#This Row],[ISI/CTN]]," ",AF6," ",AB6," ",AD6," ",AH6))),TRIM(UPPER(CONCATENATE(P6," ",R6," ",T6," ",V6," ",X6," ",Z6," ","X"," ",Table43[[#This Row],[ISI/CTN]]," ",AB6," ",AD6," ",AH6)))) -> ABC KECAP MANIS 62 GR X 48 PCH | O6: =LEN(N6) -> 30 | P6: ABC | Q6: A1 | R6: KECAP | S6: 01 | T6: MANIS | U6: 1 | W6: 0 | Y6: 00 | Z6: 62 GR | AA6: 0062 | AB6: PCH | AC6: 1 | AE6: 0 | AI6: GRAM | AJ6: 1 | AL6: =Table43[[#This Row],[Harga Jual Pcs GT (-PPN)]]-(Table43[[#This Row],[Harga Jual Pcs GT (-PPN)]]*6%) -> 1354.9536 | AM6: =Table43[[#This Row],[Harga Beli Pcs (-PPN)]]*Table43[[#This Row],[ISI/CTN]] -> 65037.773 | AN6: =Table43[[#This Row],[Harga Beli Pcs (-PPN)]]*1.11 -> 1503.9985 | AO6: =Table43[[#This Row],[Harga Beli Krt (- PPN)]]*1.11 -> 72191.928 | AP6: 1441.44 | AQ6: =Table43[[#This Row],[Harga Jual Pcs GT (-PPN)]]*Table43[[#This Row],[ISI/CTN]] -> 69189.12 | AR6: =Table43[[#This Row],[Harga Jual Pcs GT (-PPN)]]*1.11 -> 1599.9984 | AS6: =Table43[[#This Row],[Harga Jual Krt GT (- PPN)]]*1.11 -> 76799.923 | AT6: 1556.76 | AU6: =(Table43[[#This Row],[Harga Jual Pcs MT (-PPN)]]*Table43[[#This Row],[ISI/CTN]]) -> 74724.48 | AV6: =Table43[[#This Row],[Harga Jual Pcs MT (-PPN)]]*1.11 -> 1728.0036 | AW6: =Table43[[#This Row],[Harga Jual Pcs MT (+PPN)]]*Table43[[#This Row],[ISI/CTN]] -> 82944.173 | AY6: 45553 | AZ6: 45553 | BA6: =IF(TODAY()-Table43[[#This Row],[Efektif Pembuatan]]>60,"Lama","Baru") -> Lama | BB6: =IF(TODAY()-Table43[[#This Row],[Efektif Naik Harga]]<30,"Naik","Sama") -> Sama | BC6: Aktif | BD6: =IF(Table43[[#This Row],[Kode BARANG Win2]]<>"","IDR","") -> IDR | BE6: =CONCATENATE(Table43[[#This Row],[kode 1 Digit (Nomor)]],Table43[[#This Row],[kode 4 Digit (Nomor)]]) -> 10062 | BF6: =Table43[[#This Row],[Nama Gramasi atau Jumlah Pack per CTN]] -> 62 GR | BG6: S-HNZ | BH6: 48HEINZ | BI6: =IF(Table43[[#This Row],[SATUAN Fix Win]]<>"","KRT") -> KRT | BJ6: =IF(Table43[[#This Row],[SATUAN Fix Win]]<>"","GD01") -> GD01 | BK6: =IF(Table43[[#This Row],[SATUAN Fix Win]]<>"",11611) -> 11611 | BL6: =IF(Table43[[#This Row],[SATUAN Fix Win]]<>"",11612) -> 11612 | BM6: 0123 | BN6: =IF(Table43[[#This Row],[SATUAN Fix Win]]<>"",1) -> 1 | BO6: PT. HEINZ ABC INDONESIA | BP6: =IFERROR(VLOOKUP(Table43[[#This Row],[Kode Pcpl]],'[1]HEINZ ABC'!$A$4:$E$112,8,0),0) -> 0 | BQ6: =Table43[[#This Row],[Harga Jual Pcs GT (-PPN)]]-Table43[[#This Row],[HARGA NAIK GT]] -> 1441.44 | BR6: =IF(Table43[[#This Row],[HARGA NAIK GT]]=0,Table43[[#This Row],[Harga Jual Pcs GT (-PPN)]],Table43[[#This Row],[HARGA NAIK GT]]) -> 1441.44 | BS6: =IFERROR(VLOOKUP(Table43[[#This Row],[Kode Pcpl]],'[1]HEINZ ABC'!$A$4:$E$112,8,0),0) -> 0 | BT6: =Table43[[#This Row],[Harga Jual Pcs GT (-PPN)]]-BS6 -> 1441.44 | BU6: =IF(BS6=0,Table43[[#This Row],[Harga Jual Pcs MT (-PPN)]]) -> 1556.76 | BV6: =IFERROR(VLOOKUP(Table43[[#This Row],[Kode Pcpl]],[2]Pricelist!$A$4:$K$112,11,0),0) -> 0 | BW6: =IFERROR(VLOOKUP(Table43[[#This Row],[Kode BARANG Win2]],[3]!RECKITT211216[[KDBRG]:[HRG_JL_PCS-PPN]],11,0),0) -> 0 | BX6: =BV6/1.11 -> 0
A7: =CONCATENATE(Table43[[#This Row],[Kode BARANG Win2]],Table43[[#This Row],[No. Urut Item Sama]]) -> A10110000062102 | B7: 2 | C7: 2 | D7: 100222 | E7: RASA MANTAP SOY | F7: ABC KCP MNS PCH 48X62G 2311 | G7: 48 | H7: 7000003102 | I7: =Table43[[#This Row],[Nama Jenis Kemasan]] -> PCH | J7: =TRIM(CONCATENATE(Table43[[#This Row],[Nama KLP]]," ",Table43[[#This Row],[Nama Sub KLP]])) -> KECAP MANIS | K7: =CONCATENATE(Table43[[#This Row],[kode 2 Digit (hrf+No)]],Table43[[#This Row],[kode 2 Digit (Nomor)]],Table43[[#This Row],[kode 1 Digit (Nomor)]]) -> A1011 | L7: =IF(AG7="",CONCATENATE(Q7,S7,U7,W7,Y7,AA7,AC7,AE7,Table43[[#This Row],[Tanda Kode Revisi]]),CONCATENATE(Q7,S7,U7,W7,Y7,AA7,AC7,AG7)) -> A1011000006210 | M7: =LEN(L7) -> 14 | N7: =IF(AF7<>"",TRIM(UPPER(CONCATENATE(P7," ",R7," ",T7," ",V7," ",X7," ",Z7," ","X"," ",Table43[[#This Row],[ISI/CTN]]," ",AF7," ",AB7," ",AD7," ",AH7))),TRIM(UPPER(CONCATENATE(P7," ",R7," ",T7," ",V7," ",X7," ",Z7," ","X"," ",Table43[[#This Row],[ISI/CTN]]," ",AB7," ",AD7," ",AH7)))) -> ABC KECAP MANIS 62 GR X 48 PCH | O7: =LEN(N7) -> 30 | P7: ABC | Q7: A1 | R7: KECAP | S7: 01 | T7: MANIS | U7: 1 | W7: 0 | Y7: 00 | Z7: 62 GR | AA7: 0062 | AB7: PCH | AC7: 1 | AE7: 0 | AI7: GRAM | AJ7: 1 | AL7: =Table43[[#This Row],[Harga Jual Pcs GT (-PPN)]]-(Table43[[#This Row],[Harga Jual Pcs GT (-PPN)]]*6%) -> 1354.9536 | AM7: =Table43[[#This Row],[Harga Beli Pcs (-PPN)]]*Table43[[#This Row],[ISI/CTN]] -> 65037.773 | AN7: =Table43[[#This Row],[Harga Beli Pcs (-PPN)]]*1.11 -> 1503.9985 | AO7: =Table43[[#This Row],[Harga Beli Krt (- PPN)]]*1.11 -> 72191.928 | AP7: 1441.44 | AQ7: =Table43[[#This Row],[Harga Jual Pcs GT (-PPN)]]*Table43[[#This Row],[ISI/CTN]] -> 69189.12 | AR7: =Table43[[#This Row],[Harga Jual Pcs GT (-PPN)]]*1.11 -> 1599.9984 | AS7: =Table43[[#This Row],[Harga Jual Krt GT (- PPN)]]*1.11 -> 76799.923 | AT7: 1556.76 | AU7: =(Table43[[#This Row],[Harga Jual Pcs MT (-PPN)]]*Table43[[#This Row],[ISI/CTN]]) -> 74724.48 | AV7: =Table43[[#This Row],[Harga Jual Pcs MT (-PPN)]]*1.11 -> 1728.0036 | AW7: =Table43[[#This Row],[Harga Jual Pcs MT (+PPN)]]*Table43[[#This Row],[ISI/CTN]] -> 82944.173 | AY7: 45553 | AZ7: 45553 | BA7: =IF(TODAY()-Table43[[#This Row],[Efektif Pembuatan]]>60,"Lama","Baru") -> Lama | BB7: =IF(TODAY()-Table43[[#This Row],[Efektif Naik Harga]]<30,"Naik","Sama") -> Sama | BC7: Aktif | BD7: =IF(Table43[[#This Row],[Kode BARANG Win2]]<>"","IDR","") -> IDR | BE7: =CONCATENATE(Table43[[#This Row],[kode 1 Digit (Nomor)]],Table43[[#This Row],[kode 4 Digit (Nomor)]]) -> 10062 | BF7: =Table43[[#This Row],[Nama Gramasi atau Jumlah Pack per CTN]] -> 62 GR | BG7: S-HNZ | BH7: 48HEINZ | BI7: =IF(Table43[[#This Row],[SATUAN Fix Win]]<>"","KRT") -> KRT | BJ7: =IF(Table43[[#This Row],[SATUAN Fix Win]]<>"","GD01") -> GD01 | BK7: =IF(Table43[[#This Row],[SATUAN Fix Win]]<>"",11611) -> 11611 | BL7: =IF(Table43[[#This Row],[SATUAN Fix Win]]<>"",11612) -> 11612 | BM7: 0123 | BN7: =IF(Table43[[#This Row],[SATUAN Fix Win]]<>"",1) -> 1 | BO7: PT. HEINZ ABC INDONESIA | BP7: =IFERROR(VLOOKUP(Table43[[#This Row],[Kode Pcpl]],'[1]HEINZ ABC'!$A$4:$E$112,8,0),0) -> 0 | BQ7: =Table43[[#This Row],[Harga Jual Pcs GT (-PPN)]]-Table43[[#This Row],[HARGA NAIK GT]] -> 1441.44 | BR7: =IF(Table43[[#This Row],[HARGA NAIK GT]]=0,Table43[[#This Row],[Harga Jual Pcs GT (-PPN)]],Table43[[#This Row],[HARGA NAIK GT]]) -> 1441.44 | BS7: =IFERROR(VLOOKUP(Table43[[#This Row],[Kode Pcpl]],'[1]HEINZ ABC'!$A$4:$E$112,8,0),0) -> 0 | BT7: =Table43[[#This Row],[Harga Jual Pcs GT (-PPN)]]-BS7 -> 1441.44 | BU7: =IF(BS7=0,Table43[[#This Row],[Harga Jual Pcs MT (-PPN)]]) -> 1556.76 | BV7: =IFERROR(VLOOKUP(Table43[[#This Row],[Kode Pcpl]],[2]Pricelist!$A$4:$K$112,11,0),0) -> 0 | BW7: =IFERROR(VLOOKUP(Table43[[#This Row],[Kode BARANG Win2]],[3]!RECKITT211216[[KDBRG]:[HRG_JL_PCS-PPN]],11,0),0) -> 0 | BX7: =BV7/1.11 -> 0
A8: =CONCATENATE(Table43[[#This Row],[Kode BARANG Win2]],Table43[[#This Row],[No. Urut Item Sama]]) -> A10110000062103 | B8: 3 | C8: 3 | D8: 100240 | E8: RASA MANTAP SOY | F8: ABC KCP MNS PCH 48X62G | G8: 48 | H8: 7000003116 | I8: =Table43[[#This Row],[Nama Jenis Kemasan]] -> PCH | J8: =TRIM(CONCATENATE(Table43[[#This Row],[Nama KLP]]," ",Table43[[#This Row],[Nama Sub KLP]])) -> KECAP MANIS | K8: =CONCATENATE(Table43[[#This Row],[kode 2 Digit (hrf+No)]],Table43[[#This Row],[kode 2 Digit (Nomor)]],Table43[[#This Row],[kode 1 Digit (Nomor)]]) -> A1011 | L8: =IF(AG8="",CONCATENATE(Q8,S8,U8,W8,Y8,AA8,AC8,AE8,Table43[[#This Row],[Tanda Kode Revisi]]),CONCATENATE(Q8,S8,U8,W8,Y8,AA8,AC8,AG8)) -> A1011000006210 | M8: =LEN(L8) -> 14 | N8: =IF(AF8<>"",TRIM(UPPER(CONCATENATE(P8," ",R8," ",T8," ",V8," ",X8," ",Z8," ","X"," ",Table43[[#This Row],[ISI/CTN]]," ",AF8," ",AB8," ",AD8," ",AH8))),TRIM(UPPER(CONCATENATE(P8," ",R8," ",T8," ",V8," ",X8," ",Z8," ","X"," ",Table43[[#This Row],[ISI/CTN]]," ",AB8," ",AD8," ",AH8)))) -> ABC KECAP MANIS 62 GR X 48 PCH | O8: =LEN(N8) -> 30 | P8: ABC | Q8: A1 | R8: KECAP | S8: 01 | T8: MANIS | U8: 1 | W8: 0 | Y8: 00 | Z8: 62 GR | AA8: 0062 | AB8: PCH | AC8: 1 | AE8: 0 | AI8: GRAM | AJ8: 1 | AL8: =Table43[[#This Row],[Harga Jual Pcs GT (-PPN)]]-(Table43[[#This Row],[Harga Jual Pcs GT (-PPN)]]*6%) -> 1354.9536 | AM8: =Table43[[#This Row],[Harga Beli Pcs (-PPN)]]*Table43[[#This Row],[ISI/CTN]] -> 65037.773 | AN8: =Table43[[#This Row],[Harga Beli Pcs (-PPN)]]*1.11 -> 1503.9985 | AO8: =Table43[[#This Row],[Harga Beli Krt (- PPN)]]*1.11 -> 72191.928 | AP8: 1441.44 | AQ8: =Table43[[#This Row],[Harga Jual Pcs GT (-PPN)]]*Table43[[#This Row],[ISI/CTN]] -> 69189.12 | AR8: =Table43[[#This Row],[Harga Jual Pcs GT (-PPN)]]*1.11 -> 1599.9984 | AS8: =Table43[[#This Row],[Harga Jual Krt GT (- PPN)]]*1.11 -> 76799.923 | AT8: 1556.76 | AU8: =(Table43[[#This Row],[Harga Jual Pcs MT (-PPN)]]*Table43[[#This Row],[ISI/CTN]]) -> 74724.48 | AV8: =Table43[[#This Row],[Harga Jual Pcs MT (-PPN)]]*1.11 -> 1728.0036 | AW8: =Table43[[#This Row],[Harga Jual Pcs MT (+PPN)]]*Table43[[#This Row],[ISI/CTN]] -> 82944.173 | AY8: 45602 | AZ8: 45553 | BA8: =IF(TODAY()-Table43[[#This Row],[Efektif Pembuatan]]>60,"Lama","Baru") -> Lama | BB8: =IF(TODAY()-Table43[[#This Row],[Efektif Naik Harga]]<30,"Naik","Sama") -> Sama | BC8: Aktif | BD8: =IF(Table43[[#This Row],[Kode BARANG Win2]]<>"","IDR","") -> IDR | BE8: =CONCATENATE(Table43[[#This Row],[kode 1 Digit (Nomor)]],Table43[[#This Row],[kode 4 Digit (Nomor)]]) -> 10062 | BF8: =Table43[[#This Row],[Nama Gramasi atau Jumlah Pack per CTN]] -> 62 GR | BG8: S-HNZ | BH8: 48HEINZ | BI8: =IF(Table43[[#This Row],[SATUAN Fix Win]]<>"","KRT") -> KRT | BJ8: =IF(Table43[[#This Row],[SATUAN Fix Win]]<>"","GD01") -> GD01 | BK8: =IF(Table43[[#This Row],[SATUAN Fix Win]]<>"",11611) -> 11611 | BL8: =IF(Table43[[#This Row],[SATUAN Fix Win]]<>"",11612) -> 11612 | BM8: 0123 | BN8: =IF(Table43[[#This Row],[SATUAN Fix Win]]<>"",1) -> 1 | BO8: PT. HEINZ ABC INDONESIA | BP8: =IFERROR(VLOOKUP(Table43[[#This Row],[Kode Pcpl]],'[1]HEINZ ABC'!$A$4:$E$112,8,0),0) -> 0 | BQ8: =Table43[[#This Row],[Harga Jual Pcs GT (-PPN)]]-Table43[[#This Row],[HARGA NAIK GT]] -> 1441.44 | BR8: =IF(Table43[[#This Row],[HARGA NAIK GT]]=0,Table43[[#This Row],[Harga Jual Pcs GT (-PPN)]],Table43[[#This Row],[HARGA NAIK GT]]) -> 1441.44 | BS8: =IFERROR(VLOOKUP(Table43[[#This Row],[Kode Pcpl]],'[1]HEINZ ABC'!$A$4:$E$112,8,0),0) -> 0 | BT8: =Table43[[#This Row],[Harga Jual Pcs GT (-PPN)]]-BS8 -> 1441.44 | BU8: =IF(BS8=0,Table43[[#This Row],[Harga Jual Pcs MT (-PPN)]]) -> 1556.76 | BV8: =IFERROR(VLOOKUP(Table43[[#This Row],[Kode Pcpl]],[2]Pricelist!$A$4:$K$112,11,0),0) -> 0 | BW8: =IFERROR(VLOOKUP(Table43[[#This Row],[Kode BARANG Win2]],[3]!RECKITT211216[[KDBRG]:[HRG_JL_PCS-PPN]],11,0),0) -> 0 | BX8: =BV8/1.11 -> 0
A9: =CONCATENATE(Table43[[#This Row],[Kode BARANG Win2]],Table43[[#This Row],[No. Urut Item Sama]]) -> A10110000062111 | B9: 1 | C9: 4 | D9: 100986 | E9: RASA MANTAP SOY | F9: ABC KCPMNS PCH 48X62G B5G12311 | G9: 48 | H9: 7000003134 | I9: =Table43[[#This Row],[Nama Jenis Kemasan]] -> PCH | J9: =TRIM(CONCATENATE(Table43[[#This Row],[Nama KLP]]," ",Table43[[#This Row],[Nama Sub KLP]])) -> KECAP MANIS | K9: =CONCATENATE(Table43[[#This Row],[kode 2 Digit (hrf+No)]],Table43[[#This Row],[kode 2 Digit (Nomor)]],Table43[[#This Row],[kode 1 Digit (Nomor)]]) -> A1011 | L9: =IF(AG9="",CONCATENATE(Q9,S9,U9,W9,Y9,AA9,AC9,AE9,Table43[[#This Row],[Tanda Kode Revisi]]),CONCATENATE(Q9,S9,U9,W9,Y9,AA9,AC9,AG9)) -> A1011000006211 | M9: =LEN(L9) -> 14 | N9: =IF(AF9<>"",TRIM(UPPER(CONCATENATE(P9," ",R9," ",T9," ",V9," ",X9," ",Z9," ","X"," ",Table43[[#This Row],[ISI/CTN]]," ",AF9," ",AB9," ",AD9," ",AH9))),TRIM(UPPER(CONCATENATE(P9," ",R9," ",T9," ",V9," ",X9," ",Z9," ","X"," ",Table43[[#This Row],[ISI/CTN]]," ",AB9," ",AD9," ",AH9)))) -> ABC KECAP MANIS 62 GR X 48 PCH B5G1 | O9: =LEN(N9) -> 35 | P9: ABC | Q9: A1 | R9: KECAP | S9: 01 | T9: MANIS | U9: 1 | W9: 0 | Y9: 00 | Z9: 62 GR | AA9: 0062 | AB9: PCH | AC9: 1 | AD9: B5G1 | AE9: 1 | AI9: GRAM | AJ9: 1 | AL9: =Table43[[#This Row],[Harga Jual Pcs GT (-PPN)]]-(Table43[[#This Row],[Harga Jual Pcs GT (-PPN)]]*6%) -> 1129.128 | AM9: =Table43[[#This Row],[Harga Beli Pcs (-PPN)]]*Table43[[#This Row],[ISI/CTN]] -> 54198.144 | AN9: =Table43[[#This Row],[Harga Beli Pcs (-PPN)]]*1.11 -> 1253.3321 | AO9: =Table43[[#This Row],[Harga Beli Krt (- PPN)]]*1.11 -> 60159.94 | AP9: 1201.2 | AQ9: =Table43[[#This Row],[Harga Jual Pcs GT (-PPN)]]*Table43[[#This Row],[ISI/CTN]] -> 57657.6 | AR9: =Table43[[#This Row],[Harga Jual Pcs GT (-PPN)]]*1.11 -> 1333.332 | AS9: =Table43[[#This Row],[Harga Jual Krt GT (- PPN)]]*1.11 -> 63999.936 | AT9: 1297.3 | AU9: =(Table43[[#This Row],[Harga Jual Pcs MT (-PPN)]]*Table43[[#This Row],[ISI/CTN]]) -> 62270.4 | AV9: =Table43[[#This Row],[Harga Jual Pcs MT (-PPN)]]*1.11 -> 1440.003 | AW9: =Table43[[#This Row],[Harga Jual Pcs MT (+PPN)]]*Table43[[#This Row],[ISI/CTN]] -> 69120.144 | AY9: 45553 | AZ9: 45553 | BA9: =IF(TODAY()-Table43[[#This Row],[Efektif Pembuatan]]>60,"Lama","Baru") -> Lama | BB9: =IF(TODAY()-Table43[[#This Row],[Efektif Naik Harga]]<30,"Naik","Sama") -> Sama | BC9: Aktif | BD9: =IF(Table43[[#This Row],[Kode BARANG Win2]]<>"","IDR","") -> IDR | BE9: =CONCATENATE(Table43[[#This Row],[kode 1 Digit (Nomor)]],Table43[[#This Row],[kode 4 Digit (Nomor)]]) -> 10062 | BF9: =Table43[[#This Row],[Nama Gramasi atau Jumlah Pack per CTN]] -> 62 GR | BG9: S-HNZ | BH9: 48HEINZ | BI9: =IF(Table43[[#This Row],[SATUAN Fix Win]]<>"","KRT") -> KRT | BJ9: =IF(Table43[[#This Row],[SATUAN Fix Win]]<>"","GD01") -> GD01 | BK9: =IF(Table43[[#This Row],[SATUAN Fix Win]]<>"",11611) -> 11611 | BL9: =IF(Table43[[#This Row],[SATUAN Fix Win]]<>"",11612) -> 11612 | BM9: 0123 | BN9: =IF(Table43[[#This Row],[SATUAN Fix Win]]<>"",1) -> 1 | BO9: PT. HEINZ ABC INDONESIA | BP9: =IFERROR(VLOOKUP(Table43[[#This Row],[Kode Pcpl]],'[1]HEINZ ABC'!$A$4:$E$112,8,0),0) -> 0 | BQ9: =Table43[[#This Row],[Harga Jual Pcs GT (-PPN)]]-Table43[[#This Row],[HARGA NAIK GT]] -> 1201.2 | BR9: =IF(Table43[[#This Row],[HARGA NAIK GT]]=0,Table43[[#This Row],[Harga Jual Pcs GT (-PPN)]],Table43[[#This Row],[HARGA NAIK GT]]) -> 1201.2 | BS9: =IFERROR(VLOOKUP(Table43[[#This Row],[Kode Pcpl]],'[1]HEINZ ABC'!$A$4:$E$112,8,0),0) -> 0 | BT9: =Table43[[#This Row],[Harga Jual Pcs GT (-PPN)]]-BS9 -> 1201.2 | BU9: =IF(BS9=0,Table43[[#This Row],[Harga Jual Pcs MT (-PPN)]]) -> 1297.3 | BV9: =IFERROR(VLOOKUP(Table43[[#This Row],[Kode Pcpl]],[2]Pricelist!$A$4:$K$112,11,0),0) -> 0 | BW9: =IFERROR(VLOOKUP(Table43[[#This Row],[Kode BARANG Win2]],[3]!RECKITT211216[[KDBRG]:[HRG_JL_PCS-PPN]],11,0),0) -> 0 | BX9: =BV9/1.11 -> 0
A10: =CONCATENATE(Table43[[#This Row],[Kode BARANG Win2]],Table43[[#This Row],[No. Urut Item Sama]]) -> A10110000080101 | B10: 1 | C10: 5 | D10: 100179 | E10: RASA MANTAP SOY | F10: ABC KCP MNS PCH 48X80ML 2007 | G10: 48 | H10: 0 | I10: =Table43[[#This Row],[Nama Jenis Kemasan]] -> PCH | J10: =TRIM(CONCATENATE(Table43[[#This Row],[Nama KLP]]," ",Table43[[#This Row],[Nama Sub KLP]])) -> KECAP MANIS | K10: =CONCATENATE(Table43[[#This Row],[kode 2 Digit (hrf+No)]],Table43[[#This Row],[kode 2 Digit (Nomor)]],Table43[[#This Row],[kode 1 Digit (Nomor)]]) -> A1011 | L10: =IF(AG10="",CONCATENATE(Q10,S10,U10,W10,Y10,AA10,AC10,AE10,Table43[[#This Row],[Tanda Kode Revisi]]),CONCATENATE(Q10,S10,U10,W10,Y10,AA10,AC10,AG10)) -> A1011000008010 | M10: =LEN(L10) -> 14 | N10: =IF(AF10<>"",TRIM(UPPER(CONCATENATE(P10," ",R10," ",T10," ",V10," ",X10," ",Z10," ","X"," ",Table43[[#This Row],[ISI/CTN]]," ",AF10," ",AB10," ",AD10," ",AH10))),TRIM(UPPER(CONCATENATE(P10," ",R10," ",T10," ",V10," ",X10," ",Z10," ","X"," ",Table43[[#This Row],[ISI/CTN]]," ",AB10," ",AD10," ",AH10)))) -> ABC KECAP MANIS 80 ML X 48 PCH | O10: =LEN(N10) -> 30 | P10: ABC | Q10: A1 | R10: KECAP | S10: 01 | T10: MANIS | U10: 1 | W10: 0 | Y10: 00 | Z10: 80 ML | AA10: 0080 | AB10: PCH | AC10: 1 | AE10: 0 | AI10: LITER | AJ10: 2 | AL10: =Table43[[#This Row],[Harga Jual Pcs GT (-PPN)]]-(Table43[[#This Row],[Harga Jual Pcs GT (-PPN)]]*6%) -> 1990.0928 | AM10: =Table43[[#This Row],[Harga Beli Pcs (-PPN)]]*Table43[[#This Row],[ISI/CTN]] -> 95524.454 | AN10: =Table43[[#This Row],[Harga Beli Pcs (-PPN)]]*1.11 -> 2209.003 | AO10: =Table43[[#This Row],[Harga Beli Krt (- PPN)]]*1.11 -> 106032.14 | AP10: 2117.12 | AQ10: =Table43[[#This Row],[Harga Jual Pcs GT (-PPN)]]*Table43[[#This Row],[ISI/CTN]] -> 101621.76 | AR10: =Table43[[#This Row],[Harga Jual Pcs GT (-PPN)]]*1.11 -> 2350.0032 | AS10: =Table43[[#This Row],[Harga Jual Krt GT (- PPN)]]*1.11 -> 112800.15 | AT10: 2286.4865 | AU10: =(Table43[[#This Row],[Harga Jual Pcs MT (-PPN)]]*Table43[[#This Row],[ISI/CTN]]) -> 109751.35 | AV10: =Table43[[#This Row],[Harga Jual Pcs MT (-PPN)]]*1.11 -> 2538 | AW10: =Table43[[#This Row],[Harga Jual Pcs MT (+PPN)]]*Table43[[#This Row],[ISI/CTN]] -> 121824 | AY10: 45553 | AZ10: 45553 | BA10: =IF(TODAY()-Table43[[#This Row],[Efektif Pembuatan]]>60,"Lama","Baru") -> Lama | BB10: =IF(TODAY()-Table43[[#This Row],[Efektif Naik Harga]]<30,"Naik","Sama") -> Sama | BC10: Aktif | BD10: =IF(Table43[[#This Row],[Kode BARANG Win2]]<>"","IDR","") -> IDR | BE10: =CONCATENATE(Table43[[#This Row],[kode 1 Digit (Nomor)]],Table43[[#This Row],[kode 4 Digit (Nomor)]]) -> 20080 | BF10: =Table43[[#This Row],[Nama Gramasi atau Jumlah Pack per CTN]] -> 80 ML | BG10: S-HNZ | BH10: 48HEINZ | BI10: =IF(Table43[[#This Row],[SATUAN Fix Win]]<>"","KRT") -> KRT | BJ10: =IF(Table43[[#This Row],[SATUAN Fix Win]]<>"","GD01") -> GD01 | BK10: =IF(Table43[[#This Row],[SATUAN Fix Win]]<>"",11611) -> 11611 | BL10: =IF(Table43[[#This Row],[SATUAN Fix Win]]<>"",11612) -> 11612 | BM10: 0123 | BN10: =IF(Table43[[#This Row],[SATUAN Fix Win]]<>"",1) -> 1 | BO10: PT. HEINZ ABC INDONESIA | BP10: =IFERROR(VLOOKUP(Table43[[#This Row],[Kode Pcpl]],'[1]HEINZ ABC'!$A$4:$E$112,8,0),0) -> 0 | BQ10: =Table43[[#This Row],[Harga Jual Pcs GT (-PPN)]]-Table43[[#This Row],[HARGA NAIK GT]] -> 2117.12 | BR10: =IF(Table43[[#This Row],[HARGA NAIK GT]]=0,Table43[[#This Row],[Harga Jual Pcs GT (-PPN)]],Table43[[#This Row],[HARGA NAIK GT]]) -> 2117.12 | BS10: =IFERROR(VLOOKUP(Table43[[#This Row],[Kode Pcpl]],'[1]HEINZ ABC'!$A$4:$E$112,8,0),0) -> 0 | BT10: =Table43[[#This Row],[Harga Jual Pcs GT (-PPN)]]-BS10 -> 2117.12 | BU10: =IF(BS10=0,Table43[[#This Row],[Harga Jual Pcs MT (-PPN)]]) -> 2286.4865 | BV10: =IFERROR(VLOOKUP(Table43[[#This Row],[Kode Pcpl]],[2]Pricelist!$A$4:$K$112,11,0),0) -> 0 | BW10: =IFERROR(VLOOKUP(Table43[[#This Row],[Kode BARANG Win2]],[3]!RECKITT211216[[KDBRG]:[HRG_JL_PCS-PPN]],11,0),0) -> 0 | BX10: =BV10/1.11 -> 0
A11: =CONCATENATE(Table43[[#This Row],[Kode BARANG Win2]],Table43[[#This Row],[No. Urut Item Sama]]) -> A10110000130101 | B11: 1 | C11: 6 | D11: 100234 | E11: RASA MANTAP SOY | F11: ABC KCPMNS PET 48X130ML GT2404 | G11: 48 | H11: 7000003111 | I11: =Table43[[#This Row],[Nama Jenis Kemasan]] -> BTL | J11: =TRIM(CONCATENATE(Table43[[#This Row],[Nama KLP]]," ",Table43[[#This Row],[Nama Sub KLP]])) -> KECAP MANIS | K11: =CONCATENATE(Table43[[#This Row],[kode 2 Digit (hrf+No)]],Table43[[#This Row],[kode 2 Digit (Nomor)]],Table43[[#This Row],[kode 1 Digit (Nomor)]]) -> A1011 | L11: =IF(AG11="",CONCATENATE(Q11,S11,U11,W11,Y11,AA11,AC11,AE11,Table43[[#This Row],[Tanda Kode Revisi]]),CONCATENATE(Q11,S11,U11,W11,Y11,AA11,AC11,AG11)) -> A1011000013010 | M11: =LEN(L11) -> 14 | N11: =IF(AF11<>"",TRIM(UPPER(CONCATENATE(P11," ",R11," ",T11," ",V11," ",X11," ",Z11," ","X"," ",Table43[[#This Row],[ISI/CTN]]," ",AF11," ",AB11," ",AD11," ",AH11))),TRIM(UPPER(CONCATENATE(P11," ",R11," ",T11," ",V11," ",X11," ",Z11," ","X"," ",Table43[[#This Row],[ISI/CTN]]," ",AB11," ",AD11," ",AH11)))) -> ABC KECAP MANIS 135 ML X 48 BTL | O11: =LEN(N11) -> 31 | P11: ABC | Q11: A1 | R11: KECAP | S11: 01 | T11: MANIS | U11: 1 | W11: 0 | Y11: 00 | Z11: 135 ML | AA11: 0130 | AB11: BTL | AC11: 1 | AE11: 0 | AI11: LITER | AJ11: 2 | AL11: =Table43[[#This Row],[Harga Jual Pcs GT (-PPN)]]-(Table43[[#This Row],[Harga Jual Pcs GT (-PPN)]]*6%) -> 6382.6 | AM11: =Table43[[#This Row],[Harga Beli Pcs (-PPN)]]*Table43[[#This Row],[ISI/CTN]] -> 306364.8 | AN11: =Table43[[#This Row],[Harga Beli Pcs (-PPN)]]*1.11 -> 7084.686 | AO11: =Table43[[#This Row],[Harga Beli Krt (- PPN)]]*1.11 -> 340064.93 | AP11: 6790 | AQ11: =Table43[[#This Row],[Harga Jual Pcs GT (-PPN)]]*Table43[[#This Row],[ISI/CTN]] -> 325920 | AR11: =Table43[[#This Row],[Harga Jual Pcs GT (-PPN)]]*1.11 -> 7536.9 | AS11: =Table43[[#This Row],[Harga Jual Krt GT (- PPN)]]*1.11 -> 361771.2 | AT11: 0 | AU11: =(Table43[[#This Row],[Harga Jual Pcs MT (-PPN)]]*Table43[[#This Row],[ISI/CTN]]) -> 0 | AV11: =Table43[[#This Row],[Harga Jual Pcs MT (-PPN)]]*1.11 -> 0 | AW11: =Table43[[#This Row],[Harga Jual Pcs MT (+PPN)]]*Table43[[#This Row],[ISI/CTN]] -> 0 | AY11: 45553 | AZ11: 45553 | BA11: =IF(TODAY()-Table43[[#This Row],[Efektif Pembuatan]]>60,"Lama","Baru") -> Lama | BB11: =IF(TODAY()-Table43[[#This Row],[Efektif Naik Harga]]<30,"Naik","Sama") -> Sama | BC11: Aktif | BD11: =IF(Table43[[#This Row],[Kode BARANG Win2]]<>"","IDR","") -> IDR | BE11: =CONCATENATE(Table43[[#This Row],[kode 1 Digit (Nomor)]],Table43[[#This Row],[kode 4 Digit (Nomor)]]) -> 20130 | BF11: =Table43[[#This Row],[Nama Gramasi atau Jumlah Pack per CTN]] -> 135 ML | BG11: S-HNZ | BH11: 48HEINZ | BI11: =IF(Table43[[#This Row],[SATUAN Fix Win]]<>"","KRT") -> KRT | BJ11: =IF(Table43[[#This Row],[SATUAN Fix Win]]<>"","GD01") -> GD01 | BK11: =IF(Table43[[#This Row],[SATUAN Fix Win]]<>"",11611) -> 11611 | BL11: =IF(Table43[[#This Row],[SATUAN Fix Win]]<>"",11612) -> 11612 | BM11: 0123 | BN11: =IF(Table43[[#This Row],[SATUAN Fix Win]]<>"",1) -> 1 | BO11: PT. HEINZ ABC INDONESIA | BP11: =IFERROR(VLOOKUP(Table43[[#This Row],[Kode Pcpl]],'[1]HEINZ ABC'!$A$4:$E$112,8,0),0) -> 0 | BQ11: =Table43[[#This Row],[Harga Jual Pcs GT (-PPN)]]-Table43[[#This Row],[HARGA NAIK GT]] -> 6790 | BR11: =IF(Table43[[#This Row],[HARGA NAIK GT]]=0,Table43[[#This Row],[Harga Jual Pcs GT (-PPN)]],Table43[[#This Row],[HARGA NAIK GT]]) -> 6790 | BS11: =IFERROR(VLOOKUP(Table43[[#This Row],[Kode Pcpl]],'[1]HEINZ ABC'!$A$4:$E$112,8,0),0) -> 0 | BT11: =Table43[[#This Row],[Harga Jual Pcs GT (-PPN)]]-BS11 -> 6790 | BU11: =IF(BS11=0,Table43[[#This Row],[Harga Jual Pcs MT (-PPN)]]) -> 0 | BV11: =IFERROR(VLOOKUP(Table43[[#This Row],[Kode Pcpl]],[2]Pricelist!$A$4:$K$112,11,0),0) -> 0 | BW11: =IFERROR(VLOOKUP(Table43[[#This Row],[Kode BARANG Win2]],[3]!RECKITT211216[[KDBRG]:[HRG_JL_PCS-PPN]],11,0),0) -> 0 | BX11: =BV11/1.11 -> 0
A12: =CONCATENATE(Table43[[#This Row],[Kode BARANG Win2]],Table43[[#This Row],[No. Urut Item Sama]]) -> A10110000135101 | B12: 1 | C12: 7 | D12: 100161 | E12: RASA MANTAP SOY | F12: ABC KCPMNS PET SB 48X135ML1607 | G12: 48 | H12: 0 | I12: =Table43[[#This Row],[Nama Jenis Kemasan]] -> BTL | J12: =TRIM(CONCATENATE(Table43[[#This Row],[Nama KLP]]," ",Table43[[#This Row],[Nama Sub KLP]])) -> KECAP MANIS | K12: =CONCATENATE(Table43[[#This Row],[kode 2 Digit (hrf+No)]],Table43[[#This Row],[kode 2 Digit (Nomor)]],Table43[[#This Row],[kode 1 Digit (Nomor)]]) -> A1011 | L12: =IF(AG12="",CONCATENATE(Q12,S12,U12,W12,Y12,AA12,AC12,AE12,Table43[[#This Row],[Tanda Kode Revisi]]),CONCATENATE(Q12,S12,U12,W12,Y12,AA12,AC12,AG12)) -> A1011000013510 | M12: =LEN(L12) -> 14 | N12: =IF(AF12<>"",TRIM(UPPER(CONCATENATE(P12," ",R12," ",T12," ",V12," ",X12," ",Z12," ","X"," ",Table43[[#This Row],[ISI/CTN]]," ",AF12," ",AB12," ",AD12," ",AH12))),TRIM(UPPER(CONCATENATE(P12," ",R12," ",T12," ",V12," ",X12," ",Z12," ","X"," ",Table43[[#This Row],[ISI/CTN]]," ",AB12," ",AD12," ",AH12)))) -> ABC KECAP MANIS 135 ML X 48 BTL | O12: =LEN(N12) -> 31 | P12: ABC | Q12: A1 | R12: KECAP | S12: 01 | T12: MANIS | U12: 1 | W12: 0 | Y12: 00 | Z12: 135 ML | AA12: 0135 | AB12: BTL | AC12: 1 | AE12: 0 | AI12: LITER | AJ12: 2 | AL12: =Table43[[#This Row],[Harga Jual Pcs GT (-PPN)]]-(Table43[[#This Row],[Harga Jual Pcs GT (-PPN)]]*6%) -> 7181.2616 | AM12: =Table43[[#This Row],[Harga Beli Pcs (-PPN)]]*Table43[[#This Row],[ISI/CTN]] -> 344700.56 | AN12: =Table43[[#This Row],[Harga Beli Pcs (-PPN)]]*1.11 -> 7971.2004 | AO12: =Table43[[#This Row],[Harga Beli Krt (- PPN)]]*1.11 -> 382617.62 | AP12: 7639.64 | AQ12: =Table43[[#This Row],[Harga Jual Pcs GT (-PPN)]]*Table43[[#This Row],[ISI/CTN]] -> 366702.72 | AR12: =Table43[[#This Row],[Harga Jual Pcs GT (-PPN)]]*1.11 -> 8480.0004 | AS12: =Table43[[#This Row],[Harga Jual Krt GT (- PPN)]]*1.11 -> 407040.02 | AT12: 8250.81 | AU12: =(Table43[[#This Row],[Harga Jual Pcs MT (-PPN)]]*Table43[[#This Row],[ISI/CTN]]) -> 396038.88 | AV12: =Table43[[#This Row],[Harga Jual Pcs MT (-PPN)]]*1.11 -> 9158.3991 | AW12: =Table43[[#This Row],[Harga Jual Pcs MT (+PPN)]]*Table43[[#This Row],[ISI/CTN]] -> 439603.16 | AY12: 45553 | AZ12: 45553 | BA12: =IF(TODAY()-Table43[[#This Row],[Efektif Pembuatan]]>60,"Lama","Baru") -> Lama | BB12: =IF(TODAY()-Table43[[#This Row],[Efektif Naik Harga]]<30,"Naik","Sama") -> Sama | BC12: Aktif | BD12: =IF(Table43[[#This Row],[Kode BARANG Win2]]<>"","IDR","") -> IDR | BE12: =CONCATENATE(Table43[[#This Row],[kode 1 Digit (Nomor)]],Table43[[#This Row],[kode 4 Digit (Nomor)]]) -> 20135 | BF12: =Table43[[#This Row],[Nama Gramasi atau Jumlah Pack per CTN]] -> 135 ML | BG12: S-HNZ | BH12: 48HEINZ | BI12: =IF(Table43[[#This Row],[SATUAN Fix Win]]<>"","KRT") -> KRT | BJ12: =IF(Table43[[#This Row],[SATUAN Fix Win]]<>"","GD01") -> GD01 | BK12: =IF(Table43[[#This Row],[SATUAN Fix Win]]<>"",11611) -> 11611 | BL12: =IF(Table43[[#This Row],[SATUAN Fix Win]]<>"",11612) -> 11612 | BM12: 0123 | BN12: =IF(Table43[[#This Row],[SATUAN Fix Win]]<>"",1) -> 1 | BO12: PT. HEINZ ABC INDONESIA | BP12: =IFERROR(VLOOKUP(Table43[[#This Row],[Kode Pcpl]],'[1]HEINZ ABC'!$A$4:$E$112,8,0),0) -> 0 | BQ12: =Table43[[#This Row],[Harga Jual Pcs GT (-PPN)]]-Table43[[#This Row],[HARGA NAIK GT]] -> 7639.64 | BR12: =IF(Table43[[#This Row],[HARGA NAIK GT]]=0,Table43[[#This Row],[Harga Jual Pcs GT (-PPN)]],Table43[[#This Row],[HARGA NAIK GT]]) -> 7639.64 | BS12: =IFERROR(VLOOKUP(Table43[[#This Row],[Kode Pcpl]],'[1]HEINZ ABC'!$A$4:$E$112,8,0),0) -> 0 | BT12: =Table43[[#This Row],[Harga Jual Pcs GT (-PPN)]]-BS12 -> 7639.64 | BU12: =IF(BS12=0,Table43[[#This Row],[Harga Jual Pcs MT (-PPN)]]) -> 8250.81 | BV12: =IFERROR(VLOOKUP(Table43[[#This Row],[Kode Pcpl]],[2]Pricelist!$A$4:$K$112,11,0),0) -> 0 | BW12: =IFERROR(VLOOKUP(Table43[[#This Row],[Kode BARANG Win2]],[3]!RECKITT211216[[KDBRG]:[HRG_JL_PCS-PPN]],11,0),0) -> 0 | BX12: =BV12/1.11 -> 0
A13: =CONCATENATE(Table43[[#This Row],[Kode BARANG Win2]],Table43[[#This Row],[No. Urut Item Sama]]) -> A10110000250101 | B13: 1 | C13: 8 | D13: 100220 | E13: RASA MANTAP SOY | F13: ABC KCP MNS PCH 24X250G 2311 | G13: 24 | H13: 7000003101 | I13: =Table43[[#This Row],[Nama Jenis Kemasan]] -> PCH | J13: =TRIM(CONCATENATE(Table43[[#This Row],[Nama KLP]]," ",Table43[[#This Row],[Nama Sub KLP]])) -> KECAP MANIS | K13: =CONCATENATE(Table43[[#This Row],[kode 2 Digit (hrf+No)]],Table43[[#This Row],[kode 2 Digit (Nomor)]],Table43[[#This Row],[kode 1 Digit (Nomor)]]) -> A1011 | L13: =IF(AG13="",CONCATENATE(Q13,S13,U13,W13,Y13,AA13,AC13,AE13,Table43[[#This Row],[Tanda Kode Revisi]]),CONCATENATE(Q13,S13,U13,W13,Y13,AA13,AC13,AG13)) -> A1011000025010 | M13: =LEN(L13) -> 14 | N13: =IF(AF13<>"",TRIM(UPPER(CONCATENATE(P13," ",R13," ",T13," ",V13," ",X13," ",Z13," ","X"," ",Table43[[#This Row],[ISI/CTN]]," ",AF13," ",AB13," ",AD13," ",AH13))),TRIM(UPPER(CONCATENATE(P13," ",R13," ",T13," ",V13," ",X13," ",Z13," ","X"," ",Table43[[#This Row],[ISI/CTN]]," ",AB13," ",AD13," ",AH13)))) -> ABC KECAP MANIS 250 GR X 24 PCH | O13: =LEN(N13) -> 31 | P13: ABC | Q13: A1 | R13: KECAP | S13: 01 | T13: MANIS | U13: 1 | W13: 0 | Y13: 00 | Z13: 250 GR | AA13: 0250 | AB13: PCH | AC13: 1 | AE13: 0 | AI13: GRAM | AJ13: 1 | AL13: =Table43[[#This Row],[Harga Jual Pcs GT (-PPN)]]-(Table43[[#This Row],[Harga Jual Pcs GT (-PPN)]]*6%) -> 6117.285 | AM13: =Table43[[#This Row],[Harga Beli Pcs (-PPN)]]*Table43[[#This Row],[ISI/CTN]] -> 146814.84 | AN13: =Table43[[#This Row],[Harga Beli Pcs (-PPN)]]*1.11 -> 6790.1864 | AO13: =Table43[[#This Row],[Harga Beli Krt (- PPN)]]*1.11 -> 162964.47 | AP13: 6507.75 | AQ13: =Table43[[#This Row],[Harga Jual Pcs GT (-PPN)]]*Table43[[#This Row],[ISI/CTN]] -> 156186 | AR13: =Table43[[#This Row],[Harga Jual Pcs GT (-PPN)]]*1.11 -> 7223.6025 | AS13: =Table43[[#This Row],[Harga Jual Krt GT (- PPN)]]*1.11 -> 173366.46 | AT13: 7028.37 | AU13: =(Table43[[#This Row],[Harga Jual Pcs MT (-PPN)]]*Table43[[#This Row],[ISI/CTN]]) -> 168680.88 | AV13: =Table43[[#This Row],[Harga Jual Pcs MT (-PPN)]]*1.11 -> 7801.4907 | AW13: =Table43[[#This Row],[Harga Jual Pcs MT (+PPN)]]*Table43[[#This Row],[ISI/CTN]] -> 187235.78 | AY13: 45553 | AZ13: 45945 | BA13: =IF(TODAY()-Table43[[#This Row],[Efektif Pembuatan]]>60,"Lama","Baru") -> Lama | BB13: =IF(TODAY()-Table43[[#This Row],[Efektif Naik Harga]]<30,"Naik","Sama") -> Sama | BC13: Aktif | BD13: =IF(Table43[[#This Row],[Kode BARANG Win2]]<>"","IDR","") -> IDR | BE13: =CONCATENATE(Table43[[#This Row],[kode 1 Digit (Nomor)]],Table43[[#This Row],[kode 4 Digit (Nomor)]]) -> 10250 | BF13: =Table43[[#This Row],[Nama Gramasi atau Jumlah Pack per CTN]] -> 250 GR | BG13: S-HNZ | BH13: 48HEINZ | BI13: =IF(Table43[[#This Row],[SATUAN Fix Win]]<>"","KRT") -> KRT | BJ13: =IF(Table43[[#This Row],[SATUAN Fix Win]]<>"","GD01") -> GD01 | BK13: =IF(Table43[[#This Row],[SATUAN Fix Win]]<>"",11611) -> 11611 | BL13: =IF(Table43[[#This Row],[SATUAN Fix Win]]<>"",11612) -> 11612 | BM13: 0123 | BN13: =IF(Table43[[#This Row],[SATUAN Fix Win]]<>"",1) -> 1 | BO13: PT. HEINZ ABC INDONESIA | BP13: =IFERROR(VLOOKUP(Table43[[#This Row],[Kode Pcpl]],'[1]HEINZ ABC'!$A$4:$E$112,8,0),0) -> 0 | BQ13: =Table43[[#This Row],[Harga Jual Pcs GT (-PPN)]]-Table43[[#This Row],[HARGA NAIK GT]] -> 6507.75 | BR13: =IF(Table43[[#This Row],[HARGA NAIK GT]]=0,Table43[[#This Row],[Harga Jual Pcs GT (-PPN)]],Table43[[#This Row],[HARGA NAIK GT]]) -> 6507.75 | BS13: =IFERROR(VLOOKUP(Table43[[#This Row],[Kode Pcpl]],'[1]HEINZ ABC'!$A$4:$E$112,8,0),0) -> 0 | BT13: =Table43[[#This Row],[Harga Jual Pcs GT (-PPN)]]-BS13 -> 6507.75 | BU13: =IF(BS13=0,Table43[[#This Row],[Harga Jual Pcs MT (-PPN)]]) -> 7028.37 | BV13: =IFERROR(VLOOKUP(Table43[[#This Row],[Kode Pcpl]],[2]Pricelist!$A$4:$K$112,11,0),0) -> 0 | BW13: =IFERROR(VLOOKUP(Table43[[#This Row],[Kode BARANG Win2]],[3]!RECKITT211216[[KDBRG]:[HRG_JL_PCS-PPN]],11,0),0) -> 0 | BX13: =BV13/1.11 -> 0
A14: =CONCATENATE(Table43[[#This Row],[Kode BARANG Win2]],Table43[[#This Row],[No. Urut Item Sama]]) -> A10110000250102 | B14: 2 | C14: 9 | D14: 100238 | E14: RASA MANTAP SOY | F14: ABC KCP MNS PCH 24X250G 2311 | G14: 24 | H14: 7000003114 | I14: =Table43[[#This Row],[Nama Jenis Kemasan]] -> PCH | J14: =TRIM(CONCATENATE(Table43[[#This Row],[Nama KLP]]," ",Table43[[#This Row],[Nama Sub KLP]])) -> KECAP MANIS | K14: =CONCATENATE(Table43[[#This Row],[kode 2 Digit (hrf+No)]],Table43[[#This Row],[kode 2 Digit (Nomor)]],Table43[[#This Row],[kode 1 Digit (Nomor)]]) -> A1011 | L14: =IF(AG14="",CONCATENATE(Q14,S14,U14,W14,Y14,AA14,AC14,AE14,Table43[[#This Row],[Tanda Kode Revisi]]),CONCATENATE(Q14,S14,U14,W14,Y14,AA14,AC14,AG14)) -> A1011000025010 | M14: =LEN(L14) -> 14 | N14: =IF(AF14<>"",TRIM(UPPER(CONCATENATE(P14," ",R14," ",T14," ",V14," ",X14," ",Z14," ","X"," ",Table43[[#This Row],[ISI/CTN]]," ",AF14," ",AB14," ",AD14," ",AH14))),TRIM(UPPER(CONCATENATE(P14," ",R14," ",T14," ",V14," ",X14," ",Z14," ","X"," ",Table43[[#This Row],[ISI/CTN]]," ",AB14," ",AD14," ",AH14)))) -> ABC KECAP MANIS 250 GR X 24 PCH | O14: =LEN(N14) -> 31 | P14: ABC | Q14: A1 | R14: KECAP | S14: 01 | T14: MANIS | U14: 1 | W14: 0 | Y14: 00 | Z14: 250 GR | AA14: 0250 | AB14: PCH | AC14: 1 | AE14: 0 | AI14: GRAM | AJ14: 1 | AL14: =Table43[[#This Row],[Harga Jual Pcs GT (-PPN)]]-(Table43[[#This Row],[Harga Jual Pcs GT (-PPN)]]*6%) -> 6117.285 | AM14: =Table43[[#This Row],[Harga Beli Pcs (-PPN)]]*Table43[[#This Row],[ISI/CTN]] -> 146814.84 | AN14: =Table43[[#This Row],[Harga Beli Pcs (-PPN)]]*1.11 -> 6790.1864 | AO14: =Table43[[#This Row],[Harga Beli Krt (- PPN)]]*1.11 -> 162964.47 | AP14: 6507.75 | AQ14: =Table43[[#This Row],[Harga Jual Pcs GT (-PPN)]]*Table43[[#This Row],[ISI/CTN]] -> 156186 | AR14: =Table43[[#This Row],[Harga Jual Pcs GT (-PPN)]]*1.11 -> 7223.6025 | AS14: =Table43[[#This Row],[Harga Jual Krt GT (- PPN)]]*1.11 -> 173366.46 | AT14: 7028.37 | AU14: =(Table43[[#This Row],[Harga Jual Pcs MT (-PPN)]]*Table43[[#This Row],[ISI/CTN]]) -> 168680.88 | AV14: =Table43[[#This Row],[Harga Jual Pcs MT (-PPN)]]*1.11 -> 7801.4907 | AW14: =Table43[[#This Row],[Harga Jual Pcs MT (+PPN)]]*Table43[[#This Row],[ISI/CTN]] -> 187235.78 | AZ14: 45945 | BA14: =IF(TODAY()-Table43[[#This Row],[Efektif Pembuatan]]>60,"Lama","Baru") -> Lama | BB14: =IF(TODAY()-Table43[[#This Row],[Efektif Naik Harga]]<30,"Naik","Sama") -> Sama | BC14: Aktif | BD14: =IF(Table43[[#This Row],[Kode BARANG Win2]]<>"","IDR","") -> IDR | BE14: =CONCATENATE(Table43[[#This Row],[kode 1 Digit (Nomor)]],Table43[[#This Row],[kode 4 Digit (Nomor)]]) -> 10250 | BF14: =Table43[[#This Row],[Nama Gramasi atau Jumlah Pack per CTN]] -> 250 GR | BG14: S-HNZ | BH14: 48HEINZ | BI14: =IF(Table43[[#This Row],[SATUAN Fix Win]]<>"","KRT") -> KRT | BJ14: =IF(Table43[[#This Row],[SATUAN Fix Win]]<>"","GD01") -> GD01 | BK14: =IF(Table43[[#This Row],[SATUAN Fix Win]]<>"",11611) -> 11611 | BL14: =IF(Table43[[#This Row],[SATUAN Fix Win]]<>"",11612) -> 11612 | BM14: 0123 | BN14: =IF(Table43[[#This Row],[SATUAN Fix Win]]<>"",1) -> 1 | BO14: PT. HEINZ ABC INDONESIA | BP14: =IFERROR(VLOOKUP(Table43[[#This Row],[Kode Pcpl]],'[1]HEINZ ABC'!$A$4:$E$112,8,0),0) -> 0 | BQ14: =Table43[[#This Row],[Harga Jual Pcs GT (-PPN)]]-Table43[[#This Row],[HARGA NAIK GT]] -> 6507.75 | BR14: =IF(Table43[[#This Row],[HARGA NAIK GT]]=0,Table43[[#This Row],[Harga Jual Pcs GT (-PPN)]],Table43[[#This Row],[HARGA NAIK GT]]) -> 6507.75 | BS14: =IFERROR(VLOOKUP(Table43[[#This Row],[Kode Pcpl]],'[1]HEINZ ABC'!$A$4:$E$112,8,0),0) -> 0 | BT14: =Table43[[#This Row],[Harga Jual Pcs GT (-PPN)]]-BS14 -> 6507.75 | BU14: =IF(BS14=0,Table43[[#This Row],[Harga Jual Pcs MT (-PPN)]]) -> 7028.37 | BV14: =IFERROR(VLOOKUP(Table43[[#This Row],[Kode Pcpl]],[2]Pricelist!$A$4:$K$112,11,0),0) -> 0 | BW14: =IFERROR(VLOOKUP(Table43[[#This Row],[Kode BARANG Win2]],[3]!RECKITT211216[[KDBRG]:[HRG_JL_PCS-PPN]],11,0),0) -> 0 | BX14: =BV14/1.11 -> 0
A15: =CONCATENATE(Table43[[#This Row],[Kode BARANG Win2]],Table43[[#This Row],[No. Urut Item Sama]]) -> A10110000250111 | B15: 1 | C15: 10 | D15: 100992 | E15: RASA MANTAP SOY | F15: ABC KMNS PCH 250+STRSI 18G2406 | G15: 24 | H15: 7000003139 | I15: =Table43[[#This Row],[Nama Jenis Kemasan]] -> PCH | J15: =TRIM(CONCATENATE(Table43[[#This Row],[Nama KLP]]," ",Table43[[#This Row],[Nama Sub KLP]])) -> KECAP MANIS | K15: =CONCATENATE(Table43[[#This Row],[kode 2 Digit (hrf+No)]],Table43[[#This Row],[kode 2 Digit (Nomor)]],Table43[[#This Row],[kode 1 Digit (Nomor)]]) -> A1011 | L15: =IF(AG15="",CONCATENATE(Q15,S15,U15,W15,Y15,AA15,AC15,AE15,Table43[[#This Row],[Tanda Kode Revisi]]),CONCATENATE(Q15,S15,U15,W15,Y15,AA15,AC15,AG15)) -> A1011000025011 | M15: =LEN(L15) -> 14 | N15: =IF(AF15<>"",TRIM(UPPER(CONCATENATE(P15," ",R15," ",T15," ",V15," ",X15," ",Z15," ","X"," ",Table43[[#This Row],[ISI/CTN]]," ",AF15," ",AB15," ",AD15," ",AH15))),TRIM(UPPER(CONCATENATE(P15," ",R15," ",T15," ",V15," ",X15," ",Z15," ","X"," ",Table43[[#This Row],[ISI/CTN]]," ",AB15," ",AD15," ",AH15)))) -> ABC KECAP MANIS 250 GR X 24 PCH BANDED | O15: =LEN(N15) -> 38 | P15: ABC | Q15: A1 | R15: KECAP | S15: 01 | T15: MANIS | U15: 1 | W15: 0 | Y15: 00 | Z15: 250 GR | AA15: 0250 | AB15: PCH | AC15: 1 | AD15: BANDED | AE15: 1 | AI15: GRAM | AJ15: 1 | AL15: =Table43[[#This Row],[Harga Jual Pcs GT (-PPN)]]-(Table43[[#This Row],[Harga Jual Pcs GT (-PPN)]]*6%) -> 6117.285 | AM15: =Table43[[#This Row],[Harga Beli Pcs (-PPN)]]*Table43[[#This Row],[ISI/CTN]] -> 146814.84 | AN15: =Table43[[#This Row],[Harga Beli Pcs (-PPN)]]*1.11 -> 6790.1864 | AO15: =Table43[[#This Row],[Harga Beli Krt (- PPN)]]*1.11 -> 162964.47 | AP15: 6507.75 | AQ15: =Table43[[#This Row],[Harga Jual Pcs GT (-PPN)]]*Table43[[#This Row],[ISI/CTN]] -> 156186 | AR15: =Table43[[#This Row],[Harga Jual Pcs GT (-PPN)]]*1.11 -> 7223.6025 | AS15: =Table43[[#This Row],[Harga Jual Krt GT (- PPN)]]*1.11 -> 173366.46 | AT15: 7028.37 | AU15: =(Table43[[#This Row],[Harga Jual Pcs MT (-PPN)]]*Table43[[#This Row],[ISI/CTN]]) -> 168680.88 | AV15: =Table43[[#This Row],[Harga Jual Pcs MT (-PPN)]]*1.11 -> 7801.4907 | AW15: =Table43[[#This Row],[Harga Jual Pcs MT (+PPN)]]*Table43[[#This Row],[ISI/CTN]] -> 187235.78 | AY15: 45730 | AZ15: 45945 | BA15: =IF(TODAY()-Table43[[#This Row],[Efektif Pembuatan]]>60,"Lama","Baru") -> Lama | BB15: =IF(TODAY()-Table43[[#This Row],[Efektif Naik Harga]]<30,"Naik","Sama") -> Sama | BC15: Aktif | BD15: =IF(Table43[[#This Row],[Kode BARANG Win2]]<>"","IDR","") -> IDR | BE15: =CONCATENATE(Table43[[#This Row],[kode 1 Digit (Nomor)]],Table43[[#This Row],[kode 4 Digit (Nomor)]]) -> 10250 | BF15: =Table43[[#This Row],[Nama Gramasi atau Jumlah Pack per CTN]] -> 250 GR | BG15: S-HNZ | BH15: 48HEINZ | BI15: =IF(Table43[[#This Row],[SATUAN Fix Win]]<>"","KRT") -> KRT | BJ15: =IF(Table43[[#This Row],[SATUAN Fix Win]]<>"","GD01") -> GD01 | BK15: =IF(Table43[[#This Row],[SATUAN Fix Win]]<>"",11611) -> 11611 | BL15: =IF(Table43[[#This Row],[SATUAN Fix Win]]<>"",11612) -> 11612 | BM15: 0123 | BN15: =IF(Table43[[#This Row],[SATUAN Fix Win]]<>"",1) -> 1 | BO15: PT. HEINZ ABC INDONESIA | BP15: =IFERROR(VLOOKUP(Table43[[#This Row],[Kode Pcpl]],'[1]HEINZ ABC'!$A$4:$E$112,8,0),0) -> 0 | BQ15: =Table43[[#This Row],[Harga Jual Pcs GT (-PPN)]]-Table43[[#This Row],[HARGA NAIK GT]] -> 6507.75 | BR15: =IF(Table43[[#This Row],[HARGA NAIK GT]]=0,Table43[[#This Row],[Harga Jual Pcs GT (-PPN)]],Table43[[#This Row],[HARGA NAIK GT]]) -> 6507.75 | BS15: =IFERROR(VLOOKUP(Table43[[#This Row],[Kode Pcpl]],'[1]HEINZ ABC'!$A$4:$E$112,8,0),0) -> 0 | BT15: =Table43[[#This Row],[Harga Jual Pcs GT (-PPN)]]-BS15 -> 6507.75 | BU15: =IF(BS15=0,Table43[[#This Row],[Harga Jual Pcs MT (-PPN)]]) -> 7028.37 | BV15: =IFERROR(VLOOKUP(Table43[[#This Row],[Kode Pcpl]],[2]Pricelist!$A$4:$K$112,11,0),0) -> 0 | BW15: =IFERROR(VLOOKUP(Table43[[#This Row],[Kode BARANG Win2]],[3]!RECKITT211216[[KDBRG]:[HRG_JL_PCS-PPN]],11,0),0) -> 0 | BX15: =BV15/1.11 -> 0
A16: =CONCATENATE(Table43[[#This Row],[Kode BARANG Win2]],Table43[[#This Row],[No. Urut Item Sama]]) -> A10110000600111 | B16: 1 | H16: 0 | I16: =Table43[[#This Row],[Nama Jenis Kemasan]] -> PCH | J16: =TRIM(CONCATENATE(Table43[[#This Row],[Nama KLP]]," ",Table43[[#This Row],[Nama Sub KLP]])) -> KECAP MANIS | K16: =CONCATENATE(Table43[[#This Row],[kode 2 Digit (hrf+No)]],Table43[[#This Row],[kode 2 Digit (Nomor)]],Table43[[#This Row],[kode 1 Digit (Nomor)]]) -> A1011 | L16: =IF(AG16="",CONCATENATE(Q16,S16,U16,W16,Y16,AA16,AC16,AE16,Table43[[#This Row],[Tanda Kode Revisi]]),CONCATENATE(Q16,S16,U16,W16,Y16,AA16,AC16,AG16)) -> A1011000060011 | M16: =LEN(L16) -> 14 | N16: =IF(AF16<>"",TRIM(UPPER(CONCATENATE(P16," ",R16," ",T16," ",V16," ",X16," ",Z16," ","X"," ",Table43[[#This Row],[ISI/CTN]]," ",AF16," ",AB16," ",AD16," ",AH16))),TRIM(UPPER(CONCATENATE(P16," ",R16," ",T16," ",V16," ",X16," ",Z16," ","X"," ",Table43[[#This Row],[ISI/CTN]]," ",AB16," ",AD16," ",AH16)))) -> ABC KECAP MANIS 600 GR X PCH BANDED | O16: =LEN(N16) -> 35 | P16: ABC | Q16: A1 | R16: KECAP | S16: 01 | T16: MANIS | U16: 1 | W16: 0 | Y16: 00 | Z16: 600 GR | AA16: 0600 | AB16: PCH | AC16: 1 | AD16: BANDED | AE16: 1 | AI16: GRAM | AJ16: 1 | AL16: =Table43[[#This Row],[Harga Jual Pcs GT (-PPN)]]-(Table43[[#This Row],[Harga Jual Pcs GT (-PPN)]]*6%) -> 16126.64 | AM16: =Table43[[#This Row],[Harga Beli Pcs (-PPN)]]*Table43[[#This Row],[ISI/CTN]] -> 0 | AN16: =Table43[[#This Row],[Harga Beli Pcs (-PPN)]]*1.11 -> 17900.57 | AO16: =Table43[[#This Row],[Harga Beli Krt (- PPN)]]*1.11 -> 0 | AP16: 17156 | AQ16: =Table43[[#This Row],[Harga Jual Pcs GT (-PPN)]]*Table43[[#This Row],[ISI/CTN]] -> 0 | AR16: =Table43[[#This Row],[Harga Jual Pcs GT (-PPN)]]*1.11 -> 19043.16 | AS16: =Table43[[#This Row],[Harga Jual Krt GT (- PPN)]]*1.11 -> 0 | AT16: 18528.48 | AU16: =(Table43[[#This Row],[Harga Jual Pcs MT (-PPN)]]*Table43[[#This Row],[ISI/CTN]]) -> 0 | AV16: =Table43[[#This Row],[Harga Jual Pcs MT (-PPN)]]*1.11 -> 20566.613 | AW16: =Table43[[#This Row],[Harga Jual Pcs MT (+PPN)]]*Table43[[#This Row],[ISI/CTN]] -> 0 | AY16: 46059 | BA16: =IF(TODAY()-Table43[[#This Row],[Efektif Pembuatan]]>60,"Lama","Baru") -> Lama | BB16: =IF(TODAY()-Table43[[#This Row],[Efektif Naik Harga]]<30,"Naik","Sama") -> Sama | BC16: Discontinue | BD16: =IF(Table43[[#This Row],[Kode BARANG Win2]]<>"","IDR","") -> IDR | BE16: =CONCATENATE(Table43[[#This Row],[kode 1 Digit (Nomor)]],Table43[[#This Row],[kode 4 Digit (Nomor)]]) -> 10600 | BF16: =Table43[[#This Row],[Nama Gramasi atau Jumlah Pack per CTN]] -> 600 GR | BG16: S-HNZ | BH16: 48HEINZ | BI16: =IF(Table43[[#This Row],[SATUAN Fix Win]]<>"","KRT") -> KRT | BJ16: =IF(Table43[[#This Row],[SATUAN Fix Win]]<>"","GD01") -> GD01 | BK16: =IF(Table43[[#This Row],[SATUAN Fix Win]]<>"",11611) -> 11611 | BL16: =IF(Table43[[#This Row],[SATUAN Fix Win]]<>"",11612) -> 11612 | BM16: 0123 | BN16: =IF(Table43[[#This Row],[SATUAN Fix Win]]<>"",1) -> 1 | BO16: PT. HEINZ ABC INDONESIA | BP16: =IFERROR(VLOOKUP(Table43[[#This Row],[Kode Pcpl]],'[1]HEINZ ABC'!$A$4:$E$112,8,0),0) -> 0 | BQ16: =Table43[[#This Row],[Harga Jual Pcs GT (-PPN)]]-Table43[[#This Row],[HARGA NAIK GT]] -> 17156 | BR16: =IF(Table43[[#This Row],[HARGA NAIK GT]]=0,Table43[[#This Row],[Harga Jual Pcs GT (-PPN)]],Table43[[#This Row],[HARGA NAIK GT]]) -> 17156
A17: =CONCATENATE(Table43[[#This Row],[Kode BARANG Win2]],Table43[[#This Row],[No. Urut Item Sama]]) -> A10110000275201 | B17: 1 | C17: 11 | D17: 100162 | E17: RASA MANTAP SOY | F17: ABC KCPMNS PET SB 24X275ML1607 | G17: 24 | H17: 0 | I17: =Table43[[#This Row],[Nama Jenis Kemasan]] -> BTL | J17: =TRIM(CONCATENATE(Table43[[#This Row],[Nama KLP]]," ",Table43[[#This Row],[Nama Sub KLP]])) -> KECAP MANIS | K17: =CONCATENATE(Table43[[#This Row],[kode 2 Digit (hrf+No)]],Table43[[#This Row],[kode 2 Digit (Nomor)]],Table43[[#This Row],[kode 1 Digit (Nomor)]]) -> A1011 | L17: =IF(AG17="",CONCATENATE(Q17,S17,U17,W17,Y17,AA17,AC17,AE17,Table43[[#This Row],[Tanda Kode Revisi]]),CONCATENATE(Q17,S17,U17,W17,Y17,AA17,AC17,AG17)) -> A1011000027520 | M17: =LEN(L17) -> 14 | N17: =IF(AF17<>"",TRIM(UPPER(CONCATENATE(P17," ",R17," ",T17," ",V17," ",X17," ",Z17," ","X"," ",Table43[[#This Row],[ISI/CTN]]," ",AF17," ",AB17," ",AD17," ",AH17))),TRIM(UPPER(CONCATENATE(P17," ",R17," ",T17," ",V17," ",X17," ",Z17," ","X"," ",Table43[[#This Row],[ISI/CTN]]," ",AB17," ",AD17," ",AH17)))) -> ABC KECAP MANIS 275 ML X 24 BTL | O17: =LEN(N17) -> 31 | P17: ABC | Q17: A1 | R17: KECAP | S17: 01 | T17: MANIS | U17: 1 | W17: 0 | Y17: 00 | Z17: 275 ML | AA17: 0275 | AB17: BTL | AC17: 2 | AE17: 0 | AI17: LITER | AJ17: 2 | AL17: =Table43[[#This Row],[Harga Jual Pcs GT (-PPN)]]-(Table43[[#This Row],[Harga Jual Pcs GT (-PPN)]]*6%) -> 15649.731 | AM17: =Table43[[#This Row],[Harga Beli Pcs (-PPN)]]*Table43[[#This Row],[ISI/CTN]] -> 375593.54 | AN17: =Table43[[#This Row],[Harga Beli Pcs (-PPN)]]*1.11 -> 17371.201 | AO17: =Table43[[#This Row],[Harga Beli Krt (- PPN)]]*1.11 -> 416908.83 | AP17: 16648.65 | AQ17: =Table43[[#This Row],[Harga Jual Pcs GT (-PPN)]]*Table43[[#This Row],[ISI/CTN]] -> 399567.6 | AR17: =Table43[[#This Row],[Harga Jual Pcs GT (-PPN)]]*1.11 -> 18480.002 | AS17: =Table43[[#This Row],[Harga Jual Krt GT (- PPN)]]*1.11 -> 443520.04 | AT17: 17980.54 | AU17: =(Table43[[#This Row],[Harga Jual Pcs MT (-PPN)]]*Table43[[#This Row],[ISI/CTN]]) -> 431532.96 | AV17: =Table43[[#This Row],[Harga Jual Pcs MT (-PPN)]]*1.11 -> 19958.399 | AW17: =Table43[[#This Row],[Harga Jual Pcs MT (+PPN)]]*Table43[[#This Row],[ISI/CTN]] -> 479001.59 | AY17: 45553 | AZ17: 45553 | BA17: =IF(TODAY()-Table43[[#This Row],[Efektif Pembuatan]]>60,"Lama","Baru") -> Lama | BB17: =IF(TODAY()-Table43[[#This Row],[Efektif Naik Harga]]<30,"Naik","Sama") -> Sama | BC17: Aktif | BD17: =IF(Table43[[#This Row],[Kode BARANG Win2]]<>"","IDR","") -> IDR | BE17: =CONCATENATE(Table43[[#This Row],[kode 1 Digit (Nomor)]],Table43[[#This Row],[kode 4 Digit (Nomor)]]) -> 20275 | BF17: =Table43[[#This Row],[Nama Gramasi atau Jumlah Pack per CTN]] -> 275 ML | BG17: S-HNZ | BH17: 48HEINZ | BI17: =IF(Table43[[#This Row],[SATUAN Fix Win]]<>"","KRT") -> KRT | BJ17: =IF(Table43[[#This Row],[SATUAN Fix Win]]<>"","GD01") -> GD01 | BK17: =IF(Table43[[#This Row],[SATUAN Fix Win]]<>"",11611) -> 11611 | BL17: =IF(Table43[[#This Row],[SATUAN Fix Win]]<>"",11612) -> 11612 | BM17: 0123 | BN17: =IF(Table43[[#This Row],[SATUAN Fix Win]]<>"",1) -> 1 | BO17: PT. HEINZ ABC INDONESIA | BP17: =IFERROR(VLOOKUP(Table43[[#This Row],[Kode Pcpl]],'[1]HEINZ ABC'!$A$4:$E$112,8,0),0) -> 0 | BQ17: =Table43[[#This Row],[Harga Jual Pcs GT (-PPN)]]-Table43[[#This Row],[HARGA NAIK GT]] -> 16648.65 | BR17: =IF(Table43[[#This Row],[HARGA NAIK GT]]=0,Table43[[#This Row],[Harga Jual Pcs GT (-PPN)]],Table43[[#This Row],[HARGA NAIK GT]]) -> 16648.65 | BS17: =IFERROR(VLOOKUP(Table43[[#This Row],[Kode Pcpl]],'[1]HEINZ ABC'!$A$4:$E$112,8,0),0) -> 0 | BT17: =Table43[[#This Row],[Harga Jual Pcs GT (-PPN)]]-BS17 -> 16648.65 | BU17: =IF(BS17=0,Table43[[#This Row],[Harga Jual Pcs MT (-PPN)]]) -> 17980.54 | BV17: =IFERROR(VLOOKUP(Table43[[#This Row],[Kode Pcpl]],[2]Pricelist!$A$4:$K$112,11,0),0) -> 0 | BW17: =IFERROR(VLOOKUP(Table43[[#This Row],[Kode BARANG Win2]],[3]!RECKITT211216[[KDBRG]:[HRG_JL_PCS-PPN]],11,0),0) -> 0 | BX17: =BV17/1.11 -> 0
A18: =CONCATENATE(Table43[[#This Row],[Kode BARANG Win2]],Table43[[#This Row],[No. Urut Item Sama]]) -> A10110000275202 | B18: 2 | C18: 12 | D18: 100236 | E18: RASA MANTAP SOY | F18: ABC KCPMNS PET SB 24X275ML1607 | G18: 24 | H18: 7000003112 | I18: =Table43[[#This Row],[Nama Jenis Kemasan]] -> BTL | J18: =TRIM(CONCATENATE(Table43[[#This Row],[Nama KLP]]," ",Table43[[#This Row],[Nama Sub KLP]])) -> KECAP MANIS | K18: =CONCATENATE(Table43[[#This Row],[kode 2 Digit (hrf+No)]],Table43[[#This Row],[kode 2 Digit (Nomor)]],Table43[[#This Row],[kode 1 Digit (Nomor)]]) -> A1011 | L18: =IF(AG18="",CONCATENATE(Q18,S18,U18,W18,Y18,AA18,AC18,AE18,Table43[[#This Row],[Tanda Kode Revisi]]),CONCATENATE(Q18,S18,U18,W18,Y18,AA18,AC18,AG18)) -> A1011000027520 | M18: =LEN(L18) -> 14 | N18: =IF(AF18<>"",TRIM(UPPER(CONCATENATE(P18," ",R18," ",T18," ",V18," ",X18," ",Z18," ","X"," ",Table43[[#This Row],[ISI/CTN]]," ",AF18," ",AB18," ",AD18," ",AH18))),TRIM(UPPER(CONCATENATE(P18," ",R18," ",T18," ",V18," ",X18," ",Z18," ","X"," ",Table43[[#This Row],[ISI/CTN]]," ",AB18," ",AD18," ",AH18)))) -> ABC KECAP MANIS 275 ML X 24 BTL | O18: =LEN(N18) -> 31 | P18: ABC | Q18: A1 | R18: KECAP | S18: 01 | T18: MANIS | U18: 1 | W18: 0 | Y18: 00 | Z18: 275 ML | AA18: 0275 | AB18: BTL | AC18: 2 | AE18: 0 | AI18: LITER | AJ18: 2 | AL18: =Table43[[#This Row],[Harga Jual Pcs GT (-PPN)]]-(Table43[[#This Row],[Harga Jual Pcs GT (-PPN)]]*6%) -> 15649.731 | AM18: =Table43[[#This Row],[Harga Beli Pcs (-PPN)]]*Table43[[#This Row],[ISI/CTN]] -> 375593.54 | AN18: =Table43[[#This Row],[Harga Beli Pcs (-PPN)]]*1.11 -> 17371.201 | AO18: =Table43[[#This Row],[Harga Beli Krt (- PPN)]]*1.11 -> 416908.83 | AP18: 16648.65 | AQ18: =Table43[[#This Row],[Harga Jual Pcs GT (-PPN)]]*Table43[[#This Row],[ISI/CTN]] -> 399567.6 | AR18: =Table43[[#This Row],[Harga Jual Pcs GT (-PPN)]]*1.11 -> 18480.002 | AS18: =Table43[[#This Row],[Harga Jual Krt GT (- PPN)]]*1.11 -> 443520.04 | AT18: 17980.54 | AU18: =(Table43[[#This Row],[Harga Jual Pcs MT (-PPN)]]*Table43[[#This Row],[ISI/CTN]]) -> 431532.96 | AV18: =Table43[[#This Row],[Harga Jual Pcs MT (-PPN)]]*1.11 -> 19958.399 | AW18: =Table43[[#This Row],[Harga Jual Pcs MT (+PPN)]]*Table43[[#This Row],[ISI/CTN]] -> 479001.59 | AY18: 45565 | AZ18: 45553 | BA18: =IF(TODAY()-Table43[[#This Row],[Efektif Pembuatan]]>60,"Lama","Baru") -> Lama | BB18: =IF(TODAY()-Table43[[#This Row],[Efektif Naik Harga]]<30,"Naik","Sama") -> Sama | BC18: Aktif | BD18: =IF(Table43[[#This Row],[Kode BARANG Win2]]<>"","IDR","") -> IDR | BE18: =CONCATENATE(Table43[[#This Row],[kode 1 Digit (Nomor)]],Table43[[#This Row],[kode 4 Digit (Nomor)]]) -> 20275 | BF18: =Table43[[#This Row],[Nama Gramasi atau Jumlah Pack per CTN]] -> 275 ML | BG18: S-HNZ | BH18: 48HEINZ | BI18: =IF(Table43[[#This Row],[SATUAN Fix Win]]<>"","KRT") -> KRT | BJ18: =IF(Table43[[#This Row],[SATUAN Fix Win]]<>"","GD01") -> GD01 | BK18: =IF(Table43[[#This Row],[SATUAN Fix Win]]<>"",11611) -> 11611 | BL18: =IF(Table43[[#This Row],[SATUAN Fix Win]]<>"",11612) -> 11612 | BM18: 0123 | BN18: =IF(Table43[[#This Row],[SATUAN Fix Win]]<>"",1) -> 1 | BO18: PT. HEINZ ABC INDONESIA | BP18: =IFERROR(VLOOKUP(Table43[[#This Row],[Kode Pcpl]],'[1]HEINZ ABC'!$A$4:$E$112,8,0),0) -> 0 | BQ18: =Table43[[#This Row],[Harga Jual Pcs GT (-PPN)]]-Table43[[#This Row],[HARGA NAIK GT]] -> 16648.65 | BR18: =IF(Table43[[#This Row],[HARGA NAIK GT]]=0,Table43[[#This Row],[Harga Jual Pcs GT (-PPN)]],Table43[[#This Row],[HARGA NAIK GT]]) -> 16648.65 | BS18: =IFERROR(VLOOKUP(Table43[[#This Row],[Kode Pcpl]],'[1]HEINZ ABC'!$A$4:$E$112,8,0),0) -> 0 | BT18: =Table43[[#This Row],[Harga Jual Pcs GT (-PPN)]]-BS18 -> 16648.65 | BU18: =IF(BS18=0,Table43[[#This Row],[Harga Jual Pcs MT (-PPN)]]) -> 17980.54 | BV18: =IFERROR(VLOOKUP(Table43[[#This Row],[Kode Pcpl]],[2]Pricelist!$A$4:$K$112,11,0),0) -> 0 | BW18: =IFERROR(VLOOKUP(Table43[[#This Row],[Kode BARANG Win2]],[3]!RECKITT211216[[KDBRG]:[HRG_JL_PCS-PPN]],11,0),0) -> 0 | BX18: =BV18/1.11 -> 0
A19: =CONCATENATE(Table43[[#This Row],[Kode BARANG Win2]],Table43[[#This Row],[No. Urut Item Sama]]) -> A10110000300101 | B19: 1 | C19: 13 | D19: 100158 | E19: RASA MANTAP SOY | F19: ABC KCPMNS PCH SB 24X225ML1607 | G19: 24 | H19: 7000003064 | I19: =Table43[[#This Row],[Nama Jenis Kemasan]] -> PCH | J19: =TRIM(CONCATENATE(Table43[[#This Row],[Nama KLP]]," ",Table43[[#This Row],[Nama Sub KLP]])) -> KECAP MANIS | K19: =CONCATENATE(Table43[[#This Row],[kode 2 Digit (hrf+No)]],Table43[[#This Row],[kode 2 Digit (Nomor)]],Table43[[#This Row],[kode 1 Digit (Nomor)]]) -> A1011 | L19: =IF(AG19="",CONCATENATE(Q19,S19,U19,W19,Y19,AA19,AC19,AE19,Table43[[#This Row],[Tanda Kode Revisi]]),CONCATENATE(Q19,S19,U19,W19,Y19,AA19,AC19,AG19)) -> A1011000030010 | M19: =LEN(L19) -> 14 | N19: =IF(AF19<>"",TRIM(UPPER(CONCATENATE(P19," ",R19," ",T19," ",V19," ",X19," ",Z19," ","X"," ",Table43[[#This Row],[ISI/CTN]]," ",AF19," ",AB19," ",AD19," ",AH19))),TRIM(UPPER(CONCATENATE(P19," ",R19," ",T19," ",V19," ",X19," ",Z19," ","X"," ",Table43[[#This Row],[ISI/CTN]]," ",AB19," ",AD19," ",AH19)))) -> ABC KECAP MANIS 300 GR X 24 PCH | O19: =LEN(N19) -> 31 | P19: ABC | Q19: A1 | R19: KECAP | S19: 01 | T19: MANIS | U19: 1 | W19: 0 | Y19: 00 | Z19: 300 GR | AA19: 0300 | AB19: PCH | AC19: 1 | AE19: 0 | AI19: GRAM | AJ19: 1 | AL19: =Table43[[#This Row],[Harga Jual Pcs GT (-PPN)]]-(Table43[[#This Row],[Harga Jual Pcs GT (-PPN)]]*6%) -> 8383.7848 | AM19: =Table43[[#This Row],[Harga Beli Pcs (-PPN)]]*Table43[[#This Row],[ISI/CTN]] -> 201210.84 | AN19: =Table43[[#This Row],[Harga Beli Pcs (-PPN)]]*1.11 -> 9306.0011 | AO19: =Table43[[#This Row],[Harga Beli Krt (- PPN)]]*1.11 -> 223344.03 | AP19: 8918.92 | AQ19: =Table43[[#This Row],[Harga Jual Pcs GT (-PPN)]]*Table43[[#This Row],[ISI/CTN]] -> 214054.08 | AR19: =Table43[[#This Row],[Harga Jual Pcs GT (-PPN)]]*1.11 -> 9900.0012 | AS19: =Table43[[#This Row],[Harga Jual Krt GT (- PPN)]]*1.11 -> 237600.03 | AT19: 9632.43 | AU19: =(Table43[[#This Row],[Harga Jual Pcs MT (-PPN)]]*Table43[[#This Row],[ISI/CTN]]) -> 231178.32 | AV19: =Table43[[#This Row],[Harga Jual Pcs MT (-PPN)]]*1.11 -> 10691.997 | AW19: =Table43[[#This Row],[Harga Jual Pcs MT (+PPN)]]*Table43[[#This Row],[ISI/CTN]] -> 256607.94 | AY19: 45553 | AZ19: 45553 | BA19: =IF(TODAY()-Table43[[#This Row],[Efektif Pembuatan]]>60,"Lama","Baru") -> Lama | BB19: =IF(TODAY()-Table43[[#This Row],[Efektif Naik Harga]]<30,"Naik","Sama") -> Sama | BC19: Aktif | BD19: =IF(Table43[[#This Row],[Kode BARANG Win2]]<>"","IDR","") -> IDR | BE19: =CONCATENATE(Table43[[#This Row],[kode 1 Digit (Nomor)]],Table43[[#This Row],[kode 4 Digit (Nomor)]]) -> 10300 | BF19: =Table43[[#This Row],[Nama Gramasi atau Jumlah Pack per CTN]] -> 300 GR | BG19: S-HNZ | BH19: 48HEINZ | BI19: =IF(Table43[[#This Row],[SATUAN Fix Win]]<>"","KRT") -> KRT | BJ19: =IF(Table43[[#This Row],[SATUAN Fix Win]]<>"","GD01") -> GD01 | BK19: =IF(Table43[[#This Row],[SATUAN Fix Win]]<>"",11611) -> 11611 | BL19: =IF(Table43[[#This Row],[SATUAN Fix Win]]<>"",11612) -> 11612 | BM19: 0123 | BN19: =IF(Table43[[#This Row],[SATUAN Fix Win]]<>"",1) -> 1 | BO19: PT. HEINZ ABC INDONESIA | BP19: =IFERROR(VLOOKUP(Table43[[#This Row],[Kode Pcpl]],'[1]HEINZ ABC'!$A$4:$E$112,8,0),0) -> 0 | BQ19: =Table43[[#This Row],[Harga Jual Pcs GT (-PPN)]]-Table43[[#This Row],[HARGA NAIK GT]] -> 8918.92 | BR19: =IF(Table43[[#This Row],[HARGA NAIK GT]]=0,Table43[[#This Row],[Harga Jual Pcs GT (-PPN)]],Table43[[#This Row],[HARGA NAIK GT]]) -> 8918.92 | BS19: =IFERROR(VLOOKUP(Table43[[#This Row],[Kode Pcpl]],'[1]HEINZ ABC'!$A$4:$E$112,8,0),0) -> 0 | BT19: =Table43[[#This Row],[Harga Jual Pcs GT (-PPN)]]-BS19 -> 8918.92 | BU19: =IF(BS19=0,Table43[[#This Row],[Harga Jual Pcs MT (-PPN)]]) -> 9632.43 | BV19: =IFERROR(VLOOKUP(Table43[[#This Row],[Kode Pcpl]],[2]Pricelist!$A$4:$K$112,11,0),0) -> 0 | BW19: =IFERROR(VLOOKUP(Table43[[#This Row],[Kode BARANG Win2]],[3]!RECKITT211216[[KDBRG]:[HRG_JL_PCS-PPN]],11,0),0) -> 0 | BX19: =BV19/1.11 -> 0
A20: =CONCATENATE(Table43[[#This Row],[Kode BARANG Win2]],Table43[[#This Row],[No. Urut Item Sama]]) -> A10110000300102 | B20: 2 | C20: 14 | D20: 100172 | E20: RASA MANTAP SOY | F20: ABC KCP MNS PCH 24X300G 2208 | G20: 24 | H20: 7000003071 | I20: =Table43[[#This Row],[Nama Jenis Kemasan]] -> PCH | J20: =TRIM(CONCATENATE(Table43[[#This Row],[Nama KLP]]," ",Table43[[#This Row],[Nama Sub KLP]])) -> KECAP MANIS | K20: =CONCATENATE(Table43[[#This Row],[kode 2 Digit (hrf+No)]],Table43[[#This Row],[kode 2 Digit (Nomor)]],Table43[[#This Row],[kode 1 Digit (Nomor)]]) -> A1011 | L20: =IF(AG20="",CONCATENATE(Q20,S20,U20,W20,Y20,AA20,AC20,AE20,Table43[[#This Row],[Tanda Kode Revisi]]),CONCATENATE(Q20,S20,U20,W20,Y20,AA20,AC20,AG20)) -> A1011000030010 | M20: =LEN(L20) -> 14 | N20: =IF(AF20<>"",TRIM(UPPER(CONCATENATE(P20," ",R20," ",T20," ",V20," ",X20," ",Z20," ","X"," ",Table43[[#This Row],[ISI/CTN]]," ",AF20," ",AB20," ",AD20," ",AH20))),TRIM(UPPER(CONCATENATE(P20," ",R20," ",T20," ",V20," ",X20," ",Z20," ","X"," ",Table43[[#This Row],[ISI/CTN]]," ",AB20," ",AD20," ",AH20)))) -> ABC KECAP MANIS 300 GR X 24 PCH | O20: =LEN(N20) -> 31 | P20: ABC | Q20: A1 | R20: KECAP | S20: 01 | T20: MANIS | U20: 1 | W20: 0 | Y20: 00 | Z20: 300 GR | AA20: 0300 | AB20: PCH | AC20: 1 | AE20: 0 | AI20: GRAM | AJ20: 1 | AL20: =Table43[[#This Row],[Harga Jual Pcs GT (-PPN)]]-(Table43[[#This Row],[Harga Jual Pcs GT (-PPN)]]*6%) -> 8383.7848 | AM20: =Table43[[#This Row],[Harga Beli Pcs (-PPN)]]*Table43[[#This Row],[ISI/CTN]] -> 201210.84 | AN20: =Table43[[#This Row],[Harga Beli Pcs (-PPN)]]*1.11 -> 9306.0011 | AO20: =Table43[[#This Row],[Harga Beli Krt (- PPN)]]*1.11 -> 223344.03 | AP20: 8918.92 | AQ20: =Table43[[#This Row],[Harga Jual Pcs GT (-PPN)]]*Table43[[#This Row],[ISI/CTN]] -> 214054.08 | AR20: =Table43[[#This Row],[Harga Jual Pcs GT (-PPN)]]*1.11 -> 9900.0012 | AS20: =Table43[[#This Row],[Harga Jual Krt GT (- PPN)]]*1.11 -> 237600.03 | AT20: 9632.43 | AU20: =(Table43[[#This Row],[Harga Jual Pcs MT (-PPN)]]*Table43[[#This Row],[ISI/CTN]]) -> 231178.32 | AV20: =Table43[[#This Row],[Harga Jual Pcs MT (-PPN)]]*1.11 -> 10691.997 | AW20: =Table43[[#This Row],[Harga Jual Pcs MT (+PPN)]]*Table43[[#This Row],[ISI/CTN]] -> 256607.94 | AY20: 45553 | AZ20: 45553 | BA20: =IF(TODAY()-Table43[[#This Row],[Efektif Pembuatan]]>60,"Lama","Baru") -> Lama | BB20: =IF(TODAY()-Table43[[#This Row],[Efektif Naik Harga]]<30,"Naik","Sama") -> Sama | BC20: Aktif | BD20: =IF(Table43[[#This Row],[Kode BARANG Win2]]<>"","IDR","") -> IDR | BE20: =CONCATENATE(Table43[[#This Row],[kode 1 Digit (Nomor)]],Table43[[#This Row],[kode 4 Digit (Nomor)]]) -> 10300 | BF20: =Table43[[#This Row],[Nama Gramasi atau Jumlah Pack per CTN]] -> 300 GR | BG20: S-HNZ | BH20: 48HEINZ | BI20: =IF(Table43[[#This Row],[SATUAN Fix Win]]<>"","KRT") -> KRT | BJ20: =IF(Table43[[#This Row],[SATUAN Fix Win]]<>"","GD01") -> GD01 | BK20: =IF(Table43[[#This Row],[SATUAN Fix Win]]<>"",11611) -> 11611 | BL20: =IF(Table43[[#This Row],[SATUAN Fix Win]]<>"",11612) -> 11612 | BM20: 0123 | BN20: =IF(Table43[[#This Row],[SATUAN Fix Win]]<>"",1) -> 1 | BO20: PT. HEINZ ABC INDONESIA | BP20: =IFERROR(VLOOKUP(Table43[[#This Row],[Kode Pcpl]],'[1]HEINZ ABC'!$A$4:$E$112,8,0),0) -> 0 | BQ20: =Table43[[#This Row],[Harga Jual Pcs GT (-PPN)]]-Table43[[#This Row],[HARGA NAIK GT]] -> 8918.92 | BR20: =IF(Table43[[#This Row],[HARGA NAIK GT]]=0,Table43[[#This Row],[Harga Jual Pcs GT (-PPN)]],Table43[[#This Row],[HARGA NAIK GT]]) -> 8918.92 | BS20: =IFERROR(VLOOKUP(Table43[[#This Row],[Kode Pcpl]],'[1]HEINZ ABC'!$A$4:$E$112,8,0),0) -> 0 | BT20: =Table43[[#This Row],[Harga Jual Pcs GT (-PPN)]]-BS20 -> 8918.92 | BU20: =IF(BS20=0,Table43[[#This Row],[Harga Jual Pcs MT (-PPN)]]) -> 9632.43 | BV20: =IFERROR(VLOOKUP(Table43[[#This Row],[Kode Pcpl]],[2]Pricelist!$A$4:$K$112,11,0),0) -> 0 | BW20: =IFERROR(VLOOKUP(Table43[[#This Row],[Kode BARANG Win2]],[3]!RECKITT211216[[KDBRG]:[HRG_JL_PCS-PPN]],11,0),0) -> 0 | BX20: =BV20/1.11 -> 0
A21: =CONCATENATE(Table43[[#This Row],[Kode BARANG Win2]],Table43[[#This Row],[No. Urut Item Sama]]) -> A10110000300121 | B21: 1 | C21: 15 | D21: 100991 | E21: RASA MANTAP SOY | F21: ABC KMNS PCH 12X600G PRBTL2407 | G21: 12 | H21: 7000003138 | I21: =Table43[[#This Row],[Nama Jenis Kemasan]] -> PCH | J21: =TRIM(CONCATENATE(Table43[[#This Row],[Nama KLP]]," ",Table43[[#This Row],[Nama Sub KLP]])) -> KECAP MANIS | K21: =CONCATENATE(Table43[[#This Row],[kode 2 Digit (hrf+No)]],Table43[[#This Row],[kode 2 Digit (Nomor)]],Table43[[#This Row],[kode 1 Digit (Nomor)]]) -> A1011 | L21: =IF(AG21="",CONCATENATE(Q21,S21,U21,W21,Y21,AA21,AC21,AE21,Table43[[#This Row],[Tanda Kode Revisi]]),CONCATENATE(Q21,S21,U21,W21,Y21,AA21,AC21,AG21)) -> A1011000030012 | M21: =LEN(L21) -> 14 | N21: =IF(AF21<>"",TRIM(UPPER(CONCATENATE(P21," ",R21," ",T21," ",V21," ",X21," ",Z21," ","X"," ",Table43[[#This Row],[ISI/CTN]]," ",AF21," ",AB21," ",AD21," ",AH21))),TRIM(UPPER(CONCATENATE(P21," ",R21," ",T21," ",V21," ",X21," ",Z21," ","X"," ",Table43[[#This Row],[ISI/CTN]]," ",AB21," ",AD21," ",AH21)))) -> ABC KECAP MANIS 600 GR X 12 PCH BANDED | O21: =LEN(N21) -> 38 | P21: ABC | Q21: A1 | R21: KECAP | S21: 01 | T21: MANIS | U21: 1 | W21: 0 | Y21: 00 | Z21: 600 GR | AA21: 0300 | AB21: PCH | AC21: 1 | AD21: BANDED | AE21: 2 | AI21: GRAM | AJ21: 1 | AL21: =Table43[[#This Row],[Harga Jual Pcs GT (-PPN)]]-(Table43[[#This Row],[Harga Jual Pcs GT (-PPN)]]*6%) -> 16126.875 | AM21: =Table43[[#This Row],[Harga Beli Pcs (-PPN)]]*Table43[[#This Row],[ISI/CTN]] -> 193522.5 | AN21: =Table43[[#This Row],[Harga Beli Pcs (-PPN)]]*1.11 -> 17900.831 | AO21: =Table43[[#This Row],[Harga Beli Krt (- PPN)]]*1.11 -> 214809.98 | AP21: 17156.25 | AQ21: =Table43[[#This Row],[Harga Jual Pcs GT (-PPN)]]*Table43[[#This Row],[ISI/CTN]] -> 205875 | AR21: =Table43[[#This Row],[Harga Jual Pcs GT (-PPN)]]*1.11 -> 19043.438 | AS21: =Table43[[#This Row],[Harga Jual Krt GT (- PPN)]]*1.11 -> 228521.25 | AT21: 0 | AU21: =(Table43[[#This Row],[Harga Jual Pcs MT (-PPN)]]*Table43[[#This Row],[ISI/CTN]]) -> 0 | AV21: =Table43[[#This Row],[Harga Jual Pcs MT (-PPN)]]*1.11 -> 0 | AW21: =Table43[[#This Row],[Harga Jual Pcs MT (+PPN)]]*Table43[[#This Row],[ISI/CTN]] -> 0 | AY21: 45553 | AZ21: 45553 | BA21: =IF(TODAY()-Table43[[#This Row],[Efektif Pembuatan]]>60,"Lama","Baru") -> Lama | BB21: =IF(TODAY()-Table43[[#This Row],[Efektif Naik Harga]]<30,"Naik","Sama") -> Sama | BC21: Aktif | BD21: =IF(Table43[[#This Row],[Kode BARANG Win2]]<>"","IDR","") -> IDR | BE21: =CONCATENATE(Table43[[#This Row],[kode 1 Digit (Nomor)]],Table43[[#This Row],[kode 4 Digit (Nomor)]]) -> 10300 | BF21: =Table43[[#This Row],[Nama Gramasi atau Jumlah Pack per CTN]] -> 600 GR | BG21: S-HNZ | BH21: 48HEINZ | BI21: =IF(Table43[[#This Row],[SATUAN Fix Win]]<>"","KRT") -> KRT | BJ21: =IF(Table43[[#This Row],[SATUAN Fix Win]]<>"","GD01") -> GD01 | BK21: =IF(Table43[[#This Row],[SATUAN Fix Win]]<>"",11611) -> 11611 | BL21: =IF(Table43[[#This Row],[SATUAN Fix Win]]<>"",11612) -> 11612 | BM21: 0123 | BN21: =IF(Table43[[#This Row],[SATUAN Fix Win]]<>"",1) -> 1 | BO21: PT. HEINZ ABC INDONESIA | BP21: =IFERROR(VLOOKUP(Table43[[#This Row],[Kode Pcpl]],'[1]HEINZ ABC'!$A$4:$E$112,8,0),0) -> 0 | BQ21: =Table43[[#This Row],[Harga Jual Pcs GT (-PPN)]]-Table43[[#This Row],[HARGA NAIK GT]] -> 17156.25 | BR21: =IF(Table43[[#This Row],[HARGA NAIK GT]]=0,Table43[[#This Row],[Harga Jual Pcs GT (-PPN)]],Table43[[#This Row],[HARGA NAIK GT]]) -> 17156.25 | BS21: =IFERROR(VLOOKUP(Table43[[#This Row],[Kode Pcpl]],'[1]HEINZ ABC'!$A$4:$E$112,8,0),0) -> 0 | BT21: =Table43[[#This Row],[Harga Jual Pcs GT (-PPN)]]-BS21 -> 17156.25 | BU21: =IF(BS21=0,Table43[[#This Row],[Harga Jual Pcs MT (-PPN)]]) -> 0 | BV21: =IFERROR(VLOOKUP(Table43[[#This Row],[Kode Pcpl]],[2]Pricelist!$A$4:$K$112,11,0),0) -> 0 | BW21: =IFERROR(VLOOKUP(Table43[[#This Row],[Kode BARANG Win2]],[3]!RECKITT211216[[KDBRG]:[HRG_JL_PCS-PPN]],11,0),0) -> 0 | BX21: =BV21/1.11 -> 0
A22: =CONCATENATE(Table43[[#This Row],[Kode BARANG Win2]],Table43[[#This Row],[No. Urut Item Sama]]) -> A10110000300122 | B22: 2 | C22: 282 | D22: 109002 | F22: ABC KCP MNS 600G+BTL 2506 | G22: 12 | H22: 7000003150 | I22: =Table43[[#This Row],[Nama Jenis Kemasan]] -> PCH | J22: =TRIM(CONCATENATE(Table43[[#This Row],[Nama KLP]]," ",Table43[[#This Row],[Nama Sub KLP]])) -> KECAP MANIS | K22: =CONCATENATE(Table43[[#This Row],[kode 2 Digit (hrf+No)]],Table43[[#This Row],[kode 2 Digit (Nomor)]],Table43[[#This Row],[kode 1 Digit (Nomor)]]) -> A1011 | L22: =IF(AG22="",CONCATENATE(Q22,S22,U22,W22,Y22,AA22,AC22,AE22,Table43[[#This Row],[Tanda Kode Revisi]]),CONCATENATE(Q22,S22,U22,W22,Y22,AA22,AC22,AG22)) -> A1011000030012 | M22: =LEN(L22) -> 14 | N22: =IF(AF22<>"",TRIM(UPPER(CONCATENATE(P22," ",R22," ",T22," ",V22," ",X22," ",Z22," ","X"," ",Table43[[#This Row],[ISI/CTN]]," ",AF22," ",AB22," ",AD22," ",AH22))),TRIM(UPPER(CONCATENATE(P22," ",R22," ",T22," ",V22," ",X22," ",Z22," ","X"," ",Table43[[#This Row],[ISI/CTN]]," ",AB22," ",AD22," ",AH22)))) -> ABC KECAP MANIS 600 GR X 12 PCH BANDED | O22: =LEN(N22) -> 38 | P22: ABC | Q22: A1 | R22: KECAP | S22: 01 | T22: MANIS | U22: 1 | W22: 0 | Y22: 00 | Z22: 600 GR | AA22: 0300 | AB22: PCH | AC22: 1 | AD22: BANDED | AE22: 2 | AI22: GRAM | AJ22: 1 | AL22: =Table43[[#This Row],[Harga Jual Pcs GT (-PPN)]]-(Table43[[#This Row],[Harga Jual Pcs GT (-PPN)]]*6%) -> 16126.875 | AM22: =Table43[[#This Row],[Harga Beli Pcs (-PPN)]]*Table43[[#This Row],[ISI/CTN]] -> 193522.5 | AN22: =Table43[[#This Row],[Harga Beli Pcs (-PPN)]]*1.11 -> 17900.831 | AO22: =Table43[[#This Row],[Harga Beli Krt (- PPN)]]*1.11 -> 214809.98 | AP22: 17156.25 | AQ22: =Table43[[#This Row],[Harga Jual Pcs GT (-PPN)]]*Table43[[#This Row],[ISI/CTN]] -> 205875 | AR22: =Table43[[#This Row],[Harga Jual Pcs GT (-PPN)]]*1.11 -> 19043.438 | AS22: =Table43[[#This Row],[Harga Jual Krt GT (- PPN)]]*1.11 -> 228521.25 | AT22: 18528.75 | AU22: =(Table43[[#This Row],[Harga Jual Pcs MT (-PPN)]]*Table43[[#This Row],[ISI/CTN]]) -> 222345 | AV22: =Table43[[#This Row],[Harga Jual Pcs MT (-PPN)]]*1.11 -> 20566.913 | AW22: =Table43[[#This Row],[Harga Jual Pcs MT (+PPN)]]*Table43[[#This Row],[ISI/CTN]] -> 246802.95 | AY22: 46027 | AZ22: 46027 | BA22: =IF(TODAY()-Table43[[#This Row],[Efektif Pembuatan]]>60,"Lama","Baru") -> Lama | BB22: =IF(TODAY()-Table43[[#This Row],[Efektif Naik Harga]]<30,"Naik","Sama") -> Sama | BC22: Aktif | BD22: =IF(Table43[[#This Row],[Kode BARANG Win2]]<>"","IDR","") -> IDR | BE22: =CONCATENATE(Table43[[#This Row],[kode 1 Digit (Nomor)]],Table43[[#This Row],[kode 4 Digit (Nomor)]]) -> 10300 | BF22: =Table43[[#This Row],[Nama Gramasi atau Jumlah Pack per CTN]] -> 600 GR | BG22: S-HNZ | BH22: 48HEINZ | BI22: =IF(Table43[[#This Row],[SATUAN Fix Win]]<>"","KRT") -> KRT | BJ22: =IF(Table43[[#This Row],[SATUAN Fix Win]]<>"","GD01") -> GD01 | BK22: =IF(Table43[[#This Row],[SATUAN Fix Win]]<>"",11611) -> 11611 | BL22: =IF(Table43[[#This Row],[SATUAN Fix Win]]<>"",11612) -> 11612 | BM22: 0123 | BN22: =IF(Table43[[#This Row],[SATUAN Fix Win]]<>"",1) -> 1 | BO22: PT. HEINZ ABC INDONESIA | BP22: =IFERROR(VLOOKUP(Table43[[#This Row],[Kode Pcpl]],'[1]HEINZ ABC'!$A$4:$E$112,8,0),0) -> 0 | BQ22: =Table43[[#This Row],[Harga Jual Pcs GT (-PPN)]]-Table43[[#This Row],[HARGA NAIK GT]] -> 17156.25 | BR22: =IF(Table43[[#This Row],[HARGA NAIK GT]]=0,Table43[[#This Row],[Harga Jual Pcs GT (-PPN)]],Table43[[#This Row],[HARGA NAIK GT]]) -> 17156.25
A23: =CONCATENATE(Table43[[#This Row],[Kode BARANG Win2]],Table43[[#This Row],[No. Urut Item Sama]]) -> A10110000300123 | B23: 3 | D23: 109001 | F23: ABC KMNS 600G+S. TIRAM 18G 250G | G23: 12 | H23: 7000003149 | I23: =Table43[[#This Row],[Nama Jenis Kemasan]] -> PCH | J23: =TRIM(CONCATENATE(Table43[[#This Row],[Nama KLP]]," ",Table43[[#This Row],[Nama Sub KLP]])) -> KECAP MANIS | K23: =CONCATENATE(Table43[[#This Row],[kode 2 Digit (hrf+No)]],Table43[[#This Row],[kode 2 Digit (Nomor)]],Table43[[#This Row],[kode 1 Digit (Nomor)]]) -> A1011 | L23: =IF(AG23="",CONCATENATE(Q23,S23,U23,W23,Y23,AA23,AC23,AE23,Table43[[#This Row],[Tanda Kode Revisi]]),CONCATENATE(Q23,S23,U23,W23,Y23,AA23,AC23,AG23)) -> A1011000030012 | M23: =LEN(L23) -> 14 | N23: =IF(AF23<>"",TRIM(UPPER(CONCATENATE(P23," ",R23," ",T23," ",V23," ",X23," ",Z23," ","X"," ",Table43[[#This Row],[ISI/CTN]]," ",AF23," ",AB23," ",AD23," ",AH23))),TRIM(UPPER(CONCATENATE(P23," ",R23," ",T23," ",V23," ",X23," ",Z23," ","X"," ",Table43[[#This Row],[ISI/CTN]]," ",AB23," ",AD23," ",AH23)))) -> ABC KECAP MANIS 600 GR X 12 PCH BANDED | O23: =LEN(N23) -> 38 | P23: ABC | Q23: A1 | R23: KECAP | S23: 01 | T23: MANIS | U23: 1 | W23: 0 | Y23: 00 | Z23: 600 GR | AA23: 0300 | AB23: PCH | AC23: 1 | AD23: BANDED | AE23: 2 | AL23: =Table43[[#This Row],[Harga Jual Pcs GT (-PPN)]]-(Table43[[#This Row],[Harga Jual Pcs GT (-PPN)]]*6%) -> 16126.875 | AM23: =Table43[[#This Row],[Harga Beli Pcs (-PPN)]]*Table43[[#This Row],[ISI/CTN]] -> 193522.5 | AN23: =Table43[[#This Row],[Harga Beli Pcs (-PPN)]]*1.11 -> 17900.831 | AO23: =Table43[[#This Row],[Harga Beli Krt (- PPN)]]*1.11 -> 214809.98 | AP23: 17156.25 | AQ23: =Table43[[#This Row],[Harga Jual Pcs GT (-PPN)]]*Table43[[#This Row],[ISI/CTN]] -> 205875 | AR23: =Table43[[#This Row],[Harga Jual Pcs GT (-PPN)]]*1.11 -> 19043.438 | AS23: =Table43[[#This Row],[Harga Jual Krt GT (- PPN)]]*1.11 -> 228521.25 | AT23: 18528.75 | AU23: =(Table43[[#This Row],[Harga Jual Pcs MT (-PPN)]]*Table43[[#This Row],[ISI/CTN]]) -> 222345 | AV23: =Table43[[#This Row],[Harga Jual Pcs MT (-PPN)]]*1.11 -> 20566.913 | AW23: =Table43[[#This Row],[Harga Jual Pcs MT (+PPN)]]*Table43[[#This Row],[ISI/CTN]] -> 246802.95 | BA23: =IF(TODAY()-Table43[[#This Row],[Efektif Pembuatan]]>60,"Lama","Baru") -> Lama | BB23: =IF(TODAY()-Table43[[#This Row],[Efektif Naik Harga]]<30,"Naik","Sama") -> Sama | BC23: Aktif | BD23: =IF(Table43[[#This Row],[Kode BARANG Win2]]<>"","IDR","") -> IDR | BE23: =CONCATENATE(Table43[[#This Row],[kode 1 Digit (Nomor)]],Table43[[#This Row],[kode 4 Digit (Nomor)]]) -> 0300 | BF23: =Table43[[#This Row],[Nama Gramasi atau Jumlah Pack per CTN]] -> 600 GR | BI23: =IF(Table43[[#This Row],[SATUAN Fix Win]]<>"","KRT") -> KRT | BJ23: =IF(Table43[[#This Row],[SATUAN Fix Win]]<>"","GD01") -> GD01 | BK23: =IF(Table43[[#This Row],[SATUAN Fix Win]]<>"",11611) -> 11611 | BL23: =IF(Table43[[#This Row],[SATUAN Fix Win]]<>"",11612) -> 11612 | BN23: =IF(Table43[[#This Row],[SATUAN Fix Win]]<>"",1) -> 1 | BP23: =IFERROR(VLOOKUP(Table43[[#This Row],[Kode Pcpl]],'[1]HEINZ ABC'!$A$4:$E$112,8,0),0) -> 0 | BQ23: =Table43[[#This Row],[Harga Jual Pcs GT (-PPN)]]-Table43[[#This Row],[HARGA NAIK GT]] -> 17156.25 | BR23: =IF(Table43[[#This Row],[HARGA NAIK GT]]=0,Table43[[#This Row],[Harga Jual Pcs GT (-PPN)]],Table43[[#This Row],[HARGA NAIK GT]]) -> 17156.25
A24: =CONCATENATE(Table43[[#This Row],[Kode BARANG Win2]],Table43[[#This Row],[No. Urut Item Sama]]) -> A10110000450101 | B24: 1 | C24: 283 | D24: 100241 | F24: ABC KCP MNS PCH 12 X 450G 2405 | G24: 12 | H24: 7000003117 | I24: =Table43[[#This Row],[Nama Jenis Kemasan]] -> PCH | J24: =TRIM(CONCATENATE(Table43[[#This Row],[Nama KLP]]," ",Table43[[#This Row],[Nama Sub KLP]])) -> KECAP MANIS | K24: =CONCATENATE(Table43[[#This Row],[kode 2 Digit (hrf+No)]],Table43[[#This Row],[kode 2 Digit (Nomor)]],Table43[[#This Row],[kode 1 Digit (Nomor)]]) -> A1011 | L24: =IF(AG24="",CONCATENATE(Q24,S24,U24,W24,Y24,AA24,AC24,AE24,Table43[[#This Row],[Tanda Kode Revisi]]),CONCATENATE(Q24,S24,U24,W24,Y24,AA24,AC24,AG24)) -> A1011000045010 | M24: =LEN(L24) -> 14 | N24: =IF(AF24<>"",TRIM(UPPER(CONCATENATE(P24," ",R24," ",T24," ",V24," ",X24," ",Z24," ","X"," ",Table43[[#This Row],[ISI/CTN]]," ",AF24," ",AB24," ",AD24," ",AH24))),TRIM(UPPER(CONCATENATE(P24," ",R24," ",T24," ",V24," ",X24," ",Z24," ","X"," ",Table43[[#This Row],[ISI/CTN]]," ",AB24," ",AD24," ",AH24)))) -> ABC KECAP MANIS 450 GR X 12 PCH | O24: =LEN(N24) -> 31 | P24: ABC | Q24: A1 | R24: KECAP | S24: 01 | T24: MANIS | U24: 1 | W24: 0 | Y24: 00 | Z24: 450 GR | AA24: 0450 | AB24: PCH | AC24: 1 | AE24: 0 | AI24: GRAM | AJ24: 1 | AL24: =Table43[[#This Row],[Harga Jual Pcs GT (-PPN)]]-(Table43[[#This Row],[Harga Jual Pcs GT (-PPN)]]*6%) -> 10467.05 | AM24: =Table43[[#This Row],[Harga Beli Pcs (-PPN)]]*Table43[[#This Row],[ISI/CTN]] -> 125604.6 | AN24: =Table43[[#This Row],[Harga Beli Pcs (-PPN)]]*1.11 -> 11618.426 | AO24: =Table43[[#This Row],[Harga Beli Krt (- PPN)]]*1.11 -> 139421.11 | AP24: 11135.16 | AQ24: =Table43[[#This Row],[Harga Jual Pcs GT (-PPN)]]*Table43[[#This Row],[ISI/CTN]] -> 133621.92 | AR24: =Table43[[#This Row],[Harga Jual Pcs GT (-PPN)]]*1.11 -> 12360.028 | AS24: =Table43[[#This Row],[Harga Jual Krt GT (- PPN)]]*1.11 -> 148320.33 | AT24: 12025.97 | AU24: =(Table43[[#This Row],[Harga Jual Pcs MT (-PPN)]]*Table43[[#This Row],[ISI/CTN]]) -> 144311.64 | AV24: =Table43[[#This Row],[Harga Jual Pcs MT (-PPN)]]*1.11 -> 13348.827 | AW24: =Table43[[#This Row],[Harga Jual Pcs MT (+PPN)]]*Table43[[#This Row],[ISI/CTN]] -> 160185.92 | BA24: =IF(TODAY()-Table43[[#This Row],[Efektif Pembuatan]]>60,"Lama","Baru") -> Lama | BB24: =IF(TODAY()-Table43[[#This Row],[Efektif Naik Harga]]<30,"Naik","Sama") -> Sama | BD24: =IF(Table43[[#This Row],[Kode BARANG Win2]]<>"","IDR","") -> IDR | BE24: =CONCATENATE(Table43[[#This Row],[kode 1 Digit (Nomor)]],Table43[[#This Row],[kode 4 Digit (Nomor)]]) -> 10450 | BF24: =Table43[[#This Row],[Nama Gramasi atau Jumlah Pack per CTN]] -> 450 GR | BI24: =IF(Table43[[#This Row],[SATUAN Fix Win]]<>"","KRT") -> KRT | BJ24: =IF(Table43[[#This Row],[SATUAN Fix Win]]<>"","GD01") -> GD01 | BK24: =IF(Table43[[#This Row],[SATUAN Fix Win]]<>"",11611) -> 11611 | BL24: =IF(Table43[[#This Row],[SATUAN Fix Win]]<>"",11612) -> 11612 | BN24: =IF(Table43[[#This Row],[SATUAN Fix Win]]<>"",1) -> 1 | BP24: =IFERROR(VLOOKUP(Table43[[#This Row],[Kode Pcpl]],'[1]HEINZ ABC'!$A$4:$E$112,8,0),0) -> 0 | BQ24: =Table43[[#This Row],[Harga Jual Pcs GT (-PPN)]]-Table43[[#This Row],[HARGA NAIK GT]] -> 11135.16 | BR24: =IF(Table43[[#This Row],[HARGA NAIK GT]]=0,Table43[[#This Row],[Harga Jual Pcs GT (-PPN)]],Table43[[#This Row],[HARGA NAIK GT]]) -> 11135.16 | BS24: =IFERROR(VLOOKUP(Table43[[#This Row],[Kode Pcpl]],'[1]HEINZ ABC'!$A$4:$E$112,8,0),0) -> 0 | BT24: =Table43[[#This Row],[Harga Jual Pcs GT (-PPN)]]-BS24 -> 11135.16 | BU24: =IF(BS24=0,Table43[[#This Row],[Harga Jual Pcs MT (-PPN)]]) -> 12025.97 | BV24: =IFERROR(VLOOKUP(Table43[[#This Row],[Kode Pcpl]],[2]Pricelist!$A$4:$K$112,11,0),0) -> 0 | BW24: =IFERROR(VLOOKUP(Table43[[#This Row],[Kode BARANG Win2]],[3]!RECKITT211216[[KDBRG]:[HRG_JL_PCS-PPN]],11,0),0) -> 0 | BX24: =BV24/1.11 -> 0
A25: =CONCATENATE(Table43[[#This Row],[Kode BARANG Win2]],Table43[[#This Row],[No. Urut Item Sama]]) -> A10110000600101 | B25: 1 | C25: 16 | D25: 100225 | E25: RASA MANTAP SOY | F25: ABC KCP MNS PCH 12X600G 2311 | G25: 12 | H25: 7000003104 | I25: =Table43[[#This Row],[Nama Jenis Kemasan]] -> PCH | J25: =TRIM(CONCATENATE(Table43[[#This Row],[Nama KLP]]," ",Table43[[#This Row],[Nama Sub KLP]])) -> KECAP MANIS | K25: =CONCATENATE(Table43[[#This Row],[kode 2 Digit (hrf+No)]],Table43[[#This Row],[kode 2 Digit (Nomor)]],Table43[[#This Row],[kode 1 Digit (Nomor)]]) -> A1011 | L25: =IF(AG25="",CONCATENATE(Q25,S25,U25,W25,Y25,AA25,AC25,AE25,Table43[[#This Row],[Tanda Kode Revisi]]),CONCATENATE(Q25,S25,U25,W25,Y25,AA25,AC25,AG25)) -> A1011000060010 | M25: =LEN(L25) -> 14 | N25: =IF(AF25<>"",TRIM(UPPER(CONCATENATE(P25," ",R25," ",T25," ",V25," ",X25," ",Z25," ","X"," ",Table43[[#This Row],[ISI/CTN]]," ",AF25," ",AB25," ",AD25," ",AH25))),TRIM(UPPER(CONCATENATE(P25," ",R25," ",T25," ",V25," ",X25," ",Z25," ","X"," ",Table43[[#This Row],[ISI/CTN]]," ",AB25," ",AD25," ",AH25)))) -> ABC KECAP MANIS 600 GR X 12 PCH | O25: =LEN(N25) -> 31 | P25: ABC | Q25: A1 | R25: KECAP | S25: 01 | T25: MANIS | U25: 1 | W25: 0 | Y25: 00 | Z25: 600 GR | AA25: 0600 | AB25: PCH | AC25: 1 | AE25: 0 | AI25: GRAM | AJ25: 1 | AL25: =Table43[[#This Row],[Harga Jual Pcs GT (-PPN)]]-(Table43[[#This Row],[Harga Jual Pcs GT (-PPN)]]*6%) -> 16126.922 | AM25: =Table43[[#This Row],[Harga Beli Pcs (-PPN)]]*Table43[[#This Row],[ISI/CTN]] -> 193523.06 | AN25: =Table43[[#This Row],[Harga Beli Pcs (-PPN)]]*1.11 -> 17900.883 | AO25: =Table43[[#This Row],[Harga Beli Krt (- PPN)]]*1.11 -> 214810.6 | AP25: 17156.3 | AQ25: =Table43[[#This Row],[Harga Jual Pcs GT (-PPN)]]*Table43[[#This Row],[ISI/CTN]] -> 205875.6 | AR25: =Table43[[#This Row],[Harga Jual Pcs GT (-PPN)]]*1.11 -> 19043.493 | AS25: =Table43[[#This Row],[Harga Jual Krt GT (- PPN)]]*1.11 -> 228521.92 | AT25: 18528.804 | AU25: =(Table43[[#This Row],[Harga Jual Pcs MT (-PPN)]]*Table43[[#This Row],[ISI/CTN]]) -> 222345.65 | AV25: =Table43[[#This Row],[Harga Jual Pcs MT (-PPN)]]*1.11 -> 20566.972 | AW25: =Table43[[#This Row],[Harga Jual Pcs MT (+PPN)]]*Table43[[#This Row],[ISI/CTN]] -> 246803.67 | AY25: 45553 | AZ25: 45553 | BA25: =IF(TODAY()-Table43[[#This Row],[Efektif Pembuatan]]>60,"Lama","Baru") -> Lama | BB25: =IF(TODAY()-Table43[[#This Row],[Efektif Naik Harga]]<30,"Naik","Sama") -> Sama | BC25: Aktif | BD25: =IF(Table43[[#This Row],[Kode BARANG Win2]]<>"","IDR","") -> IDR | BE25: =CONCATENATE(Table43[[#This Row],[kode 1 Digit (Nomor)]],Table43[[#This Row],[kode 4 Digit (Nomor)]]) -> 10600 | BF25: =Table43[[#This Row],[Nama Gramasi atau Jumlah Pack per CTN]] -> 600 GR | BG25: S-HNZ | BH25: 48HEINZ | BI25: =IF(Table43[[#This Row],[SATUAN Fix Win]]<>"","KRT") -> KRT | BJ25: =IF(Table43[[#This Row],[SATUAN Fix Win]]<>"","GD01") -> GD01 | BK25: =IF(Table43[[#This Row],[SATUAN Fix Win]]<>"",11611) -> 11611 | BL25: =IF(Table43[[#This Row],[SATUAN Fix Win]]<>"",11612) -> 11612 | BM25: 0123 | BN25: =IF(Table43[[#This Row],[SATUAN Fix Win]]<>"",1) -> 1 | BO25: PT. HEINZ ABC INDONESIA | BP25: =IFERROR(VLOOKUP(Table43[[#This Row],[Kode Pcpl]],'[1]HEINZ ABC'!$A$4:$E$112,8,0),0) -> 0 | BQ25: =Table43[[#This Row],[Harga Jual Pcs GT (-PPN)]]-Table43[[#This Row],[HARGA NAIK GT]] -> 17156.3 | BR25: =IF(Table43[[#This Row],[HARGA NAIK GT]]=0,Table43[[#This Row],[Harga Jual Pcs GT (-PPN)]],Table43[[#This Row],[HARGA NAIK GT]]) -> 17156.3
A26: =CONCATENATE(Table43[[#This Row],[Kode BARANG Win2]],Table43[[#This Row],[No. Urut Item Sama]]) -> A10110000600102 | B26: 2 | C26: 17 | D26: 100242 | E26: RASA MANTAP SOY | F26: ABC KCP MNS PCH 12X600G | G26: 12 | H26: 7000003118 | I26: =Table43[[#This Row],[Nama Jenis Kemasan]] -> PCH | J26: =TRIM(CONCATENATE(Table43[[#This Row],[Nama KLP]]," ",Table43[[#This Row],[Nama Sub KLP]])) -> KECAP MANIS | K26: =CONCATENATE(Table43[[#This Row],[kode 2 Digit (hrf+No)]],Table43[[#This Row],[kode 2 Digit (Nomor)]],Table43[[#This Row],[kode 1 Digit (Nomor)]]) -> A1011 | L26: =IF(AG26="",CONCATENATE(Q26,S26,U26,W26,Y26,AA26,AC26,AE26,Table43[[#This Row],[Tanda Kode Revisi]]),CONCATENATE(Q26,S26,U26,W26,Y26,AA26,AC26,AG26)) -> A1011000060010 | M26: =LEN(L26) -> 14 | N26: =IF(AF26<>"",TRIM(UPPER(CONCATENATE(P26," ",R26," ",T26," ",V26," ",X26," ",Z26," ","X"," ",Table43[[#This Row],[ISI/CTN]]," ",AF26," ",AB26," ",AD26," ",AH26))),TRIM(UPPER(CONCATENATE(P26," ",R26," ",T26," ",V26," ",X26," ",Z26," ","X"," ",Table43[[#This Row],[ISI/CTN]]," ",AB26," ",AD26," ",AH26)))) -> ABC KECAP MANIS 600 GR X 12 PCH | O26: =LEN(N26) -> 31 | P26: ABC | Q26: A1 | R26: KECAP | S26: 01 | T26: MANIS | U26: 1 | W26: 0 | Y26: 00 | Z26: 600 GR | AA26: 0600 | AB26: PCH | AC26: 1 | AE26: 0 | AI26: GRAM | AJ26: 1 | AL26: =Table43[[#This Row],[Harga Jual Pcs GT (-PPN)]]-(Table43[[#This Row],[Harga Jual Pcs GT (-PPN)]]*6%) -> 16126.922 | AM26: =Table43[[#This Row],[Harga Beli Pcs (-PPN)]]*Table43[[#This Row],[ISI/CTN]] -> 193523.06 | AN26: =Table43[[#This Row],[Harga Beli Pcs (-PPN)]]*1.11 -> 17900.883 | AO26: =Table43[[#This Row],[Harga Beli Krt (- PPN)]]*1.11 -> 214810.6 | AP26: 17156.3 | AQ26: =Table43[[#This Row],[Harga Jual Pcs GT (-PPN)]]*Table43[[#This Row],[ISI/CTN]] -> 205875.6 | AR26: =Table43[[#This Row],[Harga Jual Pcs GT (-PPN)]]*1.11 -> 19043.493 | AS26: =Table43[[#This Row],[Harga Jual Krt GT (- PPN)]]*1.11 -> 228521.92 | AT26: 18528.804 | AU26: =(Table43[[#This Row],[Harga Jual Pcs MT (-PPN)]]*Table43[[#This Row],[ISI/CTN]]) -> 222345.65 | AV26: =Table43[[#This Row],[Harga Jual Pcs MT (-PPN)]]*1.11 -> 20566.972 | AW26: =Table43[[#This Row],[Harga Jual Pcs MT (+PPN)]]*Table43[[#This Row],[ISI/CTN]] -> 246803.67 | AY26: 45589 | AZ26: 45553 | BA26: =IF(TODAY()-Table43[[#This Row],[Efektif Pembuatan]]>60,"Lama","Baru") -> Lama | BB26: =IF(TODAY()-Table43[[#This Row],[Efektif Naik Harga]]<30,"Naik","Sama") -> Sama | BC26: Aktif | BD26: =IF(Table43[[#This Row],[Kode BARANG Win2]]<>"","IDR","") -> IDR | BE26: =CONCATENATE(Table43[[#This Row],[kode 1 Digit (Nomor)]],Table43[[#This Row],[kode 4 Digit (Nomor)]]) -> 10600 | BF26: =Table43[[#This Row],[Nama Gramasi atau Jumlah Pack per CTN]] -> 600 GR | BG26: S-HNZ | BH26: 48HEINZ | BI26: =IF(Table43[[#This Row],[SATUAN Fix Win]]<>"","KRT") -> KRT | BJ26: =IF(Table43[[#This Row],[SATUAN Fix Win]]<>"","GD01") -> GD01 | BK26: =IF(Table43[[#This Row],[SATUAN Fix Win]]<>"",11611) -> 11611 | BL26: =IF(Table43[[#This Row],[SATUAN Fix Win]]<>"",11612) -> 11612 | BM26: 0123 | BN26: =IF(Table43[[#This Row],[SATUAN Fix Win]]<>"",1) -> 1 | BO26: PT. HEINZ ABC INDONESIA | BP26: =IFERROR(VLOOKUP(Table43[[#This Row],[Kode Pcpl]],'[1]HEINZ ABC'!$A$4:$E$112,8,0),0) -> 0 | BQ26: =Table43[[#This Row],[Harga Jual Pcs GT (-PPN)]]-Table43[[#This Row],[HARGA NAIK GT]] -> 17156.3 | BR26: =IF(Table43[[#This Row],[HARGA NAIK GT]]=0,Table43[[#This Row],[Harga Jual Pcs GT (-PPN)]],Table43[[#This Row],[HARGA NAIK GT]]) -> 17156.3 | BS26: =IFERROR(VLOOKUP(Table43[[#This Row],[Kode Pcpl]],'[1]HEINZ ABC'!$A$4:$E$112,8,0),0) -> 0 | BT26: =Table43[[#This Row],[Harga Jual Pcs GT (-PPN)]]-BS26 -> 17156.3 | BU26: =IF(BS26=0,Table43[[#This Row],[Harga Jual Pcs MT (-PPN)]]) -> 18528.804 | BV26: =IFERROR(VLOOKUP(Table43[[#This Row],[Kode Pcpl]],[2]Pricelist!$A$4:$K$112,11,0),0) -> 0 | BW26: =IFERROR(VLOOKUP(Table43[[#This Row],[Kode BARANG Win2]],[3]!RECKITT211216[[KDBRG]:[HRG_JL_PCS-PPN]],11,0),0) -> 0 | BX26: =BV26/1.11 -> 0
A27: =CONCATENATE(Table43[[#This Row],[Kode BARANG Win2]],Table43[[#This Row],[No. Urut Item Sama]]) -> A10110000600201 | B27: 1 | C27: 18 | D27: 100163 | E27: RASA MANTAP SOY | F27: ABC KCPMNS PET SB 12X600ML1607 | G27: 12 | H27: 0 | I27: =Table43[[#This Row],[Nama Jenis Kemasan]] -> BTL | J27: =TRIM(CONCATENATE(Table43[[#This Row],[Nama KLP]]," ",Table43[[#This Row],[Nama Sub KLP]])) -> KECAP MANIS | K27: =CONCATENATE(Table43[[#This Row],[kode 2 Digit (hrf+No)]],Table43[[#This Row],[kode 2 Digit (Nomor)]],Table43[[#This Row],[kode 1 Digit (Nomor)]]) -> A1011 | L27: =IF(AG27="",CONCATENATE(Q27,S27,U27,W27,Y27,AA27,AC27,AE27,Table43[[#This Row],[Tanda Kode Revisi]]),CONCATENATE(Q27,S27,U27,W27,Y27,AA27,AC27,AG27)) -> A1011000060020 | M27: =LEN(L27) -> 14 | N27: =IF(AF27<>"",TRIM(UPPER(CONCATENATE(P27," ",R27," ",T27," ",V27," ",X27," ",Z27," ","X"," ",Table43[[#This Row],[ISI/CTN]]," ",AF27," ",AB27," ",AD27," ",AH27))),TRIM(UPPER(CONCATENATE(P27," ",R27," ",T27," ",V27," ",X27," ",Z27," ","X"," ",Table43[[#This Row],[ISI/CTN]]," ",AB27," ",AD27," ",AH27)))) -> ABC KECAP MANIS 600 ML X 12 BTL | O27: =LEN(N27) -> 31 | P27: ABC | Q27: A1 | R27: KECAP | S27: 01 | T27: MANIS | U27: 1 | W27: 0 | Y27: 00 | Z27: 600 ML | AA27: 0600 | AB27: BTL | AC27: 2 | AE27: 0 | AI27: LITER | AJ27: 2 | AL27: =Table43[[#This Row],[Harga Jual Pcs GT (-PPN)]]-(Table43[[#This Row],[Harga Jual Pcs GT (-PPN)]]*6%) -> 23525.408 | AM27: =Table43[[#This Row],[Harga Beli Pcs (-PPN)]]*Table43[[#This Row],[ISI/CTN]] -> 282304.9 | AN27: =Table43[[#This Row],[Harga Beli Pcs (-PPN)]]*1.11 -> 26113.203 | AO27: =Table43[[#This Row],[Harga Beli Krt (- PPN)]]*1.11 -> 313358.44 | AP27: 25027.03 | AQ27: =Table43[[#This Row],[Harga Jual Pcs GT (-PPN)]]*Table43[[#This Row],[ISI/CTN]] -> 300324.36 | AR27: =Table43[[#This Row],[Harga Jual Pcs GT (-PPN)]]*1.11 -> 27780.003 | AS27: =Table43[[#This Row],[Harga Jual Krt GT (- PPN)]]*1.11 -> 333360.04 | AT27: 27029.19 | AU27: =(Table43[[#This Row],[Harga Jual Pcs MT (-PPN)]]*Table43[[#This Row],[ISI/CTN]]) -> 324350.28 | AV27: =Table43[[#This Row],[Harga Jual Pcs MT (-PPN)]]*1.11 -> 30002.401 | AW27: =Table43[[#This Row],[Harga Jual Pcs MT (+PPN)]]*Table43[[#This Row],[ISI/CTN]] -> 360028.81 | AY27: 45553 | AZ27: 45553 | BA27: =IF(TODAY()-Table43[[#This Row],[Efektif Pembuatan]]>60,"Lama","Baru") -> Lama | BB27: =IF(TODAY()-Table43[[#This Row],[Efektif Naik Harga]]<30,"Naik","Sama") -> Sama | BC27: Aktif | BD27: =IF(Table43[[#This Row],[Kode BARANG Win2]]<>"","IDR","") -> IDR | BE27: =CONCATENATE(Table43[[#This Row],[kode 1 Digit (Nomor)]],Table43[[#This Row],[kode 4 Digit (Nomor)]]) -> 20600 | BF27: =Table43[[#This Row],[Nama Gramasi atau Jumlah Pack per CTN]] -> 600 ML | BG27: S-HNZ | BH27: 48HEINZ | BI27: =IF(Table43[[#This Row],[SATUAN Fix Win]]<>"","KRT") -> KRT | BJ27: =IF(Table43[[#This Row],[SATUAN Fix Win]]<>"","GD01") -> GD01 | BK27: =IF(Table43[[#This Row],[SATUAN Fix Win]]<>"",11611) -> 11611 | BL27: =IF(Table43[[#This Row],[SATUAN Fix Win]]<>"",11612) -> 11612 | BM27: 0123 | BN27: =IF(Table43[[#This Row],[SATUAN Fix Win]]<>"",1) -> 1 | BO27: PT. HEINZ ABC INDONESIA | BP27: =IFERROR(VLOOKUP(Table43[[#This Row],[Kode Pcpl]],'[1]HEINZ ABC'!$A$4:$E$112,8,0),0) -> 0 | BQ27: =Table43[[#This Row],[Harga Jual Pcs GT (-PPN)]]-Table43[[#This Row],[HARGA NAIK GT]] -> 25027.03 | BR27: =IF(Table43[[#This Row],[HARGA NAIK GT]]=0,Table43[[#This Row],[Harga Jual Pcs GT (-PPN)]],Table43[[#This Row],[HARGA NAIK GT]]) -> 25027.03 | BS27: =IFERROR(VLOOKUP(Table43[[#This Row],[Kode Pcpl]],'[1]HEINZ ABC'!$A$4:$E$112,8,0),0) -> 0 | BT27: =Table43[[#This Row],[Harga Jual Pcs GT (-PPN)]]-BS27 -> 25027.03 | BU27: =IF(BS27=0,Table43[[#This Row],[Harga Jual Pcs MT (-PPN)]]) -> 27029.19 | BV27: =IFERROR(VLOOKUP(Table43[[#This Row],[Kode Pcpl]],[2]Pricelist!$A$4:$K$112,11,0),0) -> 0 | BW27: =IFERROR(VLOOKUP(Table43[[#This Row],[Kode BARANG Win2]],[3]!RECKITT211216[[KDBRG]:[HRG_JL_PCS-PPN]],11,0),0) -> 0 | BX27: =BV27/1.11 -> 0
A28: =CONCATENATE(Table43[[#This Row],[Kode BARANG Win2]],Table43[[#This Row],[No. Urut Item Sama]]) -> A10110000600202 | B28: 2 | C28: 19 | D28: 100226 | E28: RASA MANTAP SOY | F28: ABC KCPMNS PET SB 12X600ML | G28: 12 | H28: 7000003105 | I28: =Table43[[#This Row],[Nama Jenis Kemasan]] -> BTL | J28: =TRIM(CONCATENATE(Table43[[#This Row],[Nama KLP]]," ",Table43[[#This Row],[Nama Sub KLP]])) -> KECAP MANIS | K28: =CONCATENATE(Table43[[#This Row],[kode 2 Digit (hrf+No)]],Table43[[#This Row],[kode 2 Digit (Nomor)]],Table43[[#This Row],[kode 1 Digit (Nomor)]]) -> A1011 | L28: =IF(AG28="",CONCATENATE(Q28,S28,U28,W28,Y28,AA28,AC28,AE28,Table43[[#This Row],[Tanda Kode Revisi]]),CONCATENATE(Q28,S28,U28,W28,Y28,AA28,AC28,AG28)) -> A1011000060020 | M28: =LEN(L28) -> 14 | N28: =IF(AF28<>"",TRIM(UPPER(CONCATENATE(P28," ",R28," ",T28," ",V28," ",X28," ",Z28," ","X"," ",Table43[[#This Row],[ISI/CTN]]," ",AF28," ",AB28," ",AD28," ",AH28))),TRIM(UPPER(CONCATENATE(P28," ",R28," ",T28," ",V28," ",X28," ",Z28," ","X"," ",Table43[[#This Row],[ISI/CTN]]," ",AB28," ",AD28," ",AH28)))) -> ABC KECAP MANIS 600 ML X 12 BTL | O28: =LEN(N28) -> 31 | P28: ABC | Q28: A1 | R28: KECAP | S28: 01 | T28: MANIS | U28: 1 | W28: 0 | Y28: 00 | Z28: 600 ML | AA28: 0600 | AB28: BTL | AC28: 2 | AE28: 0 | AI28: LITER | AJ28: 2 | AL28: =Table43[[#This Row],[Harga Jual Pcs GT (-PPN)]]-(Table43[[#This Row],[Harga Jual Pcs GT (-PPN)]]*6%) -> 23525.408 | AM28: =Table43[[#This Row],[Harga Beli Pcs (-PPN)]]*Table43[[#This Row],[ISI/CTN]] -> 282304.9 | AN28: =Table43[[#This Row],[Harga Beli Pcs (-PPN)]]*1.11 -> 26113.203 | AO28: =Table43[[#This Row],[Harga Beli Krt (- PPN)]]*1.11 -> 313358.44 | AP28: 25027.03 | AQ28: =Table43[[#This Row],[Harga Jual Pcs GT (-PPN)]]*Table43[[#This Row],[ISI/CTN]] -> 300324.36 | AR28: =Table43[[#This Row],[Harga Jual Pcs GT (-PPN)]]*1.11 -> 27780.003 | AS28: =Table43[[#This Row],[Harga Jual Krt GT (- PPN)]]*1.11 -> 333360.04 | AT28: 27029.19 | AU28: =(Table43[[#This Row],[Harga Jual Pcs MT (-PPN)]]*Table43[[#This Row],[ISI/CTN]]) -> 324350.28 | AV28: =Table43[[#This Row],[Harga Jual Pcs MT (-PPN)]]*1.11 -> 30002.401 | AW28: =Table43[[#This Row],[Harga Jual Pcs MT (+PPN)]]*Table43[[#This Row],[ISI/CTN]] -> 360028.81 | AY28: 45565 | AZ28: 45553 | BA28: =IF(TODAY()-Table43[[#This Row],[Efektif Pembuatan]]>60,"Lama","Baru") -> Lama | BB28: =IF(TODAY()-Table43[[#This Row],[Efektif Naik Harga]]<30,"Naik","Sama") -> Sama | BC28: Aktif | BD28: =IF(Table43[[#This Row],[Kode BARANG Win2]]<>"","IDR","") -> IDR | BE28: =CONCATENATE(Table43[[#This Row],[kode 1 Digit (Nomor)]],Table43[[#This Row],[kode 4 Digit (Nomor)]]) -> 20600 | BF28: =Table43[[#This Row],[Nama Gramasi atau Jumlah Pack per CTN]] -> 600 ML | BG28: S-HNZ | BH28: 48HEINZ | BI28: =IF(Table43[[#This Row],[SATUAN Fix Win]]<>"","KRT") -> KRT | BJ28: =IF(Table43[[#This Row],[SATUAN Fix Win]]<>"","GD01") -> GD01 | BK28: =IF(Table43[[#This Row],[SATUAN Fix Win]]<>"",11611) -> 11611 | BL28: =IF(Table43[[#This Row],[SATUAN Fix Win]]<>"",11612) -> 11612 | BM28: 0123 | BN28: =IF(Table43[[#This Row],[SATUAN Fix Win]]<>"",1) -> 1 | BO28: PT. HEINZ ABC INDONESIA | BP28: =IFERROR(VLOOKUP(Table43[[#This Row],[Kode Pcpl]],'[1]HEINZ ABC'!$A$4:$E$112,8,0),0) -> 0 | BQ28: =Table43[[#This Row],[Harga Jual Pcs GT (-PPN)]]-Table43[[#This Row],[HARGA NAIK GT]] -> 25027.03 | BR28: =IF(Table43[[#This Row],[HARGA NAIK GT]]=0,Table43[[#This Row],[Harga Jual Pcs GT (-PPN)]],Table43[[#This Row],[HARGA NAIK GT]]) -> 25027.03 | BS28: =IFERROR(VLOOKUP(Table43[[#This Row],[Kode Pcpl]],'[1]HEINZ ABC'!$A$4:$E$112,8,0),0) -> 0 | BT28: =Table43[[#This Row],[Harga Jual Pcs GT (-PPN)]]-BS28 -> 25027.03 | BU28: =IF(BS28=0,Table43[[#This Row],[Harga Jual Pcs MT (-PPN)]]) -> 27029.19 | BV28: =IFERROR(VLOOKUP(Table43[[#This Row],[Kode Pcpl]],[2]Pricelist!$A$4:$K$112,11,0),0) -> 0 | BW28: =IFERROR(VLOOKUP(Table43[[#This Row],[Kode BARANG Win2]],[3]!RECKITT211216[[KDBRG]:[HRG_JL_PCS-PPN]],11,0),0) -> 0 | BX28: =BV28/1.11 -> 0
