Workbook
Name Consol: "Error"

Sheet PRICE LIST Motasa
A3: KELOMPOK PRODUK | B3: KODE PRODUK PRINSIPAL | C3: NAMA ITEM | D3: ISI/CTN | E3: SATUAN | F3: HARGA INCLUDE PPN 11% IN CTN | G3: HARGA/PCS
A4: ANTANGIN GROUP | B4: 10002 | C4: ANTANGIN JRG PLUS JAHE MERAH TD20 | D4: 1000 | E4: STRIP | F4: 3210000 | G4: =F4/D4 -> 3210
A5: ANTANGIN GROUP | B5: 10063 | C5: ANTANGIN JUNIORS SD5 | D5: 300 | E5: SACHET | F5: 600000 | G5: =F5/D5 -> 2000
A6: ANTANGIN GROUP | B6: 10074 | C6: ANTANGIN JRG + MADU SD12 | D6: 360 | E6: SACHET | F6: 1116000 | G6: =F6/D6 -> 3100
A7: ANTANGIN GROUP | B7: 10075 | C7: ANTANGIN MINT SD12 | D7: 360 | E7: SACHET | F7: 1116000 | G7: =F7/D7 -> 3100
A8: ANTANGIN GROUP | B8: 10077 | C8: ANTANGIN MINT SD5 | D8: 300 | E8: SACHET | F8: 930000 | G8: =F8/D8 -> 3100
A9: ANTANGIN GROUP | B9: 10110 | C9: ANTANGIN GOOD NIGTH TD20 | D9: 1000 | E9: STRIP | F9: 4036000 | G9: =F9/D9 -> 4036
A10: ANTANGIN GROUP | B10: 10112 | C10: ANTANGIN HABBATUSSAUDA SD12 | D10: 360 | E10: SACHET | F10: 1116000 | G10: =F10/D10 -> 3100
A11: ANTANGIN GROUP | B11: 10134 | C11: ANTANGIN HABBATUSSAUDA SD14 | D11: 420 | E11: SACHET | F11: 1115998.8 | G11: =F11/D11 -> 2657.14
A12: ANTANGIN GROUP | B12: 10135 | C12: ANTANGIN MINT SD14 | D12: 420 | E12: SACHET | F12: 1115998.8 | G12: =F12/D12 -> 2657.14
A13: CANDY GROUP | B13: 10039 | C13: OB HERBAL PERMEN HERBAL RASA MINT S5 | D13: 270 | E13: SACHET | F13: 558090 | G13: =F13/D13 -> 2067
A14: CANDY GROUP | B14: 10048 | C14: ANTANGIN PERMEN HERBAL RASA MADU MINT T30 | D14: 180 | E14: SACHET | F14: 372060 | G14: =F14/D14 -> 2067
A15: CANDY GROUP | B15: 10067 | C15: ANTANGIN PERMEN ANEKA RASA T250 | D15: 6 | E15: TOPLES | F15: 213666 | G15: =F15/D15 -> 35611
... A149: MADU GROUP | B149: 60108 | C149: MADU TJ STRAWBERRY D12 (DUS) | D149: 24 | E149: DUS | F149: 201531.6 | G149: =F149/D149 -> 8397.15

Sheet FORM DASAR KLP
A3: KODE PRODUK PRINSIPAL | B3: KELOMPOK PRODUK By Principle | C3: NAMA ITEM | D3: ISI/CTN | E3: SATUAN | F3: HARGA INCLUDE PPN 11% IN CTN | G3: HARGA/PCS
A4: 10002 | B4: ANTANGIN GROUP | C4: ANTANGIN JRG PLUS JAHE MERAH TD20 | D4: 1000 | E4: STRIP | F4: 3563100 | G4: =F4/D4 -> 3563.1
A5: 10063 | B5: ANTANGIN GROUP | C5: ANTANGIN JUNIORS SD5 | D5: 300 | E5: SACHET | F5: 666000 | G5: =F5/D5 -> 2220
A6: 10074 | B6: ANTANGIN GROUP | C6: ANTANGIN JRG + MADU SD12 | D6: 360 | E6: SACHET | F6: 1238760 | G6: =F6/D6 -> 3441
A7: 10075 | B7: ANTANGIN GROUP | C7: ANTANGIN MINT SD12 | D7: 360 | E7: SACHET | F7: 1238760 | G7: =F7/D7 -> 3441
A8: 10077 | B8: ANTANGIN GROUP | C8: ANTANGIN MINT SD5 | D8: 300 | E8: SACHET | F8: 1032300 | G8: =F8/D8 -> 3441
A9: 10110 | B9: ANTANGIN GROUP | C9: ANTANGIN GOOD NIGTH TD20 | D9: 1000 | E9: STRIP | F9: 4479960 | G9: =F9/D9 -> 4479.96
A10: 10112 | B10: ANTANGIN GROUP | C10: ANTANGIN HABBATUSSAUDA SD12 | D10: 360 | E10: SACHET | F10: 1238760 | G10: =F10/D10 -> 3441
A11: 10134 | B11: ANTANGIN GROUP | C11: ANTANGIN HABBATUSSAUDA SD14 | D11: 420 | E11: SACHET | F11: 1238758.7 | G11: =F11/D11 -> 2949.4254
A12: 10135 | B12: ANTANGIN GROUP | C12: ANTANGIN MINT SD14 | D12: 420 | E12: SACHET | F12: 1238758.7 | G12: =F12/D12 -> 2949.4254
A13: 10039 | B13: CANDY GROUP | C13: OB HERBAL PERMEN HERBAL RASA MINT S5 | D13: 270 | E13: SACHET | F13: 619479.9 | G13: =F13/D13 -> 2294.37
A14: 10048 | B14: CANDY GROUP | C14: ANTANGIN PERMEN HERBAL RASA MADU MINT T30 | D14: 180 | E14: SACHET | F14: 412986.6 | G14: =F14/D14 -> 2294.37
A15: 10067 | B15: CANDY GROUP | C15: ANTANGIN PERMEN ANEKA RASA T250 | D15: 6 | E15: TOPLES | F15: 237169.26 | G15: =F15/D15 -> 39528.21
... A149: 60108 | B149: MADU GROUP | C149: MADU TJ STRAWBERRY D12 (DUS) | D149: 24 | E149: DUS | F149: 223700.08 | G149: =F149/D149 -> 9320.8365

Sheet Cara Buat
A3: 1 | B3: Sortir Daftar Produk Principle sesuai Nama lalu sortir lagi by kelompok | D3: 1 | E3: Buat satu folder master barang, master kelompok, price list, mapping produk win to pcpl dan mapping produk pcpl to win
A4: 2 | B4: Copy dan Paste kan ke Sheet Form Master (sesuaikan kolom nya) | D4: 2 | E4: Master barang, master kelompok, price list, mapping produk win to pcpl dan mapping produk pcpl to win berdiri sendiri dalam satu book
A5: 3 | B5: Sheet kuning adalah rumus, jangan diganggu

Sheet Pvt Map 1
A3: Kode BARANG Win2 | B3: SATUAN Fix Win | C3: Kode Pcpl | D3: ISI/CTN | E3: Sum of No. Urut Item Sama
A4: R1054001000010 | B4: PCS | C4: 3300965 | D4: 576 | E4: 1
A5: R1054002000010 | B5: PCS | C5: 3300964 | D5: 576 | E5: 1
A6: R1071001001520 | B6: SCH | C6: 3239831 | D6: 144 | E6: 1
A7: R1071001001520 | B7: SCH | C7: 3120730 | D7: 144 | E7: 2
A8: R1071001001520 | B8: SCH | C8: 3090609 | D8: 144 | E8: 3
A9: R1052002000010 | B9: PCS | C9: 8021803 | D9: 576 | E9: 1
A10: R1052001000010 | B10: PCS | C10: 8021804 | D10: 576 | E10: 1
A11: R1072001003010 | B11: PCS | C11: 3301366 | D11: 72 | E11: 1
A12: R1021007006010 | B12: PCS | C12: 3193501 | D12: 144 | E12: 1
A13: R1021007006010 | B13: PCS | C13: 3337511 | D13: 144 | E13: 2
A14: R1021006006010 | B14: PCS | C14: 3193502 | D14: 144 | E14: 1
A15: R1021005006010 | B15: PCS | C15: 3166975 | D15: 144 | E15: 1
... A27: R1021001006010 | B27: PCS | C27: 3331432 | D27: 144 | E27: 4
A28: R1071002006020 | B28: SCH | C28: 3297500 | D28: 72
A29: R1071002006020 | B29: SCH | C29: 3239844 | D29: 72
A30: R1071002006020 | B30: SCH | C30: 3120741 | D30: 72
A31: R1071002006020 | B31: SCH | C31: 3052120 | D31: 72
A32: R1071002006020 | B32: SCH | C32: 3195853 | D32: 72
A33: R1071002006020 | B33: SCH | C33: 3108501 | D33: 72
A34: R1071001006020 | B34: SCH | C34: 3297499 | D34: 72
A35: R1071001006020 | B35: SCH | C35: 3120734 | D35: 72
A36: R1071001006020 | B36: SCH | C36: 3239832 | D36: 72
A37: R1071001006020 | B37: SCH | C37: 3017044 | D37: 72
A38: R1071001006020 | B38: SCH | C38: 3185296 | D38: 72
A39: R1071001006020 | B39: SCH | C39: 3090608 | D39: 72
... A42: R1063001000010 | B42: PCS | C42: 8204617 | D42: 60
A43: R1063001000010 | B43: PCS | C43: ID0365729 | D43: 60
A44: R1063001000010 | B44: PCS | C44: ID8153746 | D44: 60
A45: R1063001000010 | B45: PCS | C45: ID0143051 | D45: 60
A46: R1061001000010 | B46: PCS | C46: 8125396 | D46: 60
A47: R1061001000010 | B47: PCS | C47: 3056005 | D47: 60
A48: R1061001000010 | B48: PCS | C48: 8204616 | D48: 60
A49: R1061001000010 | B49: PCS | C49: ID0346825 | D49: 60
A50: R1061001000010 | B50: PCS | C50: ID8153744 | D50: 60
A51: R1061001000010 | B51: PCS | C51: ID0143020 | D51: 60
A52: R1062001000010 | B52: PCS | C52: 8125395 | D52: 60
A53: R1062001000010 | B53: PCS | C53: ID8153739 | D53: 60
A54: R1062001000010 | B54: PCS | C54: ID0143060 | D54: 60
A55: R1062001000010 | B55: PCS | C55: 8204615 | D55: 60
A56: R1062001000010 | B56: PCS | C56: ID8153741 | D56: 60
A57: R1021005010010 | B57: PCS | C57: 3166958 | D57: 144 | E57: 1
A58: R1021005010010 | B58: PCS | C58: 3083294 | D58: 144 | E58: 2
A59: R1021005010010 | B59: PCS | C59: 3238701 | D59: 144 | E59: 3
A60: R1021005010010 | B60: PCS | C60: 3061093 | D60: 144 | E60: 4
A61: R1021005010010 | B61: PCS | C61: 3224745 | D61: 144 | E61: 5
A62: R1021005010010 | B62: PCS | C62: 3087035 | D62: 144 | E62: 6
A63: R1021005010010 | B63: PCS | C63: ID8208591 | D63: 144 | E63: 7
A64: R1021005010010 | B64: PCS | C64: ID8046692M | D64: 144 | E64: 8
A65: R1021005010010 | B65: PCS | C65: ID8099814M | D65: 144 | E65: 9
A66: R1021005010010 | B66: PCS | C66: ID8195137M | D66: 144 | E66: 1
A67: R1021005010010 | B67: PCS | C67: ID0344251M | D67: 144 | E67: 2
A68: R1021005010010 | B68: PCS | C68: ID8088692M | D68: 144 | E68: 3
A69: R1021004010010 | B69: PCS | C69: 3166942 | D69: 144 | E69: 1
A70: R1021004010010 | B70: PCS | C70: 3060668 | D70: 144 | E70: 2
A71: R1021004010010 | B71: PCS | C71: 3087594 | D71: 144 | E71: 3
A72: R1021004010010 | B72: PCS | C72: ID8195069M | D72: 144 | E72: 4
A73: R1021004010010 | B73: PCS | C73: 3031729 | D73: 144 | E73: 5
A74: R1021004010010 | B74: PCS | C74: ID8162950 | D74: 144 | E74: 6
A75: R1021004010010 | B75: PCS | C75: ID8162950M | D75: 144 | E75: 7
A76: R1021002010010 | B76: PCS | C76: 3300517 | D76: 144 | E76: 1
A77: R1021001010010 | B77: PCS | C77: 3171286 | D77: 144 | E77: 1
A78: R1021001010010 | B78: PCS | C78: 3166924 | D78: 144 | E78: 2
A79: R1021001010010 | B79: PCS | C79: 3060311 | D79: 144 | E79: 3
A80: R1021001010010 | B80: PCS | C80: 3087451 | D80: 144 | E80: 4
A81: R1021001010010 | B81: PCS | C81: ID8195121M | D81: 144 | E81: 5
A82: R1021001010010 | B82: PCS | C82: 3031726 | D82: 144 | E82: 6
A83: R1021001010010 | B83: PCS | C83: ID8099810M | D83: 144 | E83: 7
A84: R1021001010010 | B84: PCS | C84: ID0344249M | D84: 144 | E84: 8
A85: R1021001010010 | B85: PCS | C85: ID8088690M | D85: 144 | E85: 9
A86: R1021209010010 | B86: PCS | C86: 3226054 | D86: 144
A87: R1021209010010 | B87: PCS | C87: 3337514 | D87: 144
A88: R1021209010010 | B88: PCS | C88: 3179981 | D88: 144
A89: R1021209010010 | B89: PCS | C89: 3072666 | D89: 144
A90: R1021209010010 | B90: PCS | C90: 3088979 | D90: 144
A91: R1021209010010 | B91: PCS | C91: 3060842 | D91: 144
A92: R1021209010010 | B92: PCS | C92: ID8195056M | D92: 144
A93: R1021209010010 | B93: PCS | C93: 3031552 | D93: 144
A94: R1021209010010 | B94: PCS | C94: 3042277 | D94: 144
A95: R1021209010010 | B95: PCS | C95: ID8096563M | D95: 144
A96: R1021209010010 | B96: PCS | C96: ID0343837 | D96: 144
A97: R1021209010010 | B97: PCS | C97: ID0343837M | D97: 144
A98: R1021209010010 | B98: PCS | C98: ID8086714 | D98: 144
A99: R1021209010010 | B99: PCS | C99: ID8086714M | D99: 144
A100: R1021209010010 | B100: PCS | C100: 8201501 | D100: 144
A101: R1021209010010 | B101: PCS | C101: ID8201501M | D101: 144
A102: R1021208010010 | B102: PCS | C102: 3226038 | D102: 144
A103: R1021208010010 | B103: PCS | C103: 3088970 | D103: 144
A104: R1021208010010 | B104: PCS | C104: 3182834 | D104: 144
A105: R1021208010010 | B105: PCS | C105: 3337509 | D105: 144
A106: R1021208010010 | B106: PCS | C106: 3072665 | D106: 144
A107: R1021208010010 | B107: PCS | C107: 3060913 | D107: 144
A108: R1021208010010 | B108: PCS | C108: ID8195042M | D108: 144
A109: R1021208010010 | B109: PCS | C109: 3031551 | D109: 144
A110: R1021208010010 | B110: PCS | C110: 3042273 | D110: 144
A111: R1021208010010 | B111: PCS | C111: ID8096561M | D111: 144
A112: R1021208010010 | B112: PCS | C112: ID0343834M | D112: 144
A113: R1021208010010 | B113: PCS | C113: ID8086712M | D113: 144
A114: R1021208010010 | B114: PCS | C114: 8201499 | D114: 144
A115: R1021207010010 | B115: PCS | C115: 3226052 | D115: 144
...

Sheet Table Pvt 1
A1: Kode Barang Win | B1: Kode Pcpl | C1: SATUAN Fix Win | D1: ISI/CTN | E1: Kode PCPL yang sama | F1: Column1
A2: R1054001000010 | B2: 3300965 | C2: PCS | D2: 576 | E2: 1 | F2: =Pvt_Map_1[[#This Row],[Kode Barang Win]] -> R1054001000010
A3: R1054002000010 | B3: 3300964 | C3: PCS | D3: 576 | E3: 1 | F3: =Pvt_Map_1[[#This Row],[Kode Barang Win]] -> R1054002000010
A4: R1071001001520 | B4: 3239831 | C4: SCH | D4: 144 | E4: 1 | F4: =Pvt_Map_1[[#This Row],[Kode Barang Win]] -> R1071001001520
A5: R1071001001520 | B5: 3120730 | C5: SCH | D5: 144 | E5: 2 | F5: =Pvt_Map_1[[#This Row],[Kode Barang Win]] -> R1071001001520
A6: R1071001001520 | B6: 3090609 | C6: SCH | D6: 144 | E6: 3 | F6: =Pvt_Map_1[[#This Row],[Kode Barang Win]] -> R1071001001520
A7: R1052002000010 | B7: 8021803 | C7: PCS | D7: 576 | E7: 1 | F7: =Pvt_Map_1[[#This Row],[Kode Barang Win]] -> R1052002000010
A8: R1052001000010 | B8: 8021804 | C8: PCS | D8: 576 | E8: 1 | F8: =Pvt_Map_1[[#This Row],[Kode Barang Win]] -> R1052001000010
A9: R1072001003010 | B9: 3301366 | C9: PCS | D9: 72 | E9: 1 | F9: =Pvt_Map_1[[#This Row],[Kode Barang Win]] -> R1072001003010
A10: R1021007006010 | B10: 3193501 | C10: PCS | D10: 144 | E10: 1 | F10: =Pvt_Map_1[[#This Row],[Kode Barang Win]] -> R1021007006010
A11: R1021007006010 | B11: 3337511 | C11: PCS | D11: 144 | E11: 2 | F11: =Pvt_Map_1[[#This Row],[Kode Barang Win]] -> R1021007006010
A12: R1021006006010 | B12: 3193502 | C12: PCS | D12: 144 | E12: 1 | F12: =Pvt_Map_1[[#This Row],[Kode Barang Win]] -> R1021006006010
A13: R1021005006010 | B13: 3166975 | C13: PCS | D13: 144 | E13: 1 | F13: =Pvt_Map_1[[#This Row],[Kode Barang Win]] -> R1021005006010
... A25: R1021001006010 | B25: 3331432 | C25: PCS | D25: 144 | E25: 4 | F25: =Pvt_Map_1[[#This Row],[Kode Barang Win]] -> R1021001006010
A26: R1071002006020 | B26: 3297500 | C26: SCH | D26: 72 | F26: =Pvt_Map_1[[#This Row],[Kode Barang Win]] -> R1071002006020
A27: R1071002006020 | B27: 3239844 | C27: SCH | D27: 72 | F27: =Pvt_Map_1[[#This Row],[Kode Barang Win]] -> R1071002006020
A28: R1071002006020 | B28: 3120741 | C28: SCH | D28: 72 | F28: =Pvt_Map_1[[#This Row],[Kode Barang Win]] -> R1071002006020
A29: R1071002006020 | B29: 3052120 | C29: SCH | D29: 72 | F29: =Pvt_Map_1[[#This Row],[Kode Barang Win]] -> R1071002006020
A30: R1071002006020 | B30: 3195853 | C30: SCH | D30: 72 | F30: =Pvt_Map_1[[#This Row],[Kode Barang Win]] -> R1071002006020
A31: R1071002006020 | B31: 3108501 | C31: SCH | D31: 72 | F31: =Pvt_Map_1[[#This Row],[Kode Barang Win]] -> R1071002006020
A32: R1071001006020 | B32: 3297499 | C32: SCH | D32: 72 | F32: =Pvt_Map_1[[#This Row],[Kode Barang Win]] -> R1071001006020
A33: R1071001006020 | B33: 3120734 | C33: SCH | D33: 72 | F33: =Pvt_Map_1[[#This Row],[Kode Barang Win]] -> R1071001006020
A34: R1071001006020 | B34: 3239832 | C34: SCH | D34: 72 | F34: =Pvt_Map_1[[#This Row],[Kode Barang Win]] -> R1071001006020
A35: R1071001006020 | B35: 3017044 | C35: SCH | D35: 72 | F35: =Pvt_Map_1[[#This Row],[Kode Barang Win]] -> R1071001006020
A36: R1071001006020 | B36: 3185296 | C36: SCH | D36: 72 | F36: =Pvt_Map_1[[#This Row],[Kode Barang Win]] -> R1071001006020
A37: R1071001006020 | B37: 3090608 | C37: SCH | D37: 72 | F37: =Pvt_Map_1[[#This Row],[Kode Barang Win]] -> R1071001006020
... A40: R1063001000010 | B40: 8204617 | C40: PCS | D40: 60 | F40: =Pvt_Map_1[[#This Row],[Kode Barang Win]] -> R1063001000010
A41: R1063001000010 | B41: ID0365729 | C41: PCS | D41: 60 | F41: =Pvt_Map_1[[#This Row],[Kode Barang Win]] -> R1063001000010
A42: R1063001000010 | B42: ID8153746 | C42: PCS | D42: 60 | F42: =Pvt_Map_1[[#This Row],[Kode Barang Win]] -> R1063001000010
A43: R1063001000010 | B43: ID0143051 | C43: PCS | D43: 60 | F43: =Pvt_Map_1[[#This Row],[Kode Barang Win]] -> R1063001000010
A44: R1061001000010 | B44: 8125396 | C44: PCS | D44: 60 | F44: =Pvt_Map_1[[#This Row],[Kode Barang Win]] -> R1061001000010
A45: R1061001000010 | B45: 3056005 | C45: PCS | D45: 60 | F45: =Pvt_Map_1[[#This Row],[Kode Barang Win]] -> R1061001000010
A46: R1061001000010 | B46: 8204616 | C46: PCS | D46: 60 | F46: =Pvt_Map_1[[#This Row],[Kode Barang Win]] -> R1061001000010
A47: R1061001000010 | B47: ID0346825 | C47: PCS | D47: 60 | F47: =Pvt_Map_1[[#This Row],[Kode Barang Win]] -> R1061001000010
A48: R1061001000010 | B48: ID8153744 | C48: PCS | D48: 60 | F48: =Pvt_Map_1[[#This Row],[Kode Barang Win]] -> R1061001000010
A49: R1061001000010 | B49: ID0143020 | C49: PCS | D49: 60 | F49: =Pvt_Map_1[[#This Row],[Kode Barang Win]] -> R1061001000010
A50: R1062001000010 | B50: 8125395 | C50: PCS | D50: 60 | F50: =Pvt_Map_1[[#This Row],[Kode Barang Win]] -> R1062001000010
A51: R1062001000010 | B51: ID8153739 | C51: PCS | D51: 60 | F51: =Pvt_Map_1[[#This Row],[Kode Barang Win]] -> R1062001000010
A52: R1062001000010 | B52: ID0143060 | C52: PCS | D52: 60 | F52: =Pvt_Map_1[[#This Row],[Kode Barang Win]] -> R1062001000010
A53: R1062001000010 | B53: 8204615 | C53: PCS | D53: 60 | F53: =Pvt_Map_1[[#This Row],[Kode Barang Win]] -> R1062001000010
A54: R1062001000010 | B54: ID8153741 | C54: PCS | D54: 60 | F54: =Pvt_Map_1[[#This Row],[Kode Barang Win]] -> R1062001000010
A55: R1021005010010 | B55: 3166958 | C55: PCS | D55: 144 | E55: 1 | F55: =Pvt_Map_1[[#This Row],[Kode Barang Win]] -> R1021005010010
A56: R1021005010010 | B56: 3083294 | C56: PCS | D56: 144 | E56: 2 | F56: =Pvt_Map_1[[#This Row],[Kode Barang Win]] -> R1021005010010
A57: R1021005010010 | B57: 3238701 | C57: PCS | D57: 144 | E57: 3 | F57: =Pvt_Map_1[[#This Row],[Kode Barang Win]] -> R1021005010010
A58: R1021005010010 | B58: 3061093 | C58: PCS | D58: 144 | E58: 4 | F58: =Pvt_Map_1[[#This Row],[Kode Barang Win]] -> R1021005010010
A59: R1021005010010 | B59: 3224745 | C59: PCS | D59: 144 | E59: 5 | F59: =Pvt_Map_1[[#This Row],[Kode Barang Win]] -> R1021005010010
A60: R1021005010010 | B60: 3087035 | C60: PCS | D60: 144 | E60: 6 | F60: =Pvt_Map_1[[#This Row],[Kode Barang Win]] -> R1021005010010
A61: R1021005010010 | B61: ID8208591 | C61: PCS | D61: 144 | E61: 7 | F61: =Pvt_Map_1[[#This Row],[Kode Barang Win]] -> R1021005010010
A62: R1021005010010 | B62: ID8046692M | C62: PCS | D62: 144 | E62: 8 | F62: =Pvt_Map_1[[#This Row],[Kode Barang Win]] -> R1021005010010
A63: R1021005010010 | B63: ID8099814M | C63: PCS | D63: 144 | E63: 9 | F63: =Pvt_Map_1[[#This Row],[Kode Barang Win]] -> R1021005010010
A64: R1021005010010 | B64: ID8195137M | C64: PCS | D64: 144 | E64: 1 | F64: =Pvt_Map_1[[#This Row],[Kode Barang Win]] -> R1021005010010
A65: R1021005010010 | B65: ID0344251M | C65: PCS | D65: 144 | E65: 2 | F65: =Pvt_Map_1[[#This Row],[Kode Barang Win]] -> R1021005010010
A66: R1021005010010 | B66: ID8088692M | C66: PCS | D66: 144 | E66: 3 | F66: =Pvt_Map_1[[#This Row],[Kode Barang Win]] -> R1021005010010
A67: R1021004010010 | B67: 3166942 | C67: PCS | D67: 144 | E67: 1 | F67: =Pvt_Map_1[[#This Row],[Kode Barang Win]] -> R1021004010010
A68: R1021004010010 | B68: 3060668 | C68: PCS | D68: 144 | E68: 2 | F68: =Pvt_Map_1[[#This Row],[Kode Barang Win]] -> R1021004010010
A69: R1021004010010 | B69: 3087594 | C69: PCS | D69: 144 | E69: 3 | F69: =Pvt_Map_1[[#This Row],[Kode Barang Win]] -> R1021004010010
A70: R1021004010010 | B70: ID8195069M | C70: PCS | D70: 144 | E70: 4 | F70: =Pvt_Map_1[[#This Row],[Kode Barang Win]] -> R1021004010010
A71: R1021004010010 | B71: 3031729 | C71: PCS | D71: 144 | E71: 5 | F71: =Pvt_Map_1[[#This Row],[Kode Barang Win]] -> R1021004010010
A72: R1021004010010 | B72: ID8162950 | C72: PCS | D72: 144 | E72: 6 | F72: =Pvt_Map_1[[#This Row],[Kode Barang Win]] -> R1021004010010
A73: R1021004010010 | B73: ID8162950M | C73: PCS | D73: 144 | E73: 7 | F73: =Pvt_Map_1[[#This Row],[Kode Barang Win]] -> R1021004010010
A74: R1021002010010 | B74: 3300517 | C74: PCS | D74: 144 | E74: 1 | F74: =Pvt_Map_1[[#This Row],[Kode Barang Win]] -> R1021002010010
A75: R1021001010010 | B75: 3171286 | C75: PCS | D75: 144 | E75: 1 | F75: =Pvt_Map_1[[#This Row],[Kode Barang Win]] -> R1021001010010
A76: R1021001010010 | B76: 3166924 | C76: PCS | D76: 144 | E76: 2 | F76: =Pvt_Map_1[[#This Row],[Kode Barang Win]] -> R1021001010010
A77: R1021001010010 | B77: 3060311 | C77: PCS | D77: 144 | E77: 3 | F77: =Pvt_Map_1[[#This Row],[Kode Barang Win]] -> R1021001010010
A78: R1021001010010 | B78: 3087451 | C78: PCS | D78: 144 | E78: 4 | F78: =Pvt_Map_1[[#This Row],[Kode Barang Win]] -> R1021001010010
A79: R1021001010010 | B79: ID8195121M | C79: PCS | D79: 144 | E79: 5 | F79: =Pvt_Map_1[[#This Row],[Kode Barang Win]] -> R1021001010010
A80: R1021001010010 | B80: 3031726 | C80: PCS | D80: 144 | E80: 6 | F80: =Pvt_Map_1[[#This Row],[Kode Barang Win]] -> R1021001010010
A81: R1021001010010 | B81: ID8099810M | C81: PCS | D81: 144 | E81: 7 | F81: =Pvt_Map_1[[#This Row],[Kode Barang Win]] -> R1021001010010
A82: R1021001010010 | B82: ID0344249M | C82: PCS | D82: 144 | E82: 8 | F82: =Pvt_Map_1[[#This Row],[Kode Barang Win]] -> R1021001010010
A83: R1021001010010 | B83: ID8088690M | C83: PCS | D83: 144 | E83: 9 | F83: =Pvt_Map_1[[#This Row],[Kode Barang Win]] -> R1021001010010
A84: R1021209010010 | B84: 3226054 | C84: PCS | D84: 144 | F84: =Pvt_Map_1[[#This Row],[Kode Barang Win]] -> R1021209010010
A85: R1021209010010 | B85: 3337514 | C85: PCS | D85: 144 | F85: =Pvt_Map_1[[#This Row],[Kode Barang Win]] -> R1021209010010
A86: R1021209010010 | B86: 3179981 | C86: PCS | D86: 144 | F86: =Pvt_Map_1[[#This Row],[Kode Barang Win]] -> R1021209010010
A87: R1021209010010 | B87: 3072666 | C87: PCS | D87: 144 | F87: =Pvt_Map_1[[#This Row],[Kode Barang Win]] -> R1021209010010
A88: R1021209010010 | B88: 3088979 | C88: PCS | D88: 144 | F88: =Pvt_Map_1[[#This Row],[Kode Barang Win]] -> R1021209010010
A89: R1021209010010 | B89: 3060842 | C89: PCS | D89: 144 | F89: =Pvt_Map_1[[#This Row],[Kode Barang Win]] -> R1021209010010
A90: R1021209010010 | B90: ID8195056M | C90: PCS | D90: 144 | F90: =Pvt_Map_1[[#This Row],[Kode Barang Win]] -> R1021209010010
A91: R1021209010010 | B91: 3031552 | C91: PCS | D91: 144 | F91: =Pvt_Map_1[[#This Row],[Kode Barang Win]] -> R1021209010010
A92: R1021209010010 | B92: 3042277 | C92: PCS | D92: 144 | F92: =Pvt_Map_1[[#This Row],[Kode Barang Win]] -> R1021209010010
A93: R1021209010010 | B93: ID8096563M | C93: PCS | D93: 144 | F93: =Pvt_Map_1[[#This Row],[Kode Barang Win]] -> R1021209010010
A94: R1021209010010 | B94: ID0343837 | C94: PCS | D94: 144 | F94: =Pvt_Map_1[[#This Row],[Kode Barang Win]] -> R1021209010010
A95: R1021209010010 | B95: ID0343837M | C95: PCS | D95: 144 | F95: =Pvt_Map_1[[#This Row],[Kode Barang Win]] -> R1021209010010
A96: R1021209010010 | B96: ID8086714 | C96: PCS | D96: 144 | F96: =Pvt_Map_1[[#This Row],[Kode Barang Win]] -> R1021209010010
A97: R1021209010010 | B97: ID8086714M | C97: PCS | D97: 144 | F97: =Pvt_Map_1[[#This Row],[Kode Barang Win]] -> R1021209010010
A98: R1021209010010 | B98: 8201501 | C98: PCS | D98: 144 | F98: =Pvt_Map_1[[#This Row],[Kode Barang Win]] -> R1021209010010
A99: R1021209010010 | B99: ID8201501M | C99: PCS | D99: 144 | F99: =Pvt_Map_1[[#This Row],[Kode Barang Win]] -> R1021209010010
A100: R1021208010010 | B100: 3226038 | C100: PCS | D100: 144 | F100: =Pvt_Map_1[[#This Row],[Kode Barang Win]] -> R1021208010010
A101: R1021208010010 | B101: 3088970 | C101: PCS | D101: 144 | F101: =Pvt_Map_1[[#This Row],[Kode Barang Win]] -> R1021208010010
A102: R1021208010010 | B102: 3182834 | C102: PCS | D102: 144 | F102: =Pvt_Map_1[[#This Row],[Kode Barang Win]] -> R1021208010010
A103: R1021208010010 | B103: 3337509 | C103: PCS | D103: 144 | F103: =Pvt_Map_1[[#This Row],[Kode Barang Win]] -> R1021208010010
A104: R1021208010010 | B104: 3072665 | C104: PCS | D104: 144 | F104: =Pvt_Map_1[[#This Row],[Kode Barang Win]] -> R1021208010010
A105: R1021208010010 | B105: 3060913 | C105: PCS | D105: 144 | F105: =Pvt_Map_1[[#This Row],[Kode Barang Win]] -> R1021208010010
A106: R1021208010010 | B106: ID8195042M | C106: PCS | D106: 144 | F106: =Pvt_Map_1[[#This Row],[Kode Barang Win]] -> R1021208010010
A107: R1021208010010 | B107: 3031551 | C107: PCS | D107: 144 | F107: =Pvt_Map_1[[#This Row],[Kode Barang Win]] -> R1021208010010
A108: R1021208010010 | B108: 3042273 | C108: PCS | D108: 144 | F108: =Pvt_Map_1[[#This Row],[Kode Barang Win]] -> R1021208010010
A109: R1021208010010 | B109: ID8096561M | C109: PCS | D109: 144 | F109: =Pvt_Map_1[[#This Row],[Kode Barang Win]] -> R1021208010010
A110: R1021208010010 | B110: ID0343834M | C110: PCS | D110: 144 | F110: =Pvt_Map_1[[#This Row],[Kode Barang Win]] -> R1021208010010
A111: R1021208010010 | B111: ID8086712M | C111: PCS | D111: 144 | F111: =Pvt_Map_1[[#This Row],[Kode Barang Win]] -> R1021208010010
A112: R1021208010010 | B112: 8201499 | C112: PCS | D112: 144 | F112: =Pvt_Map_1[[#This Row],[Kode Barang Win]] -> R1021208010010
A113: R1021207010010 | B113: 3226052 | C113: PCS | D113: 144 | F113: =Pvt_Map_1[[#This Row],[Kode Barang Win]] -> R1021207010010
...

Sheet Fix Mapping
A1: KODE BARANG | B1: NAMA BARANG | C1: ISI/CTN | D1: SATUAN | E1: NAMA KELOMPOK | F1: Harga Beli Pcs (-PPN) | G1: Harga Beli Krt (- PPN) | H1: Harga Beli Pcs (+PPN) | I1: Harga Beli Krt (+PPN) | J1: Harga Jual Pcs GT (-PPN) | K1: Harga Jual Krt GT (- PPN) | L1: Harga Jual Pcs GT (+PPN | M1: Harga Jual Krt GT (+PPN) | N1: Harga Jual Pcs MT (-PPN) | O1: Harga Jual Krt MT (- PPN) | P1: Harga Jual Pcs MT (+PPN) | Q1: Harga Jual Krt MT (+PPN) | R1: NAMA PRINCIPLE | S1: PCPL KODE 1 | T1: PCPL KODE 2 | U1: PCPL KODE 3 | V1: PCPL KODE 4 | W1: PCPL KODE 5
A2: R1011000010010 | B2: RB BRASSO METAL POOLISH 100ML X 48 PCS | C2: 48 | D2: PCS | E2: BRASSO METAL POOLISH | F2: 22749.168 | G2: 1091960.1 | H2: 25251.577 | I2: 1212075.7 | J2: 24862.479 | K2: 1193399 | L2: 27597.352 | M2: 1324672.9 | N2: 24862.479 | O2: 1193399 | P2: 27597.352 | Q2: 1324672.9 | S2: =IFERROR(VLOOKUP(CONCATENATE(Fix_Mapping[[#This Row],[KODE BARANG]],1),'Form Fix'!$A$6:$F$911,4,0),0) -> 3121445 | T2: =IFERROR(VLOOKUP(CONCATENATE(Fix_Mapping[[#This Row],[KODE BARANG]],2),'Form Fix'!$A$6:$F$911,4,0),0) -> 3055580 | U2: =IFERROR(VLOOKUP(CONCATENATE(Fix_Mapping[[#This Row],[KODE BARANG]],3),'Form Fix'!$A$6:$F$911,4,0),0) -> ID020064 | V2: =IFERROR(VLOOKUP(CONCATENATE(Fix_Mapping[[#This Row],[KODE BARANG]],4),'Form Fix'!$A$6:$F$911,4,0),0) -> 0 | W2: =IFERROR(VLOOKUP(CONCATENATE(Fix_Mapping[[#This Row],[KODE BARANG]],5),'Form Fix'!$A$6:$F$911,4,0),0) -> 0
A3: R1021001006010 | B3: RB DETTOL BODY SOAP COOL 60GR X 144 PCS | C3: 144 | D3: PCS | E3: DETTOL BODY SOAP | F3: 3048.78 | G3: 439024.32 | H3: 3384.1458 | I3: 487317 | J3: 3332 | K3: 479808 | L3: 3698.52 | M3: 532586.88 | N3: 3332 | O3: 479808 | P3: 3698.52 | Q3: 532586.88 | S3: =IFERROR(VLOOKUP(CONCATENATE(Fix_Mapping[[#This Row],[KODE BARANG]],1),'Form Fix'!$A$6:$F$911,4,0),0) -> 3171295 | T3: =IFERROR(VLOOKUP(CONCATENATE(Fix_Mapping[[#This Row],[KODE BARANG]],2),'Form Fix'!$A$6:$F$911,4,0),0) -> 3166934 | U3: =IFERROR(VLOOKUP(CONCATENATE(Fix_Mapping[[#This Row],[KODE BARANG]],3),'Form Fix'!$A$6:$F$911,4,0),0) -> 3119258 | V3: =IFERROR(VLOOKUP(CONCATENATE(Fix_Mapping[[#This Row],[KODE BARANG]],4),'Form Fix'!$A$6:$F$911,4,0),0) -> 3331432 | W3: =IFERROR(VLOOKUP(CONCATENATE(Fix_Mapping[[#This Row],[KODE BARANG]],5),'Form Fix'!$A$6:$F$911,4,0),0) -> 0
A4: R1021001010010 | B4: RB DETTOL BODY SOAP COOL 100GR X 144 PCS | C4: 144 | D4: PCS | E4: DETTOL BODY SOAP | F4: 5864.5654 | G4: 844497.42 | H4: 6509.6676 | I4: 937392.14 | J4: 6409.3611 | K4: 922948 | L4: 7114.3908 | M4: 1024472.3 | N4: 6409.3611 | O4: 922948 | P4: 7114.3908 | Q4: 1024472.3 | S4: =IFERROR(VLOOKUP(CONCATENATE(Fix_Mapping[[#This Row],[KODE BARANG]],1),'Form Fix'!$A$6:$F$911,4,0),0) -> 3171286 | T4: =IFERROR(VLOOKUP(CONCATENATE(Fix_Mapping[[#This Row],[KODE BARANG]],2),'Form Fix'!$A$6:$F$911,4,0),0) -> 3166924 | U4: =IFERROR(VLOOKUP(CONCATENATE(Fix_Mapping[[#This Row],[KODE BARANG]],3),'Form Fix'!$A$6:$F$911,4,0),0) -> 3060311 | V4: =IFERROR(VLOOKUP(CONCATENATE(Fix_Mapping[[#This Row],[KODE BARANG]],4),'Form Fix'!$A$6:$F$911,4,0),0) -> 3087451 | W4: =IFERROR(VLOOKUP(CONCATENATE(Fix_Mapping[[#This Row],[KODE BARANG]],5),'Form Fix'!$A$6:$F$911,4,0),0) -> ID8195121M
A5: R1021002010010 | B5: RB DETTOL BODY SOAP FAMILY PROTECT 100GR X 144 PCS | C5: 144 | D5: PCS | E5: DETTOL BODY SOAP | F5: 5864.5654 | G5: 844497.42 | H5: 6509.6676 | I5: 937392.14 | J5: 6409.3611 | K5: 922948 | L5: 7114.3908 | M5: 1024472.3 | N5: 6409.3611 | O5: 922948 | P5: 7114.3908 | Q5: 1024472.3 | S5: =IFERROR(VLOOKUP(CONCATENATE(Fix_Mapping[[#This Row],[KODE BARANG]],1),'Form Fix'!$A$6:$F$911,4,0),0) -> 3300517 | T5: =IFERROR(VLOOKUP(CONCATENATE(Fix_Mapping[[#This Row],[KODE BARANG]],2),'Form Fix'!$A$6:$F$911,4,0),0) -> 0 | U5: =IFERROR(VLOOKUP(CONCATENATE(Fix_Mapping[[#This Row],[KODE BARANG]],3),'Form Fix'!$A$6:$F$911,4,0),0) -> 0 | V5: =IFERROR(VLOOKUP(CONCATENATE(Fix_Mapping[[#This Row],[KODE BARANG]],4),'Form Fix'!$A$6:$F$911,4,0),0) -> 0 | W5: =IFERROR(VLOOKUP(CONCATENATE(Fix_Mapping[[#This Row],[KODE BARANG]],5),'Form Fix'!$A$6:$F$911,4,0),0) -> 0
A6: R1021003006010 | B6: RB DETTOL BODY SOAP FRESH 60GR X 144 PCS | C6: 144 | D6: PCS | E6: DETTOL BODY SOAP | F6: 3048.78 | G6: 439024.32 | H6: 3384.1458 | I6: 487317 | J6: 3332 | K6: 479808 | L6: 3698.52 | M6: 532586.88 | N6: 3332 | O6: 479808 | P6: 3698.52 | Q6: 532586.88 | S6: =IFERROR(VLOOKUP(CONCATENATE(Fix_Mapping[[#This Row],[KODE BARANG]],1),'Form Fix'!$A$6:$F$911,4,0),0) -> 3170933 | T6: =IFERROR(VLOOKUP(CONCATENATE(Fix_Mapping[[#This Row],[KODE BARANG]],2),'Form Fix'!$A$6:$F$911,4,0),0) -> 3147626 | U6: =IFERROR(VLOOKUP(CONCATENATE(Fix_Mapping[[#This Row],[KODE BARANG]],3),'Form Fix'!$A$6:$F$911,4,0),0) -> 0 | V6: =IFERROR(VLOOKUP(CONCATENATE(Fix_Mapping[[#This Row],[KODE BARANG]],4),'Form Fix'!$A$6:$F$911,4,0),0) -> 0 | W6: =IFERROR(VLOOKUP(CONCATENATE(Fix_Mapping[[#This Row],[KODE BARANG]],5),'Form Fix'!$A$6:$F$911,4,0),0) -> 0
A7: R1021003010010 | B7: RB DETTOL BODY SOAP FRESH 100GR X 144 PCS | C7: 144 | D7: PCS | E7: DETTOL BODY SOAP | F7: 5864.5654 | G7: 844497.42 | H7: 6509.6676 | I7: 937392.14 | J7: 6409.3611 | K7: 922948 | L7: 7114.3908 | M7: 1024472.3 | O7: 0 | P7: 0 | Q7: 0 | S7: =IFERROR(VLOOKUP(CONCATENATE(Fix_Mapping[[#This Row],[KODE BARANG]],1),'Form Fix'!$A$6:$F$911,4,0),0) -> 3170945 | T7: =IFERROR(VLOOKUP(CONCATENATE(Fix_Mapping[[#This Row],[KODE BARANG]],2),'Form Fix'!$A$6:$F$911,4,0),0) -> 0 | U7: =IFERROR(VLOOKUP(CONCATENATE(Fix_Mapping[[#This Row],[KODE BARANG]],3),'Form Fix'!$A$6:$F$911,4,0),0) -> 0 | V7: =IFERROR(VLOOKUP(CONCATENATE(Fix_Mapping[[#This Row],[KODE BARANG]],4),'Form Fix'!$A$6:$F$911,4,0),0) -> 0 | W7: =IFERROR(VLOOKUP(CONCATENATE(Fix_Mapping[[#This Row],[KODE BARANG]],5),'Form Fix'!$A$6:$F$911,4,0),0) -> 0
A8: R1021004006010 | B8: RB DETTOL BODY SOAP LASTING 60GR X 144 PCS | C8: 144 | D8: PCS | E8: DETTOL BODY SOAP | F8: 3048.78 | G8: 439024.32 | H8: 3384.1458 | I8: 487317 | J8: 3332 | K8: 479808 | L8: 3698.52 | M8: 532586.88 | N8: 3332 | O8: 479808 | P8: 3698.52 | Q8: 532586.88 | S8: =IFERROR(VLOOKUP(CONCATENATE(Fix_Mapping[[#This Row],[KODE BARANG]],1),'Form Fix'!$A$6:$F$911,4,0),0) -> 3166937 | T8: =IFERROR(VLOOKUP(CONCATENATE(Fix_Mapping[[#This Row],[KODE BARANG]],2),'Form Fix'!$A$6:$F$911,4,0),0) -> 3148248 | U8: =IFERROR(VLOOKUP(CONCATENATE(Fix_Mapping[[#This Row],[KODE BARANG]],3),'Form Fix'!$A$6:$F$911,4,0),0) -> 0 | V8: =IFERROR(VLOOKUP(CONCATENATE(Fix_Mapping[[#This Row],[KODE BARANG]],4),'Form Fix'!$A$6:$F$911,4,0),0) -> 0 | W8: =IFERROR(VLOOKUP(CONCATENATE(Fix_Mapping[[#This Row],[KODE BARANG]],5),'Form Fix'!$A$6:$F$911,4,0),0) -> 0
A9: R1021004010010 | B9: RB DETTOL BODY SOAP LASTING 100GR X 144 PCS | C9: 144 | D9: PCS | E9: DETTOL BODY SOAP | F9: 5864.5654 | G9: 844497.42 | H9: 6509.6676 | I9: 937392.14 | J9: 6409.3611 | K9: 922948 | L9: 7114.3908 | M9: 1024472.3 | N9: 6409.3611 | O9: 922948 | P9: 7114.3908 | Q9: 1024472.3 | S9: =IFERROR(VLOOKUP(CONCATENATE(Fix_Mapping[[#This Row],[KODE BARANG]],1),'Form Fix'!$A$6:$F$911,4,0),0) -> 3166942 | T9: =IFERROR(VLOOKUP(CONCATENATE(Fix_Mapping[[#This Row],[KODE BARANG]],2),'Form Fix'!$A$6:$F$911,4,0),0) -> 3060668 | U9: =IFERROR(VLOOKUP(CONCATENATE(Fix_Mapping[[#This Row],[KODE BARANG]],3),'Form Fix'!$A$6:$F$911,4,0),0) -> 3087594 | V9: =IFERROR(VLOOKUP(CONCATENATE(Fix_Mapping[[#This Row],[KODE BARANG]],4),'Form Fix'!$A$6:$F$911,4,0),0) -> ID8195069M | W9: =IFERROR(VLOOKUP(CONCATENATE(Fix_Mapping[[#This Row],[KODE BARANG]],5),'Form Fix'!$A$6:$F$911,4,0),0) -> 3031729
A10: R1021005006010 | B10: RB DETTOL BODY SOAP ORIGINAL 60GR X 144 PCS | C10: 144 | D10: PCS | E10: DETTOL BODY SOAP | F10: 3048.78 | G10: 439024.32 | H10: 3384.1458 | I10: 487317 | J10: 3332 | K10: 479808 | L10: 3698.52 | M10: 532586.88 | N10: 3332 | O10: 479808 | P10: 3698.52 | Q10: 532586.88 | S10: =IFERROR(VLOOKUP(CONCATENATE(Fix_Mapping[[#This Row],[KODE BARANG]],1),'Form Fix'!$A$6:$F$911,4,0),0) -> 3166975 | T10: =IFERROR(VLOOKUP(CONCATENATE(Fix_Mapping[[#This Row],[KODE BARANG]],2),'Form Fix'!$A$6:$F$911,4,0),0) -> 3331433 | U10: =IFERROR(VLOOKUP(CONCATENATE(Fix_Mapping[[#This Row],[KODE BARANG]],3),'Form Fix'!$A$6:$F$911,4,0),0) -> 3119259 | V10: =IFERROR(VLOOKUP(CONCATENATE(Fix_Mapping[[#This Row],[KODE BARANG]],4),'Form Fix'!$A$6:$F$911,4,0),0) -> 3238406 | W10: =IFERROR(VLOOKUP(CONCATENATE(Fix_Mapping[[#This Row],[KODE BARANG]],5),'Form Fix'!$A$6:$F$911,4,0),0) -> 3224742
A11: R1021005010010 | B11: RB DETTOL BODY SOAP ORIGINAL 100GR X 144 PCS | C11: 144 | D11: PCS | E11: DETTOL BODY SOAP | F11: 5864.5654 | G11: 844497.42 | H11: 6509.6676 | I11: 937392.14 | J11: 6409.3611 | K11: 922948 | L11: 7114.3908 | M11: 1024472.3 | N11: 6409.3611 | O11: 922948 | P11: 7114.3908 | Q11: 1024472.3 | S11: =IFERROR(VLOOKUP(CONCATENATE(Fix_Mapping[[#This Row],[KODE BARANG]],1),'Form Fix'!$A$6:$F$911,4,0),0) -> 3166958 | T11: =IFERROR(VLOOKUP(CONCATENATE(Fix_Mapping[[#This Row],[KODE BARANG]],2),'Form Fix'!$A$6:$F$911,4,0),0) -> 3083294 | U11: =IFERROR(VLOOKUP(CONCATENATE(Fix_Mapping[[#This Row],[KODE BARANG]],3),'Form Fix'!$A$6:$F$911,4,0),0) -> 3238701 | V11: =IFERROR(VLOOKUP(CONCATENATE(Fix_Mapping[[#This Row],[KODE BARANG]],4),'Form Fix'!$A$6:$F$911,4,0),0) -> 3061093 | W11: =IFERROR(VLOOKUP(CONCATENATE(Fix_Mapping[[#This Row],[KODE BARANG]],5),'Form Fix'!$A$6:$F$911,4,0),0) -> 3224745
A12: R1021006006010 | B12: RB DETTOL BODY SOAP RE-ENERGIZER 60GR X 144 PCS | C12: 144 | D12: PCS | E12: DETTOL BODY SOAP | F12: 3048.78 | G12: 439024.32 | H12: 3384.1458 | I12: 487317 | J12: 3332 | K12: 479808 | L12: 3698.52 | M12: 532586.88 | N12: 3332 | O12: 479808 | P12: 3698.52 | Q12: 532586.88 | S12: =IFERROR(VLOOKUP(CONCATENATE(Fix_Mapping[[#This Row],[KODE BARANG]],1),'Form Fix'!$A$6:$F$911,4,0),0) -> 3193502 | T12: =IFERROR(VLOOKUP(CONCATENATE(Fix_Mapping[[#This Row],[KODE BARANG]],2),'Form Fix'!$A$6:$F$911,4,0),0) -> 0 | U12: =IFERROR(VLOOKUP(CONCATENATE(Fix_Mapping[[#This Row],[KODE BARANG]],3),'Form Fix'!$A$6:$F$911,4,0),0) -> 0 | V12: =IFERROR(VLOOKUP(CONCATENATE(Fix_Mapping[[#This Row],[KODE BARANG]],4),'Form Fix'!$A$6:$F$911,4,0),0) -> 0 | W12: =IFERROR(VLOOKUP(CONCATENATE(Fix_Mapping[[#This Row],[KODE BARANG]],5),'Form Fix'!$A$6:$F$911,4,0),0) -> 0
A13: R1021007006010 | B13: RB DETTOL BODY SOAP SKINCARE 60GR X 144 PCS | C13: 144 | D13: PCS | E13: DETTOL BODY SOAP | F13: 3048.78 | G13: 439024.32 | H13: 3384.1458 | I13: 487317 | J13: 3332 | K13: 479808 | L13: 3698.52 | M13: 532586.88 | N13: 3332 | O13: 479808 | P13: 3698.52 | Q13: 532586.88 | S13: =IFERROR(VLOOKUP(CONCATENATE(Fix_Mapping[[#This Row],[KODE BARANG]],1),'Form Fix'!$A$6:$F$911,4,0),0) -> 3193501 | T13: =IFERROR(VLOOKUP(CONCATENATE(Fix_Mapping[[#This Row],[KODE BARANG]],2),'Form Fix'!$A$6:$F$911,4,0),0) -> 3337511 | U13: =IFERROR(VLOOKUP(CONCATENATE(Fix_Mapping[[#This Row],[KODE BARANG]],3),'Form Fix'!$A$6:$F$911,4,0),0) -> 0 | V13: =IFERROR(VLOOKUP(CONCATENATE(Fix_Mapping[[#This Row],[KODE BARANG]],4),'Form Fix'!$A$6:$F$911,4,0),0) -> 0 | W13: =IFERROR(VLOOKUP(CONCATENATE(Fix_Mapping[[#This Row],[KODE BARANG]],5),'Form Fix'!$A$6:$F$911,4,0),0) -> 0
A14: R1021008006010 | B14: RB DETTOL BODY SOAP 3SP LASTING FRESH 60GR X 48 PCS | C14: 48 | D14: PCS | E14: DETTOL BODY SOAP | F14: 8231.7022 | G14: 395121.71 | H14: 9137.1894 | I14: 438585.09 | J14: 8996.3958 | K14: 431827 | L14: 9985.9994 | M14: 479327.97 | O14: 0 | P14: 0 | Q14: 0 | S14: =IFERROR(VLOOKUP(CONCATENATE(Fix_Mapping[[#This Row],[KODE BARANG]],1),'Form Fix'!$A$6:$F$911,4,0),0) -> 3346278 | T14: =IFERROR(VLOOKUP(CONCATENATE(Fix_Mapping[[#This Row],[KODE BARANG]],2),'Form Fix'!$A$6:$F$911,4,0),0) -> 3347342 | U14: =IFERROR(VLOOKUP(CONCATENATE(Fix_Mapping[[#This Row],[KODE BARANG]],3),'Form Fix'!$A$6:$F$911,4,0),0) -> 0 | V14: =IFERROR(VLOOKUP(CONCATENATE(Fix_Mapping[[#This Row],[KODE BARANG]],4),'Form Fix'!$A$6:$F$911,4,0),0) -> 0 | W14: =IFERROR(VLOOKUP(CONCATENATE(Fix_Mapping[[#This Row],[KODE BARANG]],5),'Form Fix'!$A$6:$F$911,4,0),0) -> 0
A15: R1021101006510 | B15: RB DETTOL BODY SOAP 3SP COOL 65GR X 48 PCS | C15: 48 | D15: PCS | E15: DETTOL BODY SOAP | F15: 8232.255 | G15: 395148.24 | H15: 9137.8031 | I15: 438614.55 | J15: 8997 | K15: 431856 | L15: 9986.67 | M15: 479360.16 | N15: 8997 | O15: 431856 | P15: 9986.67 | Q15: 479360.16 | S15: =IFERROR(VLOOKUP(CONCATENATE(Fix_Mapping[[#This Row],[KODE BARANG]],1),'Form Fix'!$A$6:$F$911,4,0),0) -> 3205578 | T15: =IFERROR(VLOOKUP(CONCATENATE(Fix_Mapping[[#This Row],[KODE BARANG]],2),'Form Fix'!$A$6:$F$911,4,0),0) -> 3171290 | U15: =IFERROR(VLOOKUP(CONCATENATE(Fix_Mapping[[#This Row],[KODE BARANG]],3),'Form Fix'!$A$6:$F$911,4,0),0) -> 3166920 | V15: =IFERROR(VLOOKUP(CONCATENATE(Fix_Mapping[[#This Row],[KODE BARANG]],4),'Form Fix'!$A$6:$F$911,4,0),0) -> 3060315 | W15: =IFERROR(VLOOKUP(CONCATENATE(Fix_Mapping[[#This Row],[KODE BARANG]],5),'Form Fix'!$A$6:$F$911,4,0),0) -> 3087442
A16: R1021101010010 | B16: RB DETTOL BODY SOAP 3SP COOL 100GR X 48 PCS | C16: 48 | D16: PCS | E16: DETTOL BODY SOAP | F16: 16012.5 | G16: 768600 | H16: 17773.875 | I16: 853146 | J16: 17500 | K16: 840000 | L16: 19425 | M16: 932400 | N16: 17500 | O16: 840000 | P16: 19425 | Q16: 932400 | S16: =IFERROR(VLOOKUP(CONCATENATE(Fix_Mapping[[#This Row],[KODE BARANG]],1),'Form Fix'!$A$6:$F$911,4,0),0) -> 0 | T16: =IFERROR(VLOOKUP(CONCATENATE(Fix_Mapping[[#This Row],[KODE BARANG]],2),'Form Fix'!$A$6:$F$911,4,0),0) -> 0 | U16: =IFERROR(VLOOKUP(CONCATENATE(Fix_Mapping[[#This Row],[KODE BARANG]],3),'Form Fix'!$A$6:$F$911,4,0),0) -> 0 | V16: =IFERROR(VLOOKUP(CONCATENATE(Fix_Mapping[[#This Row],[KODE BARANG]],4),'Form Fix'!$A$6:$F$911,4,0),0) -> 0 | W16: =IFERROR(VLOOKUP(CONCATENATE(Fix_Mapping[[#This Row],[KODE BARANG]],5),'Form Fix'!$A$6:$F$911,4,0),0) -> 0
A17: R1021101010011 | B17: RB DETTOL BODY SOAP 3SP COOL 100GR X 36 PCS 3+1 | C17: 36 | D17: PCS | E17: DETTOL BODY SOAP | F17: 17593.696 | G17: 633373.06 | H17: 19529.003 | I17: 703044.1 | J17: 19228.083 | K17: 692211 | L17: 21343.173 | M17: 768354.21 | N17: 6409.3656 | O17: 230737.16 | P17: 7114.3958 | Q17: 256118.25 | S17: =IFERROR(VLOOKUP(CONCATENATE(Fix_Mapping[[#This Row],[KODE BARANG]],1),'Form Fix'!$A$6:$F$911,4,0),0) -> 0 | T17: =IFERROR(VLOOKUP(CONCATENATE(Fix_Mapping[[#This Row],[KODE BARANG]],2),'Form Fix'!$A$6:$F$911,4,0),0) -> 0 | U17: =IFERROR(VLOOKUP(CONCATENATE(Fix_Mapping[[#This Row],[KODE BARANG]],3),'Form Fix'!$A$6:$F$911,4,0),0) -> 0 | V17: =IFERROR(VLOOKUP(CONCATENATE(Fix_Mapping[[#This Row],[KODE BARANG]],4),'Form Fix'!$A$6:$F$911,4,0),0) -> 0 | W17: =IFERROR(VLOOKUP(CONCATENATE(Fix_Mapping[[#This Row],[KODE BARANG]],5),'Form Fix'!$A$6:$F$911,4,0),0) -> 0
A18: R1021102010010 | B18: RB DETTOL BODY SOAP 3SP FAMILY PROTECT 100GR X 48 PCS | C18: 48 | D18: PCS | E18: DETTOL BODY SOAP | F18: 16012.5 | G18: 768600 | H18: 17773.875 | I18: 853146 | J18: 17500 | K18: 840000 | L18: 19425 | M18: 932400 | N18: 17500 | O18: 840000 | P18: 19425 | Q18: 932400 | S18: =IFERROR(VLOOKUP(CONCATENATE(Fix_Mapping[[#This Row],[KODE BARANG]],1),'Form Fix'!$A$6:$F$911,4,0),0) -> 0 | T18: =IFERROR(VLOOKUP(CONCATENATE(Fix_Mapping[[#This Row],[KODE BARANG]],2),'Form Fix'!$A$6:$F$911,4,0),0) -> 0 | U18: =IFERROR(VLOOKUP(CONCATENATE(Fix_Mapping[[#This Row],[KODE BARANG]],3),'Form Fix'!$A$6:$F$911,4,0),0) -> 0 | V18: =IFERROR(VLOOKUP(CONCATENATE(Fix_Mapping[[#This Row],[KODE BARANG]],4),'Form Fix'!$A$6:$F$911,4,0),0) -> 0 | W18: =IFERROR(VLOOKUP(CONCATENATE(Fix_Mapping[[#This Row],[KODE BARANG]],5),'Form Fix'!$A$6:$F$911,4,0),0) -> 0
A19: R1021103006510 | B19: RB DETTOL BODY SOAP 3SP FRESH 65GR X 48 PCS | C19: 48 | D19: PCS | E19: DETTOL BODY SOAP | F19: 8232.255 | G19: 395148.24 | H19: 9137.8031 | I19: 438614.55 | J19: 8997 | K19: 431856 | L19: 9986.67 | M19: 479360.16 | N19: 8997 | O19: 431856 | P19: 9986.67 | Q19: 479360.16 | S19: =IFERROR(VLOOKUP(CONCATENATE(Fix_Mapping[[#This Row],[KODE BARANG]],1),'Form Fix'!$A$6:$F$911,4,0),0) -> 0 | T19: =IFERROR(VLOOKUP(CONCATENATE(Fix_Mapping[[#This Row],[KODE BARANG]],2),'Form Fix'!$A$6:$F$911,4,0),0) -> 0 | U19: =IFERROR(VLOOKUP(CONCATENATE(Fix_Mapping[[#This Row],[KODE BARANG]],3),'Form Fix'!$A$6:$F$911,4,0),0) -> 0 | V19: =IFERROR(VLOOKUP(CONCATENATE(Fix_Mapping[[#This Row],[KODE BARANG]],4),'Form Fix'!$A$6:$F$911,4,0),0) -> 0 | W19: =IFERROR(VLOOKUP(CONCATENATE(Fix_Mapping[[#This Row],[KODE BARANG]],5),'Form Fix'!$A$6:$F$911,4,0),0) -> 0
A20: R1021103010010 | B20: RB DETTOL BODY SOAP 3SP FRESH 100GR X 48 PCS | C20: 48 | D20: PCS | E20: DETTOL BODY SOAP | F20: 16012.5 | G20: 768600 | H20: 17773.875 | I20: 853146 | J20: 17500 | K20: 840000 | L20: 19425 | M20: 932400 | N20: 17500 | O20: 840000 | P20: 19425 | Q20: 932400 | S20: =IFERROR(VLOOKUP(CONCATENATE(Fix_Mapping[[#This Row],[KODE BARANG]],1),'Form Fix'!$A$6:$F$911,4,0),0) -> 0 | T20: =IFERROR(VLOOKUP(CONCATENATE(Fix_Mapping[[#This Row],[KODE BARANG]],2),'Form Fix'!$A$6:$F$911,4,0),0) -> 0 | U20: =IFERROR(VLOOKUP(CONCATENATE(Fix_Mapping[[#This Row],[KODE BARANG]],3),'Form Fix'!$A$6:$F$911,4,0),0) -> 0 | V20: =IFERROR(VLOOKUP(CONCATENATE(Fix_Mapping[[#This Row],[KODE BARANG]],4),'Form Fix'!$A$6:$F$911,4,0),0) -> 0 | W20: =IFERROR(VLOOKUP(CONCATENATE(Fix_Mapping[[#This Row],[KODE BARANG]],5),'Form Fix'!$A$6:$F$911,4,0),0) -> 0
A21: R1021103010011 | B21: RB DETTOL BODY SOAP 3SP FRESH 100GR X 36 PCS 3+1 | C21: 36 | D21: PCS | E21: DETTOL BODY SOAP | F21: 17593.696 | G21: 633373.06 | H21: 19529.003 | I21: 703044.1 | J21: 19228.083 | K21: 692211 | L21: 21343.173 | M21: 768354.21 | N21: 6409.3656 | O21: 230737.16 | P21: 7114.3958 | Q21: 256118.25 | S21: =IFERROR(VLOOKUP(CONCATENATE(Fix_Mapping[[#This Row],[KODE BARANG]],1),'Form Fix'!$A$6:$F$911,4,0),0) -> 0 | T21: =IFERROR(VLOOKUP(CONCATENATE(Fix_Mapping[[#This Row],[KODE BARANG]],2),'Form Fix'!$A$6:$F$911,4,0),0) -> 0 | U21: =IFERROR(VLOOKUP(CONCATENATE(Fix_Mapping[[#This Row],[KODE BARANG]],3),'Form Fix'!$A$6:$F$911,4,0),0) -> 0 | V21: =IFERROR(VLOOKUP(CONCATENATE(Fix_Mapping[[#This Row],[KODE BARANG]],4),'Form Fix'!$A$6:$F$911,4,0),0) -> 0 | W21: =IFERROR(VLOOKUP(CONCATENATE(Fix_Mapping[[#This Row],[KODE BARANG]],5),'Form Fix'!$A$6:$F$911,4,0),0) -> 0
A22: R1021104010010 | B22: RB DETTOL BODY SOAP 3SP LASTING 100GR X 48 PCS | C22: 48 | D22: PCS | E22: DETTOL BODY SOAP | F22: 16012.5 | G22: 768600 | H22: 17773.875 | I22: 853146 | J22: 17500 | K22: 840000 | L22: 19425 | M22: 932400 | N22: 17500 | O22: 840000 | P22: 19425 | Q22: 932400 | S22: =IFERROR(VLOOKUP(CONCATENATE(Fix_Mapping[[#This Row],[KODE BARANG]],1),'Form Fix'!$A$6:$F$911,4,0),0) -> 0 | T22: =IFERROR(VLOOKUP(CONCATENATE(Fix_Mapping[[#This Row],[KODE BARANG]],2),'Form Fix'!$A$6:$F$911,4,0),0) -> 0 | U22: =IFERROR(VLOOKUP(CONCATENATE(Fix_Mapping[[#This Row],[KODE BARANG]],3),'Form Fix'!$A$6:$F$911,4,0),0) -> 0 | V22: =IFERROR(VLOOKUP(CONCATENATE(Fix_Mapping[[#This Row],[KODE BARANG]],4),'Form Fix'!$A$6:$F$911,4,0),0) -> 0 | W22: =IFERROR(VLOOKUP(CONCATENATE(Fix_Mapping[[#This Row],[KODE BARANG]],5),'Form Fix'!$A$6:$F$911,4,0),0) -> 0
A23: R1021104010011 | B23: RB DETTOL BODY SOAP 3SP LASTING 100GR X 36 PCS 3+1 | C23: 36 | D23: PCS | E23: DETTOL BODY SOAP | F23: 17593.696 | G23: 633373.06 | H23: 19529.003 | I23: 703044.1 | J23: 19228.083 | K23: 692211 | L23: 21343.173 | M23: 768354.21 | N23: 6409.3656 | O23: 230737.16 | P23: 7114.3958 | Q23: 256118.25 | S23: =IFERROR(VLOOKUP(CONCATENATE(Fix_Mapping[[#This Row],[KODE BARANG]],1),'Form Fix'!$A$6:$F$911,4,0),0) -> 0 | T23: =IFERROR(VLOOKUP(CONCATENATE(Fix_Mapping[[#This Row],[KODE BARANG]],2),'Form Fix'!$A$6:$F$911,4,0),0) -> 0 | U23: =IFERROR(VLOOKUP(CONCATENATE(Fix_Mapping[[#This Row],[KODE BARANG]],3),'Form Fix'!$A$6:$F$911,4,0),0) -> 0 | V23: =IFERROR(VLOOKUP(CONCATENATE(Fix_Mapping[[#This Row],[KODE BARANG]],4),'Form Fix'!$A$6:$F$911,4,0),0) -> 0 | W23: =IFERROR(VLOOKUP(CONCATENATE(Fix_Mapping[[#This Row],[KODE BARANG]],5),'Form Fix'!$A$6:$F$911,4,0),0) -> 0
A24: R1021105006010 | B24: RB DETTOL BODY SOAP 3SP ORIGINAL 60GR X 48 PCS | C24: 48 | D24: PCS | E24: DETTOL BODY SOAP | F24: 8232.255 | G24: 395148.24 | H24: 9137.8031 | I24: 438614.55 | J24: 8997 | K24: 431856 | L24: 9986.67 | M24: 479360.16 | N24: 8997 | O24: 431856 | P24: 9986.67 | Q24: 479360.16 | S24: =IFERROR(VLOOKUP(CONCATENATE(Fix_Mapping[[#This Row],[KODE BARANG]],1),'Form Fix'!$A$6:$F$911,4,0),0) -> 0 | T24: =IFERROR(VLOOKUP(CONCATENATE(Fix_Mapping[[#This Row],[KODE BARANG]],2),'Form Fix'!$A$6:$F$911,4,0),0) -> 0 | U24: =IFERROR(VLOOKUP(CONCATENATE(Fix_Mapping[[#This Row],[KODE BARANG]],3),'Form Fix'!$A$6:$F$911,4,0),0) -> 0 | V24: =IFERROR(VLOOKUP(CONCATENATE(Fix_Mapping[[#This Row],[KODE BARANG]],4),'Form Fix'!$A$6:$F$911,4,0),0) -> 0 | W24: =IFERROR(VLOOKUP(CONCATENATE(Fix_Mapping[[#This Row],[KODE BARANG]],5),'Form Fix'!$A$6:$F$911,4,0),0) -> 0
A25: R1021105010010 | B25: RB DETTOL BODY SOAP 3SP ORIGINAL 100GR X 48 PCS | C25: 48 | D25: PCS | E25: DETTOL BODY SOAP | F25: 16012.5 | G25: 768600 | H25: 17773.875 | I25: 853146 | J25: 17500 | K25: 840000 | L25: 19425 | M25: 932400 | N25: 17500 | O25: 840000 | P25: 19425 | Q25: 932400 | S25: =IFERROR(VLOOKUP(CONCATENATE(Fix_Mapping[[#This Row],[KODE BARANG]],1),'Form Fix'!$A$6:$F$911,4,0),0) -> 0 | T25: =IFERROR(VLOOKUP(CONCATENATE(Fix_Mapping[[#This Row],[KODE BARANG]],2),'Form Fix'!$A$6:$F$911,4,0),0) -> 0 | U25: =IFERROR(VLOOKUP(CONCATENATE(Fix_Mapping[[#This Row],[KODE BARANG]],3),'Form Fix'!$A$6:$F$911,4,0),0) -> 0 | V25: =IFERROR(VLOOKUP(CONCATENATE(Fix_Mapping[[#This Row],[KODE BARANG]],4),'Form Fix'!$A$6:$F$911,4,0),0) -> 0 | W25: =IFERROR(VLOOKUP(CONCATENATE(Fix_Mapping[[#This Row],[KODE BARANG]],5),'Form Fix'!$A$6:$F$911,4,0),0) -> 0
A26: R1021105010011 | B26: RB DETTOL BODY SOAP 3SP ORIGINAL 100GR X 36 PCS 3+1 | C26: 36 | D26: PCS | E26: DETTOL BODY SOAP | F26: 17593.696 | G26: 633373.06 | H26: 19529.003 | I26: 703044.1 | J26: 19228.083 | K26: 692211 | L26: 21343.173 | M26: 768354.21 | N26: 6409.3656 | O26: 230737.16 | P26: 7114.3958 | Q26: 256118.25 | S26: =IFERROR(VLOOKUP(CONCATENATE(Fix_Mapping[[#This Row],[KODE BARANG]],1),'Form Fix'!$A$6:$F$911,4,0),0) -> 0 | T26: =IFERROR(VLOOKUP(CONCATENATE(Fix_Mapping[[#This Row],[KODE BARANG]],2),'Form Fix'!$A$6:$F$911,4,0),0) -> 0 | U26: =IFERROR(VLOOKUP(CONCATENATE(Fix_Mapping[[#This Row],[KODE BARANG]],3),'Form Fix'!$A$6:$F$911,4,0),0) -> 0 | V26: =IFERROR(VLOOKUP(CONCATENATE(Fix_Mapping[[#This Row],[KODE BARANG]],4),'Form Fix'!$A$6:$F$911,4,0),0) -> 0 | W26: =IFERROR(VLOOKUP(CONCATENATE(Fix_Mapping[[#This Row],[KODE BARANG]],5),'Form Fix'!$A$6:$F$911,4,0),0) -> 0
A27: R1021106006010 | B27: RB DETTOL BODY SOAP 3SP RE-ENERGIZER 60GR X 48 PCS | C27: 48 | D27: PCS | E27: DETTOL BODY SOAP | F27: 8231.7022 | G27: 395121.71 | H27: 9137.1894 | I27: 438585.09 | J27: 8996.3958 | K27: 431827 | L27: 9985.9994 | M27: 479327.97 | O27: 0 | P27: 0 | Q27: 0 | S27: =IFERROR(VLOOKUP(CONCATENATE(Fix_Mapping[[#This Row],[KODE BARANG]],1),'Form Fix'!$A$6:$F$911,4,0),0) -> 0 | T27: =IFERROR(VLOOKUP(CONCATENATE(Fix_Mapping[[#This Row],[KODE BARANG]],2),'Form Fix'!$A$6:$F$911,4,0),0) -> 0 | U27: =IFERROR(VLOOKUP(CONCATENATE(Fix_Mapping[[#This Row],[KODE BARANG]],3),'Form Fix'!$A$6:$F$911,4,0),0) -> 0 | V27: =IFERROR(VLOOKUP(CONCATENATE(Fix_Mapping[[#This Row],[KODE BARANG]],4),'Form Fix'!$A$6:$F$911,4,0),0) -> 0 | W27: =IFERROR(VLOOKUP(CONCATENATE(Fix_Mapping[[#This Row],[KODE BARANG]],5),'Form Fix'!$A$6:$F$911,4,0),0) -> 0
A28: R1021106010010 | B28: RB DETTOL BODY SOAP 3SP RE-ENERGIZER 100GR X 48 PCS | C28: 48 | D28: PCS | E28: DETTOL BODY SOAP | F28: 16012.5 | G28: 768600 | H28: 17773.875 | I28: 853146 | J28: 17500 | K28: 840000 | L28: 19425 | M28: 932400 | N28: 17500 | O28: 840000 | P28: 19425 | Q28: 932400 | S28: =IFERROR(VLOOKUP(CONCATENATE(Fix_Mapping[[#This Row],[KODE BARANG]],1),'Form Fix'!$A$6:$F$911,4,0),0) -> 0 | T28: =IFERROR(VLOOKUP(CONCATENATE(Fix_Mapping[[#This Row],[KODE BARANG]],2),'Form Fix'!$A$6:$F$911,4,0),0) -> 0 | U28: =IFERROR(VLOOKUP(CONCATENATE(Fix_Mapping[[#This Row],[KODE BARANG]],3),'Form Fix'!$A$6:$F$911,4,0),0) -> 0 | V28: =IFERROR(VLOOKUP(CONCATENATE(Fix_Mapping[[#This Row],[KODE BARANG]],4),'Form Fix'!$A$6:$F$911,4,0),0) -> 0 | W28: =IFERROR(VLOOKUP(CONCATENATE(Fix_Mapping[[#This Row],[KODE BARANG]],5),'Form Fix'!$A$6:$F$911,4,0),0) -> 0
A29: R1021107006010 | B29: RB DETTOL BODY SOAP 3SP SKINCARE 60GR X 48 PCS | C29: 48 | D29: PCS | E29: DETTOL BODY SOAP | F29: 8231.7022 | G29: 395121.71 | H29: 9137.1894 | I29: 438585.09 | J29: 8996.3958 | K29: 431827 | L29: 9985.9994 | M29: 479327.97 | O29: 0 | P29: 0 | Q29: 0 | S29: =IFERROR(VLOOKUP(CONCATENATE(Fix_Mapping[[#This Row],[KODE BARANG]],1),'Form Fix'!$A$6:$F$911,4,0),0) -> 0 | T29: =IFERROR(VLOOKUP(CONCATENATE(Fix_Mapping[[#This Row],[KODE BARANG]],2),'Form Fix'!$A$6:$F$911,4,0),0) -> 0 | U29: =IFERROR(VLOOKUP(CONCATENATE(Fix_Mapping[[#This Row],[KODE BARANG]],3),'Form Fix'!$A$6:$F$911,4,0),0) -> 0 | V29: =IFERROR(VLOOKUP(CONCATENATE(Fix_Mapping[[#This Row],[KODE BARANG]],4),'Form Fix'!$A$6:$F$911,4,0),0) -> 0 | W29: =IFERROR(VLOOKUP(CONCATENATE(Fix_Mapping[[#This Row],[KODE BARANG]],5),'Form Fix'!$A$6:$F$911,4,0),0) -> 0
A30: R1021107010010 | B30: RB DETTOL BODY SOAP 3SP SKINCARE 100GR X 48 PCS | C30: 48 | D30: PCS | E30: DETTOL BODY SOAP | F30: 16012.5 | G30: 768600 | H30: 17773.875 | I30: 853146 | J30: 17500 | K30: 840000 | L30: 19425 | M30: 932400 | N30: 17500 | O30: 840000 | P30: 19425 | Q30: 932400 | S30: =IFERROR(VLOOKUP(CONCATENATE(Fix_Mapping[[#This Row],[KODE BARANG]],1),'Form Fix'!$A$6:$F$911,4,0),0) -> 0 | T30: =IFERROR(VLOOKUP(CONCATENATE(Fix_Mapping[[#This Row],[KODE BARANG]],2),'Form Fix'!$A$6:$F$911,4,0),0) -> 0 | U30: =IFERROR(VLOOKUP(CONCATENATE(Fix_Mapping[[#This Row],[KODE BARANG]],3),'Form Fix'!$A$6:$F$911,4,0),0) -> 0 | V30: =IFERROR(VLOOKUP(CONCATENATE(Fix_Mapping[[#This Row],[KODE BARANG]],4),'Form Fix'!$A$6:$F$911,4,0),0) -> 0 | W30: =IFERROR(VLOOKUP(CONCATENATE(Fix_Mapping[[#This Row],[KODE BARANG]],5),'Form Fix'!$A$6:$F$911,4,0),0) -> 0
A31: R1021107010011 | B31: RB DETTOL BODY SOAP 3SP SKINCARE 100GR X 36 PCS 3+1 | C31: 36 | D31: PCS | E31: DETTOL BODY SOAP | F31: 17593.696 | G31: 633373.06 | H31: 19529.003 | I31: 703044.1 | J31: 19228.083 | K31: 692211 | L31: 21343.173 | M31: 768354.21 | N31: 17500 | O31: 630000 | P31: 19425 | Q31: 699300 | S31: =IFERROR(VLOOKUP(CONCATENATE(Fix_Mapping[[#This Row],[KODE BARANG]],1),'Form Fix'!$A$6:$F$911,4,0),0) -> 0 | T31: =IFERROR(VLOOKUP(CONCATENATE(Fix_Mapping[[#This Row],[KODE BARANG]],2),'Form Fix'!$A$6:$F$911,4,0),0) -> 0 | U31: =IFERROR(VLOOKUP(CONCATENATE(Fix_Mapping[[#This Row],[KODE BARANG]],3),'Form Fix'!$A$6:$F$911,4,0),0) -> 0 | V31: =IFERROR(VLOOKUP(CONCATENATE(Fix_Mapping[[#This Row],[KODE BARANG]],4),'Form Fix'!$A$6:$F$911,4,0),0) -> 0 | W31: =IFERROR(VLOOKUP(CONCATENATE(Fix_Mapping[[#This Row],[KODE BARANG]],5),'Form Fix'!$A$6:$F$911,4,0),0) -> 0
A32: R1021109010011 | B32: RB DETTOL BODY SOAP 3SP SKINCARE 100GR X 36 PCS 3+1 | C32: 36 | D32: PCS | E32: DETTOL BODY SOAP | F32: 17593.696 | G32: 633373.06 | H32: 19529.003 | I32: 703044.1 | J32: 19228.083 | K32: 692211 | L32: 21343.173 | M32: 768354.21 | N32: 6409.3656 | O32: 230737.16 | P32: 7114.3958 | Q32: 256118.25 | S32: =IFERROR(VLOOKUP(CONCATENATE(Fix_Mapping[[#This Row],[KODE BARANG]],1),'Form Fix'!$A$6:$F$911,4,0),0) -> 0 | T32: =IFERROR(VLOOKUP(CONCATENATE(Fix_Mapping[[#This Row],[KODE BARANG]],2),'Form Fix'!$A$6:$F$911,4,0),0) -> 0 | U32: =IFERROR(VLOOKUP(CONCATENATE(Fix_Mapping[[#This Row],[KODE BARANG]],3),'Form Fix'!$A$6:$F$911,4,0),0) -> 0 | V32: =IFERROR(VLOOKUP(CONCATENATE(Fix_Mapping[[#This Row],[KODE BARANG]],4),'Form Fix'!$A$6:$F$911,4,0),0) -> 0 | W32: =IFERROR(VLOOKUP(CONCATENATE(Fix_Mapping[[#This Row],[KODE BARANG]],5),'Form Fix'!$A$6:$F$911,4,0),0) -> 0
A33: R1021201010010 | B33: RB DETTOL BODY SOAP HK ALOE VERA 100GR X 144 PCS | C33: 144 | D33: PCS | E33: DETTOL BODY SOAP | F33: 5864.5695 | G33: 844498.01 | H33: 6509.6722 | I33: 937392.79 | J33: 6409.3656 | K33: 922948.65 | L33: 7114.3958 | M33: 1024473 | N33: 6409.3656 | O33: 922948.65 | P33: 7114.3958 | Q33: 1024473 | S33: =IFERROR(VLOOKUP(CONCATENATE(Fix_Mapping[[#This Row],[KODE BARANG]],1),'Form Fix'!$A$6:$F$911,4,0),0) -> 0 | T33: =IFERROR(VLOOKUP(CONCATENATE(Fix_Mapping[[#This Row],[KODE BARANG]],2),'Form Fix'!$A$6:$F$911,4,0),0) -> 0 | U33: =IFERROR(VLOOKUP(CONCATENATE(Fix_Mapping[[#This Row],[KODE BARANG]],3),'Form Fix'!$A$6:$F$911,4,0),0) -> 0 | V33: =IFERROR(VLOOKUP(CONCATENATE(Fix_Mapping[[#This Row],[KODE BARANG]],4),'Form Fix'!$A$6:$F$911,4,0),0) -> 0 | W33: =IFERROR(VLOOKUP(CONCATENATE(Fix_Mapping[[#This Row],[KODE BARANG]],5),'Form Fix'!$A$6:$F$911,4,0),0) -> 0
A34: R1021201010011 | B34: RB DETTOL BODY SOAP HK ALOE VERA 100GR X 36 PCS 3+1 | C34: 36 | D34: PCS | E34: DETTOL BODY SOAP | F34: 17593.696 | G34: 633373.06 | H34: 19529.003 | I34: 703044.1 | J34: 19228.083 | K34: 692211 | L34: 21343.173 | M34: 768354.21 | N34: 6409.3656 | O34: 230737.16 | P34: 7114.3958 | Q34: 256118.25 | S34: =IFERROR(VLOOKUP(CONCATENATE(Fix_Mapping[[#This Row],[KODE BARANG]],1),'Form Fix'!$A$6:$F$911,4,0),0) -> 0 | T34: =IFERROR(VLOOKUP(CONCATENATE(Fix_Mapping[[#This Row],[KODE BARANG]],2),'Form Fix'!$A$6:$F$911,4,0),0) -> 0 | U34: =IFERROR(VLOOKUP(CONCATENATE(Fix_Mapping[[#This Row],[KODE BARANG]],3),'Form Fix'!$A$6:$F$911,4,0),0) -> 0 | V34: =IFERROR(VLOOKUP(CONCATENATE(Fix_Mapping[[#This Row],[KODE BARANG]],4),'Form Fix'!$A$6:$F$911,4,0),0) -> 0 | W34: =IFERROR(VLOOKUP(CONCATENATE(Fix_Mapping[[#This Row],[KODE BARANG]],5),'Form Fix'!$A$6:$F$911,4,0),0) -> 0
A35: R1021202010010 | B35: RB DETTOL BODY SOAP HK COOL 100GR X 144 PCS | C35: 144 | D35: PCS | E35: DETTOL BODY SOAP | F35: 5864.5695 | G35: 844498.01 | H35: 6509.6722 | I35: 937392.79 | J35: 6409.3656 | K35: 922948.65 | L35: 7114.3958 | M35: 1024473 | N35: 6409.3656 | O35: 922948.65 | P35: 7114.3958 | Q35: 1024473 | S35: =IFERROR(VLOOKUP(CONCATENATE(Fix_Mapping[[#This Row],[KODE BARANG]],1),'Form Fix'!$A$6:$F$911,4,0),0) -> 0 | T35: =IFERROR(VLOOKUP(CONCATENATE(Fix_Mapping[[#This Row],[KODE BARANG]],2),'Form Fix'!$A$6:$F$911,4,0),0) -> 0 | U35: =IFERROR(VLOOKUP(CONCATENATE(Fix_Mapping[[#This Row],[KODE BARANG]],3),'Form Fix'!$A$6:$F$911,4,0),0) -> 0 | V35: =IFERROR(VLOOKUP(CONCATENATE(Fix_Mapping[[#This Row],[KODE BARANG]],4),'Form Fix'!$A$6:$F$911,4,0),0) -> 0 | W35: =IFERROR(VLOOKUP(CONCATENATE(Fix_Mapping[[#This Row],[KODE BARANG]],5),'Form Fix'!$A$6:$F$911,4,0),0) -> 0
A36: R1021203010010 | B36: RB DETTOL BODY SOAP HK FRESH 100GR X 144 PCS | C36: 144 | D36: PCS | E36: DETTOL BODY SOAP | F36: 5864.5695 | G36: 844498.01 | H36: 6509.6722 | I36: 937392.79 | J36: 6409.3656 | K36: 922948.65 | L36: 7114.3958 | M36: 1024473 | N36: 6409.3656 | O36: 922948.65 | P36: 7114.3958 | Q36: 1024473 | S36: =IFERROR(VLOOKUP(CONCATENATE(Fix_Mapping[[#This Row],[KODE BARANG]],1),'Form Fix'!$A$6:$F$911,4,0),0) -> 0 | T36: =IFERROR(VLOOKUP(CONCATENATE(Fix_Mapping[[#This Row],[KODE BARANG]],2),'Form Fix'!$A$6:$F$911,4,0),0) -> 0 | U36: =IFERROR(VLOOKUP(CONCATENATE(Fix_Mapping[[#This Row],[KODE BARANG]],3),'Form Fix'!$A$6:$F$911,4,0),0) -> 0 | V36: =IFERROR(VLOOKUP(CONCATENATE(Fix_Mapping[[#This Row],[KODE BARANG]],4),'Form Fix'!$A$6:$F$911,4,0),0) -> 0 | W36: =IFERROR(VLOOKUP(CONCATENATE(Fix_Mapping[[#This Row],[KODE BARANG]],5),'Form Fix'!$A$6:$F$911,4,0),0) -> 0
A37: R1021204010010 | B37: RB DETTOL BODY SOAP HK INVIGORATE 100GR X 144 PCS | C37: 144 | D37: PCS | E37: DETTOL BODY SOAP | F37: 5864.5695 | G37: 844498.01 | H37: 6509.6722 | I37: 937392.79 | J37: 6409.3656 | K37: 922948.65 | L37: 7114.3958 | M37: 1024473 | N37: 6409.3656 | O37: 922948.65 | P37: 7114.3958 | Q37: 1024473 | S37: =IFERROR(VLOOKUP(CONCATENATE(Fix_Mapping[[#This Row],[KODE BARANG]],1),'Form Fix'!$A$6:$F$911,4,0),0) -> 0 | T37: =IFERROR(VLOOKUP(CONCATENATE(Fix_Mapping[[#This Row],[KODE BARANG]],2),'Form Fix'!$A$6:$F$911,4,0),0) -> 0 | U37: =IFERROR(VLOOKUP(CONCATENATE(Fix_Mapping[[#This Row],[KODE BARANG]],3),'Form Fix'!$A$6:$F$911,4,0),0) -> 0 | V37: =IFERROR(VLOOKUP(CONCATENATE(Fix_Mapping[[#This Row],[KODE BARANG]],4),'Form Fix'!$A$6:$F$911,4,0),0) -> 0 | W37: =IFERROR(VLOOKUP(CONCATENATE(Fix_Mapping[[#This Row],[KODE BARANG]],5),'Form Fix'!$A$6:$F$911,4,0),0) -> 0
A38: R1021204010011 | B38: RB DETTOL BODY SOAP HK INVIGORATE 100GR X 36 PCS 3+1 | C38: 36 | D38: PCS | E38: DETTOL BODY SOAP | F38: 17593.696 | G38: 633373.06 | H38: 19529.003 | I38: 703044.1 | J38: 19228.083 | K38: 692211 | L38: 21343.173 | M38: 768354.21 | N38: 6409.3656 | O38: 230737.16 | P38: 7114.3958 | Q38: 256118.25 | S38: =IFERROR(VLOOKUP(CONCATENATE(Fix_Mapping[[#This Row],[KODE BARANG]],1),'Form Fix'!$A$6:$F$911,4,0),0) -> 0 | T38: =IFERROR(VLOOKUP(CONCATENATE(Fix_Mapping[[#This Row],[KODE BARANG]],2),'Form Fix'!$A$6:$F$911,4,0),0) -> 0 | U38: =IFERROR(VLOOKUP(CONCATENATE(Fix_Mapping[[#This Row],[KODE BARANG]],3),'Form Fix'!$A$6:$F$911,4,0),0) -> 0 | V38: =IFERROR(VLOOKUP(CONCATENATE(Fix_Mapping[[#This Row],[KODE BARANG]],4),'Form Fix'!$A$6:$F$911,4,0),0) -> 0 | W38: =IFERROR(VLOOKUP(CONCATENATE(Fix_Mapping[[#This Row],[KODE BARANG]],5),'Form Fix'!$A$6:$F$911,4,0),0) -> 0
A39: R1021205010010 | B39: RB DETTOL BODY SOAP HK LASTING 100GR X 144 PCS | C39: 144 | D39: PCS | E39: DETTOL BODY SOAP | F39: 5864.5695 | G39: 844498.01 | H39: 6509.6722 | I39: 937392.79 | J39: 6409.3656 | K39: 922948.65 | L39: 7114.3958 | M39: 1024473 | N39: 6409.3656 | O39: 922948.65 | P39: 7114.3958 | Q39: 1024473 | S39: =IFERROR(VLOOKUP(CONCATENATE(Fix_Mapping[[#This Row],[KODE BARANG]],1),'Form Fix'!$A$6:$F$911,4,0),0) -> 0 | T39: =IFERROR(VLOOKUP(CONCATENATE(Fix_Mapping[[#This Row],[KODE BARANG]],2),'Form Fix'!$A$6:$F$911,4,0),0) -> 0 | U39: =IFERROR(VLOOKUP(CONCATENATE(Fix_Mapping[[#This Row],[KODE BARANG]],3),'Form Fix'!$A$6:$F$911,4,0),0) -> 0 | V39: =IFERROR(VLOOKUP(CONCATENATE(Fix_Mapping[[#This Row],[KODE BARANG]],4),'Form Fix'!$A$6:$F$911,4,0),0) -> 0 | W39: =IFERROR(VLOOKUP(CONCATENATE(Fix_Mapping[[#This Row],[KODE BARANG]],5),'Form Fix'!$A$6:$F$911,4,0),0) -> 0
A40: R1021205010011 | B40: RB DETTOL BODY SOAP HK LASTING 100GR X 36 PCS 3+1 | C40: 36 | D40: PCS | E40: DETTOL BODY SOAP | F40: 17593.696 | G40: 633373.06 | H40: 19529.003 | I40: 703044.1 | J40: 19228.083 | K40: 692211 | L40: 21343.173 | M40: 768354.21 | N40: 6409.3656 | O40: 230737.16 | P40: 7114.3958 | Q40: 256118.25 | S40: =IFERROR(VLOOKUP(CONCATENATE(Fix_Mapping[[#This Row],[KODE BARANG]],1),'Form Fix'!$A$6:$F$911,4,0),0) -> 0 | T40: =IFERROR(VLOOKUP(CONCATENATE(Fix_Mapping[[#This Row],[KODE BARANG]],2),'Form Fix'!$A$6:$F$911,4,0),0) -> 0 | U40: =IFERROR(VLOOKUP(CONCATENATE(Fix_Mapping[[#This Row],[KODE BARANG]],3),'Form Fix'!$A$6:$F$911,4,0),0) -> 0 | V40: =IFERROR(VLOOKUP(CONCATENATE(Fix_Mapping[[#This Row],[KODE BARANG]],4),'Form Fix'!$A$6:$F$911,4,0),0) -> 0 | W40: =IFERROR(VLOOKUP(CONCATENATE(Fix_Mapping[[#This Row],[KODE BARANG]],5),'Form Fix'!$A$6:$F$911,4,0),0) -> 0
A41: R1021206010010 | B41: RB DETTOL BODY SOAP HK ORIGINAL 100GR X 144 PCS | C41: 144 | D41: PCS | E41: DETTOL BODY SOAP | F41: 5864.5695 | G41: 844498.01 | H41: 6509.6722 | I41: 937392.79 | J41: 6409.3656 | K41: 922948.65 | L41: 7114.3958 | M41: 1024473 | N41: 6409.3656 | O41: 922948.65 | P41: 7114.3958 | Q41: 1024473 | S41: =IFERROR(VLOOKUP(CONCATENATE(Fix_Mapping[[#This Row],[KODE BARANG]],1),'Form Fix'!$A$6:$F$911,4,0),0) -> 0 | T41: =IFERROR(VLOOKUP(CONCATENATE(Fix_Mapping[[#This Row],[KODE BARANG]],2),'Form Fix'!$A$6:$F$911,4,0),0) -> 0 | U41: =IFERROR(VLOOKUP(CONCATENATE(Fix_Mapping[[#This Row],[KODE BARANG]],3),'Form Fix'!$A$6:$F$911,4,0),0) -> 0 | V41: =IFERROR(VLOOKUP(CONCATENATE(Fix_Mapping[[#This Row],[KODE BARANG]],4),'Form Fix'!$A$6:$F$911,4,0),0) -> 0 | W41: =IFERROR(VLOOKUP(CONCATENATE(Fix_Mapping[[#This Row],[KODE BARANG]],5),'Form Fix'!$A$6:$F$911,4,0),0) -> 0
A42: R1021206010010B | B42: RB B> DETTOL BODY SOAP HK ORIGINAL 100GR X 144 PCS | C42: 144 | D42: PCS | E42: DETTOL BODY SOAP | F42: 5864.5736 | G42: 844498.59 | H42: 6509.6766 | I42: 937393.44 | J42: 6409.37 | K42: 922949.28 | L42: 7114.4007 | M42: 1024473.7 | O42: 0 | P42: 0 | Q42: 0 | S42: =IFERROR(VLOOKUP(CONCATENATE(Fix_Mapping[[#This Row],[KODE BARANG]],1),'Form Fix'!$A$6:$F$911,4,0),0) -> 0 | T42: =IFERROR(VLOOKUP(CONCATENATE(Fix_Mapping[[#This Row],[KODE BARANG]],2),'Form Fix'!$A$6:$F$911,4,0),0) -> 0 | U42: =IFERROR(VLOOKUP(CONCATENATE(Fix_Mapping[[#This Row],[KODE BARANG]],3),'Form Fix'!$A$6:$F$911,4,0),0) -> 0 | V42: =IFERROR(VLOOKUP(CONCATENATE(Fix_Mapping[[#This Row],[KODE BARANG]],4),'Form Fix'!$A$6:$F$911,4,0),0) -> 0 | W42: =IFERROR(VLOOKUP(CONCATENATE(Fix_Mapping[[#This Row],[KODE BARANG]],5),'Form Fix'!$A$6:$F$911,4,0),0) -> 0
A43: R1021207010010 | B43: RB DETTOL BODY SOAP HK RE-ENERGIZER 100GR X 144 PCS | C43: 144 | D43: PCS | E43: DETTOL BODY SOAP | F43: 5864.5695 | G43: 844498.01 | H43: 6509.6722 | I43: 937392.79 | J43: 6409.3656 | K43: 922948.65 | L43: 7114.3958 | M43: 1024473 | N43: 6409.3656 | O43: 922948.65 | P43: 7114.3958 | Q43: 1024473 | S43: =IFERROR(VLOOKUP(CONCATENATE(Fix_Mapping[[#This Row],[KODE BARANG]],1),'Form Fix'!$A$6:$F$911,4,0),0) -> 0 | T43: =IFERROR(VLOOKUP(CONCATENATE(Fix_Mapping[[#This Row],[KODE BARANG]],2),'Form Fix'!$A$6:$F$911,4,0),0) -> 0 | U43: =IFERROR(VLOOKUP(CONCATENATE(Fix_Mapping[[#This Row],[KODE BARANG]],3),'Form Fix'!$A$6:$F$911,4,0),0) -> 0 | V43: =IFERROR(VLOOKUP(CONCATENATE(Fix_Mapping[[#This Row],[KODE BARANG]],4),'Form Fix'!$A$6:$F$911,4,0),0) -> 0 | W43: =IFERROR(VLOOKUP(CONCATENATE(Fix_Mapping[[#This Row],[KODE BARANG]],5),'Form Fix'!$A$6:$F$911,4,0),0) -> 0
A44: R1021207010011 | B44: RB DETTOL BODY SOAP HK RE-ENERGIZER 100GR X 36 PCS 3+1 | C44: 36 | D44: PCS | E44: DETTOL BODY SOAP | F44: 17593.696 | G44: 633373.06 | H44: 19529.003 | I44: 703044.1 | J44: 19228.083 | K44: 692211 | L44: 21343.173 | M44: 768354.21 | N44: 6409.3656 | O44: 230737.16 | P44: 7114.3958 | Q44: 256118.25 | S44: =IFERROR(VLOOKUP(CONCATENATE(Fix_Mapping[[#This Row],[KODE BARANG]],1),'Form Fix'!$A$6:$F$911,4,0),0) -> 0 | T44: =IFERROR(VLOOKUP(CONCATENATE(Fix_Mapping[[#This Row],[KODE BARANG]],2),'Form Fix'!$A$6:$F$911,4,0),0) -> 0 | U44: =IFERROR(VLOOKUP(CONCATENATE(Fix_Mapping[[#This Row],[KODE BARANG]],3),'Form Fix'!$A$6:$F$911,4,0),0) -> 0 | V44: =IFERROR(VLOOKUP(CONCATENATE(Fix_Mapping[[#This Row],[KODE BARANG]],4),'Form Fix'!$A$6:$F$911,4,0),0) -> 0 | W44: =IFERROR(VLOOKUP(CONCATENATE(Fix_Mapping[[#This Row],[KODE BARANG]],5),'Form Fix'!$A$6:$F$911,4,0),0) -> 0
A45: R1021208010010 | B45: RB DETTOL BODY SOAP HK SENSITIVE 100GR X 144 PCS | C45: 144 | D45: PCS | E45: DETTOL BODY SOAP | F45: 5864.5695 | G45: 844498.01 | H45: 6509.6722 | I45: 937392.79 | J45: 6409.3656 | K45: 922948.65 | L45: 7114.3958 | M45: 1024473 | N45: 6409.3656 | O45: 922948.65 | P45: 7114.3958 | Q45: 1024473 | S45: =IFERROR(VLOOKUP(CONCATENATE(Fix_Mapping[[#This Row],[KODE BARANG]],1),'Form Fix'!$A$6:$F$911,4,0),0) -> 0 | T45: =IFERROR(VLOOKUP(CONCATENATE(Fix_Mapping[[#This Row],[KODE BARANG]],2),'Form Fix'!$A$6:$F$911,4,0),0) -> 0 | U45: =IFERROR(VLOOKUP(CONCATENATE(Fix_Mapping[[#This Row],[KODE BARANG]],3),'Form Fix'!$A$6:$F$911,4,0),0) -> 0 | V45: =IFERROR(VLOOKUP(CONCATENATE(Fix_Mapping[[#This Row],[KODE BARANG]],4),'Form Fix'!$A$6:$F$911,4,0),0) -> 0 | W45: =IFERROR(VLOOKUP(CONCATENATE(Fix_Mapping[[#This Row],[KODE BARANG]],5),'Form Fix'!$A$6:$F$911,4,0),0) -> 0
A46: R1021208010011 | B46: RB DETTOL BODY SOAP HK SENSITIVE 100GR X 36 PCS 3+1 | C46: 36 | D46: PCS | E46: DETTOL BODY SOAP | F46: 17593.696 | G46: 633373.06 | H46: 19529.003 | I46: 703044.1 | J46: 19228.083 | K46: 692211 | L46: 21343.173 | M46: 768354.21 | N46: 6409.3656 | O46: 230737.16 | P46: 7114.3958 | Q46: 256118.25 | S46: =IFERROR(VLOOKUP(CONCATENATE(Fix_Mapping[[#This Row],[KODE BARANG]],1),'Form Fix'!$A$6:$F$911,4,0),0) -> 0 | T46: =IFERROR(VLOOKUP(CONCATENATE(Fix_Mapping[[#This Row],[KODE BARANG]],2),'Form Fix'!$A$6:$F$911,4,0),0) -> 0 | U46: =IFERROR(VLOOKUP(CONCATENATE(Fix_Mapping[[#This Row],[KODE BARANG]],3),'Form Fix'!$A$6:$F$911,4,0),0) -> 0 | V46: =IFERROR(VLOOKUP(CONCATENATE(Fix_Mapping[[#This Row],[KODE BARANG]],4),'Form Fix'!$A$6:$F$911,4,0),0) -> 0 | W46: =IFERROR(VLOOKUP(CONCATENATE(Fix_Mapping[[#This Row],[KODE BARANG]],5),'Form Fix'!$A$6:$F$911,4,0),0) -> 0
A47: R1021209010010 | B47: RB DETTOL BODY SOAP HK SKINCARE 100GR X 144 PCS | C47: 144 | D47: PCS | E47: DETTOL BODY SOAP | F47: 5864.5695 | G47: 844498.01 | H47: 6509.6722 | I47: 937392.79 | J47: 6409.3656 | K47: 922948.65 | L47: 7114.3958 | M47: 1024473 | N47: 6409.3656 | O47: 922948.65 | P47: 7114.3958 | Q47: 1024473 | S47: =IFERROR(VLOOKUP(CONCATENATE(Fix_Mapping[[#This Row],[KODE BARANG]],1),'Form Fix'!$A$6:$F$911,4,0),0) -> 0 | T47: =IFERROR(VLOOKUP(CONCATENATE(Fix_Mapping[[#This Row],[KODE BARANG]],2),'Form Fix'!$A$6:$F$911,4,0),0) -> 0 | U47: =IFERROR(VLOOKUP(CONCATENATE(Fix_Mapping[[#This Row],[KODE BARANG]],3),'Form Fix'!$A$6:$F$911,4,0),0) -> 0 | V47: =IFERROR(VLOOKUP(CONCATENATE(Fix_Mapping[[#This Row],[KODE BARANG]],4),'Form Fix'!$A$6:$F$911,4,0),0) -> 0 | W47: =IFERROR(VLOOKUP(CONCATENATE(Fix_Mapping[[#This Row],[KODE BARANG]],5),'Form Fix'!$A$6:$F$911,4,0),0) -> 0
A48: R1021209010011 | B48: RB DETTOL BODY SOAP HK SKINCARE 100GR X 36 PCS 3+1 | C48: 36 | D48: PCS | E48: DETTOL BODY SOAP | F48: 17593.696 | G48: 633373.06 | H48: 19529.003 | I48: 703044.1 | J48: 19228.083 | K48: 692211 | L48: 21343.173 | M48: 768354.21 | N48: 6409.3656 | O48: 230737.16 | P48: 7114.3958 | Q48: 256118.25 | S48: =IFERROR(VLOOKUP(CONCATENATE(Fix_Mapping[[#This Row],[KODE BARANG]],1),'Form Fix'!$A$6:$F$911,4,0),0) -> 0 | T48: =IFERROR(VLOOKUP(CONCATENATE(Fix_Mapping[[#This Row],[KODE BARANG]],2),'Form Fix'!$A$6:$F$911,4,0),0) -> 0 | U48: =IFERROR(VLOOKUP(CONCATENATE(Fix_Mapping[[#This Row],[KODE BARANG]],3),'Form Fix'!$A$6:$F$911,4,0),0) -> 0 | V48: =IFERROR(VLOOKUP(CONCATENATE(Fix_Mapping[[#This Row],[KODE BARANG]],4),'Form Fix'!$A$6:$F$911,4,0),0) -> 0 | W48: =IFERROR(VLOOKUP(CONCATENATE(Fix_Mapping[[#This Row],[KODE BARANG]],5),'Form Fix'!$A$6:$F$911,4,0),0) -> 0
A49: R1021301010010 | B49: RB DETTOL BODY SOAP SH COOL 100GR X 27 PCS | C49: 27 | D49: PCS | E49: DETTOL BODY SOAP | F49: 25693.2 | G49: 693716.4 | H49: 28519.452 | I49: 770025.2 | J49: 28080 | K49: 758160 | L49: 31168.8 | M49: 841557.6 | N49: 28080 | O49: 758160 | P49: 31168.8 | Q49: 841557.6 | S49: =IFERROR(VLOOKUP(CONCATENATE(Fix_Mapping[[#This Row],[KODE BARANG]],1),'Form Fix'!$A$6:$F$911,4,0),0) -> 0 | T49: =IFERROR(VLOOKUP(CONCATENATE(Fix_Mapping[[#This Row],[KODE BARANG]],2),'Form Fix'!$A$6:$F$911,4,0),0) -> 0 | U49: =IFERROR(VLOOKUP(CONCATENATE(Fix_Mapping[[#This Row],[KODE BARANG]],3),'Form Fix'!$A$6:$F$911,4,0),0) -> 0 | V49: =IFERROR(VLOOKUP(CONCATENATE(Fix_Mapping[[#This Row],[KODE BARANG]],4),'Form Fix'!$A$6:$F$911,4,0),0) -> 0 | W49: =IFERROR(VLOOKUP(CONCATENATE(Fix_Mapping[[#This Row],[KODE BARANG]],5),'Form Fix'!$A$6:$F$911,4,0),0) -> 0
A50: R1021302010010 | B50: RB DETTOL BODY SOAP SH FRESH 100GR X 27 PCS | C50: 27 | D50: PCS | E50: DETTOL BODY SOAP | F50: 25693.2 | G50: 693716.4 | H50: 28519.452 | I50: 770025.2 | J50: 28080 | K50: 758160 | L50: 31168.8 | M50: 841557.6 | N50: 28080 | O50: 758160 | P50: 31168.8 | Q50: 841557.6 | S50: =IFERROR(VLOOKUP(CONCATENATE(Fix_Mapping[[#This Row],[KODE BARANG]],1),'Form Fix'!$A$6:$F$911,4,0),0) -> 0 | T50: =IFERROR(VLOOKUP(CONCATENATE(Fix_Mapping[[#This Row],[KODE BARANG]],2),'Form Fix'!$A$6:$F$911,4,0),0) -> 0 | U50: =IFERROR(VLOOKUP(CONCATENATE(Fix_Mapping[[#This Row],[KODE BARANG]],3),'Form Fix'!$A$6:$F$911,4,0),0) -> 0 | V50: =IFERROR(VLOOKUP(CONCATENATE(Fix_Mapping[[#This Row],[KODE BARANG]],4),'Form Fix'!$A$6:$F$911,4,0),0) -> 0 | W50: =IFERROR(VLOOKUP(CONCATENATE(Fix_Mapping[[#This Row],[KODE BARANG]],5),'Form Fix'!$A$6:$F$911,4,0),0) -> 0
A51: R1021303010010 | B51: RB DETTOL BODY SOAP SH LASTING 100GR X 27 PCS | C51: 27 | D51: PCS | E51: DETTOL BODY SOAP | F51: 25693.2 | G51: 693716.4 | H51: 28519.452 | I51: 770025.2 | J51: 28080 | K51: 758160 | L51: 31168.8 | M51: 841557.6 | N51: 28080 | O51: 758160 | P51: 31168.8 | Q51: 841557.6 | S51: =IFERROR(VLOOKUP(CONCATENATE(Fix_Mapping[[#This Row],[KODE BARANG]],1),'Form Fix'!$A$6:$F$911,4,0),0) -> 0 | T51: =IFERROR(VLOOKUP(CONCATENATE(Fix_Mapping[[#This Row],[KODE BARANG]],2),'Form Fix'!$A$6:$F$911,4,0),0) -> 0 | U51: =IFERROR(VLOOKUP(CONCATENATE(Fix_Mapping[[#This Row],[KODE BARANG]],3),'Form Fix'!$A$6:$F$911,4,0),0) -> 0 | V51: =IFERROR(VLOOKUP(CONCATENATE(Fix_Mapping[[#This Row],[KODE BARANG]],4),'Form Fix'!$A$6:$F$911,4,0),0) -> 0 | W51: =IFERROR(VLOOKUP(CONCATENATE(Fix_Mapping[[#This Row],[KODE BARANG]],5),'Form Fix'!$A$6:$F$911,4,0),0) -> 0
A52: R1021304006510 | B52: RB DETTOL BODY SOAP SH ORIGINAL 65GR X 27 PCS | C52: 27 | D52: PCS | E52: DETTOL BODY SOAP | F52: 20792.951 | G52: 561409.69 | H52: 23080.176 | I52: 623164.75 | J52: 22724.537 | K52: 613562.5 | L52: 25224.236 | M52: 681054.38 | O52: 0 | P52: 0 | Q52: 0 | S52: =IFERROR(VLOOKUP(CONCATENATE(Fix_Mapping[[#This Row],[KODE BARANG]],1),'Form Fix'!$A$6:$F$911,4,0),0) -> 0 | T52: =IFERROR(VLOOKUP(CONCATENATE(Fix_Mapping[[#This Row],[KODE BARANG]],2),'Form Fix'!$A$6:$F$911,4,0),0) -> 0 | U52: =IFERROR(VLOOKUP(CONCATENATE(Fix_Mapping[[#This Row],[KODE BARANG]],3),'Form Fix'!$A$6:$F$911,4,0),0) -> 0 | V52: =IFERROR(VLOOKUP(CONCATENATE(Fix_Mapping[[#This Row],[KODE BARANG]],4),'Form Fix'!$A$6:$F$911,4,0),0) -> 0 | W52: =IFERROR(VLOOKUP(CONCATENATE(Fix_Mapping[[#This Row],[KODE BARANG]],5),'Form Fix'!$A$6:$F$911,4,0),0) -> 0
A53: R1021304010010 | B53: RB DETTOL BODY SOAP SH ORIGINAL 100GR X 27 PCS | C53: 27 | D53: PCS | E53: DETTOL BODY SOAP | F53: 25693.2 | G53: 693716.4 | H53: 28519.452 | I53: 770025.2 | J53: 28080 | K53: 758160 | L53: 31168.8 | M53: 841557.6 | N53: 28080 | O53: 758160 | P53: 31168.8 | Q53: 841557.6 | S53: =IFERROR(VLOOKUP(CONCATENATE(Fix_Mapping[[#This Row],[KODE BARANG]],1),'Form Fix'!$A$6:$F$911,4,0),0) -> 0 | T53: =IFERROR(VLOOKUP(CONCATENATE(Fix_Mapping[[#This Row],[KODE BARANG]],2),'Form Fix'!$A$6:$F$911,4,0),0) -> 0 | U53: =IFERROR(VLOOKUP(CONCATENATE(Fix_Mapping[[#This Row],[KODE BARANG]],3),'Form Fix'!$A$6:$F$911,4,0),0) -> 0 | V53: =IFERROR(VLOOKUP(CONCATENATE(Fix_Mapping[[#This Row],[KODE BARANG]],4),'Form Fix'!$A$6:$F$911,4,0),0) -> 0 | W53: =IFERROR(VLOOKUP(CONCATENATE(Fix_Mapping[[#This Row],[KODE BARANG]],5),'Form Fix'!$A$6:$F$911,4,0),0) -> 0
A54: R1021305010010 | B54: RB DETTOL BODY SOAP SH RE-ENERGIZER 100GR X 27 PCS | C54: 27 | D54: PCS | E54: DETTOL BODY SOAP | F54: 25693.2 | G54: 693716.4 | H54: 28519.452 | I54: 770025.2 | J54: 28080 | K54: 758160 | L54: 31168.8 | M54: 841557.6 | N54: 28080 | O54: 758160 | P54: 31168.8 | Q54: 841557.6 | S54: =IFERROR(VLOOKUP(CONCATENATE(Fix_Mapping[[#This Row],[KODE BARANG]],1),'Form Fix'!$A$6:$F$911,4,0),0) -> 0 | T54: =IFERROR(VLOOKUP(CONCATENATE(Fix_Mapping[[#This Row],[KODE BARANG]],2),'Form Fix'!$A$6:$F$911,4,0),0) -> 0 | U54: =IFERROR(VLOOKUP(CONCATENATE(Fix_Mapping[[#This Row],[KODE BARANG]],3),'Form Fix'!$A$6:$F$911,4,0),0) -> 0 | V54: =IFERROR(VLOOKUP(CONCATENATE(Fix_Mapping[[#This Row],[KODE BARANG]],4),'Form Fix'!$A$6:$F$911,4,0),0) -> 0 | W54: =IFERROR(VLOOKUP(CONCATENATE(Fix_Mapping[[#This Row],[KODE BARANG]],5),'Form Fix'!$A$6:$F$911,4,0),0) -> 0
A55: R1021306010010 | B55: RB DETTOL BODY SOAP SH SKINCARE 100GR X 27 PCS | C55: 27 | D55: PCS | E55: DETTOL BODY SOAP | F55: 25693.2 | G55: 693716.4 | H55: 28519.452 | I55: 770025.2 | J55: 28080 | K55: 758160 | L55: 31168.8 | M55: 841557.6 | N55: 28080 | O55: 758160 | P55: 31168.8 | Q55: 841557.6 | S55: =IFERROR(VLOOKUP(CONCATENATE(Fix_Mapping[[#This Row],[KODE BARANG]],1),'Form Fix'!$A$6:$F$911,4,0),0) -> 0 | T55: =IFERROR(VLOOKUP(CONCATENATE(Fix_Mapping[[#This Row],[KODE BARANG]],2),'Form Fix'!$A$6:$F$911,4,0),0) -> 0 | U55: =IFERROR(VLOOKUP(CONCATENATE(Fix_Mapping[[#This Row],[KODE BARANG]],3),'Form Fix'!$A$6:$F$911,4,0),0) -> 0 | V55: =IFERROR(VLOOKUP(CONCATENATE(Fix_Mapping[[#This Row],[KODE BARANG]],4),'Form Fix'!$A$6:$F$911,4,0),0) -> 0 | W55: =IFERROR(VLOOKUP(CONCATENATE(Fix_Mapping[[#This Row],[KODE BARANG]],5),'Form Fix'!$A$6:$F$911,4,0),0) -> 0
A56: R1021307010010 | B56: RB DETTOL BODY SOAP SH SENSITIVE 100GR X 27 PCS | C56: 27 | D56: PCS | E56: DETTOL BODY SOAP | F56: 25693.2 | G56: 693716.4 | H56: 28519.452 | I56: 770025.2 | J56: 28080 | K56: 758160 | L56: 31168.8 | M56: 841557.6 | O56: 0 | P56: 0 | Q56: 0 | S56: =IFERROR(VLOOKUP(CONCATENATE(Fix_Mapping[[#This Row],[KODE BARANG]],1),'Form Fix'!$A$6:$F$911,4,0),0) -> 0 | T56: =IFERROR(VLOOKUP(CONCATENATE(Fix_Mapping[[#This Row],[KODE BARANG]],2),'Form Fix'!$A$6:$F$911,4,0),0) -> 0 | U56: =IFERROR(VLOOKUP(CONCATENATE(Fix_Mapping[[#This Row],[KODE BARANG]],3),'Form Fix'!$A$6:$F$911,4,0),0) -> 0 | V56: =IFERROR(VLOOKUP(CONCATENATE(Fix_Mapping[[#This Row],[KODE BARANG]],4),'Form Fix'!$A$6:$F$911,4,0),0) -> 0 | W56: =IFERROR(VLOOKUP(CONCATENATE(Fix_Mapping[[#This Row],[KODE BARANG]],5),'Form Fix'!$A$6:$F$911,4,0),0) -> 0
A57: R1022001010010 | B57: RB DETTOL BODY WASH COOL 100ML X 24 BTL | C57: 24 | D57: BTL | E57: DETTOL BODY WASH | F57: 17212.37 | G57: 413096.88 | H57: 19105.731 | I57: 458537.54 | J57: 18811.333 | K57: 451472 | L57: 20880.58 | M57: 501133.92 | N57: 18811.333 | O57: 451472 | P57: 20880.58 | Q57: 501133.92 | S57: =IFERROR(VLOOKUP(CONCATENATE(Fix_Mapping[[#This Row],[KODE BARANG]],1),'Form Fix'!$A$6:$F$911,4,0),0) -> 0 | T57: =IFERROR(VLOOKUP(CONCATENATE(Fix_Mapping[[#This Row],[KODE BARANG]],2),'Form Fix'!$A$6:$F$911,4,0),0) -> 0 | U57: =IFERROR(VLOOKUP(CONCATENATE(Fix_Mapping[[#This Row],[KODE BARANG]],3),'Form Fix'!$A$6:$F$911,4,0),0) -> 0 | V57: =IFERROR(VLOOKUP(CONCATENATE(Fix_Mapping[[#This Row],[KODE BARANG]],4),'Form Fix'!$A$6:$F$911,4,0),0) -> 0 | W57: =IFERROR(VLOOKUP(CONCATENATE(Fix_Mapping[[#This Row],[KODE BARANG]],5),'Form Fix'!$A$6:$F$911,4,0),0) -> 0
A58: R1022001020020 | B58: RB DETTOL BODY WASH COOL 200ML X 24 PCH | C58: 24 | D58: PCH | E58: DETTOL BODY WASH | F58: 15372 | G58: 368928 | H58: 17062.92 | I58: 409510.08 | J58: 16800 | K58: 403200 | L58: 18648 | M58: 447552 | N58: 16800 | O58: 403200 | P58: 18648 | Q58: 447552 | S58: =IFERROR(VLOOKUP(CONCATENATE(Fix_Mapping[[#This Row],[KODE BARANG]],1),'Form Fix'!$A$6:$F$911,4,0),0) -> 0 | T58: =IFERROR(VLOOKUP(CONCATENATE(Fix_Mapping[[#This Row],[KODE BARANG]],2),'Form Fix'!$A$6:$F$911,4,0),0) -> 0 | U58: =IFERROR(VLOOKUP(CONCATENATE(Fix_Mapping[[#This Row],[KODE BARANG]],3),'Form Fix'!$A$6:$F$911,4,0),0) -> 0 | V58: =IFERROR(VLOOKUP(CONCATENATE(Fix_Mapping[[#This Row],[KODE BARANG]],4),'Form Fix'!$A$6:$F$911,4,0),0) -> 0 | W58: =IFERROR(VLOOKUP(CONCATENATE(Fix_Mapping[[#This Row],[KODE BARANG]],5),'Form Fix'!$A$6:$F$911,4,0),0) -> 0
A59: R1022001020021 | B59: RB DETTOL BODY WASH COOL 200ML X 24 PCH BANDED | C59: 24 | D59: PCH | E59: DETTOL BODY WASH | F59: 15372 | G59: 368928 | H59: 17062.92 | I59: 409510.08 | J59: 16800 | K59: 403200 | L59: 18648 | M59: 447552 | N59: 16800 | O59: 403200 | P59: 18648 | Q59: 447552 | S59: =IFERROR(VLOOKUP(CONCATENATE(Fix_Mapping[[#This Row],[KODE BARANG]],1),'Form Fix'!$A$6:$F$911,4,0),0) -> 0 | T59: =IFERROR(VLOOKUP(CONCATENATE(Fix_Mapping[[#This Row],[KODE BARANG]],2),'Form Fix'!$A$6:$F$911,4,0),0) -> 0 | U59: =IFERROR(VLOOKUP(CONCATENATE(Fix_Mapping[[#This Row],[KODE BARANG]],3),'Form Fix'!$A$6:$F$911,4,0),0) -> 0 | V59: =IFERROR(VLOOKUP(CONCATENATE(Fix_Mapping[[#This Row],[KODE BARANG]],4),'Form Fix'!$A$6:$F$911,4,0),0) -> 0 | W59: =IFERROR(VLOOKUP(CONCATENATE(Fix_Mapping[[#This Row],[KODE BARANG]],5),'Form Fix'!$A$6:$F$911,4,0),0) -> 0
A60: R1022001030020 | B60: RB DETTOL BODY WASH COOL 300ML X 12 PCH | C60: 12 | D60: PCH | E60: DETTOL BODY WASH | F60: 36201.975 | G60: 434423.7 | H60: 40184.192 | I60: 482210.31 | J60: 39565 | K60: 474780 | L60: 43917.15 | M60: 527005.8 | O60: 0 | P60: 0 | Q60: 0 | S60: =IFERROR(VLOOKUP(CONCATENATE(Fix_Mapping[[#This Row],[KODE BARANG]],1),'Form Fix'!$A$6:$F$911,4,0),0) -> 0 | T60: =IFERROR(VLOOKUP(CONCATENATE(Fix_Mapping[[#This Row],[KODE BARANG]],2),'Form Fix'!$A$6:$F$911,4,0),0) -> 0 | U60: =IFERROR(VLOOKUP(CONCATENATE(Fix_Mapping[[#This Row],[KODE BARANG]],3),'Form Fix'!$A$6:$F$911,4,0),0) -> 0 | V60: =IFERROR(VLOOKUP(CONCATENATE(Fix_Mapping[[#This Row],[KODE BARANG]],4),'Form Fix'!$A$6:$F$911,4,0),0) -> 0 | W60: =IFERROR(VLOOKUP(CONCATENATE(Fix_Mapping[[#This Row],[KODE BARANG]],5),'Form Fix'!$A$6:$F$911,4,0),0) -> 0
A61: R1022001037020 | B61: RB DETTOL BODY WASH COOL 370ML X 24 PCH | C61: 24 | D61: PCH | E61: DETTOL BODY WASH | F61: 20717.43 | G61: 497218.32 | H61: 22996.347 | I61: 551912.34 | J61: 22642 | K61: 543408 | L61: 25132.62 | M61: 603182.88 | N61: 22642 | O61: 543408 | P61: 25132.62 | Q61: 603182.88 | S61: =IFERROR(VLOOKUP(CONCATENATE(Fix_Mapping[[#This Row],[KODE BARANG]],1),'Form Fix'!$A$6:$F$911,4,0),0) -> 0 | T61: =IFERROR(VLOOKUP(CONCATENATE(Fix_Mapping[[#This Row],[KODE BARANG]],2),'Form Fix'!$A$6:$F$911,4,0),0) -> 0 | U61: =IFERROR(VLOOKUP(CONCATENATE(Fix_Mapping[[#This Row],[KODE BARANG]],3),'Form Fix'!$A$6:$F$911,4,0),0) -> 0 | V61: =IFERROR(VLOOKUP(CONCATENATE(Fix_Mapping[[#This Row],[KODE BARANG]],4),'Form Fix'!$A$6:$F$911,4,0),0) -> 0 | W61: =IFERROR(VLOOKUP(CONCATENATE(Fix_Mapping[[#This Row],[KODE BARANG]],5),'Form Fix'!$A$6:$F$911,4,0),0) -> 0
A62: R1022001037021 | B62: RB DETTOL BODY WASH COOL 370ML X 24 PCH BANDED | C62: 24 | D62: PCH | E62: DETTOL BODY WASH | F62: 20717.43 | G62: 497218.32 | H62: 22996.347 | I62: 551912.34 | J62: 22642 | K62: 543408 | L62: 25132.62 | M62: 603182.88 | N62: 22642 | O62: 543408 | P62: 25132.62 | Q62: 603182.88 | S62: =IFERROR(VLOOKUP(CONCATENATE(Fix_Mapping[[#This Row],[KODE BARANG]],1),'Form Fix'!$A$6:$F$911,4,0),0) -> 0 | T62: =IFERROR(VLOOKUP(CONCATENATE(Fix_Mapping[[#This Row],[KODE BARANG]],2),'Form Fix'!$A$6:$F$911,4,0),0) -> 0 | U62: =IFERROR(VLOOKUP(CONCATENATE(Fix_Mapping[[#This Row],[KODE BARANG]],3),'Form Fix'!$A$6:$F$911,4,0),0) -> 0 | V62: =IFERROR(VLOOKUP(CONCATENATE(Fix_Mapping[[#This Row],[KODE BARANG]],4),'Form Fix'!$A$6:$F$911,4,0),0) -> 0 | W62: =IFERROR(VLOOKUP(CONCATENATE(Fix_Mapping[[#This Row],[KODE BARANG]],5),'Form Fix'!$A$6:$F$911,4,0),0) -> 0
A63: R1022001050030 | B63: RB DETTOL BODY WASH COOL 500ML X 12 PUMP | C63: 12 | D63: PUMP | E63: DETTOL BODY WASH | F63: 53802 | G63: 645624 | H63: 59720.22 | I63: 716642.64 | J63: 58800 | K63: 705600 | L63: 65268 | M63: 783216 | N63: 58800 | O63: 705600 | P63: 65268 | Q63: 783216 | S63: =IFERROR(VLOOKUP(CONCATENATE(Fix_Mapping[[#This Row],[KODE BARANG]],1),'Form Fix'!$A$6:$F$911,4,0),0) -> 0 | T63: =IFERROR(VLOOKUP(CONCATENATE(Fix_Mapping[[#This Row],[KODE BARANG]],2),'Form Fix'!$A$6:$F$911,4,0),0) -> 0 | U63: =IFERROR(VLOOKUP(CONCATENATE(Fix_Mapping[[#This Row],[KODE BARANG]],3),'Form Fix'!$A$6:$F$911,4,0),0) -> 0 | V63: =IFERROR(VLOOKUP(CONCATENATE(Fix_Mapping[[#This Row],[KODE BARANG]],4),'Form Fix'!$A$6:$F$911,4,0),0) -> 0 | W63: =IFERROR(VLOOKUP(CONCATENATE(Fix_Mapping[[#This Row],[KODE BARANG]],5),'Form Fix'!$A$6:$F$911,4,0),0) -> 0
A64: R1022001072020 | B64: RB DETTOL BODY WASH COOL 720ML X 12 PCH | C64: 12 | D64: PCH | E64: DETTOL BODY WASH | F64: 36069.3 | G64: 432831.6 | H64: 40036.923 | I64: 480443.08 | J64: 39420 | K64: 473040 | L64: 43756.2 | M64: 525074.4 | N64: 39420 | O64: 473040 | P64: 43756.2 | Q64: 525074.4 | S64: =IFERROR(VLOOKUP(CONCATENATE(Fix_Mapping[[#This Row],[KODE BARANG]],1),'Form Fix'!$A$6:$F$911,4,0),0) -> 0 | T64: =IFERROR(VLOOKUP(CONCATENATE(Fix_Mapping[[#This Row],[KODE BARANG]],2),'Form Fix'!$A$6:$F$911,4,0),0) -> 0 | U64: =IFERROR(VLOOKUP(CONCATENATE(Fix_Mapping[[#This Row],[KODE BARANG]],3),'Form Fix'!$A$6:$F$911,4,0),0) -> 0 | V64: =IFERROR(VLOOKUP(CONCATENATE(Fix_Mapping[[#This Row],[KODE BARANG]],4),'Form Fix'!$A$6:$F$911,4,0),0) -> 0 | W64: =IFERROR(VLOOKUP(CONCATENATE(Fix_Mapping[[#This Row],[KODE BARANG]],5),'Form Fix'!$A$6:$F$911,4,0),0) -> 0
A65: R1022001072021 | B65: RB DETTOL BODY WASH COOL 720ML X 6 PCH BANDED | C65: 6 | D65: PCH | E65: DETTOL BODY WASH | F65: 64383.67 | G65: 386302.02 | H65: 71465.874 | I65: 428795.24 | J65: 70364.667 | K65: 422188 | L65: 78104.78 | M65: 468628.68 | O65: 0 | P65: 0 | Q65: 0 | S65: =IFERROR(VLOOKUP(CONCATENATE(Fix_Mapping[[#This Row],[KODE BARANG]],1),'Form Fix'!$A$6:$F$911,4,0),0) -> 0 | T65: =IFERROR(VLOOKUP(CONCATENATE(Fix_Mapping[[#This Row],[KODE BARANG]],2),'Form Fix'!$A$6:$F$911,4,0),0) -> 0 | U65: =IFERROR(VLOOKUP(CONCATENATE(Fix_Mapping[[#This Row],[KODE BARANG]],3),'Form Fix'!$A$6:$F$911,4,0),0) -> 0 | V65: =IFERROR(VLOOKUP(CONCATENATE(Fix_Mapping[[#This Row],[KODE BARANG]],4),'Form Fix'!$A$6:$F$911,4,0),0) -> 0 | W65: =IFERROR(VLOOKUP(CONCATENATE(Fix_Mapping[[#This Row],[KODE BARANG]],5),'Form Fix'!$A$6:$F$911,4,0),0) -> 0
A66: R1022002037020 | B66: RB DETTOL BODY WASH FAMILY PROTECT 370ML X 24 PCH BANDED | C66: 24 | D66: PCH | E66: DETTOL BODY WASH | F66: 20717.43 | G66: 497218.32 | H66: 22996.347 | I66: 551912.34 | J66: 22642 | K66: 543408 | L66: 25132.62 | M66: 603182.88 | N66: 22642 | O66: 543408 | P66: 25132.62 | Q66: 603182.88 | S66: =IFERROR(VLOOKUP(CONCATENATE(Fix_Mapping[[#This Row],[KODE BARANG]],1),'Form Fix'!$A$6:$F$911,4,0),0) -> 0 | T66: =IFERROR(VLOOKUP(CONCATENATE(Fix_Mapping[[#This Row],[KODE BARANG]],2),'Form Fix'!$A$6:$F$911,4,0),0) -> 0 | U66: =IFERROR(VLOOKUP(CONCATENATE(Fix_Mapping[[#This Row],[KODE BARANG]],3),'Form Fix'!$A$6:$F$911,4,0),0) -> 0 | V66: =IFERROR(VLOOKUP(CONCATENATE(Fix_Mapping[[#This Row],[KODE BARANG]],4),'Form Fix'!$A$6:$F$911,4,0),0) -> 0 | W66: =IFERROR(VLOOKUP(CONCATENATE(Fix_Mapping[[#This Row],[KODE BARANG]],5),'Form Fix'!$A$6:$F$911,4,0),0) -> 0
A67: R1022002037021 | B67: RB DETTOL BODY WASH FAMILY PROTECT 370ML X 24 PCH | C67: 24 | D67: PCH | E67: DETTOL BODY WASH | F67: 16309.875 | G67: 391437 | H67: 18103.961 | I67: 434495.07 | J67: 17825 | K67: 427800 | L67: 19785.75 | M67: 474858 | N67: 22642 | O67: 543408 | P67: 25132.62 | Q67: 603182.88 | S67: =IFERROR(VLOOKUP(CONCATENATE(Fix_Mapping[[#This Row],[KODE BARANG]],1),'Form Fix'!$A$6:$F$911,4,0),0) -> 0 | T67: =IFERROR(VLOOKUP(CONCATENATE(Fix_Mapping[[#This Row],[KODE BARANG]],2),'Form Fix'!$A$6:$F$911,4,0),0) -> 0 | U67: =IFERROR(VLOOKUP(CONCATENATE(Fix_Mapping[[#This Row],[KODE BARANG]],3),'Form Fix'!$A$6:$F$911,4,0),0) -> 0 | V67: =IFERROR(VLOOKUP(CONCATENATE(Fix_Mapping[[#This Row],[KODE BARANG]],4),'Form Fix'!$A$6:$F$911,4,0),0) -> 0 | W67: =IFERROR(VLOOKUP(CONCATENATE(Fix_Mapping[[#This Row],[KODE BARANG]],5),'Form Fix'!$A$6:$F$911,4,0),0) -> 0
A68: R1022002072021 | B68: RB DETTOL BODY WASH FAMILY PROTECT 720ML X 6 PCH BANDED | C68: 6 | D68: PCH | E68: DETTOL BODY WASH | F68: 64383.67 | G68: 386302.02 | H68: 71465.874 | I68: 428795.24 | J68: 70364.667 | K68: 422188 | L68: 78104.78 | M68: 468628.68 | N68: 65153 | O68: 390918 | P68: 72319.83 | Q68: 433918.98 | S68: =IFERROR(VLOOKUP(CONCATENATE(Fix_Mapping[[#This Row],[KODE BARANG]],1),'Form Fix'!$A$6:$F$911,4,0),0) -> 0 | T68: =IFERROR(VLOOKUP(CONCATENATE(Fix_Mapping[[#This Row],[KODE BARANG]],2),'Form Fix'!$A$6:$F$911,4,0),0) -> 0 | U68: =IFERROR(VLOOKUP(CONCATENATE(Fix_Mapping[[#This Row],[KODE BARANG]],3),'Form Fix'!$A$6:$F$911,4,0),0) -> 0 | V68: =IFERROR(VLOOKUP(CONCATENATE(Fix_Mapping[[#This Row],[KODE BARANG]],4),'Form Fix'!$A$6:$F$911,4,0),0) -> 0 | W68: =IFERROR(VLOOKUP(CONCATENATE(Fix_Mapping[[#This Row],[KODE BARANG]],5),'Form Fix'!$A$6:$F$911,4,0),0) -> 0
A69: R1022003010010 | B69: RB DETTOL BODY WASH FRESH 100ML X 24 BTL | C69: 24 | D69: BTL | E69: DETTOL BODY WASH | F69: 17212.37 | G69: 413096.88 | H69: 19105.731 | I69: 458537.54 | J69: 18811.333 | K69: 451472 | L69: 20880.58 | M69: 501133.92 | N69: 18811.333 | O69: 451472 | P69: 20880.58 | Q69: 501133.92 | S69: =IFERROR(VLOOKUP(CONCATENATE(Fix_Mapping[[#This Row],[KODE BARANG]],1),'Form Fix'!$A$6:$F$911,4,0),0) -> 0 | T69: =IFERROR(VLOOKUP(CONCATENATE(Fix_Mapping[[#This Row],[KODE BARANG]],2),'Form Fix'!$A$6:$F$911,4,0),0) -> 0 | U69: =IFERROR(VLOOKUP(CONCATENATE(Fix_Mapping[[#This Row],[KODE BARANG]],3),'Form Fix'!$A$6:$F$911,4,0),0) -> 0 | V69: =IFERROR(VLOOKUP(CONCATENATE(Fix_Mapping[[#This Row],[KODE BARANG]],4),'Form Fix'!$A$6:$F$911,4,0),0) -> 0 | W69: =IFERROR(VLOOKUP(CONCATENATE(Fix_Mapping[[#This Row],[KODE BARANG]],5),'Form Fix'!$A$6:$F$911,4,0),0) -> 0
A70: R1022003010020 | B70: RB DETTOL BODY WASH FRESH 100ML X 24 PCH | C70: 24 | D70: PCH | E70: DETTOL BODY WASH | F70: 17212.37 | G70: 413096.88 | H70: 19105.731 | I70: 458537.54 | J70: 18811.333 | K70: 451472 | L70: 20880.58 | M70: 501133.92 | N70: 16800 | O70: 403200 | P70: 18648 | Q70: 447552 | S70: =IFERROR(VLOOKUP(CONCATENATE(Fix_Mapping[[#This Row],[KODE BARANG]],1),'Form Fix'!$A$6:$F$911,4,0),0) -> 0 | T70: =IFERROR(VLOOKUP(CONCATENATE(Fix_Mapping[[#This Row],[KODE BARANG]],2),'Form Fix'!$A$6:$F$911,4,0),0) -> 0 | U70: =IFERROR(VLOOKUP(CONCATENATE(Fix_Mapping[[#This Row],[KODE BARANG]],3),'Form Fix'!$A$6:$F$911,4,0),0) -> 0 | V70: =IFERROR(VLOOKUP(CONCATENATE(Fix_Mapping[[#This Row],[KODE BARANG]],4),'Form Fix'!$A$6:$F$911,4,0),0) -> 0 | W70: =IFERROR(VLOOKUP(CONCATENATE(Fix_Mapping[[#This Row],[KODE BARANG]],5),'Form Fix'!$A$6:$F$911,4,0),0) -> 0
A71: R1022003020020 | B71: RB DETTOL BODY WASH FRESH 200ML X 24 PCH | C71: 24 | D71: PCH | E71: DETTOL BODY WASH | F71: 15372 | G71: 368928 | H71: 17062.92 | I71: 409510.08 | J71: 16800 | K71: 403200 | L71: 18648 | M71: 447552 | N71: 16800 | O71: 403200 | P71: 18648 | Q71: 447552 | S71: =IFERROR(VLOOKUP(CONCATENATE(Fix_Mapping[[#This Row],[KODE BARANG]],1),'Form Fix'!$A$6:$F$911,4,0),0) -> 0 | T71: =IFERROR(VLOOKUP(CONCATENATE(Fix_Mapping[[#This Row],[KODE BARANG]],2),'Form Fix'!$A$6:$F$911,4,0),0) -> 0 | U71: =IFERROR(VLOOKUP(CONCATENATE(Fix_Mapping[[#This Row],[KODE BARANG]],3),'Form Fix'!$A$6:$F$911,4,0),0) -> 0 | V71: =IFERROR(VLOOKUP(CONCATENATE(Fix_Mapping[[#This Row],[KODE BARANG]],4),'Form Fix'!$A$6:$F$911,4,0),0) -> 0 | W71: =IFERROR(VLOOKUP(CONCATENATE(Fix_Mapping[[#This Row],[KODE BARANG]],5),'Form Fix'!$A$6:$F$911,4,0),0) -> 0
A72: R1022003030010 | B72: RB DETTOL BODY WASH FRESH 300ML X 12 BTL | C72: 12 | D72: BTL | E72: DETTOL BODY WASH | F72: 36201.975 | G72: 434423.7 | H72: 40184.192 | I72: 482210.31 | J72: 39565 | K72: 474780 | L72: 43917.15 | M72: 527005.8 | O72: 0 | P72: 0 | Q72: 0 | S72: =IFERROR(VLOOKUP(CONCATENATE(Fix_Mapping[[#This Row],[KODE BARANG]],1),'Form Fix'!$A$6:$F$911,4,0),0) -> 0 | T72: =IFERROR(VLOOKUP(CONCATENATE(Fix_Mapping[[#This Row],[KODE BARANG]],2),'Form Fix'!$A$6:$F$911,4,0),0) -> 0 | U72: =IFERROR(VLOOKUP(CONCATENATE(Fix_Mapping[[#This Row],[KODE BARANG]],3),'Form Fix'!$A$6:$F$911,4,0),0) -> 0 | V72: =IFERROR(VLOOKUP(CONCATENATE(Fix_Mapping[[#This Row],[KODE BARANG]],4),'Form Fix'!$A$6:$F$911,4,0),0) -> 0 | W72: =IFERROR(VLOOKUP(CONCATENATE(Fix_Mapping[[#This Row],[KODE BARANG]],5),'Form Fix'!$A$6:$F$911,4,0),0) -> 0
A73: R1022003037020 | B73: RB DETTOL BODY WASH FRESH 370/410ML X 24 PCH | C73: 24 | D73: PCH | E73: DETTOL BODY WASH | F73: 20717.43 | G73: 497218.32 | H73: 22996.347 | I73: 551912.34 | J73: 22642 | K73: 543408 | L73: 25132.62 | M73: 603182.88 | N73: 22642 | O73: 543408 | P73: 25132.62 | Q73: 603182.88 | S73: =IFERROR(VLOOKUP(CONCATENATE(Fix_Mapping[[#This Row],[KODE BARANG]],1),'Form Fix'!$A$6:$F$911,4,0),0) -> 0 | T73: =IFERROR(VLOOKUP(CONCATENATE(Fix_Mapping[[#This Row],[KODE BARANG]],2),'Form Fix'!$A$6:$F$911,4,0),0) -> 0 | U73: =IFERROR(VLOOKUP(CONCATENATE(Fix_Mapping[[#This Row],[KODE BARANG]],3),'Form Fix'!$A$6:$F$911,4,0),0) -> 0 | V73: =IFERROR(VLOOKUP(CONCATENATE(Fix_Mapping[[#This Row],[KODE BARANG]],4),'Form Fix'!$A$6:$F$911,4,0),0) -> 0 | W73: =IFERROR(VLOOKUP(CONCATENATE(Fix_Mapping[[#This Row],[KODE BARANG]],5),'Form Fix'!$A$6:$F$911,4,0),0) -> 0
A74: R1022003037021 | B74: RB DETTOL BODY WASH FRESH 370/410ML X 24 PCH BANDED | C74: 24 | D74: PCH | E74: DETTOL BODY WASH | F74: 20717.43 | G74: 497218.32 | H74: 22996.347 | I74: 551912.34 | J74: 22642 | K74: 543408 | L74: 25132.62 | M74: 603182.88 | N74: 22642 | O74: 543408 | P74: 25132.62 | Q74: 603182.88 | S74: =IFERROR(VLOOKUP(CONCATENATE(Fix_Mapping[[#This Row],[KODE BARANG]],1),'Form Fix'!$A$6:$F$911,4,0),0) -> 0 | T74: =IFERROR(VLOOKUP(CONCATENATE(Fix_Mapping[[#This Row],[KODE BARANG]],2),'Form Fix'!$A$6:$F$911,4,0),0) -> 0 | U74: =IFERROR(VLOOKUP(CONCATENATE(Fix_Mapping[[#This Row],[KODE BARANG]],3),'Form Fix'!$A$6:$F$911,4,0),0) -> 0 | V74: =IFERROR(VLOOKUP(CONCATENATE(Fix_Mapping[[#This Row],[KODE BARANG]],4),'Form Fix'!$A$6:$F$911,4,0),0) -> 0 | W74: =IFERROR(VLOOKUP(CONCATENATE(Fix_Mapping[[#This Row],[KODE BARANG]],5),'Form Fix'!$A$6:$F$911,4,0),0) -> 0
A75: R1022003050030 | B75: RB DETTOL BODY WASH FRESH 500ML X 12 PUMP | C75: 12 | D75: PUMP | E75: DETTOL BODY WASH | F75: 53802 | G75: 645624 | H75: 59720.22 | I75: 716642.64 | J75: 58800 | K75: 705600 | L75: 65268 | M75: 783216 | N75: 58800 | O75: 705600 | P75: 65268 | Q75: 783216 | S75: =IFERROR(VLOOKUP(CONCATENATE(Fix_Mapping[[#This Row],[KODE BARANG]],1),'Form Fix'!$A$6:$F$911,4,0),0) -> 0 | T75: =IFERROR(VLOOKUP(CONCATENATE(Fix_Mapping[[#This Row],[KODE BARANG]],2),'Form Fix'!$A$6:$F$911,4,0),0) -> 0 | U75: =IFERROR(VLOOKUP(CONCATENATE(Fix_Mapping[[#This Row],[KODE BARANG]],3),'Form Fix'!$A$6:$F$911,4,0),0) -> 0 | V75: =IFERROR(VLOOKUP(CONCATENATE(Fix_Mapping[[#This Row],[KODE BARANG]],4),'Form Fix'!$A$6:$F$911,4,0),0) -> 0 | W75: =IFERROR(VLOOKUP(CONCATENATE(Fix_Mapping[[#This Row],[KODE BARANG]],5),'Form Fix'!$A$6:$F$911,4,0),0) -> 0
A76: R1022003072020 | B76: RB DETTOL BODY WASH FRESH 720/800ML X 12 PCH | C76: 12 | D76: PCH | E76: DETTOL BODY WASH | F76: 36069.3 | G76: 432831.6 | H76: 40036.923 | I76: 480443.08 | J76: 39420 | K76: 473040 | L76: 43756.2 | M76: 525074.4 | N76: 39420 | O76: 473040 | P76: 43756.2 | Q76: 525074.4 | S76: =IFERROR(VLOOKUP(CONCATENATE(Fix_Mapping[[#This Row],[KODE BARANG]],1),'Form Fix'!$A$6:$F$911,4,0),0) -> 0 | T76: =IFERROR(VLOOKUP(CONCATENATE(Fix_Mapping[[#This Row],[KODE BARANG]],2),'Form Fix'!$A$6:$F$911,4,0),0) -> 0 | U76: =IFERROR(VLOOKUP(CONCATENATE(Fix_Mapping[[#This Row],[KODE BARANG]],3),'Form Fix'!$A$6:$F$911,4,0),0) -> 0 | V76: =IFERROR(VLOOKUP(CONCATENATE(Fix_Mapping[[#This Row],[KODE BARANG]],4),'Form Fix'!$A$6:$F$911,4,0),0) -> 0 | W76: =IFERROR(VLOOKUP(CONCATENATE(Fix_Mapping[[#This Row],[KODE BARANG]],5),'Form Fix'!$A$6:$F$911,4,0),0) -> 0
A77: R1022003072021 | B77: RB DETTOL BODY WASH FRESH 720ML X 6 PCH BANDED | C77: 6 | D77: PCH | E77: DETTOL BODY WASH | F77: 64383.67 | G77: 386302.02 | H77: 71465.874 | I77: 428795.24 | J77: 70364.667 | K77: 422188 | L77: 78104.78 | M77: 468628.68 | O77: 0 | P77: 0 | Q77: 0 | S77: =IFERROR(VLOOKUP(CONCATENATE(Fix_Mapping[[#This Row],[KODE BARANG]],1),'Form Fix'!$A$6:$F$911,4,0),0) -> 3288763 | T77: =IFERROR(VLOOKUP(CONCATENATE(Fix_Mapping[[#This Row],[KODE BARANG]],2),'Form Fix'!$A$6:$F$911,4,0),0) -> 3306725 | U77: =IFERROR(VLOOKUP(CONCATENATE(Fix_Mapping[[#This Row],[KODE BARANG]],3),'Form Fix'!$A$6:$F$911,4,0),0) -> 3328392 | V77: =IFERROR(VLOOKUP(CONCATENATE(Fix_Mapping[[#This Row],[KODE BARANG]],4),'Form Fix'!$A$6:$F$911,4,0),0) -> 0 | W77: =IFERROR(VLOOKUP(CONCATENATE(Fix_Mapping[[#This Row],[KODE BARANG]],5),'Form Fix'!$A$6:$F$911,4,0),0) -> 0
A78: R1022004037020 | B78: RB DETTOL BODY WASH GREEN TEA 370GR X 24 PCH | C78: 24 | D78: PCH | E78: DETTOL BODY WASH | F78: 20717.43 | G78: 497218.32 | H78: 22996.347 | I78: 551912.34 | J78: 22642 | K78: 543408 | L78: 25132.62 | M78: 603182.88 | N78: 22642 | O78: 543408 | P78: 25132.62 | Q78: 603182.88 | S78: =IFERROR(VLOOKUP(CONCATENATE(Fix_Mapping[[#This Row],[KODE BARANG]],1),'Form Fix'!$A$6:$F$911,4,0),0) -> 0 | T78: =IFERROR(VLOOKUP(CONCATENATE(Fix_Mapping[[#This Row],[KODE BARANG]],2),'Form Fix'!$A$6:$F$911,4,0),0) -> 0 | U78: =IFERROR(VLOOKUP(CONCATENATE(Fix_Mapping[[#This Row],[KODE BARANG]],3),'Form Fix'!$A$6:$F$911,4,0),0) -> 0 | V78: =IFERROR(VLOOKUP(CONCATENATE(Fix_Mapping[[#This Row],[KODE BARANG]],4),'Form Fix'!$A$6:$F$911,4,0),0) -> 0 | W78: =IFERROR(VLOOKUP(CONCATENATE(Fix_Mapping[[#This Row],[KODE BARANG]],5),'Form Fix'!$A$6:$F$911,4,0),0) -> 0
A79: R1022004041020 | B79: RB DETTOL BODY WASH ALOE VERA 410ML X 24 PCH | C79: 24 | D79: PCH | E79: DETTOL BODY WASH | F79: 20717.43 | G79: 497218.32 | H79: 22996.347 | I79: 551912.34 | J79: 22642 | K79: 543408 | L79: 25132.62 | M79: 603182.88 | O79: 0 | P79: 0 | Q79: 0 | S79: =IFERROR(VLOOKUP(CONCATENATE(Fix_Mapping[[#This Row],[KODE BARANG]],1),'Form Fix'!$A$6:$F$911,4,0),0) -> 0 | T79: =IFERROR(VLOOKUP(CONCATENATE(Fix_Mapping[[#This Row],[KODE BARANG]],2),'Form Fix'!$A$6:$F$911,4,0),0) -> 0 | U79: =IFERROR(VLOOKUP(CONCATENATE(Fix_Mapping[[#This Row],[KODE BARANG]],3),'Form Fix'!$A$6:$F$911,4,0),0) -> 0 | V79: =IFERROR(VLOOKUP(CONCATENATE(Fix_Mapping[[#This Row],[KODE BARANG]],4),'Form Fix'!$A$6:$F$911,4,0),0) -> 0 | W79: =IFERROR(VLOOKUP(CONCATENATE(Fix_Mapping[[#This Row],[KODE BARANG]],5),'Form Fix'!$A$6:$F$911,4,0),0) -> 0
A80: R1022005037020 | B80: RB DETTOL BODY WASH HONEY 370/410ML X 24 PCH | C80: 24 | D80: PCH | E80: DETTOL BODY WASH | F80: 20717.43 | G80: 497218.32 | H80: 22996.347 | I80: 551912.34 | J80: 22642 | K80: 543408 | L80: 25132.62 | M80: 603182.88 | N80: 22642 | O80: 543408 | P80: 25132.62 | Q80: 603182.88 | S80: =IFERROR(VLOOKUP(CONCATENATE(Fix_Mapping[[#This Row],[KODE BARANG]],1),'Form Fix'!$A$6:$F$911,4,0),0) -> 0 | T80: =IFERROR(VLOOKUP(CONCATENATE(Fix_Mapping[[#This Row],[KODE BARANG]],2),'Form Fix'!$A$6:$F$911,4,0),0) -> 0 | U80: =IFERROR(VLOOKUP(CONCATENATE(Fix_Mapping[[#This Row],[KODE BARANG]],3),'Form Fix'!$A$6:$F$911,4,0),0) -> 0 | V80: =IFERROR(VLOOKUP(CONCATENATE(Fix_Mapping[[#This Row],[KODE BARANG]],4),'Form Fix'!$A$6:$F$911,4,0),0) -> 0 | W80: =IFERROR(VLOOKUP(CONCATENATE(Fix_Mapping[[#This Row],[KODE BARANG]],5),'Form Fix'!$A$6:$F$911,4,0),0) -> 0
A81: R1022005037021 | B81: RB DETTOL BODY WASH HONEY 370/410ML X 24 PCH BANDED | C81: 24 | D81: PCH | E81: DETTOL BODY WASH | F81: 20717.43 | G81: 497218.32 | H81: 22996.347 | I81: 551912.34 | J81: 22642 | K81: 543408 | L81: 25132.62 | M81: 603182.88 | N81: 22642 | O81: 543408 | P81: 25132.62 | Q81: 603182.88 | S81: =IFERROR(VLOOKUP(CONCATENATE(Fix_Mapping[[#This Row],[KODE BARANG]],1),'Form Fix'!$A$6:$F$911,4,0),0) -> 0 | T81: =IFERROR(VLOOKUP(CONCATENATE(Fix_Mapping[[#This Row],[KODE BARANG]],2),'Form Fix'!$A$6:$F$911,4,0),0) -> 0 | U81: =IFERROR(VLOOKUP(CONCATENATE(Fix_Mapping[[#This Row],[KODE BARANG]],3),'Form Fix'!$A$6:$F$911,4,0),0) -> 0 | V81: =IFERROR(VLOOKUP(CONCATENATE(Fix_Mapping[[#This Row],[KODE BARANG]],4),'Form Fix'!$A$6:$F$911,4,0),0) -> 0 | W81: =IFERROR(VLOOKUP(CONCATENATE(Fix_Mapping[[#This Row],[KODE BARANG]],5),'Form Fix'!$A$6:$F$911,4,0),0) -> 0
A82: R1022006030010 | B82: RB DETTOL BODY WASH LASTING 300ML X 12 BTL | C82: 12 | D82: BTL | E82: DETTOL BODY WASH | F82: 36201.975 | G82: 434423.7 | H82: 40184.192 | I82: 482210.31 | J82: 39565 | K82: 474780 | L82: 43917.15 | M82: 527005.8 | O82: 0 | P82: 0 | Q82: 0 | S82: =IFERROR(VLOOKUP(CONCATENATE(Fix_Mapping[[#This Row],[KODE BARANG]],1),'Form Fix'!$A$6:$F$911,4,0),0) -> 0 | T82: =IFERROR(VLOOKUP(CONCATENATE(Fix_Mapping[[#This Row],[KODE BARANG]],2),'Form Fix'!$A$6:$F$911,4,0),0) -> 0 | U82: =IFERROR(VLOOKUP(CONCATENATE(Fix_Mapping[[#This Row],[KODE BARANG]],3),'Form Fix'!$A$6:$F$911,4,0),0) -> 0 | V82: =IFERROR(VLOOKUP(CONCATENATE(Fix_Mapping[[#This Row],[KODE BARANG]],4),'Form Fix'!$A$6:$F$911,4,0),0) -> 0 | W82: =IFERROR(VLOOKUP(CONCATENATE(Fix_Mapping[[#This Row],[KODE BARANG]],5),'Form Fix'!$A$6:$F$911,4,0),0) -> 0
A83: R1022006037020 | B83: RB DETTOL BODY WASH LASTING 370/410ML X 24 PCH | C83: 24 | D83: PCH | E83: DETTOL BODY WASH | F83: 20717.43 | G83: 497218.32 | H83: 22996.347 | I83: 551912.34 | J83: 22642 | K83: 543408 | L83: 25132.62 | M83: 603182.88 | N83: 22642 | O83: 543408 | P83: 25132.62 | Q83: 603182.88 | S83: =IFERROR(VLOOKUP(CONCATENATE(Fix_Mapping[[#This Row],[KODE BARANG]],1),'Form Fix'!$A$6:$F$911,4,0),0) -> 0 | T83: =IFERROR(VLOOKUP(CONCATENATE(Fix_Mapping[[#This Row],[KODE BARANG]],2),'Form Fix'!$A$6:$F$911,4,0),0) -> 0 | U83: =IFERROR(VLOOKUP(CONCATENATE(Fix_Mapping[[#This Row],[KODE BARANG]],3),'Form Fix'!$A$6:$F$911,4,0),0) -> 0 | V83: =IFERROR(VLOOKUP(CONCATENATE(Fix_Mapping[[#This Row],[KODE BARANG]],4),'Form Fix'!$A$6:$F$911,4,0),0) -> 0 | W83: =IFERROR(VLOOKUP(CONCATENATE(Fix_Mapping[[#This Row],[KODE BARANG]],5),'Form Fix'!$A$6:$F$911,4,0),0) -> 0
A84: R1022006037021 | B84: RB DETTOL BODY WASH LASTING 370/410ML X 24 PCH BANDED | C84: 24 | D84: PCH | E84: DETTOL BODY WASH | F84: 20717.43 | G84: 497218.32 | H84: 22996.347 | I84: 551912.34 | J84: 22642 | K84: 543408 | L84: 25132.62 | M84: 603182.88 | N84: 22642 | O84: 543408 | P84: 25132.62 | Q84: 603182.88 | S84: =IFERROR(VLOOKUP(CONCATENATE(Fix_Mapping[[#This Row],[KODE BARANG]],1),'Form Fix'!$A$6:$F$911,4,0),0) -> 0 | T84: =IFERROR(VLOOKUP(CONCATENATE(Fix_Mapping[[#This Row],[KODE BARANG]],2),'Form Fix'!$A$6:$F$911,4,0),0) -> 0 | U84: =IFERROR(VLOOKUP(CONCATENATE(Fix_Mapping[[#This Row],[KODE BARANG]],3),'Form Fix'!$A$6:$F$911,4,0),0) -> 0 | V84: =IFERROR(VLOOKUP(CONCATENATE(Fix_Mapping[[#This Row],[KODE BARANG]],4),'Form Fix'!$A$6:$F$911,4,0),0) -> 0 | W84: =IFERROR(VLOOKUP(CONCATENATE(Fix_Mapping[[#This Row],[KODE BARANG]],5),'Form Fix'!$A$6:$F$911,4,0),0) -> 0
A85: R1022006075020 | B85: RB DETTOL BODY WASH LASTING 750ML X 12 PCH | C85: 12 | D85: PCH | E85: DETTOL BODY WASH | F85: 36069.3 | G85: 432831.6 | H85: 40036.923 | I85: 480443.08 | J85: 39420 | K85: 473040 | L85: 43756.2 | M85: 525074.4 | N85: 39420 | O85: 473040 | P85: 43756.2 | Q85: 525074.4 | S85: =IFERROR(VLOOKUP(CONCATENATE(Fix_Mapping[[#This Row],[KODE BARANG]],1),'Form Fix'!$A$6:$F$911,4,0),0) -> 0 | T85: =IFERROR(VLOOKUP(CONCATENATE(Fix_Mapping[[#This Row],[KODE BARANG]],2),'Form Fix'!$A$6:$F$911,4,0),0) -> 0 | U85: =IFERROR(VLOOKUP(CONCATENATE(Fix_Mapping[[#This Row],[KODE BARANG]],3),'Form Fix'!$A$6:$F$911,4,0),0) -> 0 | V85: =IFERROR(VLOOKUP(CONCATENATE(Fix_Mapping[[#This Row],[KODE BARANG]],4),'Form Fix'!$A$6:$F$911,4,0),0) -> 0 | W85: =IFERROR(VLOOKUP(CONCATENATE(Fix_Mapping[[#This Row],[KODE BARANG]],5),'Form Fix'!$A$6:$F$911,4,0),0) -> 0
A86: R1022007037020 | B86: RB DETTOL BODY WASH LAVENDER 370GR X 24 PCH | C86: 24 | D86: PCH | E86: DETTOL BODY WASH | F86: 20717.43 | G86: 497218.32 | H86: 22996.347 | I86: 551912.34 | J86: 22642 | K86: 543408 | L86: 25132.62 | M86: 603182.88 | N86: 22642 | O86: 543408 | P86: 25132.62 | Q86: 603182.88 | S86: =IFERROR(VLOOKUP(CONCATENATE(Fix_Mapping[[#This Row],[KODE BARANG]],1),'Form Fix'!$A$6:$F$911,4,0),0) -> 0 | T86: =IFERROR(VLOOKUP(CONCATENATE(Fix_Mapping[[#This Row],[KODE BARANG]],2),'Form Fix'!$A$6:$F$911,4,0),0) -> 0 | U86: =IFERROR(VLOOKUP(CONCATENATE(Fix_Mapping[[#This Row],[KODE BARANG]],3),'Form Fix'!$A$6:$F$911,4,0),0) -> 0 | V86: =IFERROR(VLOOKUP(CONCATENATE(Fix_Mapping[[#This Row],[KODE BARANG]],4),'Form Fix'!$A$6:$F$911,4,0),0) -> 0 | W86: =IFERROR(VLOOKUP(CONCATENATE(Fix_Mapping[[#This Row],[KODE BARANG]],5),'Form Fix'!$A$6:$F$911,4,0),0) -> 0
A87: R1022008010010 | B87: RB DETTOL BODY WASH ORIGINAL 100ML X 24 BTL | C87: 24 | D87: BTL | E87: DETTOL BODY WASH | F87: 17212.37 | G87: 413096.88 | H87: 19105.731 | I87: 458537.54 | J87: 18811.333 | K87: 451472 | L87: 20880.58 | M87: 501133.92 | N87: 18811.333 | O87: 451472 | P87: 20880.58 | Q87: 501133.92 | S87: =IFERROR(VLOOKUP(CONCATENATE(Fix_Mapping[[#This Row],[KODE BARANG]],1),'Form Fix'!$A$6:$F$911,4,0),0) -> 0 | T87: =IFERROR(VLOOKUP(CONCATENATE(Fix_Mapping[[#This Row],[KODE BARANG]],2),'Form Fix'!$A$6:$F$911,4,0),0) -> 0 | U87: =IFERROR(VLOOKUP(CONCATENATE(Fix_Mapping[[#This Row],[KODE BARANG]],3),'Form Fix'!$A$6:$F$911,4,0),0) -> 0 | V87: =IFERROR(VLOOKUP(CONCATENATE(Fix_Mapping[[#This Row],[KODE BARANG]],4),'Form Fix'!$A$6:$F$911,4,0),0) -> 0 | W87: =IFERROR(VLOOKUP(CONCATENATE(Fix_Mapping[[#This Row],[KODE BARANG]],5),'Form Fix'!$A$6:$F$911,4,0),0) -> 0
A88: R1022008010030 | B88: RB DETTOL BODY WASH ORIGINAL 100ML X 24 PCS | C88: 24 | D88: PCS | E88: DETTOL BODY WASH | F88: 4823.88 | G88: 115773.12 | H88: 5354.5068 | I88: 128508.16 | J88: 5272 | K88: 126528 | L88: 5851.92 | M88: 140446.08 | O88: 0 | P88: 0 | Q88: 0 | S88: =IFERROR(VLOOKUP(CONCATENATE(Fix_Mapping[[#This Row],[KODE BARANG]],1),'Form Fix'!$A$6:$F$911,4,0),0) -> 0 | T88: =IFERROR(VLOOKUP(CONCATENATE(Fix_Mapping[[#This Row],[KODE BARANG]],2),'Form Fix'!$A$6:$F$911,4,0),0) -> 0 | U88: =IFERROR(VLOOKUP(CONCATENATE(Fix_Mapping[[#This Row],[KODE BARANG]],3),'Form Fix'!$A$6:$F$911,4,0),0) -> 0 | V88: =IFERROR(VLOOKUP(CONCATENATE(Fix_Mapping[[#This Row],[KODE BARANG]],4),'Form Fix'!$A$6:$F$911,4,0),0) -> 0 | W88: =IFERROR(VLOOKUP(CONCATENATE(Fix_Mapping[[#This Row],[KODE BARANG]],5),'Form Fix'!$A$6:$F$911,4,0),0) -> 0
A89: R1022008020020 | B89: RB DETTOL BODY WASH ORIGINAL 200ML X 24 PCH | C89: 24 | D89: PCH | E89: DETTOL BODY WASH | F89: 15372 | G89: 368928 | H89: 17062.92 | I89: 409510.08 | J89: 16800 | K89: 403200 | L89: 18648 | M89: 447552 | N89: 16800 | O89: 403200 | P89: 18648 | Q89: 447552 | S89: =IFERROR(VLOOKUP(CONCATENATE(Fix_Mapping[[#This Row],[KODE BARANG]],1),'Form Fix'!$A$6:$F$911,4,0),0) -> 0 | T89: =IFERROR(VLOOKUP(CONCATENATE(Fix_Mapping[[#This Row],[KODE BARANG]],2),'Form Fix'!$A$6:$F$911,4,0),0) -> 0 | U89: =IFERROR(VLOOKUP(CONCATENATE(Fix_Mapping[[#This Row],[KODE BARANG]],3),'Form Fix'!$A$6:$F$911,4,0),0) -> 0 | V89: =IFERROR(VLOOKUP(CONCATENATE(Fix_Mapping[[#This Row],[KODE BARANG]],4),'Form Fix'!$A$6:$F$911,4,0),0) -> 0 | W89: =IFERROR(VLOOKUP(CONCATENATE(Fix_Mapping[[#This Row],[KODE BARANG]],5),'Form Fix'!$A$6:$F$911,4,0),0) -> 0
A90: R1022008030010 | B90: RB DETTOL BODY WASH ORIGINAL 300ML X 12 BTL | C90: 12 | D90: BTL | E90: DETTOL BODY WASH | F90: 36201.975 | G90: 434423.7 | H90: 40184.192 | I90: 482210.31 | J90: 39565 | K90: 474780 | L90: 43917.15 | M90: 527005.8 | O90: 0 | P90: 0 | Q90: 0 | S90: =IFERROR(VLOOKUP(CONCATENATE(Fix_Mapping[[#This Row],[KODE BARANG]],1),'Form Fix'!$A$6:$F$911,4,0),0) -> 0 | T90: =IFERROR(VLOOKUP(CONCATENATE(Fix_Mapping[[#This Row],[KODE BARANG]],2),'Form Fix'!$A$6:$F$911,4,0),0) -> 0 | U90: =IFERROR(VLOOKUP(CONCATENATE(Fix_Mapping[[#This Row],[KODE BARANG]],3),'Form Fix'!$A$6:$F$911,4,0),0) -> 0 | V90: =IFERROR(VLOOKUP(CONCATENATE(Fix_Mapping[[#This Row],[KODE BARANG]],4),'Form Fix'!$A$6:$F$911,4,0),0) -> 0 | W90: =IFERROR(VLOOKUP(CONCATENATE(Fix_Mapping[[#This Row],[KODE BARANG]],5),'Form Fix'!$A$6:$F$911,4,0),0) -> 0
A91: R1022008037020 | B91: RB DETTOL BODY WASH ORIGINAL 370ML X 24 PCH | C91: 24 | D91: PCH | E91: DETTOL BODY WASH | F91: 20717.43 | G91: 497218.32 | H91: 22996.347 | I91: 551912.34 | J91: 22642 | K91: 543408 | L91: 25132.62 | M91: 603182.88 | N91: 22642 | O91: 543408 | P91: 25132.62 | Q91: 603182.88 | S91: =IFERROR(VLOOKUP(CONCATENATE(Fix_Mapping[[#This Row],[KODE BARANG]],1),'Form Fix'!$A$6:$F$911,4,0),0) -> 0 | T91: =IFERROR(VLOOKUP(CONCATENATE(Fix_Mapping[[#This Row],[KODE BARANG]],2),'Form Fix'!$A$6:$F$911,4,0),0) -> 0 | U91: =IFERROR(VLOOKUP(CONCATENATE(Fix_Mapping[[#This Row],[KODE BARANG]],3),'Form Fix'!$A$6:$F$911,4,0),0) -> 0 | V91: =IFERROR(VLOOKUP(CONCATENATE(Fix_Mapping[[#This Row],[KODE BARANG]],4),'Form Fix'!$A$6:$F$911,4,0),0) -> 0 | W91: =IFERROR(VLOOKUP(CONCATENATE(Fix_Mapping[[#This Row],[KODE BARANG]],5),'Form Fix'!$A$6:$F$911,4,0),0) -> 0
A92: R1022008037021 | B92: RB DETTOL BODY WASH ORIGINAL 370ML X 24 PCH BANDED | C92: 24 | D92: PCH | E92: DETTOL BODY WASH | F92: 20717.43 | G92: 497218.32 | H92: 22996.347 | I92: 551912.34 | J92: 22642 | K92: 543408 | L92: 25132.62 | M92: 603182.88 | N92: 22642 | O92: 543408 | P92: 25132.62 | Q92: 603182.88 | S92: =IFERROR(VLOOKUP(CONCATENATE(Fix_Mapping[[#This Row],[KODE BARANG]],1),'Form Fix'!$A$6:$F$911,4,0),0) -> 0 | T92: =IFERROR(VLOOKUP(CONCATENATE(Fix_Mapping[[#This Row],[KODE BARANG]],2),'Form Fix'!$A$6:$F$911,4,0),0) -> 0 | U92: =IFERROR(VLOOKUP(CONCATENATE(Fix_Mapping[[#This Row],[KODE BARANG]],3),'Form Fix'!$A$6:$F$911,4,0),0) -> 0 | V92: =IFERROR(VLOOKUP(CONCATENATE(Fix_Mapping[[#This Row],[KODE BARANG]],4),'Form Fix'!$A$6:$F$911,4,0),0) -> 0 | W92: =IFERROR(VLOOKUP(CONCATENATE(Fix_Mapping[[#This Row],[KODE BARANG]],5),'Form Fix'!$A$6:$F$911,4,0),0) -> 0
A93: R1022008050030 | B93: RB DETTOL BODY WASH ORIGINAL 500ML X 12 PUMP | C93: 12 | D93: PUMP | E93: DETTOL BODY WASH | F93: 53802 | G93: 645624 | H93: 59720.22 | I93: 716642.64 | J93: 58800 | K93: 705600 | L93: 65268 | M93: 783216 | N93: 58800 | O93: 705600 | P93: 65268 | Q93: 783216 | S93: =IFERROR(VLOOKUP(CONCATENATE(Fix_Mapping[[#This Row],[KODE BARANG]],1),'Form Fix'!$A$6:$F$911,4,0),0) -> 0 | T93: =IFERROR(VLOOKUP(CONCATENATE(Fix_Mapping[[#This Row],[KODE BARANG]],2),'Form Fix'!$A$6:$F$911,4,0),0) -> 0 | U93: =IFERROR(VLOOKUP(CONCATENATE(Fix_Mapping[[#This Row],[KODE BARANG]],3),'Form Fix'!$A$6:$F$911,4,0),0) -> 0 | V93: =IFERROR(VLOOKUP(CONCATENATE(Fix_Mapping[[#This Row],[KODE BARANG]],4),'Form Fix'!$A$6:$F$911,4,0),0) -> 0 | W93: =IFERROR(VLOOKUP(CONCATENATE(Fix_Mapping[[#This Row],[KODE BARANG]],5),'Form Fix'!$A$6:$F$911,4,0),0) -> 0
A94: R1022008072020 | B94: RB DETTOL BODY WASH ORIGINAL 720ML X 12 PCH | C94: 12 | D94: PCH | E94: DETTOL BODY WASH | F94: 36069.3 | G94: 432831.6 | H94: 40036.923 | I94: 480443.08 | J94: 39420 | K94: 473040 | L94: 43756.2 | M94: 525074.4 | N94: 39420 | O94: 473040 | P94: 43756.2 | Q94: 525074.4 | S94: =IFERROR(VLOOKUP(CONCATENATE(Fix_Mapping[[#This Row],[KODE BARANG]],1),'Form Fix'!$A$6:$F$911,4,0),0) -> 0 | T94: =IFERROR(VLOOKUP(CONCATENATE(Fix_Mapping[[#This Row],[KODE BARANG]],2),'Form Fix'!$A$6:$F$911,4,0),0) -> 0 | U94: =IFERROR(VLOOKUP(CONCATENATE(Fix_Mapping[[#This Row],[KODE BARANG]],3),'Form Fix'!$A$6:$F$911,4,0),0) -> 0 | V94: =IFERROR(VLOOKUP(CONCATENATE(Fix_Mapping[[#This Row],[KODE BARANG]],4),'Form Fix'!$A$6:$F$911,4,0),0) -> 0 | W94: =IFERROR(VLOOKUP(CONCATENATE(Fix_Mapping[[#This Row],[KODE BARANG]],5),'Form Fix'!$A$6:$F$911,4,0),0) -> 0
A95: R1022009020010 | B95: RB DETTOL BODY WASH RE-ENERGIZER 200ML X 24 BTL | C95: 24 | D95: BTL | E95: DETTOL BODY WASH | F95: 15372 | G95: 368928 | H95: 17062.92 | I95: 409510.08 | J95: 16800 | K95: 403200 | L95: 18648 | M95: 447552 | O95: 0 | P95: 0 | Q95: 0 | S95: =IFERROR(VLOOKUP(CONCATENATE(Fix_Mapping[[#This Row],[KODE BARANG]],1),'Form Fix'!$A$6:$F$911,4,0),0) -> 0 | T95: =IFERROR(VLOOKUP(CONCATENATE(Fix_Mapping[[#This Row],[KODE BARANG]],2),'Form Fix'!$A$6:$F$911,4,0),0) -> 0 | U95: =IFERROR(VLOOKUP(CONCATENATE(Fix_Mapping[[#This Row],[KODE BARANG]],3),'Form Fix'!$A$6:$F$911,4,0),0) -> 0 | V95: =IFERROR(VLOOKUP(CONCATENATE(Fix_Mapping[[#This Row],[KODE BARANG]],4),'Form Fix'!$A$6:$F$911,4,0),0) -> 0 | W95: =IFERROR(VLOOKUP(CONCATENATE(Fix_Mapping[[#This Row],[KODE BARANG]],5),'Form Fix'!$A$6:$F$911,4,0),0) -> 0
A96: R1022009030010 | B96: RB DETTOL BODY WASH RE-ENERGIZER 300ML X 12 BTL | C96: 12 | D96: BTL | E96: DETTOL BODY WASH | F96: 36201.975 | G96: 434423.7 | H96: 40184.192 | I96: 482210.31 | J96: 39565 | K96: 474780 | L96: 43917.15 | M96: 527005.8 | O96: 0 | P96: 0 | Q96: 0 | S96: =IFERROR(VLOOKUP(CONCATENATE(Fix_Mapping[[#This Row],[KODE BARANG]],1),'Form Fix'!$A$6:$F$911,4,0),0) -> 0 | T96: =IFERROR(VLOOKUP(CONCATENATE(Fix_Mapping[[#This Row],[KODE BARANG]],2),'Form Fix'!$A$6:$F$911,4,0),0) -> 0 | U96: =IFERROR(VLOOKUP(CONCATENATE(Fix_Mapping[[#This Row],[KODE BARANG]],3),'Form Fix'!$A$6:$F$911,4,0),0) -> 0 | V96: =IFERROR(VLOOKUP(CONCATENATE(Fix_Mapping[[#This Row],[KODE BARANG]],4),'Form Fix'!$A$6:$F$911,4,0),0) -> 0 | W96: =IFERROR(VLOOKUP(CONCATENATE(Fix_Mapping[[#This Row],[KODE BARANG]],5),'Form Fix'!$A$6:$F$911,4,0),0) -> 0
A97: R1022009037020 | B97: RB DETTOL BODY WASH RE-ENERGIZER 370/410ML X 24 PCH | C97: 24 | D97: PCH | E97: DETTOL BODY WASH | F97: 20717.43 | G97: 497218.32 | H97: 22996.347 | I97: 551912.34 | J97: 22642 | K97: 543408 | L97: 25132.62 | M97: 603182.88 | N97: 22642 | O97: 543408 | P97: 25132.62 | Q97: 603182.88 | S97: =IFERROR(VLOOKUP(CONCATENATE(Fix_Mapping[[#This Row],[KODE BARANG]],1),'Form Fix'!$A$6:$F$911,4,0),0) -> 0 | T97: =IFERROR(VLOOKUP(CONCATENATE(Fix_Mapping[[#This Row],[KODE BARANG]],2),'Form Fix'!$A$6:$F$911,4,0),0) -> 0 | U97: =IFERROR(VLOOKUP(CONCATENATE(Fix_Mapping[[#This Row],[KODE BARANG]],3),'Form Fix'!$A$6:$F$911,4,0),0) -> 0 | V97: =IFERROR(VLOOKUP(CONCATENATE(Fix_Mapping[[#This Row],[KODE BARANG]],4),'Form Fix'!$A$6:$F$911,4,0),0) -> 0 | W97: =IFERROR(VLOOKUP(CONCATENATE(Fix_Mapping[[#This Row],[KODE BARANG]],5),'Form Fix'!$A$6:$F$911,4,0),0) -> 0
A98: R1022009037021 | B98: RB DETTOL BODY WASH RE-ENERGIZER 370/410ML X 24 PCH BANDED | C98: 24 | D98: PCH | E98: DETTOL BODY WASH | F98: 20717.43 | G98: 497218.32 | H98: 22996.347 | I98: 551912.34 | J98: 22642 | K98: 543408 | L98: 25132.62 | M98: 603182.88 | N98: 22642 | O98: 543408 | P98: 25132.62 | Q98: 603182.88 | S98: =IFERROR(VLOOKUP(CONCATENATE(Fix_Mapping[[#This Row],[KODE BARANG]],1),'Form Fix'!$A$6:$F$911,4,0),0) -> 0 | T98: =IFERROR(VLOOKUP(CONCATENATE(Fix_Mapping[[#This Row],[KODE BARANG]],2),'Form Fix'!$A$6:$F$911,4,0),0) -> 0 | U98: =IFERROR(VLOOKUP(CONCATENATE(Fix_Mapping[[#This Row],[KODE BARANG]],3),'Form Fix'!$A$6:$F$911,4,0),0) -> 0 | V98: =IFERROR(VLOOKUP(CONCATENATE(Fix_Mapping[[#This Row],[KODE BARANG]],4),'Form Fix'!$A$6:$F$911,4,0),0) -> 0 | W98: =IFERROR(VLOOKUP(CONCATENATE(Fix_Mapping[[#This Row],[KODE BARANG]],5),'Form Fix'!$A$6:$F$911,4,0),0) -> 0
A99: R1022010010010 | B99: RB DETTOL BODY WASH SKINCARE 100ML X 24 BTL | C99: 24 | D99: BTL | E99: DETTOL BODY WASH | F99: 17212.37 | G99: 413096.88 | H99: 19105.731 | I99: 458537.54 | J99: 18811.333 | K99: 451472 | L99: 20880.58 | M99: 501133.92 | O99: 0 | P99: 0 | Q99: 0 | S99: =IFERROR(VLOOKUP(CONCATENATE(Fix_Mapping[[#This Row],[KODE BARANG]],1),'Form Fix'!$A$6:$F$911,4,0),0) -> 0 | T99: =IFERROR(VLOOKUP(CONCATENATE(Fix_Mapping[[#This Row],[KODE BARANG]],2),'Form Fix'!$A$6:$F$911,4,0),0) -> 0 | U99: =IFERROR(VLOOKUP(CONCATENATE(Fix_Mapping[[#This Row],[KODE BARANG]],3),'Form Fix'!$A$6:$F$911,4,0),0) -> 0 | V99: =IFERROR(VLOOKUP(CONCATENATE(Fix_Mapping[[#This Row],[KODE BARANG]],4),'Form Fix'!$A$6:$F$911,4,0),0) -> 0 | W99: =IFERROR(VLOOKUP(CONCATENATE(Fix_Mapping[[#This Row],[KODE BARANG]],5),'Form Fix'!$A$6:$F$911,4,0),0) -> 0
A100: R1022010020020 | B100: RB DETTOL BODY WASH SKINCARE 200ML X 24 PCH | C100: 24 | D100: PCH | E100: DETTOL BODY WASH | F100: 15372 | G100: 368928 | H100: 17062.92 | I100: 409510.08 | J100: 16800 | K100: 403200 | L100: 18648 | M100: 447552 | N100: 16800 | O100: 403200 | P100: 18648 | Q100: 447552 | S100: =IFERROR(VLOOKUP(CONCATENATE(Fix_Mapping[[#This Row],[KODE BARANG]],1),'Form Fix'!$A$6:$F$911,4,0),0) -> 0 | T100: =IFERROR(VLOOKUP(CONCATENATE(Fix_Mapping[[#This Row],[KODE BARANG]],2),'Form Fix'!$A$6:$F$911,4,0),0) -> 0 | U100: =IFERROR(VLOOKUP(CONCATENATE(Fix_Mapping[[#This Row],[KODE BARANG]],3),'Form Fix'!$A$6:$F$911,4,0),0) -> 0 | V100: =IFERROR(VLOOKUP(CONCATENATE(Fix_Mapping[[#This Row],[KODE BARANG]],4),'Form Fix'!$A$6:$F$911,4,0),0) -> 0 | W100: =IFERROR(VLOOKUP(CONCATENATE(Fix_Mapping[[#This Row],[KODE BARANG]],5),'Form Fix'!$A$6:$F$911,4,0),0) -> 0
...

Sheet Query Map.BrgDoubleDms
A1: Kode BARANG Win2 | B1: Nama Win | C1: PCPL KODE 1 | D1: PCPL KODE 2 | E1: PCPL KODE 3 | F1: PCPL KODE 4 | G1: PCPL KODE 5
A2: R1011000010010 | B2: RB BRASSO METAL POOLISH 100ML X 48 PCS | C2: =IFERROR(VLOOKUP(CONCATENATE(Table43_1[[#This Row],[Kode BARANG Win2]],1),'Form Fix'!$A$6:$F$911,4,0),0) -> 3121445 | D2: =IFERROR(VLOOKUP(CONCATENATE(Table43_1[[#This Row],[Kode BARANG Win2]],2),'Form Fix'!$A$6:$F$911,4,0),0) -> 3055580 | E2: =IFERROR(VLOOKUP(CONCATENATE(Table43_1[[#This Row],[Kode BARANG Win2]],3),'Form Fix'!$A$6:$F$911,4,0),0) -> ID020064 | F2: =IFERROR(VLOOKUP(CONCATENATE(Table43_1[[#This Row],[Kode BARANG Win2]],4),'Form Fix'!$A$6:$F$911,4,0),0) -> 0 | G2: =IFERROR(VLOOKUP(CONCATENATE(Table43_1[[#This Row],[Kode BARANG Win2]],5),'Form Fix'!$A$6:$F$911,4,0),0) -> 0
A3: R1021001006010 | B3: RB DETTOL BODY SOAP COOL 60GR X 144 PCS | C3: =IFERROR(VLOOKUP(CONCATENATE(Table43_1[[#This Row],[Kode BARANG Win2]],1),'Form Fix'!$A$6:$F$911,4,0),0) -> 3171295 | D3: =IFERROR(VLOOKUP(CONCATENATE(Table43_1[[#This Row],[Kode BARANG Win2]],2),'Form Fix'!$A$6:$F$911,4,0),0) -> 3166934 | E3: =IFERROR(VLOOKUP(CONCATENATE(Table43_1[[#This Row],[Kode BARANG Win2]],3),'Form Fix'!$A$6:$F$911,4,0),0) -> 3119258 | F3: =IFERROR(VLOOKUP(CONCATENATE(Table43_1[[#This Row],[Kode BARANG Win2]],4),'Form Fix'!$A$6:$F$911,4,0),0) -> 3331432 | G3: =IFERROR(VLOOKUP(CONCATENATE(Table43_1[[#This Row],[Kode BARANG Win2]],5),'Form Fix'!$A$6:$F$911,4,0),0) -> 0
A4: R1021001010010 | B4: RB DETTOL BODY SOAP COOL 100GR X 144 PCS | C4: =IFERROR(VLOOKUP(CONCATENATE(Table43_1[[#This Row],[Kode BARANG Win2]],1),'Form Fix'!$A$6:$F$911,4,0),0) -> 3171286 | D4: =IFERROR(VLOOKUP(CONCATENATE(Table43_1[[#This Row],[Kode BARANG Win2]],2),'Form Fix'!$A$6:$F$911,4,0),0) -> 3166924 | E4: =IFERROR(VLOOKUP(CONCATENATE(Table43_1[[#This Row],[Kode BARANG Win2]],3),'Form Fix'!$A$6:$F$911,4,0),0) -> 3060311 | F4: =IFERROR(VLOOKUP(CONCATENATE(Table43_1[[#This Row],[Kode BARANG Win2]],4),'Form Fix'!$A$6:$F$911,4,0),0) -> 3087451 | G4: =IFERROR(VLOOKUP(CONCATENATE(Table43_1[[#This Row],[Kode BARANG Win2]],5),'Form Fix'!$A$6:$F$911,4,0),0) -> ID8195121M
A5: R1021002010010 | B5: RB DETTOL BODY SOAP FAMILY PROTECT 100GR X 144 PCS | C5: =IFERROR(VLOOKUP(CONCATENATE(Table43_1[[#This Row],[Kode BARANG Win2]],1),'Form Fix'!$A$6:$F$911,4,0),0) -> 3300517 | D5: =IFERROR(VLOOKUP(CONCATENATE(Table43_1[[#This Row],[Kode BARANG Win2]],2),'Form Fix'!$A$6:$F$911,4,0),0) -> 0 | E5: =IFERROR(VLOOKUP(CONCATENATE(Table43_1[[#This Row],[Kode BARANG Win2]],3),'Form Fix'!$A$6:$F$911,4,0),0) -> 0 | F5: =IFERROR(VLOOKUP(CONCATENATE(Table43_1[[#This Row],[Kode BARANG Win2]],4),'Form Fix'!$A$6:$F$911,4,0),0) -> 0 | G5: =IFERROR(VLOOKUP(CONCATENATE(Table43_1[[#This Row],[Kode BARANG Win2]],5),'Form Fix'!$A$6:$F$911,4,0),0) -> 0
A6: R1021003006010 | B6: RB DETTOL BODY SOAP FRESH 60GR X 144 PCS | C6: =IFERROR(VLOOKUP(CONCATENATE(Table43_1[[#This Row],[Kode BARANG Win2]],1),'Form Fix'!$A$6:$F$911,4,0),0) -> 3170933 | D6: =IFERROR(VLOOKUP(CONCATENATE(Table43_1[[#This Row],[Kode BARANG Win2]],2),'Form Fix'!$A$6:$F$911,4,0),0) -> 3147626 | E6: =IFERROR(VLOOKUP(CONCATENATE(Table43_1[[#This Row],[Kode BARANG Win2]],3),'Form Fix'!$A$6:$F$911,4,0),0) -> 0 | F6: =IFERROR(VLOOKUP(CONCATENATE(Table43_1[[#This Row],[Kode BARANG Win2]],4),'Form Fix'!$A$6:$F$911,4,0),0) -> 0 | G6: =IFERROR(VLOOKUP(CONCATENATE(Table43_1[[#This Row],[Kode BARANG Win2]],5),'Form Fix'!$A$6:$F$911,4,0),0) -> 0
A7: R1021003010010 | B7: RB DETTOL BODY SOAP FRESH 100GR X 144 PCS | C7: =IFERROR(VLOOKUP(CONCATENATE(Table43_1[[#This Row],[Kode BARANG Win2]],1),'Form Fix'!$A$6:$F$911,4,0),0) -> 3170945 | D7: =IFERROR(VLOOKUP(CONCATENATE(Table43_1[[#This Row],[Kode BARANG Win2]],2),'Form Fix'!$A$6:$F$911,4,0),0) -> 0 | E7: =IFERROR(VLOOKUP(CONCATENATE(Table43_1[[#This Row],[Kode BARANG Win2]],3),'Form Fix'!$A$6:$F$911,4,0),0) -> 0 | F7: =IFERROR(VLOOKUP(CONCATENATE(Table43_1[[#This Row],[Kode BARANG Win2]],4),'Form Fix'!$A$6:$F$911,4,0),0) -> 0 | G7: =IFERROR(VLOOKUP(CONCATENATE(Table43_1[[#This Row],[Kode BARANG Win2]],5),'Form Fix'!$A$6:$F$911,4,0),0) -> 0
A8: R1021004006010 | B8: RB DETTOL BODY SOAP LASTING 60GR X 144 PCS | C8: =IFERROR(VLOOKUP(CONCATENATE(Table43_1[[#This Row],[Kode BARANG Win2]],1),'Form Fix'!$A$6:$F$911,4,0),0) -> 3166937 | D8: =IFERROR(VLOOKUP(CONCATENATE(Table43_1[[#This Row],[Kode BARANG Win2]],2),'Form Fix'!$A$6:$F$911,4,0),0) -> 3148248 | E8: =IFERROR(VLOOKUP(CONCATENATE(Table43_1[[#This Row],[Kode BARANG Win2]],3),'Form Fix'!$A$6:$F$911,4,0),0) -> 0 | F8: =IFERROR(VLOOKUP(CONCATENATE(Table43_1[[#This Row],[Kode BARANG Win2]],4),'Form Fix'!$A$6:$F$911,4,0),0) -> 0 | G8: =IFERROR(VLOOKUP(CONCATENATE(Table43_1[[#This Row],[Kode BARANG Win2]],5),'Form Fix'!$A$6:$F$911,4,0),0) -> 0
A9: R1021004010010 | B9: RB DETTOL BODY SOAP LASTING 100GR X 144 PCS | C9: =IFERROR(VLOOKUP(CONCATENATE(Table43_1[[#This Row],[Kode BARANG Win2]],1),'Form Fix'!$A$6:$F$911,4,0),0) -> 3166942 | D9: =IFERROR(VLOOKUP(CONCATENATE(Table43_1[[#This Row],[Kode BARANG Win2]],2),'Form Fix'!$A$6:$F$911,4,0),0) -> 3060668 | E9: =IFERROR(VLOOKUP(CONCATENATE(Table43_1[[#This Row],[Kode BARANG Win2]],3),'Form Fix'!$A$6:$F$911,4,0),0) -> 3087594 | F9: =IFERROR(VLOOKUP(CONCATENATE(Table43_1[[#This Row],[Kode BARANG Win2]],4),'Form Fix'!$A$6:$F$911,4,0),0) -> ID8195069M | G9: =IFERROR(VLOOKUP(CONCATENATE(Table43_1[[#This Row],[Kode BARANG Win2]],5),'Form Fix'!$A$6:$F$911,4,0),0) -> 3031729
A10: R1021005006010 | B10: RB DETTOL BODY SOAP ORIGINAL 60GR X 144 PCS | C10: =IFERROR(VLOOKUP(CONCATENATE(Table43_1[[#This Row],[Kode BARANG Win2]],1),'Form Fix'!$A$6:$F$911,4,0),0) -> 3166975 | D10: =IFERROR(VLOOKUP(CONCATENATE(Table43_1[[#This Row],[Kode BARANG Win2]],2),'Form Fix'!$A$6:$F$911,4,0),0) -> 3331433 | E10: =IFERROR(VLOOKUP(CONCATENATE(Table43_1[[#This Row],[Kode BARANG Win2]],3),'Form Fix'!$A$6:$F$911,4,0),0) -> 3119259 | F10: =IFERROR(VLOOKUP(CONCATENATE(Table43_1[[#This Row],[Kode BARANG Win2]],4),'Form Fix'!$A$6:$F$911,4,0),0) -> 3238406 | G10: =IFERROR(VLOOKUP(CONCATENATE(Table43_1[[#This Row],[Kode BARANG Win2]],5),'Form Fix'!$A$6:$F$911,4,0),0) -> 3224742
A11: R1021005010010 | B11: RB DETTOL BODY SOAP ORIGINAL 100GR X 144 PCS | C11: =IFERROR(VLOOKUP(CONCATENATE(Table43_1[[#This Row],[Kode BARANG Win2]],1),'Form Fix'!$A$6:$F$911,4,0),0) -> 3166958 | D11: =IFERROR(VLOOKUP(CONCATENATE(Table43_1[[#This Row],[Kode BARANG Win2]],2),'Form Fix'!$A$6:$F$911,4,0),0) -> 3083294 | E11: =IFERROR(VLOOKUP(CONCATENATE(Table43_1[[#This Row],[Kode BARANG Win2]],3),'Form Fix'!$A$6:$F$911,4,0),0) -> 3238701 | F11: =IFERROR(VLOOKUP(CONCATENATE(Table43_1[[#This Row],[Kode BARANG Win2]],4),'Form Fix'!$A$6:$F$911,4,0),0) -> 3061093 | G11: =IFERROR(VLOOKUP(CONCATENATE(Table43_1[[#This Row],[Kode BARANG Win2]],5),'Form Fix'!$A$6:$F$911,4,0),0) -> 3224745
A12: R1021006006010 | B12: RB DETTOL BODY SOAP RE-ENERGIZER 60GR X 144 PCS | C12: =IFERROR(VLOOKUP(CONCATENATE(Table43_1[[#This Row],[Kode BARANG Win2]],1),'Form Fix'!$A$6:$F$911,4,0),0) -> 3193502 | D12: =IFERROR(VLOOKUP(CONCATENATE(Table43_1[[#This Row],[Kode BARANG Win2]],2),'Form Fix'!$A$6:$F$911,4,0),0) -> 0 | E12: =IFERROR(VLOOKUP(CONCATENATE(Table43_1[[#This Row],[Kode BARANG Win2]],3),'Form Fix'!$A$6:$F$911,4,0),0) -> 0 | F12: =IFERROR(VLOOKUP(CONCATENATE(Table43_1[[#This Row],[Kode BARANG Win2]],4),'Form Fix'!$A$6:$F$911,4,0),0) -> 0 | G12: =IFERROR(VLOOKUP(CONCATENATE(Table43_1[[#This Row],[Kode BARANG Win2]],5),'Form Fix'!$A$6:$F$911,4,0),0) -> 0
A13: R1021007006010 | B13: RB DETTOL BODY SOAP SKINCARE 60GR X 144 PCS | C13: =IFERROR(VLOOKUP(CONCATENATE(Table43_1[[#This Row],[Kode BARANG Win2]],1),'Form Fix'!$A$6:$F$911,4,0),0) -> 3193501 | D13: =IFERROR(VLOOKUP(CONCATENATE(Table43_1[[#This Row],[Kode BARANG Win2]],2),'Form Fix'!$A$6:$F$911,4,0),0) -> 3337511 | E13: =IFERROR(VLOOKUP(CONCATENATE(Table43_1[[#This Row],[Kode BARANG Win2]],3),'Form Fix'!$A$6:$F$911,4,0),0) -> 0 | F13: =IFERROR(VLOOKUP(CONCATENATE(Table43_1[[#This Row],[Kode BARANG Win2]],4),'Form Fix'!$A$6:$F$911,4,0),0) -> 0 | G13: =IFERROR(VLOOKUP(CONCATENATE(Table43_1[[#This Row],[Kode BARANG Win2]],5),'Form Fix'!$A$6:$F$911,4,0),0) -> 0
... A201: R1100000003010 | B201: RB MULTI PURPOSE CLEANER LEMON 30S X 9 PCS | C201: =IFERROR(VLOOKUP(CONCATENATE(Table43_1[[#This Row],[Kode BARANG Win2]],1),'Form Fix'!$A$6:$F$911,4,0),0) -> 0 | D201: =IFERROR(VLOOKUP(CONCATENATE(Table43_1[[#This Row],[Kode BARANG Win2]],2),'Form Fix'!$A$6:$F$911,4,0),0) -> 0 | E201: =IFERROR(VLOOKUP(CONCATENATE(Table43_1[[#This Row],[Kode BARANG Win2]],3),'Form Fix'!$A$6:$F$911,4,0),0) -> 0 | F201: =IFERROR(VLOOKUP(CONCATENATE(Table43_1[[#This Row],[Kode BARANG Win2]],4),'Form Fix'!$A$6:$F$911,4,0),0) -> 0 | G201: =IFERROR(VLOOKUP(CONCATENATE(Table43_1[[#This Row],[Kode BARANG Win2]],5),'Form Fix'!$A$6:$F$911,4,0),0) -> 0

Sheet Form Fix
C1: UPDATE TGL
P2: =COUNTIF(Table43[LEN 50], ">50") -> 97
D3: PASTE NAMA DAN CODE PRINCIPLE (Buat Format seperti ini dan Ambil dari Daftar Harga Principle) | Q3: CPI | AN3: Daftar Harga | BC3: Update Per
J4: ISI SESUAIKAN ANTARA DMS vs WIN | L4: HASIL CODE KELOMPOK, CODE BARANG & NAMA BARANG WIN | Q4: Kolom Principle | AN4: Harga Beli | AR4: Harga Jual GT | AV4: Harga Jual MT | AZ4: MARGIN | BH4: To Win, diisi oleh Admin
A5: CONCATENATE MAPPING | B5: No. Urut Item Sama | C5: NO | D5: Kode Pcpl | E5: Klp Brg Pcpl | F5: Nama Barang Principle | G5: ISI/CTN | H5: Column3 | I5: Ket. Tambahan / Pembantu | J5: SATUAN Fix Win | K5: Nama Kelompok Win | L5: Kode Kelompok Win | M5: Kode BARANG Win2 | N5: LEN 15 | O5: Nama Win | P5: LEN 50 | Q5: Nama Pcpl | R5: kode 2 Digit (hrf+No) | S5: Nama KLP | T5: kode 2 Digit (Nomor) | U5: Nama Sub KLP | V5: kode 1 Digit (Nomor) | W5: Nama Sub KLP2 | X5: kode 1 Digit (Nomor)5 | Y5: Nama Aroma/ Rasa | Z5: kode 2 Digit (Nomor)2 | AA5: Nama Gramasi atau Jumlah Pack per CTN | AB5: kode 4 Digit (Nomor) | AC5: Nama Jenis Kemasan | AD5: kode 1 Digit (Nomor)3 | AE5: Nama Promo | AF5: kode 1 Digit (Nomor)4 | AG5: Gunakan ini apabila item tersebut sachet | AH5: kode 1 Digit (Nomor)32 | AI5: KET TAMBAHAN2 | AJ5: KET TAMBAHAN3 | AK5: KET. GOLONGAN | AL5: kode 1 Digit (Nomor) | AM5: Tanda Kode Revisi | AN5: Harga Beli Pcs (-PPN) | AO5: Harga Beli Krt (- PPN) | AP5: Harga Beli Pcs (+PPN) | AQ5: Harga Beli Krt (+PPN) | AR5: Harga Jual Pcs GT (-PPN) | AS5: Harga Jual Krt GT (- PPN) | AT5: Harga Jual Pcs GT (+PPN | AU5: Harga Jual Krt GT (+PPN) | AV5: Harga Jual Pcs MT (-PPN) | AW5: Harga Jual Krt MT (- PPN) | AX5: Harga Jual Pcs MT (+PPN) | AY5: Harga Jual Krt MT (+PPN) | AZ5: MARGIN | BA5: Column1 | BB5: Column2 | BC5: Efektif Pembuatan | BD5: Efektif Naik Harga | BE5: Status Pembuatan | BF5: Status Harga | BG5: Status Barang | BH5: Mata Uang | BI5: Kode Golongan | BJ5: Nama Golongan | BK5: Kode PCPL To Win | BL5: Kode Jenis Produk | BM5: SAT BSR | BN5: GD | BO5: Kode PRK | BP5: Kode PRK SJ | BQ5: Kode Job | BR5: Approval | BS5: Nama Principle
A6: =CONCATENATE(Table43[[#This Row],[Kode BARANG Win2]],Table43[[#This Row],[No. Urut Item Sama]]) -> R10110000100101 | B6: 1 | C6: BRASO METAL POLISH 48 PCS X 100ML "3121445"B01 | D6: 3121445 | E6: =IFERROR(VLOOKUP(Table43[[#This Row],[NO]],[1]Sheet1!$G$3:$K$1267,5,0),0) -> 0 | F6: BRASOID6X8X100ML | G6: 48 | H6: BRASO METAL POLISH 48 PCS X 100ML "3121445"B01 | I6: 8888071280000 | J6: =Table43[[#This Row],[Nama Jenis Kemasan]] -> PCS | K6: =TRIM(CONCATENATE(Table43[[#This Row],[Nama KLP]]," ",Table43[[#This Row],[Nama Sub KLP]])) -> BRASSO METAL POOLISH | L6: =CONCATENATE(Table43[[#This Row],[kode 2 Digit (hrf+No)]],Table43[[#This Row],[kode 2 Digit (Nomor)]],Table43[[#This Row],[kode 1 Digit (Nomor)]]) -> R1011 | M6: =IF(AH6="",CONCATENATE(R6,T6,V6,X6,Z6,AB6,AD6,AF6,Table43[[#This Row],[Tanda Kode Revisi]]),CONCATENATE(R6,T6,V6,X6,Z6,AB6,AD6,AH6)) -> R1011000010010 | N6: =LEN(M6) -> 14 | O6: =IF(AG6<>"",TRIM(UPPER(CONCATENATE(Q6," ",S6," ",U6," ",W6," ",Y6," ",AA6," ","X"," ",Table43[[#This Row],[ISI/CTN]]," ",AG6," ",AC6," ",AE6," ",AI6))),TRIM(UPPER(CONCATENATE(Q6," ",S6," ",U6," ",W6," ",Y6," ",AA6," ","X"," ",Table43[[#This Row],[ISI/CTN]]," ",AC6," ",AE6," ",AI6)))) -> RB BRASSO METAL POOLISH 100ML X 48 PCS | P6: =LEN(O6) -> 38 | Q6: RB | R6: R1 | S6: BRASSO | T6: 01 | U6: METAL POOLISH | V6: 1 | X6: 0 | Z6: 00 | AA6: 100ML | AB6: 0100 | AC6: PCS | AD6: 1 | AF6: 0 | AJ6: =IFERROR(VLOOKUP(Table43[[#This Row],[Kode BARANG Win2]],'[2]Template Impor Barang'!#REF!,2,0),0) -> 0 | AK6: =Table43[[#This Row],[ISI/CTN]] -> 48 | AL6: =Table43[[#This Row],[Kode Pcpl]] -> 3121445 | AN6: =Table43[[#This Row],[Harga Jual Pcs GT (-PPN)]]-(Table43[[#This Row],[Harga Jual Pcs GT (-PPN)]]*8.5%) -> 22749.168 | AO6: =Table43[[#This Row],[Harga Beli Pcs (-PPN)]]*Table43[[#This Row],[ISI/CTN]] -> 1091960.1 | AP6: =Table43[[#This Row],[Harga Beli Pcs (-PPN)]]*1.11 -> 25251.577 | AQ6: =Table43[[#This Row],[Harga Beli Krt (- PPN)]]*1.11 -> 1212075.7 | AR6: 24862.479 | AS6: =Table43[[#This Row],[Harga Jual Pcs GT (-PPN)]]*Table43[[#This Row],[ISI/CTN]] -> 1193399 | AT6: =Table43[[#This Row],[Harga Jual Pcs GT (-PPN)]]*1.11 -> 27597.352 | AU6: =Table43[[#This Row],[Harga Jual Krt GT (- PPN)]]*1.11 -> 1324672.9 | AV6: 24862.479 | AW6: =Table43[[#This Row],[Harga Jual Pcs MT (-PPN)]]*Table43[[#This Row],[ISI/CTN]] -> 1193399 | AX6: =Table43[[#This Row],[Harga Jual Pcs MT (-PPN)]]*1.11 -> 27597.352 | AY6: =Table43[[#This Row],[Harga Jual Pcs MT (+PPN)]]*Table43[[#This Row],[ISI/CTN]] -> 1324672.9 | AZ6: =(Table43[[#This Row],[Harga Jual Pcs GT (-PPN)]]-Table43[[#This Row],[Harga Beli Pcs (-PPN)]])/Table43[[#This Row],[Harga Jual Pcs GT (-PPN)]] -> 0.085 | BA6: =Table43[[#This Row],[Harga Jual Pcs MT (-PPN)]]-Table43[[#This Row],[Harga Beli Pcs (-PPN)]] -> 2113.3107 | BB6: =Table43[[#This Row],[Column1]]/Table43[[#This Row],[Harga Jual Pcs MT (-PPN)]] -> 0.085 | BD6: =IFERROR(VLOOKUP(Table43[[#This Row],[Kode BARANG Win2]],'[3]Daftar Barang dan Jasa'!$B$2:$D$3515,3,0),0) -> RB BRASSO METAL POOLISH 100ML X 48 PCS | BE6: =IF(TODAY()-Table43[[#This Row],[Efektif Pembuatan]]>60,"Lama","Baru") -> Lama | BF6: =IF(TODAY()-Table43[[#This Row],[Efektif Naik Harga]]<30,"Naik","Sama") -> #VALUE! | BG6: Aktif | BH6: =IF(Table43[[#This Row],[Kode BARANG Win2]]<>"","IDR","") -> IDR | BI6: =CONCATENATE(Table43[[#This Row],[kode 1 Digit (Nomor)]],Table43[[#This Row],[kode 4 Digit (Nomor)]]) -> 31214450100 | BJ6: =Table43[[#This Row],[Nama Gramasi atau Jumlah Pack per CTN]] -> 100ML | BM6: =IF(Table43[[#This Row],[SATUAN Fix Win]]<>"","KRT") -> KRT | BN6: =IF(Table43[[#This Row],[SATUAN Fix Win]]<>"","GD01") -> GD01 | BO6: =IF(Table43[[#This Row],[SATUAN Fix Win]]<>"",11611) -> 11611 | BP6: =IF(Table43[[#This Row],[SATUAN Fix Win]]<>"",11612) -> 11612 | BR6: =IF(Table43[[#This Row],[SATUAN Fix Win]]<>"",1) -> 1
A7: =CONCATENATE(Table43[[#This Row],[Kode BARANG Win2]],Table43[[#This Row],[No. Urut Item Sama]]) -> R10110000100102 | B7: 2 | C7: BRASO METAL POLISH 48 PCS X 100ML "3121445"B01 | D7: 3055580 | E7: =IFERROR(VLOOKUP(Table43[[#This Row],[NO]],[1]Sheet1!$G$3:$K$1267,5,0),0) -> 0 | F7: BRASOINPOLISH 100ML-EXP ID | G7: 48 | I7: 8888071280000 | J7: =Table43[[#This Row],[Nama Jenis Kemasan]] -> PCS | K7: =TRIM(CONCATENATE(Table43[[#This Row],[Nama KLP]]," ",Table43[[#This Row],[Nama Sub KLP]])) -> BRASSO METAL POOLISH | L7: =CONCATENATE(Table43[[#This Row],[kode 2 Digit (hrf+No)]],Table43[[#This Row],[kode 2 Digit (Nomor)]],Table43[[#This Row],[kode 1 Digit (Nomor)]]) -> R1011 | M7: =IF(AH7="",CONCATENATE(R7,T7,V7,X7,Z7,AB7,AD7,AF7,Table43[[#This Row],[Tanda Kode Revisi]]),CONCATENATE(R7,T7,V7,X7,Z7,AB7,AD7,AH7)) -> R1011000010010 | N7: =LEN(M7) -> 14 | O7: =IF(AG7<>"",TRIM(UPPER(CONCATENATE(Q7," ",S7," ",U7," ",W7," ",Y7," ",AA7," ","X"," ",Table43[[#This Row],[ISI/CTN]]," ",AG7," ",AC7," ",AE7," ",AI7))),TRIM(UPPER(CONCATENATE(Q7," ",S7," ",U7," ",W7," ",Y7," ",AA7," ","X"," ",Table43[[#This Row],[ISI/CTN]]," ",AC7," ",AE7," ",AI7)))) -> RB BRASSO METAL POOLISH 100ML X 48 PCS | P7: =LEN(O7) -> 38 | Q7: RB | R7: R1 | S7: BRASSO | T7: 01 | U7: METAL POOLISH | V7: 1 | X7: 0 | Z7: 00 | AA7: 100ML | AB7: 0100 | AC7: PCS | AD7: 1 | AF7: 0 | AJ7: =IFERROR(VLOOKUP(Table43[[#This Row],[Kode BARANG Win2]],'[2]Template Impor Barang'!#REF!,2,0),0) -> 0 | AK7: =Table43[[#This Row],[ISI/CTN]] -> 48 | AL7: =Table43[[#This Row],[Kode Pcpl]] -> 3055580 | AN7: =Table43[[#This Row],[Harga Jual Pcs GT (-PPN)]]-(Table43[[#This Row],[Harga Jual Pcs GT (-PPN)]]*8.5%) -> 22749.168 | AO7: =Table43[[#This Row],[Harga Beli Pcs (-PPN)]]*Table43[[#This Row],[ISI/CTN]] -> 1091960.1 | AP7: =Table43[[#This Row],[Harga Beli Pcs (-PPN)]]*1.11 -> 25251.577 | AQ7: =Table43[[#This Row],[Harga Beli Krt (- PPN)]]*1.11 -> 1212075.7 | AR7: 24862.479 | AS7: =Table43[[#This Row],[Harga Jual Pcs GT (-PPN)]]*Table43[[#This Row],[ISI/CTN]] -> 1193399 | AT7: =Table43[[#This Row],[Harga Jual Pcs GT (-PPN)]]*1.11 -> 27597.352 | AU7: =Table43[[#This Row],[Harga Jual Krt GT (- PPN)]]*1.11 -> 1324672.9 | AV7: 24862.479 | AW7: =Table43[[#This Row],[Harga Jual Pcs MT (-PPN)]]*Table43[[#This Row],[ISI/CTN]] -> 1193399 | AX7: =Table43[[#This Row],[Harga Jual Pcs MT (-PPN)]]*1.11 -> 27597.352 | AY7: =Table43[[#This Row],[Harga Jual Pcs MT (+PPN)]]*Table43[[#This Row],[ISI/CTN]] -> 1324672.9 | AZ7: =(Table43[[#This Row],[Harga Jual Pcs GT (-PPN)]]-Table43[[#This Row],[Harga Beli Pcs (-PPN)]])/Table43[[#This Row],[Harga Jual Pcs GT (-PPN)]] -> 0.085 | BA7: =Table43[[#This Row],[Harga Jual Pcs MT (-PPN)]]-Table43[[#This Row],[Harga Beli Pcs (-PPN)]] -> 2113.3107 | BB7: =Table43[[#This Row],[Column1]]/Table43[[#This Row],[Harga Jual Pcs MT (-PPN)]] -> 0.085 | BD7: =IFERROR(VLOOKUP(Table43[[#This Row],[Kode BARANG Win2]],'[3]Daftar Barang dan Jasa'!$B$2:$D$3515,3,0),0) -> RB BRASSO METAL POOLISH 100ML X 48 PCS | BE7: =IF(TODAY()-Table43[[#This Row],[Efektif Pembuatan]]>60,"Lama","Baru") -> Lama | BF7: =IF(TODAY()-Table43[[#This Row],[Efektif Naik Harga]]<30,"Naik","Sama") -> #VALUE! | BG7: Aktif | BH7: =IF(Table43[[#This Row],[Kode BARANG Win2]]<>"","IDR","") -> IDR | BI7: =CONCATENATE(Table43[[#This Row],[kode 1 Digit (Nomor)]],Table43[[#This Row],[kode 4 Digit (Nomor)]]) -> 30555800100 | BJ7: =Table43[[#This Row],[Nama Gramasi atau Jumlah Pack per CTN]] -> 100ML | BM7: =IF(Table43[[#This Row],[SATUAN Fix Win]]<>"","KRT") -> KRT | BN7: =IF(Table43[[#This Row],[SATUAN Fix Win]]<>"","GD01") -> GD01 | BO7: =IF(Table43[[#This Row],[SATUAN Fix Win]]<>"",11611) -> 11611 | BP7: =IF(Table43[[#This Row],[SATUAN Fix Win]]<>"",11612) -> 11612 | BR7: =IF(Table43[[#This Row],[SATUAN Fix Win]]<>"",1) -> 1
A8: =CONCATENATE(Table43[[#This Row],[Kode BARANG Win2]],Table43[[#This Row],[No. Urut Item Sama]]) -> R10110000100103 | B8: 3 | C8: BRASO METAL POLISH 48 PCS X 100ML "3121445"B01 | D8: ID020064 | E8: =IFERROR(VLOOKUP(Table43[[#This Row],[NO]],[1]Sheet1!$G$3:$K$1267,5,0),0) -> 0 | F8: Brasso Metal Polish 100ml | G8: 48 | I8: 8888071280000 | J8: =Table43[[#This Row],[Nama Jenis Kemasan]] -> PCS | K8: =TRIM(CONCATENATE(Table43[[#This Row],[Nama KLP]]," ",Table43[[#This Row],[Nama Sub KLP]])) -> BRASSO METAL POOLISH | L8: =CONCATENATE(Table43[[#This Row],[kode 2 Digit (hrf+No)]],Table43[[#This Row],[kode 2 Digit (Nomor)]],Table43[[#This Row],[kode 1 Digit (Nomor)]]) -> R1011 | M8: =IF(AH8="",CONCATENATE(R8,T8,V8,X8,Z8,AB8,AD8,AF8,Table43[[#This Row],[Tanda Kode Revisi]]),CONCATENATE(R8,T8,V8,X8,Z8,AB8,AD8,AH8)) -> R1011000010010 | N8: =LEN(M8) -> 14 | O8: =IF(AG8<>"",TRIM(UPPER(CONCATENATE(Q8," ",S8," ",U8," ",W8," ",Y8," ",AA8," ","X"," ",Table43[[#This Row],[ISI/CTN]]," ",AG8," ",AC8," ",AE8," ",AI8))),TRIM(UPPER(CONCATENATE(Q8," ",S8," ",U8," ",W8," ",Y8," ",AA8," ","X"," ",Table43[[#This Row],[ISI/CTN]]," ",AC8," ",AE8," ",AI8)))) -> RB BRASSO METAL POOLISH 100ML X 48 PCS | P8: =LEN(O8) -> 38 | Q8: RB | R8: R1 | S8: BRASSO | T8: 01 | U8: METAL POOLISH | V8: 1 | X8: 0 | Z8: 00 | AA8: 100ML | AB8: 0100 | AC8: PCS | AD8: 1 | AF8: 0 | AJ8: =IFERROR(VLOOKUP(Table43[[#This Row],[Kode BARANG Win2]],'[2]Template Impor Barang'!#REF!,2,0),0) -> 0 | AK8: =Table43[[#This Row],[ISI/CTN]] -> 48 | AL8: =Table43[[#This Row],[Kode Pcpl]] -> ID020064 | AN8: =Table43[[#This Row],[Harga Jual Pcs GT (-PPN)]]-(Table43[[#This Row],[Harga Jual Pcs GT (-PPN)]]*8.5%) -> 22749.168 | AO8: =Table43[[#This Row],[Harga Beli Pcs (-PPN)]]*Table43[[#This Row],[ISI/CTN]] -> 1091960.1 | AP8: =Table43[[#This Row],[Harga Beli Pcs (-PPN)]]*1.11 -> 25251.577 | AQ8: =Table43[[#This Row],[Harga Beli Krt (- PPN)]]*1.11 -> 1212075.7 | AR8: 24862.479 | AS8: =Table43[[#This Row],[Harga Jual Pcs GT (-PPN)]]*Table43[[#This Row],[ISI/CTN]] -> 1193399 | AT8: =Table43[[#This Row],[Harga Jual Pcs GT (-PPN)]]*1.11 -> 27597.352 | AU8: =Table43[[#This Row],[Harga Jual Krt GT (- PPN)]]*1.11 -> 1324672.9 | AV8: 24862.479 | AW8: =Table43[[#This Row],[Harga Jual Pcs MT (-PPN)]]*Table43[[#This Row],[ISI/CTN]] -> 1193399 | AX8: =Table43[[#This Row],[Harga Jual Pcs MT (-PPN)]]*1.11 -> 27597.352 | AY8: =Table43[[#This Row],[Harga Jual Pcs MT (+PPN)]]*Table43[[#This Row],[ISI/CTN]] -> 1324672.9 | AZ8: =(Table43[[#This Row],[Harga Jual Pcs GT (-PPN)]]-Table43[[#This Row],[Harga Beli Pcs (-PPN)]])/Table43[[#This Row],[Harga Jual Pcs GT (-PPN)]] -> 0.085 | BA8: =Table43[[#This Row],[Harga Jual Pcs MT (-PPN)]]-Table43[[#This Row],[Harga Beli Pcs (-PPN)]] -> 2113.3107 | BB8: =Table43[[#This Row],[Column1]]/Table43[[#This Row],[Harga Jual Pcs MT (-PPN)]] -> 0.085 | BD8: =IFERROR(VLOOKUP(Table43[[#This Row],[Kode BARANG Win2]],'[3]Daftar Barang dan Jasa'!$B$2:$D$3515,3,0),0) -> RB BRASSO METAL POOLISH 100ML X 48 PCS | BE8: =IF(TODAY()-Table43[[#This Row],[Efektif Pembuatan]]>60,"Lama","Baru") -> Lama | BF8: =IF(TODAY()-Table43[[#This Row],[Efektif Naik Harga]]<30,"Naik","Sama") -> #VALUE! | BG8: Aktif | BH8: =IF(Table43[[#This Row],[Kode BARANG Win2]]<>"","IDR","") -> IDR | BI8: =CONCATENATE(Table43[[#This Row],[kode 1 Digit (Nomor)]],Table43[[#This Row],[kode 4 Digit (Nomor)]]) -> ID0200640100 | BJ8: =Table43[[#This Row],[Nama Gramasi atau Jumlah Pack per CTN]] -> 100ML | BM8: =IF(Table43[[#This Row],[SATUAN Fix Win]]<>"","KRT") -> KRT | BN8: =IF(Table43[[#This Row],[SATUAN Fix Win]]<>"","GD01") -> GD01 | BO8: =IF(Table43[[#This Row],[SATUAN Fix Win]]<>"",11611) -> 11611 | BP8: =IF(Table43[[#This Row],[SATUAN Fix Win]]<>"",11612) -> 11612 | BR8: =IF(Table43[[#This Row],[SATUAN Fix Win]]<>"",1) -> 1
A9: =CONCATENATE(Table43[[#This Row],[Kode BARANG Win2]],Table43[[#This Row],[No. Urut Item Sama]]) -> R10210010060101 | B9: 1 | C9: SOAP COOL 144PCS X 60GR"3171295"DBS105 | D9: 3171295 | E9: =IFERROR(VLOOKUP(Table43[[#This Row],[NO]],[1]Sheet1!$G$3:$K$1267,5,0),0) -> 0 | F9: DETOLIDBS COOL 60GX144JOL | G9: 144 | H9: SOAP COOL 144PCS X 60GR"3171295"DBS105 | I9: 8993560025502 | J9: =Table43[[#This Row],[Nama Jenis Kemasan]] -> PCS | K9: =TRIM(CONCATENATE(Table43[[#This Row],[Nama KLP]]," ",Table43[[#This Row],[Nama Sub KLP]])) -> DETTOL BODY SOAP | L9: =CONCATENATE(Table43[[#This Row],[kode 2 Digit (hrf+No)]],Table43[[#This Row],[kode 2 Digit (Nomor)]],Table43[[#This Row],[kode 1 Digit (Nomor)]]) -> R1021 | M9: =IF(AH9="",CONCATENATE(R9,T9,V9,X9,Z9,AB9,AD9,AF9,Table43[[#This Row],[Tanda Kode Revisi]]),CONCATENATE(R9,T9,V9,X9,Z9,AB9,AD9,AH9)) -> R1021001006010 | N9: =LEN(M9) -> 14 | O9: =IF(AG9<>"",TRIM(UPPER(CONCATENATE(Q9," ",S9," ",U9," ",W9," ",Y9," ",AA9," ","X"," ",Table43[[#This Row],[ISI/CTN]]," ",AG9," ",AC9," ",AE9," ",AI9))),TRIM(UPPER(CONCATENATE(Q9," ",S9," ",U9," ",W9," ",Y9," ",AA9," ","X"," ",Table43[[#This Row],[ISI/CTN]]," ",AC9," ",AE9," ",AI9)))) -> RB DETTOL BODY SOAP COOL 60GR X 144 PCS | P9: =LEN(O9) -> 39 | Q9: RB | R9: R1 | S9: DETTOL | T9: 02 | U9: BODY SOAP | V9: 1 | X9: 0 | Y9: COOL | Z9: 01 | AA9: 60GR | AB9: 0060 | AC9: PCS | AD9: 1 | AF9: 0 | AJ9: =IFERROR(VLOOKUP(Table43[[#This Row],[Kode BARANG Win2]],'[2]Template Impor Barang'!#REF!,2,0),0) -> 0 | AK9: =Table43[[#This Row],[ISI/CTN]] -> 144 | AL9: =Table43[[#This Row],[Kode Pcpl]] -> 3171295 | AN9: =Table43[[#This Row],[Harga Jual Pcs GT (-PPN)]]-(Table43[[#This Row],[Harga Jual Pcs GT (-PPN)]]*8.5%) -> 3048.78 | AO9: =Table43[[#This Row],[Harga Beli Pcs (-PPN)]]*Table43[[#This Row],[ISI/CTN]] -> 439024.32 | AP9: =Table43[[#This Row],[Harga Beli Pcs (-PPN)]]*1.11 -> 3384.1458 | AQ9: =Table43[[#This Row],[Harga Beli Krt (- PPN)]]*1.11 -> 487317 | AR9: 3332 | AS9: =Table43[[#This Row],[Harga Jual Pcs GT (-PPN)]]*Table43[[#This Row],[ISI/CTN]] -> 479808 | AT9: =Table43[[#This Row],[Harga Jual Pcs GT (-PPN)]]*1.11 -> 3698.52 | AU9: =Table43[[#This Row],[Harga Jual Krt GT (- PPN)]]*1.11 -> 532586.88 | AV9: 3332 | AW9: =Table43[[#This Row],[Harga Jual Pcs MT (-PPN)]]*Table43[[#This Row],[ISI/CTN]] -> 479808 | AX9: =Table43[[#This Row],[Harga Jual Pcs MT (-PPN)]]*1.11 -> 3698.52 | AY9: =Table43[[#This Row],[Harga Jual Pcs MT (+PPN)]]*Table43[[#This Row],[ISI/CTN]] -> 532586.88 | AZ9: =(Table43[[#This Row],[Harga Jual Pcs GT (-PPN)]]-Table43[[#This Row],[Harga Beli Pcs (-PPN)]])/Table43[[#This Row],[Harga Jual Pcs GT (-PPN)]] -> 0.085 | BA9: =Table43[[#This Row],[Harga Jual Pcs MT (-PPN)]]-Table43[[#This Row],[Harga Beli Pcs (-PPN)]] -> 283.22 | BB9: =Table43[[#This Row],[Column1]]/Table43[[#This Row],[Harga Jual Pcs MT (-PPN)]] -> 0.085 | BD9: =IFERROR(VLOOKUP(Table43[[#This Row],[Kode BARANG Win2]],'[3]Daftar Barang dan Jasa'!$B$2:$D$3515,3,0),0) -> RB DETTOL BODY SOAP COOL 60GR X 144 PCS | BE9: =IF(TODAY()-Table43[[#This Row],[Efektif Pembuatan]]>60,"Lama","Baru") -> Lama | BF9: =IF(TODAY()-Table43[[#This Row],[Efektif Naik Harga]]<30,"Naik","Sama") -> #VALUE! | BG9: Aktif | BH9: =IF(Table43[[#This Row],[Kode BARANG Win2]]<>"","IDR","") -> IDR | BI9: =CONCATENATE(Table43[[#This Row],[kode 1 Digit (Nomor)]],Table43[[#This Row],[kode 4 Digit (Nomor)]]) -> 31712950060 | BJ9: =Table43[[#This Row],[Nama Gramasi atau Jumlah Pack per CTN]] -> 60GR | BM9: =IF(Table43[[#This Row],[SATUAN Fix Win]]<>"","KRT") -> KRT | BN9: =IF(Table43[[#This Row],[SATUAN Fix Win]]<>"","GD01") -> GD01 | BO9: =IF(Table43[[#This Row],[SATUAN Fix Win]]<>"",11611) -> 11611 | BP9: =IF(Table43[[#This Row],[SATUAN Fix Win]]<>"",11612) -> 11612 | BR9: =IF(Table43[[#This Row],[SATUAN Fix Win]]<>"",1) -> 1
A10: =CONCATENATE(Table43[[#This Row],[Kode BARANG Win2]],Table43[[#This Row],[No. Urut Item Sama]]) -> R10210010060102 | B10: 2 | C10: SOAP COOL 144PCS X 60GR"3171295"DBS105 | D10: 3166934 | E10: =IFERROR(VLOOKUP(Table43[[#This Row],[NO]],[1]Sheet1!$G$3:$K$1267,5,0),0) -> 0 | F10: DETOLIDBS COOL 60GX144B | G10: 144 | I10: 8993560025502 | J10: =Table43[[#This Row],[Nama Jenis Kemasan]] -> PCS | K10: =TRIM(CONCATENATE(Table43[[#This Row],[Nama KLP]]," ",Table43[[#This Row],[Nama Sub KLP]])) -> DETTOL BODY SOAP | L10: =CONCATENATE(Table43[[#This Row],[kode 2 Digit (hrf+No)]],Table43[[#This Row],[kode 2 Digit (Nomor)]],Table43[[#This Row],[kode 1 Digit (Nomor)]]) -> R1021 | M10: =IF(AH10="",CONCATENATE(R10,T10,V10,X10,Z10,AB10,AD10,AF10,Table43[[#This Row],[Tanda Kode Revisi]]),CONCATENATE(R10,T10,V10,X10,Z10,AB10,AD10,AH10)) -> R1021001006010 | N10: =LEN(M10) -> 14 | O10: =IF(AG10<>"",TRIM(UPPER(CONCATENATE(Q10," ",S10," ",U10," ",W10," ",Y10," ",AA10," ","X"," ",Table43[[#This Row],[ISI/CTN]]," ",AG10," ",AC10," ",AE10," ",AI10))),TRIM(UPPER(CONCATENATE(Q10," ",S10," ",U10," ",W10," ",Y10," ",AA10," ","X"," ",Table43[[#This Row],[ISI/CTN]]," ",AC10," ",AE10," ",AI10)))) -> RB DETTOL BODY SOAP COOL 60GR X 144 PCS | P10: =LEN(O10) -> 39 | Q10: RB | R10: R1 | S10: DETTOL | T10: 02 | U10: BODY SOAP | V10: 1 | X10: 0 | Y10: COOL | Z10: 01 | AA10: 60GR | AB10: 0060 | AC10: PCS | AD10: 1 | AF10: 0 | AJ10: =IFERROR(VLOOKUP(Table43[[#This Row],[Kode BARANG Win2]],'[2]Template Impor Barang'!#REF!,2,0),0) -> 0 | AK10: =Table43[[#This Row],[ISI/CTN]] -> 144 | AL10: =Table43[[#This Row],[Kode Pcpl]] -> 3166934 | AN10: =Table43[[#This Row],[Harga Jual Pcs GT (-PPN)]]-(Table43[[#This Row],[Harga Jual Pcs GT (-PPN)]]*8.5%) -> 3048.78 | AO10: =Table43[[#This Row],[Harga Beli Pcs (-PPN)]]*Table43[[#This Row],[ISI/CTN]] -> 439024.32 | AP10: =Table43[[#This Row],[Harga Beli Pcs (-PPN)]]*1.11 -> 3384.1458 | AQ10: =Table43[[#This Row],[Harga Beli Krt (- PPN)]]*1.11 -> 487317 | AR10: 3332 | AS10: =Table43[[#This Row],[Harga Jual Pcs GT (-PPN)]]*Table43[[#This Row],[ISI/CTN]] -> 479808 | AT10: =Table43[[#This Row],[Harga Jual Pcs GT (-PPN)]]*1.11 -> 3698.52 | AU10: =Table43[[#This Row],[Harga Jual Krt GT (- PPN)]]*1.11 -> 532586.88 | AV10: 3332 | AW10: =Table43[[#This Row],[Harga Jual Pcs MT (-PPN)]]*Table43[[#This Row],[ISI/CTN]] -> 479808 | AX10: =Table43[[#This Row],[Harga Jual Pcs MT (-PPN)]]*1.11 -> 3698.52 | AY10: =Table43[[#This Row],[Harga Jual Pcs MT (+PPN)]]*Table43[[#This Row],[ISI/CTN]] -> 532586.88 | AZ10: =(Table43[[#This Row],[Harga Jual Pcs GT (-PPN)]]-Table43[[#This Row],[Harga Beli Pcs (-PPN)]])/Table43[[#This Row],[Harga Jual Pcs GT (-PPN)]] -> 0.085 | BA10: =Table43[[#This Row],[Harga Jual Pcs MT (-PPN)]]-Table43[[#This Row],[Harga Beli Pcs (-PPN)]] -> 283.22 | BB10: =Table43[[#This Row],[Column1]]/Table43[[#This Row],[Harga Jual Pcs MT (-PPN)]] -> 0.085 | BD10: =IFERROR(VLOOKUP(Table43[[#This Row],[Kode BARANG Win2]],'[3]Daftar Barang dan Jasa'!$B$2:$D$3515,3,0),0) -> RB DETTOL BODY SOAP COOL 60GR X 144 PCS | BE10: =IF(TODAY()-Table43[[#This Row],[Efektif Pembuatan]]>60,"Lama","Baru") -> Lama | BF10: =IF(TODAY()-Table43[[#This Row],[Efektif Naik Harga]]<30,"Naik","Sama") -> #VALUE! | BG10: Aktif | BH10: =IF(Table43[[#This Row],[Kode BARANG Win2]]<>"","IDR","") -> IDR | BI10: =CONCATENATE(Table43[[#This Row],[kode 1 Digit (Nomor)]],Table43[[#This Row],[kode 4 Digit (Nomor)]]) -> 31669340060 | BJ10: =Table43[[#This Row],[Nama Gramasi atau Jumlah Pack per CTN]] -> 60GR | BM10: =IF(Table43[[#This Row],[SATUAN Fix Win]]<>"","KRT") -> KRT | BN10: =IF(Table43[[#This Row],[SATUAN Fix Win]]<>"","GD01") -> GD01 | BO10: =IF(Table43[[#This Row],[SATUAN Fix Win]]<>"",11611) -> 11611 | BP10: =IF(Table43[[#This Row],[SATUAN Fix Win]]<>"",11612) -> 11612 | BR10: =IF(Table43[[#This Row],[SATUAN Fix Win]]<>"",1) -> 1
A11: =CONCATENATE(Table43[[#This Row],[Kode BARANG Win2]],Table43[[#This Row],[No. Urut Item Sama]]) -> R10210010060103 | B11: 3 | C11: SOAP COOL 144PCS X 60GR"3171295"DBS105 | D11: 3119258 | E11: =IFERROR(VLOOKUP(Table43[[#This Row],[NO]],[1]Sheet1!$G$3:$K$1267,5,0),0) -> 0 | F11: DETOLIDBSCOOL 60GX144 | G11: 144 | I11: 8993560025502 | J11: =Table43[[#This Row],[Nama Jenis Kemasan]] -> PCS | K11: =TRIM(CONCATENATE(Table43[[#This Row],[Nama KLP]]," ",Table43[[#This Row],[Nama Sub KLP]])) -> DETTOL BODY SOAP | L11: =CONCATENATE(Table43[[#This Row],[kode 2 Digit (hrf+No)]],Table43[[#This Row],[kode 2 Digit (Nomor)]],Table43[[#This Row],[kode 1 Digit (Nomor)]]) -> R1021 | M11: =IF(AH11="",CONCATENATE(R11,T11,V11,X11,Z11,AB11,AD11,AF11,Table43[[#This Row],[Tanda Kode Revisi]]),CONCATENATE(R11,T11,V11,X11,Z11,AB11,AD11,AH11)) -> R1021001006010 | N11: =LEN(M11) -> 14 | O11: =IF(AG11<>"",TRIM(UPPER(CONCATENATE(Q11," ",S11," ",U11," ",W11," ",Y11," ",AA11," ","X"," ",Table43[[#This Row],[ISI/CTN]]," ",AG11," ",AC11," ",AE11," ",AI11))),TRIM(UPPER(CONCATENATE(Q11," ",S11," ",U11," ",W11," ",Y11," ",AA11," ","X"," ",Table43[[#This Row],[ISI/CTN]]," ",AC11," ",AE11," ",AI11)))) -> RB DETTOL BODY SOAP COOL 60GR X 144 PCS | P11: =LEN(O11) -> 39 | Q11: RB | R11: R1 | S11: DETTOL | T11: 02 | U11: BODY SOAP | V11: 1 | X11: 0 | Y11: COOL | Z11: 01 | AA11: 60GR | AB11: 0060 | AC11: PCS | AD11: 1 | AF11: 0 | AJ11: =IFERROR(VLOOKUP(Table43[[#This Row],[Kode BARANG Win2]],'[2]Template Impor Barang'!#REF!,2,0),0) -> 0 | AK11: =Table43[[#This Row],[ISI/CTN]] -> 144 | AL11: =Table43[[#This Row],[Kode Pcpl]] -> 3119258 | AN11: =Table43[[#This Row],[Harga Jual Pcs GT (-PPN)]]-(Table43[[#This Row],[Harga Jual Pcs GT (-PPN)]]*8.5%) -> 3048.78 | AO11: =Table43[[#This Row],[Harga Beli Pcs (-PPN)]]*Table43[[#This Row],[ISI/CTN]] -> 439024.32 | AP11: =Table43[[#This Row],[Harga Beli Pcs (-PPN)]]*1.11 -> 3384.1458 | AQ11: =Table43[[#This Row],[Harga Beli Krt (- PPN)]]*1.11 -> 487317 | AR11: 3332 | AS11: =Table43[[#This Row],[Harga Jual Pcs GT (-PPN)]]*Table43[[#This Row],[ISI/CTN]] -> 479808 | AT11: =Table43[[#This Row],[Harga Jual Pcs GT (-PPN)]]*1.11 -> 3698.52 | AU11: =Table43[[#This Row],[Harga Jual Krt GT (- PPN)]]*1.11 -> 532586.88 | AV11: 3332 | AW11: =Table43[[#This Row],[Harga Jual Pcs MT (-PPN)]]*Table43[[#This Row],[ISI/CTN]] -> 479808 | AX11: =Table43[[#This Row],[Harga Jual Pcs MT (-PPN)]]*1.11 -> 3698.52 | AY11: =Table43[[#This Row],[Harga Jual Pcs MT (+PPN)]]*Table43[[#This Row],[ISI/CTN]] -> 532586.88 | AZ11: =(Table43[[#This Row],[Harga Jual Pcs GT (-PPN)]]-Table43[[#This Row],[Harga Beli Pcs (-PPN)]])/Table43[[#This Row],[Harga Jual Pcs GT (-PPN)]] -> 0.085 | BA11: =Table43[[#This Row],[Harga Jual Pcs MT (-PPN)]]-Table43[[#This Row],[Harga Beli Pcs (-PPN)]] -> 283.22 | BB11: =Table43[[#This Row],[Column1]]/Table43[[#This Row],[Harga Jual Pcs MT (-PPN)]] -> 0.085 | BD11: =IFERROR(VLOOKUP(Table43[[#This Row],[Kode BARANG Win2]],'[3]Daftar Barang dan Jasa'!$B$2:$D$3515,3,0),0) -> RB DETTOL BODY SOAP COOL 60GR X 144 PCS | BE11: =IF(TODAY()-Table43[[#This Row],[Efektif Pembuatan]]>60,"Lama","Baru") -> Lama | BF11: =IF(TODAY()-Table43[[#This Row],[Efektif Naik Harga]]<30,"Naik","Sama") -> #VALUE! | BG11: Aktif | BH11: =IF(Table43[[#This Row],[Kode BARANG Win2]]<>"","IDR","") -> IDR | BI11: =CONCATENATE(Table43[[#This Row],[kode 1 Digit (Nomor)]],Table43[[#This Row],[kode 4 Digit (Nomor)]]) -> 31192580060 | BJ11: =Table43[[#This Row],[Nama Gramasi atau Jumlah Pack per CTN]] -> 60GR | BM11: =IF(Table43[[#This Row],[SATUAN Fix Win]]<>"","KRT") -> KRT | BN11: =IF(Table43[[#This Row],[SATUAN Fix Win]]<>"","GD01") -> GD01 | BO11: =IF(Table43[[#This Row],[SATUAN Fix Win]]<>"",11611) -> 11611 | BP11: =IF(Table43[[#This Row],[SATUAN Fix Win]]<>"",11612) -> 11612 | BR11: =IF(Table43[[#This Row],[SATUAN Fix Win]]<>"",1) -> 1
A12: =CONCATENATE(Table43[[#This Row],[Kode BARANG Win2]],Table43[[#This Row],[No. Urut Item Sama]]) -> R10210010060104 | B12: 4 | C12: SOAP COOL 144PCS X 60GR"3171295"DBS105 | D12: 3331432 | E12: =IFERROR(VLOOKUP(Table43[[#This Row],[NO]],[1]Sheet1!$G$3:$K$1267,5,0),0) -> 0 | F12: DETOLIDBSCOOL 60GX4X36 | G12: 144 | I12: 8993560025502 | J12: =Table43[[#This Row],[Nama Jenis Kemasan]] -> PCS | K12: =TRIM(CONCATENATE(Table43[[#This Row],[Nama KLP]]," ",Table43[[#This Row],[Nama Sub KLP]])) -> DETTOL BODY SOAP | L12: =CONCATENATE(Table43[[#This Row],[kode 2 Digit (hrf+No)]],Table43[[#This Row],[kode 2 Digit (Nomor)]],Table43[[#This Row],[kode 1 Digit (Nomor)]]) -> R1021 | M12: =IF(AH12="",CONCATENATE(R12,T12,V12,X12,Z12,AB12,AD12,AF12,Table43[[#This Row],[Tanda Kode Revisi]]),CONCATENATE(R12,T12,V12,X12,Z12,AB12,AD12,AH12)) -> R1021001006010 | N12: =LEN(M12) -> 14 | O12: =IF(AG12<>"",TRIM(UPPER(CONCATENATE(Q12," ",S12," ",U12," ",W12," ",Y12," ",AA12," ","X"," ",Table43[[#This Row],[ISI/CTN]]," ",AG12," ",AC12," ",AE12," ",AI12))),TRIM(UPPER(CONCATENATE(Q12," ",S12," ",U12," ",W12," ",Y12," ",AA12," ","X"," ",Table43[[#This Row],[ISI/CTN]]," ",AC12," ",AE12," ",AI12)))) -> RB DETTOL BODY SOAP COOL 60GR X 144 PCS | P12: =LEN(O12) -> 39 | Q12: RB | R12: R1 | S12: DETTOL | T12: 02 | U12: BODY SOAP | V12: 1 | X12: 0 | Y12: COOL | Z12: 01 | AA12: 60GR | AB12: 0060 | AC12: PCS | AD12: 1 | AF12: 0 | AJ12: =IFERROR(VLOOKUP(Table43[[#This Row],[Kode BARANG Win2]],'[2]Template Impor Barang'!#REF!,2,0),0) -> 0 | AK12: =Table43[[#This Row],[ISI/CTN]] -> 144 | AL12: =Table43[[#This Row],[Kode Pcpl]] -> 3331432 | AN12: =Table43[[#This Row],[Harga Jual Pcs GT (-PPN)]]-(Table43[[#This Row],[Harga Jual Pcs GT (-PPN)]]*8.5%) -> 3048.78 | AO12: =Table43[[#This Row],[Harga Beli Pcs (-PPN)]]*Table43[[#This Row],[ISI/CTN]] -> 439024.32 | AP12: =Table43[[#This Row],[Harga Beli Pcs (-PPN)]]*1.11 -> 3384.1458 | AQ12: =Table43[[#This Row],[Harga Beli Krt (- PPN)]]*1.11 -> 487317 | AR12: 3332 | AS12: =Table43[[#This Row],[Harga Jual Pcs GT (-PPN)]]*Table43[[#This Row],[ISI/CTN]] -> 479808 | AT12: =Table43[[#This Row],[Harga Jual Pcs GT (-PPN)]]*1.11 -> 3698.52 | AU12: =Table43[[#This Row],[Harga Jual Krt GT (- PPN)]]*1.11 -> 532586.88 | AV12: 3332 | AW12: =Table43[[#This Row],[Harga Jual Pcs MT (-PPN)]]*Table43[[#This Row],[ISI/CTN]] -> 479808 | AX12: =Table43[[#This Row],[Harga Jual Pcs MT (-PPN)]]*1.11 -> 3698.52 | AY12: =Table43[[#This Row],[Harga Jual Pcs MT (+PPN)]]*Table43[[#This Row],[ISI/CTN]] -> 532586.88 | AZ12: =(Table43[[#This Row],[Harga Jual Pcs GT (-PPN)]]-Table43[[#This Row],[Harga Beli Pcs (-PPN)]])/Table43[[#This Row],[Harga Jual Pcs GT (-PPN)]] -> 0.085 | BA12: =Table43[[#This Row],[Harga Jual Pcs MT (-PPN)]]-Table43[[#This Row],[Harga Beli Pcs (-PPN)]] -> 283.22 | BB12: =Table43[[#This Row],[Column1]]/Table43[[#This Row],[Harga Jual Pcs MT (-PPN)]] -> 0.085 | BD12: =IFERROR(VLOOKUP(Table43[[#This Row],[Kode BARANG Win2]],'[3]Daftar Barang dan Jasa'!$B$2:$D$3515,3,0),0) -> RB DETTOL BODY SOAP COOL 60GR X 144 PCS | BE12: =IF(TODAY()-Table43[[#This Row],[Efektif Pembuatan]]>60,"Lama","Baru") -> Lama | BF12: =IF(TODAY()-Table43[[#This Row],[Efektif Naik Harga]]<30,"Naik","Sama") -> #VALUE! | BG12: Aktif | BH12: =IF(Table43[[#This Row],[Kode BARANG Win2]]<>"","IDR","") -> IDR | BI12: =CONCATENATE(Table43[[#This Row],[kode 1 Digit (Nomor)]],Table43[[#This Row],[kode 4 Digit (Nomor)]]) -> 33314320060 | BJ12: =Table43[[#This Row],[Nama Gramasi atau Jumlah Pack per CTN]] -> 60GR | BM12: =IF(Table43[[#This Row],[SATUAN Fix Win]]<>"","KRT") -> KRT | BN12: =IF(Table43[[#This Row],[SATUAN Fix Win]]<>"","GD01") -> GD01 | BO12: =IF(Table43[[#This Row],[SATUAN Fix Win]]<>"",11611) -> 11611 | BP12: =IF(Table43[[#This Row],[SATUAN Fix Win]]<>"",11612) -> 11612 | BR12: =IF(Table43[[#This Row],[SATUAN Fix Win]]<>"",1) -> 1
A13: =CONCATENATE(Table43[[#This Row],[Kode BARANG Win2]],Table43[[#This Row],[No. Urut Item Sama]]) -> R10210010100101 | B13: 1 | C13: SOAP COOL 144PCS X 100GR"3171286"DBS107 | D13: 3171286 | E13: =IFERROR(VLOOKUP(Table43[[#This Row],[NO]],[1]Sheet1!$G$3:$K$1267,5,0),0) -> 0 | F13: DETOLIDBS COOL 100GX144JOL | G13: 144 | H13: SOAP COOL 144PCS X 100GR"3171286"DBS107 | I13: 8993560024178 | J13: =Table43[[#This Row],[Nama Jenis Kemasan]] -> PCS | K13: =TRIM(CONCATENATE(Table43[[#This Row],[Nama KLP]]," ",Table43[[#This Row],[Nama Sub KLP]])) -> DETTOL BODY SOAP | L13: =CONCATENATE(Table43[[#This Row],[kode 2 Digit (hrf+No)]],Table43[[#This Row],[kode 2 Digit (Nomor)]],Table43[[#This Row],[kode 1 Digit (Nomor)]]) -> R1021 | M13: =IF(AH13="",CONCATENATE(R13,T13,V13,X13,Z13,AB13,AD13,AF13,Table43[[#This Row],[Tanda Kode Revisi]]),CONCATENATE(R13,T13,V13,X13,Z13,AB13,AD13,AH13)) -> R1021001010010 | N13: =LEN(M13) -> 14 | O13: =IF(AG13<>"",TRIM(UPPER(CONCATENATE(Q13," ",S13," ",U13," ",W13," ",Y13," ",AA13," ","X"," ",Table43[[#This Row],[ISI/CTN]]," ",AG13," ",AC13," ",AE13," ",AI13))),TRIM(UPPER(CONCATENATE(Q13," ",S13," ",U13," ",W13," ",Y13," ",AA13," ","X"," ",Table43[[#This Row],[ISI/CTN]]," ",AC13," ",AE13," ",AI13)))) -> RB DETTOL BODY SOAP COOL 100GR X 144 PCS | P13: =LEN(O13) -> 40 | Q13: RB | R13: R1 | S13: DETTOL | T13: 02 | U13: BODY SOAP | V13: 1 | X13: 0 | Y13: COOL | Z13: 01 | AA13: 100GR | AB13: 0100 | AC13: PCS | AD13: 1 | AF13: 0 | AJ13: =IFERROR(VLOOKUP(Table43[[#This Row],[Kode BARANG Win2]],'[2]Template Impor Barang'!#REF!,2,0),0) -> 0 | AK13: =Table43[[#This Row],[ISI/CTN]] -> 144 | AL13: =Table43[[#This Row],[Kode Pcpl]] -> 3171286 | AN13: =Table43[[#This Row],[Harga Jual Pcs GT (-PPN)]]-(Table43[[#This Row],[Harga Jual Pcs GT (-PPN)]]*8.5%) -> 5864.5654 | AO13: =Table43[[#This Row],[Harga Beli Pcs (-PPN)]]*Table43[[#This Row],[ISI/CTN]] -> 844497.42 | AP13: =Table43[[#This Row],[Harga Beli Pcs (-PPN)]]*1.11 -> 6509.6676 | AQ13: =Table43[[#This Row],[Harga Beli Krt (- PPN)]]*1.11 -> 937392.14 | AR13: 6409.3611 | AS13: =Table43[[#This Row],[Harga Jual Pcs GT (-PPN)]]*Table43[[#This Row],[ISI/CTN]] -> 922948 | AT13: =Table43[[#This Row],[Harga Jual Pcs GT (-PPN)]]*1.11 -> 7114.3908 | AU13: =Table43[[#This Row],[Harga Jual Krt GT (- PPN)]]*1.11 -> 1024472.3 | AV13: 6409.3611 | AW13: =Table43[[#This Row],[Harga Jual Pcs MT (-PPN)]]*Table43[[#This Row],[ISI/CTN]] -> 922948 | AX13: =Table43[[#This Row],[Harga Jual Pcs MT (-PPN)]]*1.11 -> 7114.3908 | AY13: =Table43[[#This Row],[Harga Jual Pcs MT (+PPN)]]*Table43[[#This Row],[ISI/CTN]] -> 1024472.3 | AZ13: =(Table43[[#This Row],[Harga Jual Pcs GT (-PPN)]]-Table43[[#This Row],[Harga Beli Pcs (-PPN)]])/Table43[[#This Row],[Harga Jual Pcs GT (-PPN)]] -> 0.085 | BA13: =Table43[[#This Row],[Harga Jual Pcs MT (-PPN)]]-Table43[[#This Row],[Harga Beli Pcs (-PPN)]] -> 544.79569 | BB13: =Table43[[#This Row],[Column1]]/Table43[[#This Row],[Harga Jual Pcs MT (-PPN)]] -> 0.085 | BD13: =IFERROR(VLOOKUP(Table43[[#This Row],[Kode BARANG Win2]],'[3]Daftar Barang dan Jasa'!$B$2:$D$3515,3,0),0) -> RB DETTOL BODY SOAP COOL 100GR X 144 PCS | BE13: =IF(TODAY()-Table43[[#This Row],[Efektif Pembuatan]]>60,"Lama","Baru") -> Lama | BF13: =IF(TODAY()-Table43[[#This Row],[Efektif Naik Harga]]<30,"Naik","Sama") -> #VALUE! | BG13: Aktif | BH13: =IF(Table43[[#This Row],[Kode BARANG Win2]]<>"","IDR","") -> IDR | BI13: =CONCATENATE(Table43[[#This Row],[kode 1 Digit (Nomor)]],Table43[[#This Row],[kode 4 Digit (Nomor)]]) -> 31712860100 | BJ13: =Table43[[#This Row],[Nama Gramasi atau Jumlah Pack per CTN]] -> 100GR | BM13: =IF(Table43[[#This Row],[SATUAN Fix Win]]<>"","KRT") -> KRT | BN13: =IF(Table43[[#This Row],[SATUAN Fix Win]]<>"","GD01") -> GD01 | BO13: =IF(Table43[[#This Row],[SATUAN Fix Win]]<>"",11611) -> 11611 | BP13: =IF(Table43[[#This Row],[SATUAN Fix Win]]<>"",11612) -> 11612 | BR13: =IF(Table43[[#This Row],[SATUAN Fix Win]]<>"",1) -> 1
A14: =CONCATENATE(Table43[[#This Row],[Kode BARANG Win2]],Table43[[#This Row],[No. Urut Item Sama]]) -> R10210010100102 | B14: 2 | C14: SOAP COOL 144PCS X 100GR"3171286"DBS107 | D14: 3166924 | E14: =IFERROR(VLOOKUP(Table43[[#This Row],[NO]],[1]Sheet1!$G$3:$K$1267,5,0),0) -> 0 | F14: DETOLIDBS COOL 100GX144B | G14: 144 | I14: 8993560024178 | J14: =Table43[[#This Row],[Nama Jenis Kemasan]] -> PCS | K14: =TRIM(CONCATENATE(Table43[[#This Row],[Nama KLP]]," ",Table43[[#This Row],[Nama Sub KLP]])) -> DETTOL BODY SOAP | L14: =CONCATENATE(Table43[[#This Row],[kode 2 Digit (hrf+No)]],Table43[[#This Row],[kode 2 Digit (Nomor)]],Table43[[#This Row],[kode 1 Digit (Nomor)]]) -> R1021 | M14: =IF(AH14="",CONCATENATE(R14,T14,V14,X14,Z14,AB14,AD14,AF14,Table43[[#This Row],[Tanda Kode Revisi]]),CONCATENATE(R14,T14,V14,X14,Z14,AB14,AD14,AH14)) -> R1021001010010 | N14: =LEN(M14) -> 14 | O14: =IF(AG14<>"",TRIM(UPPER(CONCATENATE(Q14," ",S14," ",U14," ",W14," ",Y14," ",AA14," ","X"," ",Table43[[#This Row],[ISI/CTN]]," ",AG14," ",AC14," ",AE14," ",AI14))),TRIM(UPPER(CONCATENATE(Q14," ",S14," ",U14," ",W14," ",Y14," ",AA14," ","X"," ",Table43[[#This Row],[ISI/CTN]]," ",AC14," ",AE14," ",AI14)))) -> RB DETTOL BODY SOAP COOL 100GR X 144 PCS | P14: =LEN(O14) -> 40 | Q14: RB | R14: R1 | S14: DETTOL | T14: 02 | U14: BODY SOAP | V14: 1 | X14: 0 | Y14: COOL | Z14: 01 | AA14: 100GR | AB14: 0100 | AC14: PCS | AD14: 1 | AF14: 0 | AJ14: =IFERROR(VLOOKUP(Table43[[#This Row],[Kode BARANG Win2]],'[2]Template Impor Barang'!#REF!,2,0),0) -> 0 | AK14: =Table43[[#This Row],[ISI/CTN]] -> 144 | AL14: =Table43[[#This Row],[Kode Pcpl]] -> 3166924 | AN14: =Table43[[#This Row],[Harga Jual Pcs GT (-PPN)]]-(Table43[[#This Row],[Harga Jual Pcs GT (-PPN)]]*8.5%) -> 5864.5654 | AO14: =Table43[[#This Row],[Harga Beli Pcs (-PPN)]]*Table43[[#This Row],[ISI/CTN]] -> 844497.42 | AP14: =Table43[[#This Row],[Harga Beli Pcs (-PPN)]]*1.11 -> 6509.6676 | AQ14: =Table43[[#This Row],[Harga Beli Krt (- PPN)]]*1.11 -> 937392.14 | AR14: 6409.3611 | AS14: =Table43[[#This Row],[Harga Jual Pcs GT (-PPN)]]*Table43[[#This Row],[ISI/CTN]] -> 922948 | AT14: =Table43[[#This Row],[Harga Jual Pcs GT (-PPN)]]*1.11 -> 7114.3908 | AU14: =Table43[[#This Row],[Harga Jual Krt GT (- PPN)]]*1.11 -> 1024472.3 | AV14: 6409.3611 | AW14: =Table43[[#This Row],[Harga Jual Pcs MT (-PPN)]]*Table43[[#This Row],[ISI/CTN]] -> 922948 | AX14: =Table43[[#This Row],[Harga Jual Pcs MT (-PPN)]]*1.11 -> 7114.3908 | AY14: =Table43[[#This Row],[Harga Jual Pcs MT (+PPN)]]*Table43[[#This Row],[ISI/CTN]] -> 1024472.3 | AZ14: =(Table43[[#This Row],[Harga Jual Pcs GT (-PPN)]]-Table43[[#This Row],[Harga Beli Pcs (-PPN)]])/Table43[[#This Row],[Harga Jual Pcs GT (-PPN)]] -> 0.085 | BA14: =Table43[[#This Row],[Harga Jual Pcs MT (-PPN)]]-Table43[[#This Row],[Harga Beli Pcs (-PPN)]] -> 544.79569 | BB14: =Table43[[#This Row],[Column1]]/Table43[[#This Row],[Harga Jual Pcs MT (-PPN)]] -> 0.085 | BD14: =IFERROR(VLOOKUP(Table43[[#This Row],[Kode BARANG Win2]],'[3]Daftar Barang dan Jasa'!$B$2:$D$3515,3,0),0) -> RB DETTOL BODY SOAP COOL 100GR X 144 PCS | BE14: =IF(TODAY()-Table43[[#This Row],[Efektif Pembuatan]]>60,"Lama","Baru") -> Lama | BF14: =IF(TODAY()-Table43[[#This Row],[Efektif Naik Harga]]<30,"Naik","Sama") -> #VALUE! | BG14: Aktif | BH14: =IF(Table43[[#This Row],[Kode BARANG Win2]]<>"","IDR","") -> IDR | BI14: =CONCATENATE(Table43[[#This Row],[kode 1 Digit (Nomor)]],Table43[[#This Row],[kode 4 Digit (Nomor)]]) -> 31669240100 | BJ14: =Table43[[#This Row],[Nama Gramasi atau Jumlah Pack per CTN]] -> 100GR | BM14: =IF(Table43[[#This Row],[SATUAN Fix Win]]<>"","KRT") -> KRT | BN14: =IF(Table43[[#This Row],[SATUAN Fix Win]]<>"","GD01") -> GD01 | BO14: =IF(Table43[[#This Row],[SATUAN Fix Win]]<>"",11611) -> 11611 | BP14: =IF(Table43[[#This Row],[SATUAN Fix Win]]<>"",11612) -> 11612 | BR14: =IF(Table43[[#This Row],[SATUAN Fix Win]]<>"",1) -> 1
A15: =CONCATENATE(Table43[[#This Row],[Kode BARANG Win2]],Table43[[#This Row],[No. Urut Item Sama]]) -> R10210010100103 | B15: 3 | C15: SOAP COOL 144PCS X 100GR"3171286"DBS107 | D15: 3060311 | E15: =IFERROR(VLOOKUP(Table43[[#This Row],[NO]],[1]Sheet1!$G$3:$K$1267,5,0),0) -> 0 | F15: DETOLIDCOL105G RG 144ZS | G15: 144 | I15: 8993560024178 | J15: =Table43[[#This Row],[Nama Jenis Kemasan]] -> PCS | K15: =TRIM(CONCATENATE(Table43[[#This Row],[Nama KLP]]," ",Table43[[#This Row],[Nama Sub KLP]])) -> DETTOL BODY SOAP | L15: =CONCATENATE(Table43[[#This Row],[kode 2 Digit (hrf+No)]],Table43[[#This Row],[kode 2 Digit (Nomor)]],Table43[[#This Row],[kode 1 Digit (Nomor)]]) -> R1021 | M15: =IF(AH15="",CONCATENATE(R15,T15,V15,X15,Z15,AB15,AD15,AF15,Table43[[#This Row],[Tanda Kode Revisi]]),CONCATENATE(R15,T15,V15,X15,Z15,AB15,AD15,AH15)) -> R1021001010010 | N15: =LEN(M15) -> 14 | O15: =IF(AG15<>"",TRIM(UPPER(CONCATENATE(Q15," ",S15," ",U15," ",W15," ",Y15," ",AA15," ","X"," ",Table43[[#This Row],[ISI/CTN]]," ",AG15," ",AC15," ",AE15," ",AI15))),TRIM(UPPER(CONCATENATE(Q15," ",S15," ",U15," ",W15," ",Y15," ",AA15," ","X"," ",Table43[[#This Row],[ISI/CTN]]," ",AC15," ",AE15," ",AI15)))) -> RB DETTOL BODY SOAP COOL 100GR X 144 PCS | P15: =LEN(O15) -> 40 | Q15: RB | R15: R1 | S15: DETTOL | T15: 02 | U15: BODY SOAP | V15: 1 | X15: 0 | Y15: COOL | Z15: 01 | AA15: 100GR | AB15: 0100 | AC15: PCS | AD15: 1 | AF15: 0 | AJ15: =IFERROR(VLOOKUP(Table43[[#This Row],[Kode BARANG Win2]],'[2]Template Impor Barang'!#REF!,2,0),0) -> 0 | AK15: =Table43[[#This Row],[ISI/CTN]] -> 144 | AL15: =Table43[[#This Row],[Kode Pcpl]] -> 3060311 | AN15: =Table43[[#This Row],[Harga Jual Pcs GT (-PPN)]]-(Table43[[#This Row],[Harga Jual Pcs GT (-PPN)]]*8.5%) -> 5864.5654 | AO15: =Table43[[#This Row],[Harga Beli Pcs (-PPN)]]*Table43[[#This Row],[ISI/CTN]] -> 844497.42 | AP15: =Table43[[#This Row],[Harga Beli Pcs (-PPN)]]*1.11 -> 6509.6676 | AQ15: =Table43[[#This Row],[Harga Beli Krt (- PPN)]]*1.11 -> 937392.14 | AR15: 6409.3611 | AS15: =Table43[[#This Row],[Harga Jual Pcs GT (-PPN)]]*Table43[[#This Row],[ISI/CTN]] -> 922948 | AT15: =Table43[[#This Row],[Harga Jual Pcs GT (-PPN)]]*1.11 -> 7114.3908 | AU15: =Table43[[#This Row],[Harga Jual Krt GT (- PPN)]]*1.11 -> 1024472.3 | AV15: 6409.3611 | AW15: =Table43[[#This Row],[Harga Jual Pcs MT (-PPN)]]*Table43[[#This Row],[ISI/CTN]] -> 922948 | AX15: =Table43[[#This Row],[Harga Jual Pcs MT (-PPN)]]*1.11 -> 7114.3908 | AY15: =Table43[[#This Row],[Harga Jual Pcs MT (+PPN)]]*Table43[[#This Row],[ISI/CTN]] -> 1024472.3 | AZ15: =(Table43[[#This Row],[Harga Jual Pcs GT (-PPN)]]-Table43[[#This Row],[Harga Beli Pcs (-PPN)]])/Table43[[#This Row],[Harga Jual Pcs GT (-PPN)]] -> 0.085 | BA15: =Table43[[#This Row],[Harga Jual Pcs MT (-PPN)]]-Table43[[#This Row],[Harga Beli Pcs (-PPN)]] -> 544.79569 | BB15: =Table43[[#This Row],[Column1]]/Table43[[#This Row],[Harga Jual Pcs MT (-PPN)]] -> 0.085 | BD15: =IFERROR(VLOOKUP(Table43[[#This Row],[Kode BARANG Win2]],'[3]Daftar Barang dan Jasa'!$B$2:$D$3515,3,0),0) -> RB DETTOL BODY SOAP COOL 100GR X 144 PCS | BE15: =IF(TODAY()-Table43[[#This Row],[Efektif Pembuatan]]>60,"Lama","Baru") -> Lama | BF15: =IF(TODAY()-Table43[[#This Row],[Efektif Naik Harga]]<30,"Naik","Sama") -> #VALUE! | BG15: Aktif | BH15: =IF(Table43[[#This Row],[Kode BARANG Win2]]<>"","IDR","") -> IDR | BI15: =CONCATENATE(Table43[[#This Row],[kode 1 Digit (Nomor)]],Table43[[#This Row],[kode 4 Digit (Nomor)]]) -> 30603110100 | BJ15: =Table43[[#This Row],[Nama Gramasi atau Jumlah Pack per CTN]] -> 100GR | BM15: =IF(Table43[[#This Row],[SATUAN Fix Win]]<>"","KRT") -> KRT | BN15: =IF(Table43[[#This Row],[SATUAN Fix Win]]<>"","GD01") -> GD01 | BO15: =IF(Table43[[#This Row],[SATUAN Fix Win]]<>"",11611) -> 11611 | BP15: =IF(Table43[[#This Row],[SATUAN Fix Win]]<>"",11612) -> 11612 | BR15: =IF(Table43[[#This Row],[SATUAN Fix Win]]<>"",1) -> 1
A16: =CONCATENATE(Table43[[#This Row],[Kode BARANG Win2]],Table43[[#This Row],[No. Urut Item Sama]]) -> R10210010100104 | B16: 4 | C16: SOAP COOL 144PCS X 100GR"3171286"DBS107 | D16: 3087451 | E16: =IFERROR(VLOOKUP(Table43[[#This Row],[NO]],[1]Sheet1!$G$3:$K$1267,5,0),0) -> 0 | F16: DETOLIDCOOL 100 RG 144JM | G16: 144 | I16: 8993560024178 | J16: =Table43[[#This Row],[Nama Jenis Kemasan]] -> PCS | K16: =TRIM(CONCATENATE(Table43[[#This Row],[Nama KLP]]," ",Table43[[#This Row],[Nama Sub KLP]])) -> DETTOL BODY SOAP | L16: =CONCATENATE(Table43[[#This Row],[kode 2 Digit (hrf+No)]],Table43[[#This Row],[kode 2 Digit (Nomor)]],Table43[[#This Row],[kode 1 Digit (Nomor)]]) -> R1021 | M16: =IF(AH16="",CONCATENATE(R16,T16,V16,X16,Z16,AB16,AD16,AF16,Table43[[#This Row],[Tanda Kode Revisi]]),CONCATENATE(R16,T16,V16,X16,Z16,AB16,AD16,AH16)) -> R1021001010010 | N16: =LEN(M16) -> 14 | O16: =IF(AG16<>"",TRIM(UPPER(CONCATENATE(Q16," ",S16," ",U16," ",W16," ",Y16," ",AA16," ","X"," ",Table43[[#This Row],[ISI/CTN]]," ",AG16," ",AC16," ",AE16," ",AI16))),TRIM(UPPER(CONCATENATE(Q16," ",S16," ",U16," ",W16," ",Y16," ",AA16," ","X"," ",Table43[[#This Row],[ISI/CTN]]," ",AC16," ",AE16," ",AI16)))) -> RB DETTOL BODY SOAP COOL 100GR X 144 PCS | P16: =LEN(O16) -> 40 | Q16: RB | R16: R1 | S16: DETTOL | T16: 02 | U16: BODY SOAP | V16: 1 | X16: 0 | Y16: COOL | Z16: 01 | AA16: 100GR | AB16: 0100 | AC16: PCS | AD16: 1 | AF16: 0 | AJ16: =IFERROR(VLOOKUP(Table43[[#This Row],[Kode BARANG Win2]],'[2]Template Impor Barang'!#REF!,2,0),0) -> 0 | AK16: =Table43[[#This Row],[ISI/CTN]] -> 144 | AL16: =Table43[[#This Row],[Kode Pcpl]] -> 3087451 | AN16: =Table43[[#This Row],[Harga Jual Pcs GT (-PPN)]]-(Table43[[#This Row],[Harga Jual Pcs GT (-PPN)]]*8.5%) -> 5864.5654 | AO16: =Table43[[#This Row],[Harga Beli Pcs (-PPN)]]*Table43[[#This Row],[ISI/CTN]] -> 844497.42 | AP16: =Table43[[#This Row],[Harga Beli Pcs (-PPN)]]*1.11 -> 6509.6676 | AQ16: =Table43[[#This Row],[Harga Beli Krt (- PPN)]]*1.11 -> 937392.14 | AR16: 6409.3611 | AS16: =Table43[[#This Row],[Harga Jual Pcs GT (-PPN)]]*Table43[[#This Row],[ISI/CTN]] -> 922948 | AT16: =Table43[[#This Row],[Harga Jual Pcs GT (-PPN)]]*1.11 -> 7114.3908 | AU16: =Table43[[#This Row],[Harga Jual Krt GT (- PPN)]]*1.11 -> 1024472.3 | AV16: 6409.3611 | AW16: =Table43[[#This Row],[Harga Jual Pcs MT (-PPN)]]*Table43[[#This Row],[ISI/CTN]] -> 922948 | AX16: =Table43[[#This Row],[Harga Jual Pcs MT (-PPN)]]*1.11 -> 7114.3908 | AY16: =Table43[[#This Row],[Harga Jual Pcs MT (+PPN)]]*Table43[[#This Row],[ISI/CTN]] -> 1024472.3 | AZ16: =(Table43[[#This Row],[Harga Jual Pcs GT (-PPN)]]-Table43[[#This Row],[Harga Beli Pcs (-PPN)]])/Table43[[#This Row],[Harga Jual Pcs GT (-PPN)]] -> 0.085 | BA16: =Table43[[#This Row],[Harga Jual Pcs MT (-PPN)]]-Table43[[#This Row],[Harga Beli Pcs (-PPN)]] -> 544.79569 | BB16: =Table43[[#This Row],[Column1]]/Table43[[#This Row],[Harga Jual Pcs MT (-PPN)]] -> 0.085 | BD16: =IFERROR(VLOOKUP(Table43[[#This Row],[Kode BARANG Win2]],'[3]Daftar Barang dan Jasa'!$B$2:$D$3515,3,0),0) -> RB DETTOL BODY SOAP COOL 100GR X 144 PCS | BE16: =IF(TODAY()-Table43[[#This Row],[Efektif Pembuatan]]>60,"Lama","Baru") -> Lama | BF16: =IF(TODAY()-Table43[[#This Row],[Efektif Naik Harga]]<30,"Naik","Sama") -> #VALUE! | BG16: Aktif | BH16: =IF(Table43[[#This Row],[Kode BARANG Win2]]<>"","IDR","") -> IDR | BI16: =CONCATENATE(Table43[[#This Row],[kode 1 Digit (Nomor)]],Table43[[#This Row],[kode 4 Digit (Nomor)]]) -> 30874510100 | BJ16: =Table43[[#This Row],[Nama Gramasi atau Jumlah Pack per CTN]] -> 100GR | BM16: =IF(Table43[[#This Row],[SATUAN Fix Win]]<>"","KRT") -> KRT | BN16: =IF(Table43[[#This Row],[SATUAN Fix Win]]<>"","GD01") -> GD01 | BO16: =IF(Table43[[#This Row],[SATUAN Fix Win]]<>"",11611) -> 11611 | BP16: =IF(Table43[[#This Row],[SATUAN Fix Win]]<>"",11612) -> 11612 | BR16: =IF(Table43[[#This Row],[SATUAN Fix Win]]<>"",1) -> 1
A17: =CONCATENATE(Table43[[#This Row],[Kode BARANG Win2]],Table43[[#This Row],[No. Urut Item Sama]]) -> R10210010100105 | B17: 5 | C17: SOAP COOL 144PCS X 100GR"3171286"DBS107 | D17: ID8195121M | E17: =IFERROR(VLOOKUP(Table43[[#This Row],[NO]],[1]Sheet1!$G$3:$K$1267,5,0),0) -> 0 | F17: Dettol DAS 105gr Cool NSAN | G17: 144 | I17: 8993560024178 | J17: =Table43[[#This Row],[Nama Jenis Kemasan]] -> PCS | K17: =TRIM(CONCATENATE(Table43[[#This Row],[Nama KLP]]," ",Table43[[#This Row],[Nama Sub KLP]])) -> DETTOL BODY SOAP | L17: =CONCATENATE(Table43[[#This Row],[kode 2 Digit (hrf+No)]],Table43[[#This Row],[kode 2 Digit (Nomor)]],Table43[[#This Row],[kode 1 Digit (Nomor)]]) -> R1021 | M17: =IF(AH17="",CONCATENATE(R17,T17,V17,X17,Z17,AB17,AD17,AF17,Table43[[#This Row],[Tanda Kode Revisi]]),CONCATENATE(R17,T17,V17,X17,Z17,AB17,AD17,AH17)) -> R1021001010010 | N17: =LEN(M17) -> 14 | O17: =IF(AG17<>"",TRIM(UPPER(CONCATENATE(Q17," ",S17," ",U17," ",W17," ",Y17," ",AA17," ","X"," ",Table43[[#This Row],[ISI/CTN]]," ",AG17," ",AC17," ",AE17," ",AI17))),TRIM(UPPER(CONCATENATE(Q17," ",S17," ",U17," ",W17," ",Y17," ",AA17," ","X"," ",Table43[[#This Row],[ISI/CTN]]," ",AC17," ",AE17," ",AI17)))) -> RB DETTOL BODY SOAP COOL 100GR X 144 PCS | P17: =LEN(O17) -> 40 | Q17: RB | R17: R1 | S17: DETTOL | T17: 02 | U17: BODY SOAP | V17: 1 | X17: 0 | Y17: COOL | Z17: 01 | AA17: 100GR | AB17: 0100 | AC17: PCS | AD17: 1 | AF17: 0 | AJ17: =IFERROR(VLOOKUP(Table43[[#This Row],[Kode BARANG Win2]],'[2]Template Impor Barang'!#REF!,2,0),0) -> 0 | AK17: =Table43[[#This Row],[ISI/CTN]] -> 144 | AL17: =Table43[[#This Row],[Kode Pcpl]] -> ID8195121M | AN17: =Table43[[#This Row],[Harga Jual Pcs GT (-PPN)]]-(Table43[[#This Row],[Harga Jual Pcs GT (-PPN)]]*8.5%) -> 5864.5654 | AO17: =Table43[[#This Row],[Harga Beli Pcs (-PPN)]]*Table43[[#This Row],[ISI/CTN]] -> 844497.42 | AP17: =Table43[[#This Row],[Harga Beli Pcs (-PPN)]]*1.11 -> 6509.6676 | AQ17: =Table43[[#This Row],[Harga Beli Krt (- PPN)]]*1.11 -> 937392.14 | AR17: 6409.3611 | AS17: =Table43[[#This Row],[Harga Jual Pcs GT (-PPN)]]*Table43[[#This Row],[ISI/CTN]] -> 922948 | AT17: =Table43[[#This Row],[Harga Jual Pcs GT (-PPN)]]*1.11 -> 7114.3908 | AU17: =Table43[[#This Row],[Harga Jual Krt GT (- PPN)]]*1.11 -> 1024472.3 | AV17: 6409.3611 | AW17: =Table43[[#This Row],[Harga Jual Pcs MT (-PPN)]]*Table43[[#This Row],[ISI/CTN]] -> 922948 | AX17: =Table43[[#This Row],[Harga Jual Pcs MT (-PPN)]]*1.11 -> 7114.3908 | AY17: =Table43[[#This Row],[Harga Jual Pcs MT (+PPN)]]*Table43[[#This Row],[ISI/CTN]] -> 1024472.3 | AZ17: =(Table43[[#This Row],[Harga Jual Pcs GT (-PPN)]]-Table43[[#This Row],[Harga Beli Pcs (-PPN)]])/Table43[[#This Row],[Harga Jual Pcs GT (-PPN)]] -> 0.085 | BA17: =Table43[[#This Row],[Harga Jual Pcs MT (-PPN)]]-Table43[[#This Row],[Harga Beli Pcs (-PPN)]] -> 544.79569 | BB17: =Table43[[#This Row],[Column1]]/Table43[[#This Row],[Harga Jual Pcs MT (-PPN)]] -> 0.085 | BD17: =IFERROR(VLOOKUP(Table43[[#This Row],[Kode BARANG Win2]],'[3]Daftar Barang dan Jasa'!$B$2:$D$3515,3,0),0) -> RB DETTOL BODY SOAP COOL 100GR X 144 PCS | BE17: =IF(TODAY()-Table43[[#This Row],[Efektif Pembuatan]]>60,"Lama","Baru") -> Lama | BF17: =IF(TODAY()-Table43[[#This Row],[Efektif Naik Harga]]<30,"Naik","Sama") -> #VALUE! | BG17: Aktif | BH17: =IF(Table43[[#This Row],[Kode BARANG Win2]]<>"","IDR","") -> IDR | BI17: =CONCATENATE(Table43[[#This Row],[kode 1 Digit (Nomor)]],Table43[[#This Row],[kode 4 Digit (Nomor)]]) -> ID8195121M0100 | BJ17: =Table43[[#This Row],[Nama Gramasi atau Jumlah Pack per CTN]] -> 100GR | BM17: =IF(Table43[[#This Row],[SATUAN Fix Win]]<>"","KRT") -> KRT | BN17: =IF(Table43[[#This Row],[SATUAN Fix Win]]<>"","GD01") -> GD01 | BO17: =IF(Table43[[#This Row],[SATUAN Fix Win]]<>"",11611) -> 11611 | BP17: =IF(Table43[[#This Row],[SATUAN Fix Win]]<>"",11612) -> 11612 | BR17: =IF(Table43[[#This Row],[SATUAN Fix Win]]<>"",1) -> 1
A18: =CONCATENATE(Table43[[#This Row],[Kode BARANG Win2]],Table43[[#This Row],[No. Urut Item Sama]]) -> R10210010100106 | B18: 6 | C18: SOAP COOL 144PCS X 100GR"3171286"DBS107 | D18: 3031726 | E18: =IFERROR(VLOOKUP(Table43[[#This Row],[NO]],[1]Sheet1!$G$3:$K$1267,5,0),0) -> 0 | F18: Dettol DAS 105gr Cool NSAN | G18: 144 | I18: 8993560024178 | J18: =Table43[[#This Row],[Nama Jenis Kemasan]] -> PCS | K18: =TRIM(CONCATENATE(Table43[[#This Row],[Nama KLP]]," ",Table43[[#This Row],[Nama Sub KLP]])) -> DETTOL BODY SOAP | L18: =CONCATENATE(Table43[[#This Row],[kode 2 Digit (hrf+No)]],Table43[[#This Row],[kode 2 Digit (Nomor)]],Table43[[#This Row],[kode 1 Digit (Nomor)]]) -> R1021 | M18: =IF(AH18="",CONCATENATE(R18,T18,V18,X18,Z18,AB18,AD18,AF18,Table43[[#This Row],[Tanda Kode Revisi]]),CONCATENATE(R18,T18,V18,X18,Z18,AB18,AD18,AH18)) -> R1021001010010 | N18: =LEN(M18) -> 14 | O18: =IF(AG18<>"",TRIM(UPPER(CONCATENATE(Q18," ",S18," ",U18," ",W18," ",Y18," ",AA18," ","X"," ",Table43[[#This Row],[ISI/CTN]]," ",AG18," ",AC18," ",AE18," ",AI18))),TRIM(UPPER(CONCATENATE(Q18," ",S18," ",U18," ",W18," ",Y18," ",AA18," ","X"," ",Table43[[#This Row],[ISI/CTN]]," ",AC18," ",AE18," ",AI18)))) -> RB DETTOL BODY SOAP COOL 100GR X 144 PCS | P18: =LEN(O18) -> 40 | Q18: RB | R18: R1 | S18: DETTOL | T18: 02 | U18: BODY SOAP | V18: 1 | X18: 0 | Y18: COOL | Z18: 01 | AA18: 100GR | AB18: 0100 | AC18: PCS | AD18: 1 | AF18: 0 | AJ18: =IFERROR(VLOOKUP(Table43[[#This Row],[Kode BARANG Win2]],'[2]Template Impor Barang'!#REF!,2,0),0) -> 0 | AK18: =Table43[[#This Row],[ISI/CTN]] -> 144 | AL18: =Table43[[#This Row],[Kode Pcpl]] -> 3031726 | AN18: =Table43[[#This Row],[Harga Jual Pcs GT (-PPN)]]-(Table43[[#This Row],[Harga Jual Pcs GT (-PPN)]]*8.5%) -> 5864.5654 | AO18: =Table43[[#This Row],[Harga Beli Pcs (-PPN)]]*Table43[[#This Row],[ISI/CTN]] -> 844497.42 | AP18: =Table43[[#This Row],[Harga Beli Pcs (-PPN)]]*1.11 -> 6509.6676 | AQ18: =Table43[[#This Row],[Harga Beli Krt (- PPN)]]*1.11 -> 937392.14 | AR18: 6409.3611 | AS18: =Table43[[#This Row],[Harga Jual Pcs GT (-PPN)]]*Table43[[#This Row],[ISI/CTN]] -> 922948 | AT18: =Table43[[#This Row],[Harga Jual Pcs GT (-PPN)]]*1.11 -> 7114.3908 | AU18: =Table43[[#This Row],[Harga Jual Krt GT (- PPN)]]*1.11 -> 1024472.3 | AV18: 6409.3611 | AW18: =Table43[[#This Row],[Harga Jual Pcs MT (-PPN)]]*Table43[[#This Row],[ISI/CTN]] -> 922948 | AX18: =Table43[[#This Row],[Harga Jual Pcs MT (-PPN)]]*1.11 -> 7114.3908 | AY18: =Table43[[#This Row],[Harga Jual Pcs MT (+PPN)]]*Table43[[#This Row],[ISI/CTN]] -> 1024472.3 | AZ18: =(Table43[[#This Row],[Harga Jual Pcs GT (-PPN)]]-Table43[[#This Row],[Harga Beli Pcs (-PPN)]])/Table43[[#This Row],[Harga Jual Pcs GT (-PPN)]] -> 0.085 | BA18: =Table43[[#This Row],[Harga Jual Pcs MT (-PPN)]]-Table43[[#This Row],[Harga Beli Pcs (-PPN)]] -> 544.79569 | BB18: =Table43[[#This Row],[Column1]]/Table43[[#This Row],[Harga Jual Pcs MT (-PPN)]] -> 0.085 | BD18: =IFERROR(VLOOKUP(Table43[[#This Row],[Kode BARANG Win2]],'[3]Daftar Barang dan Jasa'!$B$2:$D$3515,3,0),0) -> RB DETTOL BODY SOAP COOL 100GR X 144 PCS | BE18: =IF(TODAY()-Table43[[#This Row],[Efektif Pembuatan]]>60,"Lama","Baru") -> Lama | BF18: =IF(TODAY()-Table43[[#This Row],[Efektif Naik Harga]]<30,"Naik","Sama") -> #VALUE! | BG18: Aktif | BH18: =IF(Table43[[#This Row],[Kode BARANG Win2]]<>"","IDR","") -> IDR | BI18: =CONCATENATE(Table43[[#This Row],[kode 1 Digit (Nomor)]],Table43[[#This Row],[kode 4 Digit (Nomor)]]) -> 30317260100 | BJ18: =Table43[[#This Row],[Nama Gramasi atau Jumlah Pack per CTN]] -> 100GR | BM18: =IF(Table43[[#This Row],[SATUAN Fix Win]]<>"","KRT") -> KRT | BN18: =IF(Table43[[#This Row],[SATUAN Fix Win]]<>"","GD01") -> GD01 | BO18: =IF(Table43[[#This Row],[SATUAN Fix Win]]<>"",11611) -> 11611 | BP18: =IF(Table43[[#This Row],[SATUAN Fix Win]]<>"",11612) -> 11612 | BR18: =IF(Table43[[#This Row],[SATUAN Fix Win]]<>"",1) -> 1
A19: =CONCATENATE(Table43[[#This Row],[Kode BARANG Win2]],Table43[[#This Row],[No. Urut Item Sama]]) -> R10210010100107 | B19: 7 | C19: SOAP COOL 144PCS X 100GR"3171286"DBS107 | D19: ID8099810M | E19: =IFERROR(VLOOKUP(Table43[[#This Row],[NO]],[1]Sheet1!$G$3:$K$1267,5,0),0) -> 0 | F19: Dettol DAS 110gr Cool COR | G19: 144 | I19: 8993560024178 | J19: =Table43[[#This Row],[Nama Jenis Kemasan]] -> PCS | K19: =TRIM(CONCATENATE(Table43[[#This Row],[Nama KLP]]," ",Table43[[#This Row],[Nama Sub KLP]])) -> DETTOL BODY SOAP | L19: =CONCATENATE(Table43[[#This Row],[kode 2 Digit (hrf+No)]],Table43[[#This Row],[kode 2 Digit (Nomor)]],Table43[[#This Row],[kode 1 Digit (Nomor)]]) -> R1021 | M19: =IF(AH19="",CONCATENATE(R19,T19,V19,X19,Z19,AB19,AD19,AF19,Table43[[#This Row],[Tanda Kode Revisi]]),CONCATENATE(R19,T19,V19,X19,Z19,AB19,AD19,AH19)) -> R1021001010010 | N19: =LEN(M19) -> 14 | O19: =IF(AG19<>"",TRIM(UPPER(CONCATENATE(Q19," ",S19," ",U19," ",W19," ",Y19," ",AA19," ","X"," ",Table43[[#This Row],[ISI/CTN]]," ",AG19," ",AC19," ",AE19," ",AI19))),TRIM(UPPER(CONCATENATE(Q19," ",S19," ",U19," ",W19," ",Y19," ",AA19," ","X"," ",Table43[[#This Row],[ISI/CTN]]," ",AC19," ",AE19," ",AI19)))) -> RB DETTOL BODY SOAP COOL 100GR X 144 PCS | P19: =LEN(O19) -> 40 | Q19: RB | R19: R1 | S19: DETTOL | T19: 02 | U19: BODY SOAP | V19: 1 | X19: 0 | Y19: COOL | Z19: 01 | AA19: 100GR | AB19: 0100 | AC19: PCS | AD19: 1 | AF19: 0 | AJ19: =IFERROR(VLOOKUP(Table43[[#This Row],[Kode BARANG Win2]],'[2]Template Impor Barang'!#REF!,2,0),0) -> 0 | AK19: =Table43[[#This Row],[ISI/CTN]] -> 144 | AL19: =Table43[[#This Row],[Kode Pcpl]] -> ID8099810M | AN19: =Table43[[#This Row],[Harga Jual Pcs GT (-PPN)]]-(Table43[[#This Row],[Harga Jual Pcs GT (-PPN)]]*8.5%) -> 5864.5654 | AO19: =Table43[[#This Row],[Harga Beli Pcs (-PPN)]]*Table43[[#This Row],[ISI/CTN]] -> 844497.42 | AP19: =Table43[[#This Row],[Harga Beli Pcs (-PPN)]]*1.11 -> 6509.6676 | AQ19: =Table43[[#This Row],[Harga Beli Krt (- PPN)]]*1.11 -> 937392.14 | AR19: 6409.3611 | AS19: =Table43[[#This Row],[Harga Jual Pcs GT (-PPN)]]*Table43[[#This Row],[ISI/CTN]] -> 922948 | AT19: =Table43[[#This Row],[Harga Jual Pcs GT (-PPN)]]*1.11 -> 7114.3908 | AU19: =Table43[[#This Row],[Harga Jual Krt GT (- PPN)]]*1.11 -> 1024472.3 | AV19: 6409.3611 | AW19: =Table43[[#This Row],[Harga Jual Pcs MT (-PPN)]]*Table43[[#This Row],[ISI/CTN]] -> 922948 | AX19: =Table43[[#This Row],[Harga Jual Pcs MT (-PPN)]]*1.11 -> 7114.3908 | AY19: =Table43[[#This Row],[Harga Jual Pcs MT (+PPN)]]*Table43[[#This Row],[ISI/CTN]] -> 1024472.3 | AZ19: =(Table43[[#This Row],[Harga Jual Pcs GT (-PPN)]]-Table43[[#This Row],[Harga Beli Pcs (-PPN)]])/Table43[[#This Row],[Harga Jual Pcs GT (-PPN)]] -> 0.085 | BA19: =Table43[[#This Row],[Harga Jual Pcs MT (-PPN)]]-Table43[[#This Row],[Harga Beli Pcs (-PPN)]] -> 544.79569 | BB19: =Table43[[#This Row],[Column1]]/Table43[[#This Row],[Harga Jual Pcs MT (-PPN)]] -> 0.085 | BD19: =IFERROR(VLOOKUP(Table43[[#This Row],[Kode BARANG Win2]],'[3]Daftar Barang dan Jasa'!$B$2:$D$3515,3,0),0) -> RB DETTOL BODY SOAP COOL 100GR X 144 PCS | BE19: =IF(TODAY()-Table43[[#This Row],[Efektif Pembuatan]]>60,"Lama","Baru") -> Lama | BF19: =IF(TODAY()-Table43[[#This Row],[Efektif Naik Harga]]<30,"Naik","Sama") -> #VALUE! | BG19: Aktif | BH19: =IF(Table43[[#This Row],[Kode BARANG Win2]]<>"","IDR","") -> IDR | BI19: =CONCATENATE(Table43[[#This Row],[kode 1 Digit (Nomor)]],Table43[[#This Row],[kode 4 Digit (Nomor)]]) -> ID8099810M0100 | BJ19: =Table43[[#This Row],[Nama Gramasi atau Jumlah Pack per CTN]] -> 100GR | BM19: =IF(Table43[[#This Row],[SATUAN Fix Win]]<>"","KRT") -> KRT | BN19: =IF(Table43[[#This Row],[SATUAN Fix Win]]<>"","GD01") -> GD01 | BO19: =IF(Table43[[#This Row],[SATUAN Fix Win]]<>"",11611) -> 11611 | BP19: =IF(Table43[[#This Row],[SATUAN Fix Win]]<>"",11612) -> 11612 | BR19: =IF(Table43[[#This Row],[SATUAN Fix Win]]<>"",1) -> 1
A20: =CONCATENATE(Table43[[#This Row],[Kode BARANG Win2]],Table43[[#This Row],[No. Urut Item Sama]]) -> R10210010100108 | B20: 8 | C20: SOAP COOL 144PCS X 100GR"3171286"DBS107 | D20: ID0344249M | E20: =IFERROR(VLOOKUP(Table43[[#This Row],[NO]],[1]Sheet1!$G$3:$K$1267,5,0),0) -> 0 | F20: Dettol DAS 110gr Cool SANT | G20: 144 | I20: 8993560024178 | J20: =Table43[[#This Row],[Nama Jenis Kemasan]] -> PCS | K20: =TRIM(CONCATENATE(Table43[[#This Row],[Nama KLP]]," ",Table43[[#This Row],[Nama Sub KLP]])) -> DETTOL BODY SOAP | L20: =CONCATENATE(Table43[[#This Row],[kode 2 Digit (hrf+No)]],Table43[[#This Row],[kode 2 Digit (Nomor)]],Table43[[#This Row],[kode 1 Digit (Nomor)]]) -> R1021 | M20: =IF(AH20="",CONCATENATE(R20,T20,V20,X20,Z20,AB20,AD20,AF20,Table43[[#This Row],[Tanda Kode Revisi]]),CONCATENATE(R20,T20,V20,X20,Z20,AB20,AD20,AH20)) -> R1021001010010 | N20: =LEN(M20) -> 14 | O20: =IF(AG20<>"",TRIM(UPPER(CONCATENATE(Q20," ",S20," ",U20," ",W20," ",Y20," ",AA20," ","X"," ",Table43[[#This Row],[ISI/CTN]]," ",AG20," ",AC20," ",AE20," ",AI20))),TRIM(UPPER(CONCATENATE(Q20," ",S20," ",U20," ",W20," ",Y20," ",AA20," ","X"," ",Table43[[#This Row],[ISI/CTN]]," ",AC20," ",AE20," ",AI20)))) -> RB DETTOL BODY SOAP COOL 100GR X 144 PCS | P20: =LEN(O20) -> 40 | Q20: RB | R20: R1 | S20: DETTOL | T20: 02 | U20: BODY SOAP | V20: 1 | X20: 0 | Y20: COOL | Z20: 01 | AA20: 100GR | AB20: 0100 | AC20: PCS | AD20: 1 | AF20: 0 | AJ20: =IFERROR(VLOOKUP(Table43[[#This Row],[Kode BARANG Win2]],'[2]Template Impor Barang'!#REF!,2,0),0) -> 0 | AK20: =Table43[[#This Row],[ISI/CTN]] -> 144 | AL20: =Table43[[#This Row],[Kode Pcpl]] -> ID0344249M | AN20: =Table43[[#This Row],[Harga Jual Pcs GT (-PPN)]]-(Table43[[#This Row],[Harga Jual Pcs GT (-PPN)]]*8.5%) -> 5864.5654 | AO20: =Table43[[#This Row],[Harga Beli Pcs (-PPN)]]*Table43[[#This Row],[ISI/CTN]] -> 844497.42 | AP20: =Table43[[#This Row],[Harga Beli Pcs (-PPN)]]*1.11 -> 6509.6676 | AQ20: =Table43[[#This Row],[Harga Beli Krt (- PPN)]]*1.11 -> 937392.14 | AR20: 6409.3611 | AS20: =Table43[[#This Row],[Harga Jual Pcs GT (-PPN)]]*Table43[[#This Row],[ISI/CTN]] -> 922948 | AT20: =Table43[[#This Row],[Harga Jual Pcs GT (-PPN)]]*1.11 -> 7114.3908 | AU20: =Table43[[#This Row],[Harga Jual Krt GT (- PPN)]]*1.11 -> 1024472.3 | AV20: 6409.3611 | AW20: =Table43[[#This Row],[Harga Jual Pcs MT (-PPN)]]*Table43[[#This Row],[ISI/CTN]] -> 922948 | AX20: =Table43[[#This Row],[Harga Jual Pcs MT (-PPN)]]*1.11 -> 7114.3908 | AY20: =Table43[[#This Row],[Harga Jual Pcs MT (+PPN)]]*Table43[[#This Row],[ISI/CTN]] -> 1024472.3 | AZ20: =(Table43[[#This Row],[Harga Jual Pcs GT (-PPN)]]-Table43[[#This Row],[Harga Beli Pcs (-PPN)]])/Table43[[#This Row],[Harga Jual Pcs GT (-PPN)]] -> 0.085 | BA20: =Table43[[#This Row],[Harga Jual Pcs MT (-PPN)]]-Table43[[#This Row],[Harga Beli Pcs (-PPN)]] -> 544.79569 | BB20: =Table43[[#This Row],[Column1]]/Table43[[#This Row],[Harga Jual Pcs MT (-PPN)]] -> 0.085 | BD20: =IFERROR(VLOOKUP(Table43[[#This Row],[Kode BARANG Win2]],'[3]Daftar Barang dan Jasa'!$B$2:$D$3515,3,0),0) -> RB DETTOL BODY SOAP COOL 100GR X 144 PCS | BE20: =IF(TODAY()-Table43[[#This Row],[Efektif Pembuatan]]>60,"Lama","Baru") -> Lama | BF20: =IF(TODAY()-Table43[[#This Row],[Efektif Naik Harga]]<30,"Naik","Sama") -> #VALUE! | BG20: Aktif | BH20: =IF(Table43[[#This Row],[Kode BARANG Win2]]<>"","IDR","") -> IDR | BI20: =CONCATENATE(Table43[[#This Row],[kode 1 Digit (Nomor)]],Table43[[#This Row],[kode 4 Digit (Nomor)]]) -> ID0344249M0100 | BJ20: =Table43[[#This Row],[Nama Gramasi atau Jumlah Pack per CTN]] -> 100GR | BM20: =IF(Table43[[#This Row],[SATUAN Fix Win]]<>"","KRT") -> KRT | BN20: =IF(Table43[[#This Row],[SATUAN Fix Win]]<>"","GD01") -> GD01 | BO20: =IF(Table43[[#This Row],[SATUAN Fix Win]]<>"",11611) -> 11611 | BP20: =IF(Table43[[#This Row],[SATUAN Fix Win]]<>"",11612) -> 11612 | BR20: =IF(Table43[[#This Row],[SATUAN Fix Win]]<>"",1) -> 1
A21: =CONCATENATE(Table43[[#This Row],[Kode BARANG Win2]],Table43[[#This Row],[No. Urut Item Sama]]) -> R10210010100109 | B21: 9 | C21: SOAP COOL 144PCS X 100GR"3171286"DBS107 | D21: ID8088690M | E21: =IFERROR(VLOOKUP(Table43[[#This Row],[NO]],[1]Sheet1!$G$3:$K$1267,5,0),0) -> 0 | F21: Dettol DAS 110gr Cool ZEN | G21: 144 | I21: 8993560024178 | J21: =Table43[[#This Row],[Nama Jenis Kemasan]] -> PCS | K21: =TRIM(CONCATENATE(Table43[[#This Row],[Nama KLP]]," ",Table43[[#This Row],[Nama Sub KLP]])) -> DETTOL BODY SOAP | L21: =CONCATENATE(Table43[[#This Row],[kode 2 Digit (hrf+No)]],Table43[[#This Row],[kode 2 Digit (Nomor)]],Table43[[#This Row],[kode 1 Digit (Nomor)]]) -> R1021 | M21: =IF(AH21="",CONCATENATE(R21,T21,V21,X21,Z21,AB21,AD21,AF21,Table43[[#This Row],[Tanda Kode Revisi]]),CONCATENATE(R21,T21,V21,X21,Z21,AB21,AD21,AH21)) -> R1021001010010 | N21: =LEN(M21) -> 14 | O21: =IF(AG21<>"",TRIM(UPPER(CONCATENATE(Q21," ",S21," ",U21," ",W21," ",Y21," ",AA21," ","X"," ",Table43[[#This Row],[ISI/CTN]]," ",AG21," ",AC21," ",AE21," ",AI21))),TRIM(UPPER(CONCATENATE(Q21," ",S21," ",U21," ",W21," ",Y21," ",AA21," ","X"," ",Table43[[#This Row],[ISI/CTN]]," ",AC21," ",AE21," ",AI21)))) -> RB DETTOL BODY SOAP COOL 100GR X 144 PCS | P21: =LEN(O21) -> 40 | Q21: RB | R21: R1 | S21: DETTOL | T21: 02 | U21: BODY SOAP | V21: 1 | X21: 0 | Y21: COOL | Z21: 01 | AA21: 100GR | AB21: 0100 | AC21: PCS | AD21: 1 | AF21: 0 | AJ21: =IFERROR(VLOOKUP(Table43[[#This Row],[Kode BARANG Win2]],'[2]Template Impor Barang'!#REF!,2,0),0) -> 0 | AK21: =Table43[[#This Row],[ISI/CTN]] -> 144 | AL21: =Table43[[#This Row],[Kode Pcpl]] -> ID8088690M | AN21: =Table43[[#This Row],[Harga Jual Pcs GT (-PPN)]]-(Table43[[#This Row],[Harga Jual Pcs GT (-PPN)]]*8.5%) -> 5864.5654 | AO21: =Table43[[#This Row],[Harga Beli Pcs (-PPN)]]*Table43[[#This Row],[ISI/CTN]] -> 844497.42 | AP21: =Table43[[#This Row],[Harga Beli Pcs (-PPN)]]*1.11 -> 6509.6676 | AQ21: =Table43[[#This Row],[Harga Beli Krt (- PPN)]]*1.11 -> 937392.14 | AR21: 6409.3611 | AS21: =Table43[[#This Row],[Harga Jual Pcs GT (-PPN)]]*Table43[[#This Row],[ISI/CTN]] -> 922948 | AT21: =Table43[[#This Row],[Harga Jual Pcs GT (-PPN)]]*1.11 -> 7114.3908 | AU21: =Table43[[#This Row],[Harga Jual Krt GT (- PPN)]]*1.11 -> 1024472.3 | AV21: 6409.3611 | AW21: =Table43[[#This Row],[Harga Jual Pcs MT (-PPN)]]*Table43[[#This Row],[ISI/CTN]] -> 922948 | AX21: =Table43[[#This Row],[Harga Jual Pcs MT (-PPN)]]*1.11 -> 7114.3908 | AY21: =Table43[[#This Row],[Harga Jual Pcs MT (+PPN)]]*Table43[[#This Row],[ISI/CTN]] -> 1024472.3 | AZ21: =(Table43[[#This Row],[Harga Jual Pcs GT (-PPN)]]-Table43[[#This Row],[Harga Beli Pcs (-PPN)]])/Table43[[#This Row],[Harga Jual Pcs GT (-PPN)]] -> 0.085 | BA21: =Table43[[#This Row],[Harga Jual Pcs MT (-PPN)]]-Table43[[#This Row],[Harga Beli Pcs (-PPN)]] -> 544.79569 | BB21: =Table43[[#This Row],[Column1]]/Table43[[#This Row],[Harga Jual Pcs MT (-PPN)]] -> 0.085 | BD21: =IFERROR(VLOOKUP(Table43[[#This Row],[Kode BARANG Win2]],'[3]Daftar Barang dan Jasa'!$B$2:$D$3515,3,0),0) -> RB DETTOL BODY SOAP COOL 100GR X 144 PCS | BE21: =IF(TODAY()-Table43[[#This Row],[Efektif Pembuatan]]>60,"Lama","Baru") -> Lama | BF21: =IF(TODAY()-Table43[[#This Row],[Efektif Naik Harga]]<30,"Naik","Sama") -> #VALUE! | BG21: Aktif | BH21: =IF(Table43[[#This Row],[Kode BARANG Win2]]<>"","IDR","") -> IDR | BI21: =CONCATENATE(Table43[[#This Row],[kode 1 Digit (Nomor)]],Table43[[#This Row],[kode 4 Digit (Nomor)]]) -> ID8088690M0100 | BJ21: =Table43[[#This Row],[Nama Gramasi atau Jumlah Pack per CTN]] -> 100GR | BM21: =IF(Table43[[#This Row],[SATUAN Fix Win]]<>"","KRT") -> KRT | BN21: =IF(Table43[[#This Row],[SATUAN Fix Win]]<>"","GD01") -> GD01 | BO21: =IF(Table43[[#This Row],[SATUAN Fix Win]]<>"",11611) -> 11611 | BP21: =IF(Table43[[#This Row],[SATUAN Fix Win]]<>"",11612) -> 11612 | BR21: =IF(Table43[[#This Row],[SATUAN Fix Win]]<>"",1) -> 1
A22: =CONCATENATE(Table43[[#This Row],[Kode BARANG Win2]],Table43[[#This Row],[No. Urut Item Sama]]) -> R10210020100101 | B22: 1 | C22: SOAP FAM PROTECT 144 X 100GR PCS "3300517"DBS121 | D22: 3300517 | E22: =IFERROR(VLOOKUP(Table43[[#This Row],[NO]],[1]Sheet1!$G$3:$K$1267,5,0),0) -> 0 | F22: DETOLIDBS FAMPRO 100GX144 | G22: 144 | H22: SOAP FAM PROTECT 144 X 100GR PCS "3300517"DBS121 | I22: 8993560003715 | J22: =Table43[[#This Row],[Nama Jenis Kemasan]] -> PCS | K22: =TRIM(CONCATENATE(Table43[[#This Row],[Nama KLP]]," ",Table43[[#This Row],[Nama Sub KLP]])) -> DETTOL BODY SOAP | L22: =CONCATENATE(Table43[[#This Row],[kode 2 Digit (hrf+No)]],Table43[[#This Row],[kode 2 Digit (Nomor)]],Table43[[#This Row],[kode 1 Digit (Nomor)]]) -> R1021 | M22: =IF(AH22="",CONCATENATE(R22,T22,V22,X22,Z22,AB22,AD22,AF22,Table43[[#This Row],[Tanda Kode Revisi]]),CONCATENATE(R22,T22,V22,X22,Z22,AB22,AD22,AH22)) -> R1021002010010 | N22: =LEN(M22) -> 14 | O22: =IF(AG22<>"",TRIM(UPPER(CONCATENATE(Q22," ",S22," ",U22," ",W22," ",Y22," ",AA22," ","X"," ",Table43[[#This Row],[ISI/CTN]]," ",AG22," ",AC22," ",AE22," ",AI22))),TRIM(UPPER(CONCATENATE(Q22," ",S22," ",U22," ",W22," ",Y22," ",AA22," ","X"," ",Table43[[#This Row],[ISI/CTN]]," ",AC22," ",AE22," ",AI22)))) -> RB DETTOL BODY SOAP FAMILY PROTECT 100GR X 144 PCS | P22: =LEN(O22) -> 50 | Q22: RB | R22: R1 | S22: DETTOL | T22: 02 | U22: BODY SOAP | V22: 1 | X22: 0 | Y22: FAMILY PROTECT | Z22: 02 | AA22: 100GR | AB22: 0100 | AC22: PCS | AD22: 1 | AF22: 0 | AJ22: =IFERROR(VLOOKUP(Table43[[#This Row],[Kode BARANG Win2]],'[2]Template Impor Barang'!#REF!,2,0),0) -> 0 | AK22: =Table43[[#This Row],[ISI/CTN]] -> 144 | AL22: =Table43[[#This Row],[Kode Pcpl]] -> 3300517 | AN22: =Table43[[#This Row],[Harga Jual Pcs GT (-PPN)]]-(Table43[[#This Row],[Harga Jual Pcs GT (-PPN)]]*8.5%) -> 5864.5654 | AO22: =Table43[[#This Row],[Harga Beli Pcs (-PPN)]]*Table43[[#This Row],[ISI/CTN]] -> 844497.42 | AP22: =Table43[[#This Row],[Harga Beli Pcs (-PPN)]]*1.11 -> 6509.6676 | AQ22: =Table43[[#This Row],[Harga Beli Krt (- PPN)]]*1.11 -> 937392.14 | AR22: 6409.3611 | AS22: =Table43[[#This Row],[Harga Jual Pcs GT (-PPN)]]*Table43[[#This Row],[ISI/CTN]] -> 922948 | AT22: =Table43[[#This Row],[Harga Jual Pcs GT (-PPN)]]*1.11 -> 7114.3908 | AU22: =Table43[[#This Row],[Harga Jual Krt GT (- PPN)]]*1.11 -> 1024472.3 | AV22: 6409.3611 | AW22: =Table43[[#This Row],[Harga Jual Pcs MT (-PPN)]]*Table43[[#This Row],[ISI/CTN]] -> 922948 | AX22: =Table43[[#This Row],[Harga Jual Pcs MT (-PPN)]]*1.11 -> 7114.3908 | AY22: =Table43[[#This Row],[Harga Jual Pcs MT (+PPN)]]*Table43[[#This Row],[ISI/CTN]] -> 1024472.3 | AZ22: =(Table43[[#This Row],[Harga Jual Pcs GT (-PPN)]]-Table43[[#This Row],[Harga Beli Pcs (-PPN)]])/Table43[[#This Row],[Harga Jual Pcs GT (-PPN)]] -> 0.085 | BA22: =Table43[[#This Row],[Harga Jual Pcs MT (-PPN)]]-Table43[[#This Row],[Harga Beli Pcs (-PPN)]] -> 544.79569 | BB22: =Table43[[#This Row],[Column1]]/Table43[[#This Row],[Harga Jual Pcs MT (-PPN)]] -> 0.085 | BD22: =IFERROR(VLOOKUP(Table43[[#This Row],[Kode BARANG Win2]],'[3]Daftar Barang dan Jasa'!$B$2:$D$3515,3,0),0) -> RB DETTOL BODY SOAP FAMILY PROTECT 100GR X 144 PCS | BE22: =IF(TODAY()-Table43[[#This Row],[Efektif Pembuatan]]>60,"Lama","Baru") -> Lama | BF22: =IF(TODAY()-Table43[[#This Row],[Efektif Naik Harga]]<30,"Naik","Sama") -> #VALUE! | BG22: Aktif | BH22: =IF(Table43[[#This Row],[Kode BARANG Win2]]<>"","IDR","") -> IDR | BI22: =CONCATENATE(Table43[[#This Row],[kode 1 Digit (Nomor)]],Table43[[#This Row],[kode 4 Digit (Nomor)]]) -> 33005170100 | BJ22: =Table43[[#This Row],[Nama Gramasi atau Jumlah Pack per CTN]] -> 100GR | BM22: =IF(Table43[[#This Row],[SATUAN Fix Win]]<>"","KRT") -> KRT | BN22: =IF(Table43[[#This Row],[SATUAN Fix Win]]<>"","GD01") -> GD01 | BO22: =IF(Table43[[#This Row],[SATUAN Fix Win]]<>"",11611) -> 11611 | BP22: =IF(Table43[[#This Row],[SATUAN Fix Win]]<>"",11612) -> 11612 | BR22: =IF(Table43[[#This Row],[SATUAN Fix Win]]<>"",1) -> 1
A23: =CONCATENATE(Table43[[#This Row],[Kode BARANG Win2]],Table43[[#This Row],[No. Urut Item Sama]]) -> R10210030060101 | B23: 1 | C23: SOAP FRESH 144PCS X 60GR"3170933"DBS108 | D23: 3170933 | E23: =IFERROR(VLOOKUP(Table43[[#This Row],[NO]],[1]Sheet1!$G$3:$K$1267,5,0),0) -> 0 | F23: DETOLIDBS FRSH 60GX144B | G23: 144 | H23: SOAP FRESH 144PCS X 60GR"3170933"DBS108 | I23: 8993560155780 | J23: =Table43[[#This Row],[Nama Jenis Kemasan]] -> PCS | K23: =TRIM(CONCATENATE(Table43[[#This Row],[Nama KLP]]," ",Table43[[#This Row],[Nama Sub KLP]])) -> DETTOL BODY SOAP | L23: =CONCATENATE(Table43[[#This Row],[kode 2 Digit (hrf+No)]],Table43[[#This Row],[kode 2 Digit (Nomor)]],Table43[[#This Row],[kode 1 Digit (Nomor)]]) -> R1021 | M23: =IF(AH23="",CONCATENATE(R23,T23,V23,X23,Z23,AB23,AD23,AF23,Table43[[#This Row],[Tanda Kode Revisi]]),CONCATENATE(R23,T23,V23,X23,Z23,AB23,AD23,AH23)) -> R1021003006010 | N23: =LEN(M23) -> 14 | O23: =IF(AG23<>"",TRIM(UPPER(CONCATENATE(Q23," ",S23," ",U23," ",W23," ",Y23," ",AA23," ","X"," ",Table43[[#This Row],[ISI/CTN]]," ",AG23," ",AC23," ",AE23," ",AI23))),TRIM(UPPER(CONCATENATE(Q23," ",S23," ",U23," ",W23," ",Y23," ",AA23," ","X"," ",Table43[[#This Row],[ISI/CTN]]," ",AC23," ",AE23," ",AI23)))) -> RB DETTOL BODY SOAP FRESH 60GR X 144 PCS | P23: =LEN(O23) -> 40 | Q23: RB | R23: R1 | S23: DETTOL | T23: 02 | U23: BODY SOAP | V23: 1 | X23: 0 | Y23: FRESH | Z23: 03 | AA23: 60GR | AB23: 0060 | AC23: PCS | AD23: 1 | AF23: 0 | AJ23: =IFERROR(VLOOKUP(Table43[[#This Row],[Kode BARANG Win2]],'[2]Template Impor Barang'!#REF!,2,0),0) -> 0 | AK23: =Table43[[#This Row],[ISI/CTN]] -> 144 | AL23: =Table43[[#This Row],[Kode Pcpl]] -> 3170933 | AN23: =Table43[[#This Row],[Harga Jual Pcs GT (-PPN)]]-(Table43[[#This Row],[Harga Jual Pcs GT (-PPN)]]*8.5%) -> 3048.78 | AO23: =Table43[[#This Row],[Harga Beli Pcs (-PPN)]]*Table43[[#This Row],[ISI/CTN]] -> 439024.32 | AP23: =Table43[[#This Row],[Harga Beli Pcs (-PPN)]]*1.11 -> 3384.1458 | AQ23: =Table43[[#This Row],[Harga Beli Krt (- PPN)]]*1.11 -> 487317 | AR23: 3332 | AS23: =Table43[[#This Row],[Harga Jual Pcs GT (-PPN)]]*Table43[[#This Row],[ISI/CTN]] -> 479808 | AT23: =Table43[[#This Row],[Harga Jual Pcs GT (-PPN)]]*1.11 -> 3698.52 | AU23: =Table43[[#This Row],[Harga Jual Krt GT (- PPN)]]*1.11 -> 532586.88 | AV23: 3332 | AW23: =Table43[[#This Row],[Harga Jual Pcs MT (-PPN)]]*Table43[[#This Row],[ISI/CTN]] -> 479808 | AX23: =Table43[[#This Row],[Harga Jual Pcs MT (-PPN)]]*1.11 -> 3698.52 | AY23: =Table43[[#This Row],[Harga Jual Pcs MT (+PPN)]]*Table43[[#This Row],[ISI/CTN]] -> 532586.88 | AZ23: =(Table43[[#This Row],[Harga Jual Pcs GT (-PPN)]]-Table43[[#This Row],[Harga Beli Pcs (-PPN)]])/Table43[[#This Row],[Harga Jual Pcs GT (-PPN)]] -> 0.085 | BA23: =Table43[[#This Row],[Harga Jual Pcs MT (-PPN)]]-Table43[[#This Row],[Harga Beli Pcs (-PPN)]] -> 283.22 | BB23: =Table43[[#This Row],[Column1]]/Table43[[#This Row],[Harga Jual Pcs MT (-PPN)]] -> 0.085 | BD23: =IFERROR(VLOOKUP(Table43[[#This Row],[Kode BARANG Win2]],'[3]Daftar Barang dan Jasa'!$B$2:$D$3515,3,0),0) -> RB DETTOL BODY SOAP FRESH 60GR X 144 PCS | BE23: =IF(TODAY()-Table43[[#This Row],[Efektif Pembuatan]]>60,"Lama","Baru") -> Lama | BF23: =IF(TODAY()-Table43[[#This Row],[Efektif Naik Harga]]<30,"Naik","Sama") -> #VALUE! | BG23: Aktif | BH23: =IF(Table43[[#This Row],[Kode BARANG Win2]]<>"","IDR","") -> IDR | BI23: =CONCATENATE(Table43[[#This Row],[kode 1 Digit (Nomor)]],Table43[[#This Row],[kode 4 Digit (Nomor)]]) -> 31709330060 | BJ23: =Table43[[#This Row],[Nama Gramasi atau Jumlah Pack per CTN]] -> 60GR | BM23: =IF(Table43[[#This Row],[SATUAN Fix Win]]<>"","KRT") -> KRT | BN23: =IF(Table43[[#This Row],[SATUAN Fix Win]]<>"","GD01") -> GD01 | BO23: =IF(Table43[[#This Row],[SATUAN Fix Win]]<>"",11611) -> 11611 | BP23: =IF(Table43[[#This Row],[SATUAN Fix Win]]<>"",11612) -> 11612 | BR23: =IF(Table43[[#This Row],[SATUAN Fix Win]]<>"",1) -> 1
A24: =CONCATENATE(Table43[[#This Row],[Kode BARANG Win2]],Table43[[#This Row],[No. Urut Item Sama]]) -> R10210030060102 | B24: 2 | C24: SOAP FRESH 144PCS X 60GR"3170933"DBS108 | D24: 3147626 | E24: =IFERROR(VLOOKUP(Table43[[#This Row],[NO]],[1]Sheet1!$G$3:$K$1267,5,0),0) -> 0 | F24: DETOLIDBS FRS 60GX144 | G24: 144 | I24: 8993560155780 | J24: =Table43[[#This Row],[Nama Jenis Kemasan]] -> PCS | K24: =TRIM(CONCATENATE(Table43[[#This Row],[Nama KLP]]," ",Table43[[#This Row],[Nama Sub KLP]])) -> DETTOL BODY SOAP | L24: =CONCATENATE(Table43[[#This Row],[kode 2 Digit (hrf+No)]],Table43[[#This Row],[kode 2 Digit (Nomor)]],Table43[[#This Row],[kode 1 Digit (Nomor)]]) -> R1021 | M24: =IF(AH24="",CONCATENATE(R24,T24,V24,X24,Z24,AB24,AD24,AF24,Table43[[#This Row],[Tanda Kode Revisi]]),CONCATENATE(R24,T24,V24,X24,Z24,AB24,AD24,AH24)) -> R1021003006010 | N24: =LEN(M24) -> 14 | O24: =IF(AG24<>"",TRIM(UPPER(CONCATENATE(Q24," ",S24," ",U24," ",W24," ",Y24," ",AA24," ","X"," ",Table43[[#This Row],[ISI/CTN]]," ",AG24," ",AC24," ",AE24," ",AI24))),TRIM(UPPER(CONCATENATE(Q24," ",S24," ",U24," ",W24," ",Y24," ",AA24," ","X"," ",Table43[[#This Row],[ISI/CTN]]," ",AC24," ",AE24," ",AI24)))) -> RB DETTOL BODY SOAP FRESH 60GR X 144 PCS | P24: =LEN(O24) -> 40 | Q24: RB | R24: R1 | S24: DETTOL | T24: 02 | U24: BODY SOAP | V24: 1 | X24: 0 | Y24: FRESH | Z24: 03 | AA24: 60GR | AB24: 0060 | AC24: PCS | AD24: 1 | AF24: 0 | AJ24: =IFERROR(VLOOKUP(Table43[[#This Row],[Kode BARANG Win2]],'[2]Template Impor Barang'!#REF!,2,0),0) -> 0 | AK24: =Table43[[#This Row],[ISI/CTN]] -> 144 | AL24: =Table43[[#This Row],[Kode Pcpl]] -> 3147626 | AN24: =Table43[[#This Row],[Harga Jual Pcs GT (-PPN)]]-(Table43[[#This Row],[Harga Jual Pcs GT (-PPN)]]*8.5%) -> 3048.78 | AO24: =Table43[[#This Row],[Harga Beli Pcs (-PPN)]]*Table43[[#This Row],[ISI/CTN]] -> 439024.32 | AP24: =Table43[[#This Row],[Harga Beli Pcs (-PPN)]]*1.11 -> 3384.1458 | AQ24: =Table43[[#This Row],[Harga Beli Krt (- PPN)]]*1.11 -> 487317 | AR24: 3332 | AS24: =Table43[[#This Row],[Harga Jual Pcs GT (-PPN)]]*Table43[[#This Row],[ISI/CTN]] -> 479808 | AT24: =Table43[[#This Row],[Harga Jual Pcs GT (-PPN)]]*1.11 -> 3698.52 | AU24: =Table43[[#This Row],[Harga Jual Krt GT (- PPN)]]*1.11 -> 532586.88 | AV24: 3332 | AW24: =Table43[[#This Row],[Harga Jual Pcs MT (-PPN)]]*Table43[[#This Row],[ISI/CTN]] -> 479808 | AX24: =Table43[[#This Row],[Harga Jual Pcs MT (-PPN)]]*1.11 -> 3698.52 | AY24: =Table43[[#This Row],[Harga Jual Pcs MT (+PPN)]]*Table43[[#This Row],[ISI/CTN]] -> 532586.88 | AZ24: =(Table43[[#This Row],[Harga Jual Pcs GT (-PPN)]]-Table43[[#This Row],[Harga Beli Pcs (-PPN)]])/Table43[[#This Row],[Harga Jual Pcs GT (-PPN)]] -> 0.085 | BA24: =Table43[[#This Row],[Harga Jual Pcs MT (-PPN)]]-Table43[[#This Row],[Harga Beli Pcs (-PPN)]] -> 283.22 | BB24: =Table43[[#This Row],[Column1]]/Table43[[#This Row],[Harga Jual Pcs MT (-PPN)]] -> 0.085 | BD24: =IFERROR(VLOOKUP(Table43[[#This Row],[Kode BARANG Win2]],'[3]Daftar Barang dan Jasa'!$B$2:$D$3515,3,0),0) -> RB DETTOL BODY SOAP FRESH 60GR X 144 PCS | BE24: =IF(TODAY()-Table43[[#This Row],[Efektif Pembuatan]]>60,"Lama","Baru") -> Lama | BF24: =IF(TODAY()-Table43[[#This Row],[Efektif Naik Harga]]<30,"Naik","Sama") -> #VALUE! | BG24: Aktif | BH24: =IF(Table43[[#This Row],[Kode BARANG Win2]]<>"","IDR","") -> IDR | BI24: =CONCATENATE(Table43[[#This Row],[kode 1 Digit (Nomor)]],Table43[[#This Row],[kode 4 Digit (Nomor)]]) -> 31476260060 | BJ24: =Table43[[#This Row],[Nama Gramasi atau Jumlah Pack per CTN]] -> 60GR | BM24: =IF(Table43[[#This Row],[SATUAN Fix Win]]<>"","KRT") -> KRT | BN24: =IF(Table43[[#This Row],[SATUAN Fix Win]]<>"","GD01") -> GD01 | BO24: =IF(Table43[[#This Row],[SATUAN Fix Win]]<>"",11611) -> 11611 | BP24: =IF(Table43[[#This Row],[SATUAN Fix Win]]<>"",11612) -> 11612 | BR24: =IF(Table43[[#This Row],[SATUAN Fix Win]]<>"",1) -> 1
A25: =CONCATENATE(Table43[[#This Row],[Kode BARANG Win2]],Table43[[#This Row],[No. Urut Item Sama]]) -> R10210030100101 | B25: 1 | D25: 3170945 | E25: =IFERROR(VLOOKUP(Table43[[#This Row],[NO]],[1]Sheet1!$G$3:$K$1267,5,0),0) -> 20010010100010 | G25: 144 | H25: SOAP FRESH 144PCS X 100GR"3170945"DBS110 | J25: =Table43[[#This Row],[Nama Jenis Kemasan]] -> PCS | K25: =TRIM(CONCATENATE(Table43[[#This Row],[Nama KLP]]," ",Table43[[#This Row],[Nama Sub KLP]])) -> DETTOL BODY SOAP | L25: =CONCATENATE(Table43[[#This Row],[kode 2 Digit (hrf+No)]],Table43[[#This Row],[kode 2 Digit (Nomor)]],Table43[[#This Row],[kode 1 Digit (Nomor)]]) -> R1021 | M25: =IF(AH25="",CONCATENATE(R25,T25,V25,X25,Z25,AB25,AD25,AF25,Table43[[#This Row],[Tanda Kode Revisi]]),CONCATENATE(R25,T25,V25,X25,Z25,AB25,AD25,AH25)) -> R1021003010010 | N25: =LEN(M25) -> 14 | O25: =IF(AG25<>"",TRIM(UPPER(CONCATENATE(Q25," ",S25," ",U25," ",W25," ",Y25," ",AA25," ","X"," ",Table43[[#This Row],[ISI/CTN]]," ",AG25," ",AC25," ",AE25," ",AI25))),TRIM(UPPER(CONCATENATE(Q25," ",S25," ",U25," ",W25," ",Y25," ",AA25," ","X"," ",Table43[[#This Row],[ISI/CTN]]," ",AC25," ",AE25," ",AI25)))) -> RB DETTOL BODY SOAP FRESH 100GR X 144 PCS | P25: =LEN(O25) -> 41 | Q25: RB | R25: R1 | S25: DETTOL | T25: 02 | U25: BODY SOAP | V25: 1 | X25: 0 | Y25: FRESH | Z25: 03 | AA25: 100GR | AB25: 0100 | AC25: PCS | AD25: 1 | AF25: 0 | AJ25: =IFERROR(VLOOKUP(Table43[[#This Row],[Kode BARANG Win2]],'[2]Template Impor Barang'!#REF!,2,0),0) -> 0 | AK25: =Table43[[#This Row],[ISI/CTN]] -> 144 | AL25: =Table43[[#This Row],[Kode Pcpl]] -> 3170945 | AN25: =Table43[[#This Row],[Harga Jual Pcs GT (-PPN)]]-(Table43[[#This Row],[Harga Jual Pcs GT (-PPN)]]*8.5%) -> 5864.5654 | AO25: =Table43[[#This Row],[Harga Beli Pcs (-PPN)]]*Table43[[#This Row],[ISI/CTN]] -> 844497.42 | AP25: =Table43[[#This Row],[Harga Beli Pcs (-PPN)]]*1.11 -> 6509.6676 | AQ25: =Table43[[#This Row],[Harga Beli Krt (- PPN)]]*1.11 -> 937392.14 | AR25: 6409.3611 | AS25: =Table43[[#This Row],[Harga Jual Pcs GT (-PPN)]]*Table43[[#This Row],[ISI/CTN]] -> 922948 | AT25: =Table43[[#This Row],[Harga Jual Pcs GT (-PPN)]]*1.11 -> 7114.3908 | AU25: =Table43[[#This Row],[Harga Jual Krt GT (- PPN)]]*1.11 -> 1024472.3 | AW25: =Table43[[#This Row],[Harga Jual Pcs MT (-PPN)]]*Table43[[#This Row],[ISI/CTN]] -> 0 | AX25: =Table43[[#This Row],[Harga Jual Pcs MT (-PPN)]]*1.11 -> 0 | AY25: =Table43[[#This Row],[Harga Jual Pcs MT (+PPN)]]*Table43[[#This Row],[ISI/CTN]] -> 0 | AZ25: =(Table43[[#This Row],[Harga Jual Pcs GT (-PPN)]]-Table43[[#This Row],[Harga Beli Pcs (-PPN)]])/Table43[[#This Row],[Harga Jual Pcs GT (-PPN)]] -> 0.085 | BA25: =Table43[[#This Row],[Harga Jual Pcs MT (-PPN)]]-Table43[[#This Row],[Harga Beli Pcs (-PPN)]] -> -5864.5654 | BB25: =Table43[[#This Row],[Column1]]/Table43[[#This Row],[Harga Jual Pcs MT (-PPN)]] -> #DIV/0! | BD25: =IFERROR(VLOOKUP(Table43[[#This Row],[Kode BARANG Win2]],'[3]Daftar Barang dan Jasa'!$B$2:$D$3515,3,0),0) -> RB DETTOL BODY SOAP FRESH 100GR X 144 PCS | BE25: =IF(TODAY()-Table43[[#This Row],[Efektif Pembuatan]]>60,"Lama","Baru") -> Lama | BF25: =IF(TODAY()-Table43[[#This Row],[Efektif Naik Harga]]<30,"Naik","Sama") -> #VALUE! | BG25: Aktif | BH25: =IF(Table43[[#This Row],[Kode BARANG Win2]]<>"","IDR","") -> IDR | BI25: =CONCATENATE(Table43[[#This Row],[kode 1 Digit (Nomor)]],Table43[[#This Row],[kode 4 Digit (Nomor)]]) -> 31709450100 | BJ25: =Table43[[#This Row],[Nama Gramasi atau Jumlah Pack per CTN]] -> 100GR | BM25: =IF(Table43[[#This Row],[SATUAN Fix Win]]<>"","KRT") -> KRT | BN25: =IF(Table43[[#This Row],[SATUAN Fix Win]]<>"","GD01") -> GD01 | BO25: =IF(Table43[[#This Row],[SATUAN Fix Win]]<>"",11611) -> 11611 | BP25: =IF(Table43[[#This Row],[SATUAN Fix Win]]<>"",11612) -> 11612 | BR25: =IF(Table43[[#This Row],[SATUAN Fix Win]]<>"",1) -> 1
